{
  "ApiVersion": "24.0.0",
  "Config": {
    "endpoint": "/api/v2/ad_hoc_commands/",
    "name": "AdHocCommand",
    "type_name": "ad_hoc_command",
    "id_key": "id",
    "property_overrides": {
      "extra_vars": {
        "type": "json",
        "description": "",
        "sensitive": false,
        "required": false,
        "trim": false,
        "post_wrap": true,
        "default_value": "",
        "element_type": ""
      },
      "launched_by": {
        "type": "id",
        "description": "",
        "sensitive": false,
        "required": false,
        "trim": false,
        "post_wrap": false,
        "default_value": "",
        "element_type": ""
      }
    },
    "search_fields": [
      {
        "url_suffix": "%d/",
        "name": "by_id",
        "fields": [
          {
            "name": "id"
          }
        ]
      },
      {
        "url_suffix": "?name__exact=%s",
        "name": "by_name",
        "fields": [
          {
            "name": "name",
            "url_escape_value": true
          }
        ],
        "multiple_results": true
      }
    ],
    "enabled": true,
    "has_object_roles": false,
    "has_survey_spec": false,
    "associate_disassociate_groups": null,
    "field_constraints": null,
    "skip_write_only": false,
    "undeletable": false,
    "pre_state_set_hook_function": "hooks.RequireResourceStateOrOrig",
    "no_id": false,
    "no_terraform_data_source": false,
    "no_terraform_resource": false,
    "api_property_resource_key": "POST",
    "api_property_data_key": "GET",
    "property_name_leave_as_is": false,
    "api_data_override": null,
    "remove_fields_data_source": null,
    "remove_fields_resource": null,
    "credential_types": null
  },
  "Description": "# List Ad Hoc Commands:\n\nMake a GET request to this resource to retrieve the list of\nad hoc commands.\n\nThe resulting data structure contains:\n\n    {\n        \"count\": 99,\n        \"next\": null,\n        \"previous\": null,\n        \"results\": [\n            ...\n        ]\n    }\n\nThe `count` field indicates the total number of ad hoc commands\nfound for the given query.  The `next` and `previous` fields provides links to\nadditional results if there are more than will fit on a single page.  The\n`results` list contains zero or more ad hoc command records.  \n\n## Results\n\nEach ad hoc command data structure includes the following fields:\n\n* `id`: Database ID for this ad hoc command. (integer)\n* `type`: Data type for this ad hoc command. (choice)\n* `url`: URL for this ad hoc command. (string)\n* `related`: Data structure with URLs of related resources. (object)\n* `summary_fields`: Data structure with name/description for related resources.  The output for some objects may be limited for performance reasons. (object)\n* `created`: Timestamp when this ad hoc command was created. (datetime)\n* `modified`: Timestamp when this ad hoc command was last modified. (datetime)\n* `name`: Name of this ad hoc command. (string)\n* `launch_type`:  (choice)\n    - `manual`: Manual\n    - `relaunch`: Relaunch\n    - `callback`: Callback\n    - `scheduled`: Scheduled\n    - `dependency`: Dependency\n    - `workflow`: Workflow\n    - `webhook`: Webhook\n    - `sync`: Sync\n    - `scm`: SCM Update\n* `status`:  (choice)\n    - `new`: New\n    - `pending`: Pending\n    - `waiting`: Waiting\n    - `running`: Running\n    - `successful`: Successful\n    - `failed`: Failed\n    - `error`: Error\n    - `canceled`: Canceled\n* `execution_environment`: The container image to be used for execution. (id)\n* `failed`:  (boolean)\n* `started`: The date and time the job was queued for starting. (datetime)\n* `finished`: The date and time the job finished execution. (datetime)\n* `canceled_on`: The date and time when the cancel request was sent. (datetime)\n* `elapsed`: Elapsed time in seconds that the job ran. (decimal)\n* `job_explanation`: A status field to indicate the state of the job if it wasn\u0026#x27;t able to run and capture stdout (string)\n* `execution_node`: The node the job executed on. (string)\n* `controller_node`: The instance that managed the execution environment. (string)\n* `launched_by`:  (field)\n* `work_unit_id`: The Receptor work unit ID associated with this job. (string)\n* `job_type`:  (choice)\n    - `run`: Run\n    - `check`: Check\n* `inventory`:  (id)\n* `limit`:  (string)\n* `credential`:  (id)\n* `module_name`:  (choice)\n    - `command`\n    - `shell`\n    - `yum`\n    - `apt`\n    - `apt_key`\n    - `apt_repository`\n    - `apt_rpm`\n    - `service`\n    - `group`\n    - `user`\n    - `mount`\n    - `ping`\n    - `selinux`\n    - `setup`\n    - `win_ping`\n    - `win_service`\n    - `win_updates`\n    - `win_group`\n    - `win_user`\n* `module_args`:  (string)\n* `forks`:  (integer)\n* `verbosity`:  (choice)\n    - `0`: 0 (Normal)\n    - `1`: 1 (Verbose)\n    - `2`: 2 (More Verbose)\n    - `3`: 3 (Debug)\n    - `4`: 4 (Connection Debug)\n    - `5`: 5 (WinRM Debug)\n* `extra_vars`:  (string)\n* `become_enabled`:  (boolean)\n* `diff_mode`:  (boolean)\n\n\n\n## Sorting\n\nTo specify that ad hoc commands are returned in a particular\norder, use the `order_by` query string parameter on the GET request.\n\n    ?order_by=name\n\nPrefix the field name with a dash `-` to sort in reverse:\n\n    ?order_by=-name\n\nMultiple sorting fields may be specified by separating the field names with a\ncomma `,`:\n\n    ?order_by=name,some_other_field\n\n## Pagination\n\nUse the `page_size` query string parameter to change the number of results\nreturned for each request.  Use the `page` query string parameter to retrieve\na particular page of results.\n\n    ?page_size=100\u0026page=2\n\nThe `previous` and `next` links returned with the results will set these query\nstring parameters automatically.\n\n## Searching\n\nUse the `search` query string parameter to perform a case-insensitive search\nwithin all designated text fields of a model.\n\n    ?search=findme\n\n(_Added in Ansible Tower 3.1.0_) Search across related fields:\n\n    ?related__search=findme\n\nNote: If you want to provide more than one search term, multiple\nsearch fields with the same key, like `?related__search=foo\u0026related__search=bar`,\nwill be ORed together. Terms separated by commas, like `?related__search=foo,bar`\nwill be ANDed together.\n\n## Filtering\n\nAny additional query string parameters may be used to filter the list of\nresults returned to those matching a given value.  Only fields and relations\nthat exist in the database may be used for filtering.  Any special characters\nin the specified value should be url-encoded. For example:\n\n    ?field=value%20xyz\n\nFields may also span relations, only for fields and relationships defined in\nthe database:\n\n    ?other__field=value\n\nTo exclude results matching certain criteria, prefix the field parameter with\n`not__`:\n\n    ?not__field=value\n\nBy default, all query string filters are AND'ed together, so\nonly the results matching *all* filters will be returned.  To combine results\nmatching *any* one of multiple criteria, prefix each query string parameter\nwith `or__`:\n\n    ?or__field=value\u0026or__field=othervalue\n    ?or__not__field=value\u0026or__field=othervalue\n\n(_Added in Ansible Tower 1.4.5_) The default AND filtering applies all filters\nsimultaneously to each related object being filtered across database\nrelationships.  The chain filter instead applies filters separately for each\nrelated object. To use, prefix the query string parameter with `chain__`:\n\n    ?chain__related__field=value\u0026chain__related__field2=othervalue\n    ?chain__not__related__field=value\u0026chain__related__field2=othervalue\n\nIf the first query above were written as\n`?related__field=value\u0026related__field2=othervalue`, it would return only the\nprimary objects where the *same* related object satisfied both conditions.  As\nwritten using the chain filter, it would return the intersection of primary\nobjects matching each condition.\n\nField lookups may also be used for more advanced queries, by appending the\nlookup to the field name:\n\n    ?field__lookup=value\n\nThe following field lookups are supported:\n\n* `exact`: Exact match (default lookup if not specified).\n* `iexact`: Case-insensitive version of `exact`.\n* `contains`: Field contains value.\n* `icontains`: Case-insensitive version of `contains`.\n* `startswith`: Field starts with value.\n* `istartswith`: Case-insensitive version of `startswith`.\n* `endswith`: Field ends with value.\n* `iendswith`: Case-insensitive version of `endswith`.\n* `regex`: Field matches the given regular expression.\n* `iregex`: Case-insensitive version of `regex`.\n* `gt`: Greater than comparison.\n* `gte`: Greater than or equal to comparison.\n* `lt`: Less than comparison.\n* `lte`: Less than or equal to comparison.\n* `isnull`: Check whether the given field or related object is null; expects a\n  boolean value.\n* `in`: Check whether the given field's value is present in the list provided;\n  expects a list of items.\n\nBoolean values may be specified as `True` or `1` for true, `False` or `0` for\nfalse (both case-insensitive).\n\nNull values may be specified as `None` or `Null` (both case-insensitive),\nthough it is preferred to use the `isnull` lookup to explicitly check for null\nvalues.\n\nLists (for the `in` lookup) may be specified as a comma-separated list of\nvalues.\n\n(_Added in Ansible Tower 3.1.0_) Filtering based on the requesting user's\nlevel of access by query string parameter.\n\n* `role_level`: Level of role to filter on, such as `admin_role`\n\n\n\n\n# Create an Ad Hoc Command:\n\nMake a POST request to this resource with the following ad hoc command\nfields to create a new ad hoc command:\n\n\n\n\n\n\n\n\n\n\n\n\n* `execution_environment`: The container image to be used for execution. (id, default=``)\n\n\n\n\n\n\n\n\n\n\n* `job_type`:  (choice)\n    - `run`: Run (default)\n    - `check`: Check\n* `inventory`:  (id, default=``)\n* `limit`:  (string, default=`\"\"`)\n* `credential`:  (id, default=``)\n* `module_name`:  (choice)\n    - `command` (default)\n    - `shell`\n    - `yum`\n    - `apt`\n    - `apt_key`\n    - `apt_repository`\n    - `apt_rpm`\n    - `service`\n    - `group`\n    - `user`\n    - `mount`\n    - `ping`\n    - `selinux`\n    - `setup`\n    - `win_ping`\n    - `win_service`\n    - `win_updates`\n    - `win_group`\n    - `win_user`\n* `module_args`:  (string, default=`\"\"`)\n* `forks`:  (integer, default=`0`)\n* `verbosity`:  (choice)\n    - `0`: 0 (Normal) (default)\n    - `1`: 1 (Verbose)\n    - `2`: 2 (More Verbose)\n    - `3`: 3 (Debug)\n    - `4`: 4 (Connection Debug)\n    - `5`: 5 (WinRM Debug)\n* `extra_vars`:  (string, default=`\"\"`)\n* `become_enabled`:  (boolean, default=`False`)\n* `diff_mode`:  (boolean, default=`False`)",
  "Endpoint": "/api/v2/ad_hoc_commands/",
  "Name": "AdHocCommand",
  "PackageName": "awx",
  "PropertyGetData": {
    "become_enabled": {
      "computed": true,
      "filterable": true,
      "label": "Become enabled",
      "name": "become_enabled",
      "required": false,
      "sensitive": false,
      "type": "boolean"
    },
    "canceled_on": {
      "computed": true,
      "filterable": true,
      "help_text": "The date and time when the cancel request was sent.",
      "label": "Canceled on",
      "name": "canceled_on",
      "required": false,
      "sensitive": false,
      "type": "datetime"
    },
    "controller_node": {
      "computed": true,
      "filterable": true,
      "help_text": "The instance that managed the execution environment.",
      "label": "Controller node",
      "name": "controller_node",
      "required": false,
      "sensitive": false,
      "type": "string"
    },
    "credential": {
      "computed": true,
      "filterable": true,
      "label": "Credential",
      "name": "credential",
      "required": false,
      "sensitive": false,
      "type": "id"
    },
    "diff_mode": {
      "computed": true,
      "filterable": true,
      "label": "Diff mode",
      "name": "diff_mode",
      "required": false,
      "sensitive": false,
      "type": "boolean"
    },
    "elapsed": {
      "computed": true,
      "filterable": true,
      "help_text": "Elapsed time in seconds that the job ran.",
      "label": "Elapsed",
      "name": "elapsed",
      "required": false,
      "sensitive": false,
      "type": "decimal"
    },
    "execution_environment": {
      "computed": true,
      "filterable": true,
      "help_text": "The container image to be used for execution.",
      "label": "Execution environment",
      "name": "execution_environment",
      "required": false,
      "sensitive": false,
      "type": "id"
    },
    "execution_node": {
      "computed": true,
      "filterable": true,
      "help_text": "The node the job executed on.",
      "label": "Execution node",
      "name": "execution_node",
      "required": false,
      "sensitive": false,
      "type": "string"
    },
    "extra_vars": {
      "computed": true,
      "filterable": true,
      "label": "Extra vars",
      "name": "extra_vars",
      "post_wrap": true,
      "required": false,
      "sensitive": false,
      "trim": false,
      "type": "json"
    },
    "failed": {
      "computed": true,
      "filterable": true,
      "label": "Failed",
      "name": "failed",
      "required": false,
      "sensitive": false,
      "type": "boolean"
    },
    "finished": {
      "computed": true,
      "filterable": true,
      "help_text": "The date and time the job finished execution.",
      "label": "Finished",
      "name": "finished",
      "required": false,
      "sensitive": false,
      "type": "datetime"
    },
    "forks": {
      "computed": true,
      "filterable": true,
      "label": "Forks",
      "max_value": 2147483647,
      "min_value": 0,
      "name": "forks",
      "required": false,
      "sensitive": false,
      "type": "integer"
    },
    "id": {
      "computed": true,
      "filterable": true,
      "help_text": "Database ID for this ad hoc command.",
      "label": "ID",
      "name": "id",
      "required": false,
      "sensitive": false,
      "type": "integer"
    },
    "inventory": {
      "computed": true,
      "filterable": true,
      "label": "Inventory",
      "name": "inventory",
      "required": false,
      "sensitive": false,
      "type": "id"
    },
    "job_explanation": {
      "computed": true,
      "filterable": true,
      "help_text": "A status field to indicate the state of the job if it wasn't able to run and capture stdout",
      "label": "Job explanation",
      "name": "job_explanation",
      "required": false,
      "sensitive": false,
      "type": "string"
    },
    "job_type": {
      "choices": [
        [
          "run",
          "Run"
        ],
        [
          "check",
          "Check"
        ]
      ],
      "computed": true,
      "filterable": true,
      "label": "Job type",
      "name": "job_type",
      "required": false,
      "sensitive": false,
      "type": "choice"
    },
    "launch_type": {
      "choices": [
        [
          "manual",
          "Manual"
        ],
        [
          "relaunch",
          "Relaunch"
        ],
        [
          "callback",
          "Callback"
        ],
        [
          "scheduled",
          "Scheduled"
        ],
        [
          "dependency",
          "Dependency"
        ],
        [
          "workflow",
          "Workflow"
        ],
        [
          "webhook",
          "Webhook"
        ],
        [
          "sync",
          "Sync"
        ],
        [
          "scm",
          "SCM Update"
        ]
      ],
      "computed": true,
      "filterable": true,
      "label": "Launch type",
      "name": "launch_type",
      "required": false,
      "sensitive": false,
      "type": "choice"
    },
    "launched_by": {
      "computed": true,
      "filterable": false,
      "label": "Launched by",
      "name": "launched_by",
      "post_wrap": false,
      "required": false,
      "sensitive": false,
      "trim": false,
      "type": "id"
    },
    "limit": {
      "computed": true,
      "filterable": true,
      "label": "Limit",
      "name": "limit",
      "required": false,
      "sensitive": false,
      "type": "string"
    },
    "module_args": {
      "computed": true,
      "filterable": true,
      "label": "Module args",
      "name": "module_args",
      "required": false,
      "sensitive": false,
      "type": "string"
    },
    "module_name": {
      "choices": [
        [
          "command",
          "command"
        ],
        [
          "shell",
          "shell"
        ],
        [
          "yum",
          "yum"
        ],
        [
          "apt",
          "apt"
        ],
        [
          "apt_key",
          "apt_key"
        ],
        [
          "apt_repository",
          "apt_repository"
        ],
        [
          "apt_rpm",
          "apt_rpm"
        ],
        [
          "service",
          "service"
        ],
        [
          "group",
          "group"
        ],
        [
          "user",
          "user"
        ],
        [
          "mount",
          "mount"
        ],
        [
          "ping",
          "ping"
        ],
        [
          "selinux",
          "selinux"
        ],
        [
          "setup",
          "setup"
        ],
        [
          "win_ping",
          "win_ping"
        ],
        [
          "win_service",
          "win_service"
        ],
        [
          "win_updates",
          "win_updates"
        ],
        [
          "win_group",
          "win_group"
        ],
        [
          "win_user",
          "win_user"
        ]
      ],
      "computed": true,
      "filterable": true,
      "label": "Module name",
      "name": "module_name",
      "required": false,
      "sensitive": false,
      "type": "choice"
    },
    "name": {
      "computed": true,
      "filterable": true,
      "help_text": "Name of this ad hoc command.",
      "label": "Name",
      "name": "name",
      "required": false,
      "sensitive": false,
      "type": "string"
    },
    "started": {
      "computed": true,
      "filterable": true,
      "help_text": "The date and time the job was queued for starting.",
      "label": "Started",
      "name": "started",
      "required": false,
      "sensitive": false,
      "type": "datetime"
    },
    "status": {
      "choices": [
        [
          "new",
          "New"
        ],
        [
          "pending",
          "Pending"
        ],
        [
          "waiting",
          "Waiting"
        ],
        [
          "running",
          "Running"
        ],
        [
          "successful",
          "Successful"
        ],
        [
          "failed",
          "Failed"
        ],
        [
          "error",
          "Error"
        ],
        [
          "canceled",
          "Canceled"
        ]
      ],
      "computed": true,
      "filterable": true,
      "label": "Status",
      "name": "status",
      "required": false,
      "sensitive": false,
      "type": "choice"
    },
    "verbosity": {
      "choices": [
        [
          0,
          "0 (Normal)"
        ],
        [
          1,
          "1 (Verbose)"
        ],
        [
          2,
          "2 (More Verbose)"
        ],
        [
          3,
          "3 (Debug)"
        ],
        [
          4,
          "4 (Connection Debug)"
        ],
        [
          5,
          "5 (WinRM Debug)"
        ]
      ],
      "computed": true,
      "filterable": true,
      "label": "Verbosity",
      "name": "verbosity",
      "required": false,
      "sensitive": false,
      "type": "choice"
    },
    "work_unit_id": {
      "computed": true,
      "filterable": true,
      "help_text": "The Receptor work unit ID associated with this job.",
      "label": "Work unit id",
      "name": "work_unit_id",
      "required": false,
      "sensitive": false,
      "type": "string"
    }
  },
  "PropertyGetKeys": [
    "become_enabled",
    "canceled_on",
    "controller_node",
    "credential",
    "diff_mode",
    "elapsed",
    "execution_environment",
    "execution_node",
    "extra_vars",
    "failed",
    "finished",
    "forks",
    "id",
    "inventory",
    "job_explanation",
    "job_type",
    "launch_type",
    "launched_by",
    "limit",
    "module_args",
    "module_name",
    "name",
    "started",
    "status",
    "verbosity",
    "work_unit_id"
  ],
  "PropertyPostData": {
    "become_enabled": {
      "computed": true,
      "default": false,
      "filterable": true,
      "label": "Become enabled",
      "name": "become_enabled",
      "required": false,
      "sensitive": false,
      "type": "boolean"
    },
    "credential": {
      "computed": true,
      "filterable": true,
      "label": "Credential",
      "name": "credential",
      "required": false,
      "sensitive": false,
      "type": "id"
    },
    "diff_mode": {
      "computed": true,
      "default": false,
      "filterable": true,
      "label": "Diff mode",
      "name": "diff_mode",
      "required": false,
      "sensitive": false,
      "type": "boolean"
    },
    "execution_environment": {
      "computed": true,
      "filterable": true,
      "help_text": "The container image to be used for execution.",
      "label": "Execution environment",
      "name": "execution_environment",
      "required": false,
      "sensitive": false,
      "type": "id"
    },
    "extra_vars": {
      "computed": true,
      "default": "",
      "default_value": "stringdefault.StaticString(``)",
      "filterable": true,
      "label": "Extra vars",
      "name": "extra_vars",
      "post_wrap": true,
      "required": false,
      "sensitive": false,
      "trim": false,
      "type": "json"
    },
    "forks": {
      "computed": true,
      "default": 0,
      "default_value": "int64default.StaticInt64(0)",
      "filterable": true,
      "label": "Forks",
      "max_value": 2147483647,
      "min_value": 0,
      "name": "forks",
      "required": false,
      "sensitive": false,
      "type": "integer"
    },
    "inventory": {
      "computed": true,
      "filterable": true,
      "label": "Inventory",
      "name": "inventory",
      "required": false,
      "sensitive": false,
      "type": "id"
    },
    "job_type": {
      "choices": [
        [
          "run",
          "Run"
        ],
        [
          "check",
          "Check"
        ]
      ],
      "computed": true,
      "default": "run",
      "default_value": "stringdefault.StaticString(`run`)",
      "filterable": true,
      "label": "Job type",
      "name": "job_type",
      "required": false,
      "sensitive": false,
      "type": "choice"
    },
    "limit": {
      "computed": true,
      "default": "",
      "default_value": "stringdefault.StaticString(``)",
      "filterable": true,
      "label": "Limit",
      "name": "limit",
      "required": false,
      "sensitive": false,
      "type": "string"
    },
    "module_args": {
      "computed": true,
      "default": "",
      "default_value": "stringdefault.StaticString(``)",
      "filterable": true,
      "label": "Module args",
      "name": "module_args",
      "required": false,
      "sensitive": false,
      "type": "string"
    },
    "module_name": {
      "choices": [
        [
          "command",
          "command"
        ],
        [
          "shell",
          "shell"
        ],
        [
          "yum",
          "yum"
        ],
        [
          "apt",
          "apt"
        ],
        [
          "apt_key",
          "apt_key"
        ],
        [
          "apt_repository",
          "apt_repository"
        ],
        [
          "apt_rpm",
          "apt_rpm"
        ],
        [
          "service",
          "service"
        ],
        [
          "group",
          "group"
        ],
        [
          "user",
          "user"
        ],
        [
          "mount",
          "mount"
        ],
        [
          "ping",
          "ping"
        ],
        [
          "selinux",
          "selinux"
        ],
        [
          "setup",
          "setup"
        ],
        [
          "win_ping",
          "win_ping"
        ],
        [
          "win_service",
          "win_service"
        ],
        [
          "win_updates",
          "win_updates"
        ],
        [
          "win_group",
          "win_group"
        ],
        [
          "win_user",
          "win_user"
        ]
      ],
      "computed": true,
      "default": "command",
      "default_value": "stringdefault.StaticString(`command`)",
      "filterable": true,
      "label": "Module name",
      "name": "module_name",
      "required": false,
      "sensitive": false,
      "type": "choice"
    },
    "verbosity": {
      "choices": [
        [
          0,
          "0 (Normal)"
        ],
        [
          1,
          "1 (Verbose)"
        ],
        [
          2,
          "2 (More Verbose)"
        ],
        [
          3,
          "3 (Debug)"
        ],
        [
          4,
          "4 (Connection Debug)"
        ],
        [
          5,
          "5 (WinRM Debug)"
        ]
      ],
      "computed": true,
      "default": 0,
      "default_value": "stringdefault.StaticString(`0`)",
      "filterable": true,
      "label": "Verbosity",
      "name": "verbosity",
      "required": false,
      "sensitive": false,
      "type": "choice"
    }
  },
  "PropertyPostKeys": [
    "become_enabled",
    "credential",
    "diff_mode",
    "execution_environment",
    "extra_vars",
    "forks",
    "inventory",
    "job_type",
    "limit",
    "module_args",
    "module_name",
    "verbosity"
  ],
  "PropertyWriteOnlyData": {},
  "PropertyWriteOnlyKeys": null
}