{
  "ApiVersion": "24.0.0",
  "Config": {
    "endpoint": "/api/v2/settings/ldap/",
    "name": "SettingsAuthLDAP",
    "type_name": "settings_auth_ldap",
    "id_key": "id",
    "property_overrides": {
      "AUTH_LDAP_1_BIND_PASSWORD": {
        "type": "",
        "description": "",
        "sensitive": true,
        "trim": false,
        "post_wrap": false,
        "default_value": "",
        "element_type": ""
      },
      "AUTH_LDAP_1_CONNECTION_OPTIONS": {
        "type": "json",
        "description": "",
        "trim": false,
        "post_wrap": false,
        "default_value": "",
        "element_type": ""
      },
      "AUTH_LDAP_1_GROUP_TYPE_PARAMS": {
        "type": "json",
        "description": "",
        "trim": false,
        "post_wrap": false,
        "default_value": "",
        "element_type": ""
      },
      "AUTH_LDAP_1_ORGANIZATION_MAP": {
        "type": "json",
        "description": "",
        "trim": false,
        "post_wrap": false,
        "default_value": "",
        "element_type": ""
      },
      "AUTH_LDAP_1_TEAM_MAP": {
        "type": "json",
        "description": "",
        "trim": false,
        "post_wrap": false,
        "default_value": "",
        "element_type": ""
      },
      "AUTH_LDAP_1_USER_ATTR_MAP": {
        "type": "json",
        "description": "",
        "trim": false,
        "post_wrap": false,
        "default_value": "",
        "element_type": ""
      },
      "AUTH_LDAP_1_USER_FLAGS_BY_GROUP": {
        "type": "json",
        "description": "",
        "trim": false,
        "post_wrap": false,
        "default_value": "",
        "element_type": ""
      },
      "AUTH_LDAP_2_BIND_PASSWORD": {
        "type": "",
        "description": "",
        "sensitive": true,
        "trim": false,
        "post_wrap": false,
        "default_value": "",
        "element_type": ""
      },
      "AUTH_LDAP_2_CONNECTION_OPTIONS": {
        "type": "json",
        "description": "",
        "trim": false,
        "post_wrap": false,
        "default_value": "",
        "element_type": ""
      },
      "AUTH_LDAP_2_GROUP_TYPE_PARAMS": {
        "type": "json",
        "description": "",
        "trim": false,
        "post_wrap": false,
        "default_value": "",
        "element_type": ""
      },
      "AUTH_LDAP_2_ORGANIZATION_MAP": {
        "type": "json",
        "description": "",
        "trim": false,
        "post_wrap": false,
        "default_value": "",
        "element_type": ""
      },
      "AUTH_LDAP_2_TEAM_MAP": {
        "type": "json",
        "description": "",
        "trim": false,
        "post_wrap": false,
        "default_value": "",
        "element_type": ""
      },
      "AUTH_LDAP_2_USER_ATTR_MAP": {
        "type": "json",
        "description": "",
        "trim": false,
        "post_wrap": false,
        "default_value": "",
        "element_type": ""
      },
      "AUTH_LDAP_2_USER_FLAGS_BY_GROUP": {
        "type": "json",
        "description": "",
        "trim": false,
        "post_wrap": false,
        "default_value": "",
        "element_type": ""
      },
      "AUTH_LDAP_3_BIND_PASSWORD": {
        "type": "",
        "description": "",
        "sensitive": true,
        "trim": false,
        "post_wrap": false,
        "default_value": "",
        "element_type": ""
      },
      "AUTH_LDAP_3_CONNECTION_OPTIONS": {
        "type": "json",
        "description": "",
        "trim": false,
        "post_wrap": false,
        "default_value": "",
        "element_type": ""
      },
      "AUTH_LDAP_3_GROUP_TYPE_PARAMS": {
        "type": "json",
        "description": "",
        "trim": false,
        "post_wrap": false,
        "default_value": "",
        "element_type": ""
      },
      "AUTH_LDAP_3_ORGANIZATION_MAP": {
        "type": "json",
        "description": "",
        "trim": false,
        "post_wrap": false,
        "default_value": "",
        "element_type": ""
      },
      "AUTH_LDAP_3_TEAM_MAP": {
        "type": "json",
        "description": "",
        "trim": false,
        "post_wrap": false,
        "default_value": "",
        "element_type": ""
      },
      "AUTH_LDAP_3_USER_ATTR_MAP": {
        "type": "json",
        "description": "",
        "trim": false,
        "post_wrap": false,
        "default_value": "",
        "element_type": ""
      },
      "AUTH_LDAP_3_USER_FLAGS_BY_GROUP": {
        "type": "json",
        "description": "",
        "trim": false,
        "post_wrap": false,
        "default_value": "",
        "element_type": ""
      },
      "AUTH_LDAP_4_BIND_PASSWORD": {
        "type": "",
        "description": "",
        "sensitive": true,
        "trim": false,
        "post_wrap": false,
        "default_value": "",
        "element_type": ""
      },
      "AUTH_LDAP_4_CONNECTION_OPTIONS": {
        "type": "json",
        "description": "",
        "trim": false,
        "post_wrap": false,
        "default_value": "",
        "element_type": ""
      },
      "AUTH_LDAP_4_GROUP_TYPE_PARAMS": {
        "type": "json",
        "description": "",
        "trim": false,
        "post_wrap": false,
        "default_value": "",
        "element_type": ""
      },
      "AUTH_LDAP_4_ORGANIZATION_MAP": {
        "type": "json",
        "description": "",
        "trim": false,
        "post_wrap": false,
        "default_value": "",
        "element_type": ""
      },
      "AUTH_LDAP_4_TEAM_MAP": {
        "type": "json",
        "description": "",
        "trim": false,
        "post_wrap": false,
        "default_value": "",
        "element_type": ""
      },
      "AUTH_LDAP_4_USER_ATTR_MAP": {
        "type": "json",
        "description": "",
        "trim": false,
        "post_wrap": false,
        "default_value": "",
        "element_type": ""
      },
      "AUTH_LDAP_4_USER_FLAGS_BY_GROUP": {
        "type": "json",
        "description": "",
        "trim": false,
        "post_wrap": false,
        "default_value": "",
        "element_type": ""
      },
      "AUTH_LDAP_5_BIND_PASSWORD": {
        "type": "",
        "description": "",
        "sensitive": true,
        "trim": false,
        "post_wrap": false,
        "default_value": "",
        "element_type": ""
      },
      "AUTH_LDAP_5_CONNECTION_OPTIONS": {
        "type": "json",
        "description": "",
        "trim": false,
        "post_wrap": false,
        "default_value": "",
        "element_type": ""
      },
      "AUTH_LDAP_5_GROUP_TYPE_PARAMS": {
        "type": "json",
        "description": "",
        "trim": false,
        "post_wrap": false,
        "default_value": "",
        "element_type": ""
      },
      "AUTH_LDAP_5_ORGANIZATION_MAP": {
        "type": "json",
        "description": "",
        "trim": false,
        "post_wrap": false,
        "default_value": "",
        "element_type": ""
      },
      "AUTH_LDAP_5_TEAM_MAP": {
        "type": "json",
        "description": "",
        "trim": false,
        "post_wrap": false,
        "default_value": "",
        "element_type": ""
      },
      "AUTH_LDAP_5_USER_ATTR_MAP": {
        "type": "json",
        "description": "",
        "trim": false,
        "post_wrap": false,
        "default_value": "",
        "element_type": ""
      },
      "AUTH_LDAP_5_USER_FLAGS_BY_GROUP": {
        "type": "json",
        "description": "",
        "trim": false,
        "post_wrap": false,
        "default_value": "",
        "element_type": ""
      },
      "AUTH_LDAP_BIND_PASSWORD": {
        "type": "",
        "description": "",
        "sensitive": true,
        "trim": false,
        "post_wrap": false,
        "default_value": "",
        "element_type": ""
      },
      "AUTH_LDAP_CONNECTION_OPTIONS": {
        "type": "json",
        "description": "",
        "trim": false,
        "post_wrap": false,
        "default_value": "",
        "element_type": ""
      },
      "AUTH_LDAP_GROUP_TYPE_PARAMS": {
        "type": "json",
        "description": "",
        "trim": false,
        "post_wrap": false,
        "default_value": "",
        "element_type": ""
      },
      "AUTH_LDAP_ORGANIZATION_MAP": {
        "type": "json",
        "description": "",
        "trim": false,
        "post_wrap": false,
        "default_value": "",
        "element_type": ""
      },
      "AUTH_LDAP_TEAM_MAP": {
        "type": "json",
        "description": "",
        "trim": false,
        "post_wrap": false,
        "default_value": "",
        "element_type": ""
      },
      "AUTH_LDAP_USER_ATTR_MAP": {
        "type": "json",
        "description": "",
        "trim": false,
        "post_wrap": false,
        "default_value": "",
        "element_type": ""
      },
      "AUTH_LDAP_USER_FLAGS_BY_GROUP": {
        "type": "json",
        "description": "",
        "trim": false,
        "post_wrap": false,
        "default_value": "",
        "element_type": ""
      }
    },
    "enabled": true,
    "has_object_roles": false,
    "has_survey_spec": false,
    "associate_disassociate_groups": null,
    "field_constraints": null,
    "skip_write_only": false,
    "undeletable": true,
    "pre_state_set_hook_function": "hookSettingsAuthLdap",
    "no_id": true,
    "no_terraform_data_source": false,
    "no_terraform_resource": false,
    "api_property_resource_key": "PUT",
    "api_property_data_key": "GET",
    "property_name_leave_as_is": true,
    "api_data_override": null,
    "remove_fields_data_source": null,
    "remove_fields_resource": null,
    "credential_types": null
  },
  "Description": "# Retrieve a Setting:\n\nMake GET request to this resource to retrieve a single setting\nrecord containing the following fields:\n\n* `AUTH_LDAP_SERVER_URI`: URI to connect to LDAP server, such as \u0026quot;ldap://ldap.example.com:389\u0026quot; (non-SSL) or \u0026quot;ldaps://ldap.example.com:636\u0026quot; (SSL). Multiple LDAP servers may be specified by separating with spaces or commas. LDAP authentication is disabled if this parameter is empty. (string)\n* `AUTH_LDAP_BIND_DN`: DN (Distinguished Name) of user to bind for all search queries. This is the system user account we will use to login to query LDAP for other user information. Refer to the documentation for example syntax. (string)\n* `AUTH_LDAP_BIND_PASSWORD`: Password used to bind LDAP user account. (string)\n* `AUTH_LDAP_START_TLS`: Whether to enable TLS when the LDAP connection is not using SSL. (boolean)\n* `AUTH_LDAP_CONNECTION_OPTIONS`: Additional options to set for the LDAP connection.  LDAP referrals are disabled by default (to prevent certain LDAP queries from hanging with AD). Option names should be strings (e.g. \u0026quot;OPT_REFERRALS\u0026quot;). Refer to https://www.python-ldap.org/doc/html/ldap.html#options for possible options and values that can be set. (nested object)\n* `AUTH_LDAP_USER_SEARCH`: LDAP search query to find users.  Any user that matches the given pattern will be able to login to the service.  The user should also be mapped into an organization (as defined in the AUTH_LDAP_ORGANIZATION_MAP setting).  If multiple search queries need to be supported use of \u0026quot;LDAPUnion\u0026quot; is possible. See the documentation for details. (list)\n* `AUTH_LDAP_USER_DN_TEMPLATE`: Alternative to user search, if user DNs are all of the same format. This approach is more efficient for user lookups than searching if it is usable in your organizational environment. If this setting has a value it will be used instead of AUTH_LDAP_USER_SEARCH. (string)\n* `AUTH_LDAP_USER_ATTR_MAP`: Mapping of LDAP user schema to API user attributes. The default setting is valid for ActiveDirectory but users with other LDAP configurations may need to change the values. Refer to the documentation for additional details. (nested object)\n* `AUTH_LDAP_GROUP_SEARCH`: Users are mapped to organizations based on their membership in LDAP groups. This setting defines the LDAP search query to find groups. Unlike the user search, group search does not support LDAPSearchUnion. (list)\n* `AUTH_LDAP_GROUP_TYPE`: The group type may need to be changed based on the type of the LDAP server.  Values are listed at: https://django-auth-ldap.readthedocs.io/en/stable/groups.html#types-of-groups (choice)\n    - `PosixGroupType`\n    - `GroupOfNamesType`\n    - `GroupOfUniqueNamesType`\n    - `ActiveDirectoryGroupType`\n    - `OrganizationalRoleGroupType`\n    - `MemberDNGroupType`\n    - `NestedGroupOfNamesType`\n    - `NestedGroupOfUniqueNamesType`\n    - `NestedActiveDirectoryGroupType`\n    - `NestedOrganizationalRoleGroupType`\n    - `NestedMemberDNGroupType`\n    - `PosixUIDGroupType`\n* `AUTH_LDAP_GROUP_TYPE_PARAMS`: Key value parameters to send the chosen group type init method. (nested object)\n* `AUTH_LDAP_REQUIRE_GROUP`: Group DN required to login. If specified, user must be a member of this group to login via LDAP. If not set, everyone in LDAP that matches the user search will be able to login to the service. Only one require group is supported. (string)\n* `AUTH_LDAP_DENY_GROUP`: Group DN denied from login. If specified, user will not be allowed to login if a member of this group.  Only one deny group is supported. (string)\n* `AUTH_LDAP_USER_FLAGS_BY_GROUP`: Retrieve users from a given group. At this time, superuser and system auditors are the only groups supported. Refer to the documentation for more detail. (nested object)\n* `AUTH_LDAP_ORGANIZATION_MAP`: Mapping between organization admins/users and LDAP groups. This controls which users are placed into which organizations relative to their LDAP group memberships. Configuration details are available in the documentation. (nested object)\n* `AUTH_LDAP_TEAM_MAP`: Mapping between team members (users) and LDAP groups. Configuration details are available in the documentation. (nested object)\n* `AUTH_LDAP_1_SERVER_URI`: URI to connect to LDAP server, such as \u0026quot;ldap://ldap.example.com:389\u0026quot; (non-SSL) or \u0026quot;ldaps://ldap.example.com:636\u0026quot; (SSL). Multiple LDAP servers may be specified by separating with spaces or commas. LDAP authentication is disabled if this parameter is empty. (string)\n* `AUTH_LDAP_1_BIND_DN`: DN (Distinguished Name) of user to bind for all search queries. This is the system user account we will use to login to query LDAP for other user information. Refer to the documentation for example syntax. (string)\n* `AUTH_LDAP_1_BIND_PASSWORD`: Password used to bind LDAP user account. (string)\n* `AUTH_LDAP_1_START_TLS`: Whether to enable TLS when the LDAP connection is not using SSL. (boolean)\n* `AUTH_LDAP_1_CONNECTION_OPTIONS`: Additional options to set for the LDAP connection.  LDAP referrals are disabled by default (to prevent certain LDAP queries from hanging with AD). Option names should be strings (e.g. \u0026quot;OPT_REFERRALS\u0026quot;). Refer to https://www.python-ldap.org/doc/html/ldap.html#options for possible options and values that can be set. (nested object)\n* `AUTH_LDAP_1_USER_SEARCH`: LDAP search query to find users.  Any user that matches the given pattern will be able to login to the service.  The user should also be mapped into an organization (as defined in the AUTH_LDAP_ORGANIZATION_MAP setting).  If multiple search queries need to be supported use of \u0026quot;LDAPUnion\u0026quot; is possible. See the documentation for details. (list)\n* `AUTH_LDAP_1_USER_DN_TEMPLATE`: Alternative to user search, if user DNs are all of the same format. This approach is more efficient for user lookups than searching if it is usable in your organizational environment. If this setting has a value it will be used instead of AUTH_LDAP_USER_SEARCH. (string)\n* `AUTH_LDAP_1_USER_ATTR_MAP`: Mapping of LDAP user schema to API user attributes. The default setting is valid for ActiveDirectory but users with other LDAP configurations may need to change the values. Refer to the documentation for additional details. (nested object)\n* `AUTH_LDAP_1_GROUP_SEARCH`: Users are mapped to organizations based on their membership in LDAP groups. This setting defines the LDAP search query to find groups. Unlike the user search, group search does not support LDAPSearchUnion. (list)\n* `AUTH_LDAP_1_GROUP_TYPE`: The group type may need to be changed based on the type of the LDAP server.  Values are listed at: https://django-auth-ldap.readthedocs.io/en/stable/groups.html#types-of-groups (choice)\n    - `PosixGroupType`\n    - `GroupOfNamesType`\n    - `GroupOfUniqueNamesType`\n    - `ActiveDirectoryGroupType`\n    - `OrganizationalRoleGroupType`\n    - `MemberDNGroupType`\n    - `NestedGroupOfNamesType`\n    - `NestedGroupOfUniqueNamesType`\n    - `NestedActiveDirectoryGroupType`\n    - `NestedOrganizationalRoleGroupType`\n    - `NestedMemberDNGroupType`\n    - `PosixUIDGroupType`\n* `AUTH_LDAP_1_GROUP_TYPE_PARAMS`: Key value parameters to send the chosen group type init method. (nested object)\n* `AUTH_LDAP_1_REQUIRE_GROUP`: Group DN required to login. If specified, user must be a member of this group to login via LDAP. If not set, everyone in LDAP that matches the user search will be able to login to the service. Only one require group is supported. (string)\n* `AUTH_LDAP_1_DENY_GROUP`: Group DN denied from login. If specified, user will not be allowed to login if a member of this group.  Only one deny group is supported. (string)\n* `AUTH_LDAP_1_USER_FLAGS_BY_GROUP`: Retrieve users from a given group. At this time, superuser and system auditors are the only groups supported. Refer to the documentation for more detail. (nested object)\n* `AUTH_LDAP_1_ORGANIZATION_MAP`: Mapping between organization admins/users and LDAP groups. This controls which users are placed into which organizations relative to their LDAP group memberships. Configuration details are available in the documentation. (nested object)\n* `AUTH_LDAP_1_TEAM_MAP`: Mapping between team members (users) and LDAP groups. Configuration details are available in the documentation. (nested object)\n* `AUTH_LDAP_2_SERVER_URI`: URI to connect to LDAP server, such as \u0026quot;ldap://ldap.example.com:389\u0026quot; (non-SSL) or \u0026quot;ldaps://ldap.example.com:636\u0026quot; (SSL). Multiple LDAP servers may be specified by separating with spaces or commas. LDAP authentication is disabled if this parameter is empty. (string)\n* `AUTH_LDAP_2_BIND_DN`: DN (Distinguished Name) of user to bind for all search queries. This is the system user account we will use to login to query LDAP for other user information. Refer to the documentation for example syntax. (string)\n* `AUTH_LDAP_2_BIND_PASSWORD`: Password used to bind LDAP user account. (string)\n* `AUTH_LDAP_2_START_TLS`: Whether to enable TLS when the LDAP connection is not using SSL. (boolean)\n* `AUTH_LDAP_2_CONNECTION_OPTIONS`: Additional options to set for the LDAP connection.  LDAP referrals are disabled by default (to prevent certain LDAP queries from hanging with AD). Option names should be strings (e.g. \u0026quot;OPT_REFERRALS\u0026quot;). Refer to https://www.python-ldap.org/doc/html/ldap.html#options for possible options and values that can be set. (nested object)\n* `AUTH_LDAP_2_USER_SEARCH`: LDAP search query to find users.  Any user that matches the given pattern will be able to login to the service.  The user should also be mapped into an organization (as defined in the AUTH_LDAP_ORGANIZATION_MAP setting).  If multiple search queries need to be supported use of \u0026quot;LDAPUnion\u0026quot; is possible. See the documentation for details. (list)\n* `AUTH_LDAP_2_USER_DN_TEMPLATE`: Alternative to user search, if user DNs are all of the same format. This approach is more efficient for user lookups than searching if it is usable in your organizational environment. If this setting has a value it will be used instead of AUTH_LDAP_USER_SEARCH. (string)\n* `AUTH_LDAP_2_USER_ATTR_MAP`: Mapping of LDAP user schema to API user attributes. The default setting is valid for ActiveDirectory but users with other LDAP configurations may need to change the values. Refer to the documentation for additional details. (nested object)\n* `AUTH_LDAP_2_GROUP_SEARCH`: Users are mapped to organizations based on their membership in LDAP groups. This setting defines the LDAP search query to find groups. Unlike the user search, group search does not support LDAPSearchUnion. (list)\n* `AUTH_LDAP_2_GROUP_TYPE`: The group type may need to be changed based on the type of the LDAP server.  Values are listed at: https://django-auth-ldap.readthedocs.io/en/stable/groups.html#types-of-groups (choice)\n    - `PosixGroupType`\n    - `GroupOfNamesType`\n    - `GroupOfUniqueNamesType`\n    - `ActiveDirectoryGroupType`\n    - `OrganizationalRoleGroupType`\n    - `MemberDNGroupType`\n    - `NestedGroupOfNamesType`\n    - `NestedGroupOfUniqueNamesType`\n    - `NestedActiveDirectoryGroupType`\n    - `NestedOrganizationalRoleGroupType`\n    - `NestedMemberDNGroupType`\n    - `PosixUIDGroupType`\n* `AUTH_LDAP_2_GROUP_TYPE_PARAMS`: Key value parameters to send the chosen group type init method. (nested object)\n* `AUTH_LDAP_2_REQUIRE_GROUP`: Group DN required to login. If specified, user must be a member of this group to login via LDAP. If not set, everyone in LDAP that matches the user search will be able to login to the service. Only one require group is supported. (string)\n* `AUTH_LDAP_2_DENY_GROUP`: Group DN denied from login. If specified, user will not be allowed to login if a member of this group.  Only one deny group is supported. (string)\n* `AUTH_LDAP_2_USER_FLAGS_BY_GROUP`: Retrieve users from a given group. At this time, superuser and system auditors are the only groups supported. Refer to the documentation for more detail. (nested object)\n* `AUTH_LDAP_2_ORGANIZATION_MAP`: Mapping between organization admins/users and LDAP groups. This controls which users are placed into which organizations relative to their LDAP group memberships. Configuration details are available in the documentation. (nested object)\n* `AUTH_LDAP_2_TEAM_MAP`: Mapping between team members (users) and LDAP groups. Configuration details are available in the documentation. (nested object)\n* `AUTH_LDAP_3_SERVER_URI`: URI to connect to LDAP server, such as \u0026quot;ldap://ldap.example.com:389\u0026quot; (non-SSL) or \u0026quot;ldaps://ldap.example.com:636\u0026quot; (SSL). Multiple LDAP servers may be specified by separating with spaces or commas. LDAP authentication is disabled if this parameter is empty. (string)\n* `AUTH_LDAP_3_BIND_DN`: DN (Distinguished Name) of user to bind for all search queries. This is the system user account we will use to login to query LDAP for other user information. Refer to the documentation for example syntax. (string)\n* `AUTH_LDAP_3_BIND_PASSWORD`: Password used to bind LDAP user account. (string)\n* `AUTH_LDAP_3_START_TLS`: Whether to enable TLS when the LDAP connection is not using SSL. (boolean)\n* `AUTH_LDAP_3_CONNECTION_OPTIONS`: Additional options to set for the LDAP connection.  LDAP referrals are disabled by default (to prevent certain LDAP queries from hanging with AD). Option names should be strings (e.g. \u0026quot;OPT_REFERRALS\u0026quot;). Refer to https://www.python-ldap.org/doc/html/ldap.html#options for possible options and values that can be set. (nested object)\n* `AUTH_LDAP_3_USER_SEARCH`: LDAP search query to find users.  Any user that matches the given pattern will be able to login to the service.  The user should also be mapped into an organization (as defined in the AUTH_LDAP_ORGANIZATION_MAP setting).  If multiple search queries need to be supported use of \u0026quot;LDAPUnion\u0026quot; is possible. See the documentation for details. (list)\n* `AUTH_LDAP_3_USER_DN_TEMPLATE`: Alternative to user search, if user DNs are all of the same format. This approach is more efficient for user lookups than searching if it is usable in your organizational environment. If this setting has a value it will be used instead of AUTH_LDAP_USER_SEARCH. (string)\n* `AUTH_LDAP_3_USER_ATTR_MAP`: Mapping of LDAP user schema to API user attributes. The default setting is valid for ActiveDirectory but users with other LDAP configurations may need to change the values. Refer to the documentation for additional details. (nested object)\n* `AUTH_LDAP_3_GROUP_SEARCH`: Users are mapped to organizations based on their membership in LDAP groups. This setting defines the LDAP search query to find groups. Unlike the user search, group search does not support LDAPSearchUnion. (list)\n* `AUTH_LDAP_3_GROUP_TYPE`: The group type may need to be changed based on the type of the LDAP server.  Values are listed at: https://django-auth-ldap.readthedocs.io/en/stable/groups.html#types-of-groups (choice)\n    - `PosixGroupType`\n    - `GroupOfNamesType`\n    - `GroupOfUniqueNamesType`\n    - `ActiveDirectoryGroupType`\n    - `OrganizationalRoleGroupType`\n    - `MemberDNGroupType`\n    - `NestedGroupOfNamesType`\n    - `NestedGroupOfUniqueNamesType`\n    - `NestedActiveDirectoryGroupType`\n    - `NestedOrganizationalRoleGroupType`\n    - `NestedMemberDNGroupType`\n    - `PosixUIDGroupType`\n* `AUTH_LDAP_3_GROUP_TYPE_PARAMS`: Key value parameters to send the chosen group type init method. (nested object)\n* `AUTH_LDAP_3_REQUIRE_GROUP`: Group DN required to login. If specified, user must be a member of this group to login via LDAP. If not set, everyone in LDAP that matches the user search will be able to login to the service. Only one require group is supported. (string)\n* `AUTH_LDAP_3_DENY_GROUP`: Group DN denied from login. If specified, user will not be allowed to login if a member of this group.  Only one deny group is supported. (string)\n* `AUTH_LDAP_3_USER_FLAGS_BY_GROUP`: Retrieve users from a given group. At this time, superuser and system auditors are the only groups supported. Refer to the documentation for more detail. (nested object)\n* `AUTH_LDAP_3_ORGANIZATION_MAP`: Mapping between organization admins/users and LDAP groups. This controls which users are placed into which organizations relative to their LDAP group memberships. Configuration details are available in the documentation. (nested object)\n* `AUTH_LDAP_3_TEAM_MAP`: Mapping between team members (users) and LDAP groups. Configuration details are available in the documentation. (nested object)\n* `AUTH_LDAP_4_SERVER_URI`: URI to connect to LDAP server, such as \u0026quot;ldap://ldap.example.com:389\u0026quot; (non-SSL) or \u0026quot;ldaps://ldap.example.com:636\u0026quot; (SSL). Multiple LDAP servers may be specified by separating with spaces or commas. LDAP authentication is disabled if this parameter is empty. (string)\n* `AUTH_LDAP_4_BIND_DN`: DN (Distinguished Name) of user to bind for all search queries. This is the system user account we will use to login to query LDAP for other user information. Refer to the documentation for example syntax. (string)\n* `AUTH_LDAP_4_BIND_PASSWORD`: Password used to bind LDAP user account. (string)\n* `AUTH_LDAP_4_START_TLS`: Whether to enable TLS when the LDAP connection is not using SSL. (boolean)\n* `AUTH_LDAP_4_CONNECTION_OPTIONS`: Additional options to set for the LDAP connection.  LDAP referrals are disabled by default (to prevent certain LDAP queries from hanging with AD). Option names should be strings (e.g. \u0026quot;OPT_REFERRALS\u0026quot;). Refer to https://www.python-ldap.org/doc/html/ldap.html#options for possible options and values that can be set. (nested object)\n* `AUTH_LDAP_4_USER_SEARCH`: LDAP search query to find users.  Any user that matches the given pattern will be able to login to the service.  The user should also be mapped into an organization (as defined in the AUTH_LDAP_ORGANIZATION_MAP setting).  If multiple search queries need to be supported use of \u0026quot;LDAPUnion\u0026quot; is possible. See the documentation for details. (list)\n* `AUTH_LDAP_4_USER_DN_TEMPLATE`: Alternative to user search, if user DNs are all of the same format. This approach is more efficient for user lookups than searching if it is usable in your organizational environment. If this setting has a value it will be used instead of AUTH_LDAP_USER_SEARCH. (string)\n* `AUTH_LDAP_4_USER_ATTR_MAP`: Mapping of LDAP user schema to API user attributes. The default setting is valid for ActiveDirectory but users with other LDAP configurations may need to change the values. Refer to the documentation for additional details. (nested object)\n* `AUTH_LDAP_4_GROUP_SEARCH`: Users are mapped to organizations based on their membership in LDAP groups. This setting defines the LDAP search query to find groups. Unlike the user search, group search does not support LDAPSearchUnion. (list)\n* `AUTH_LDAP_4_GROUP_TYPE`: The group type may need to be changed based on the type of the LDAP server.  Values are listed at: https://django-auth-ldap.readthedocs.io/en/stable/groups.html#types-of-groups (choice)\n    - `PosixGroupType`\n    - `GroupOfNamesType`\n    - `GroupOfUniqueNamesType`\n    - `ActiveDirectoryGroupType`\n    - `OrganizationalRoleGroupType`\n    - `MemberDNGroupType`\n    - `NestedGroupOfNamesType`\n    - `NestedGroupOfUniqueNamesType`\n    - `NestedActiveDirectoryGroupType`\n    - `NestedOrganizationalRoleGroupType`\n    - `NestedMemberDNGroupType`\n    - `PosixUIDGroupType`\n* `AUTH_LDAP_4_GROUP_TYPE_PARAMS`: Key value parameters to send the chosen group type init method. (nested object)\n* `AUTH_LDAP_4_REQUIRE_GROUP`: Group DN required to login. If specified, user must be a member of this group to login via LDAP. If not set, everyone in LDAP that matches the user search will be able to login to the service. Only one require group is supported. (string)\n* `AUTH_LDAP_4_DENY_GROUP`: Group DN denied from login. If specified, user will not be allowed to login if a member of this group.  Only one deny group is supported. (string)\n* `AUTH_LDAP_4_USER_FLAGS_BY_GROUP`: Retrieve users from a given group. At this time, superuser and system auditors are the only groups supported. Refer to the documentation for more detail. (nested object)\n* `AUTH_LDAP_4_ORGANIZATION_MAP`: Mapping between organization admins/users and LDAP groups. This controls which users are placed into which organizations relative to their LDAP group memberships. Configuration details are available in the documentation. (nested object)\n* `AUTH_LDAP_4_TEAM_MAP`: Mapping between team members (users) and LDAP groups. Configuration details are available in the documentation. (nested object)\n* `AUTH_LDAP_5_SERVER_URI`: URI to connect to LDAP server, such as \u0026quot;ldap://ldap.example.com:389\u0026quot; (non-SSL) or \u0026quot;ldaps://ldap.example.com:636\u0026quot; (SSL). Multiple LDAP servers may be specified by separating with spaces or commas. LDAP authentication is disabled if this parameter is empty. (string)\n* `AUTH_LDAP_5_BIND_DN`: DN (Distinguished Name) of user to bind for all search queries. This is the system user account we will use to login to query LDAP for other user information. Refer to the documentation for example syntax. (string)\n* `AUTH_LDAP_5_BIND_PASSWORD`: Password used to bind LDAP user account. (string)\n* `AUTH_LDAP_5_START_TLS`: Whether to enable TLS when the LDAP connection is not using SSL. (boolean)\n* `AUTH_LDAP_5_CONNECTION_OPTIONS`: Additional options to set for the LDAP connection.  LDAP referrals are disabled by default (to prevent certain LDAP queries from hanging with AD). Option names should be strings (e.g. \u0026quot;OPT_REFERRALS\u0026quot;). Refer to https://www.python-ldap.org/doc/html/ldap.html#options for possible options and values that can be set. (nested object)\n* `AUTH_LDAP_5_USER_SEARCH`: LDAP search query to find users.  Any user that matches the given pattern will be able to login to the service.  The user should also be mapped into an organization (as defined in the AUTH_LDAP_ORGANIZATION_MAP setting).  If multiple search queries need to be supported use of \u0026quot;LDAPUnion\u0026quot; is possible. See the documentation for details. (list)\n* `AUTH_LDAP_5_USER_DN_TEMPLATE`: Alternative to user search, if user DNs are all of the same format. This approach is more efficient for user lookups than searching if it is usable in your organizational environment. If this setting has a value it will be used instead of AUTH_LDAP_USER_SEARCH. (string)\n* `AUTH_LDAP_5_USER_ATTR_MAP`: Mapping of LDAP user schema to API user attributes. The default setting is valid for ActiveDirectory but users with other LDAP configurations may need to change the values. Refer to the documentation for additional details. (nested object)\n* `AUTH_LDAP_5_GROUP_SEARCH`: Users are mapped to organizations based on their membership in LDAP groups. This setting defines the LDAP search query to find groups. Unlike the user search, group search does not support LDAPSearchUnion. (list)\n* `AUTH_LDAP_5_GROUP_TYPE`: The group type may need to be changed based on the type of the LDAP server.  Values are listed at: https://django-auth-ldap.readthedocs.io/en/stable/groups.html#types-of-groups (choice)\n    - `PosixGroupType`\n    - `GroupOfNamesType`\n    - `GroupOfUniqueNamesType`\n    - `ActiveDirectoryGroupType`\n    - `OrganizationalRoleGroupType`\n    - `MemberDNGroupType`\n    - `NestedGroupOfNamesType`\n    - `NestedGroupOfUniqueNamesType`\n    - `NestedActiveDirectoryGroupType`\n    - `NestedOrganizationalRoleGroupType`\n    - `NestedMemberDNGroupType`\n    - `PosixUIDGroupType`\n* `AUTH_LDAP_5_GROUP_TYPE_PARAMS`: Key value parameters to send the chosen group type init method. (nested object)\n* `AUTH_LDAP_5_REQUIRE_GROUP`: Group DN required to login. If specified, user must be a member of this group to login via LDAP. If not set, everyone in LDAP that matches the user search will be able to login to the service. Only one require group is supported. (string)\n* `AUTH_LDAP_5_DENY_GROUP`: Group DN denied from login. If specified, user will not be allowed to login if a member of this group.  Only one deny group is supported. (string)\n* `AUTH_LDAP_5_USER_FLAGS_BY_GROUP`: Retrieve users from a given group. At this time, superuser and system auditors are the only groups supported. Refer to the documentation for more detail. (nested object)\n* `AUTH_LDAP_5_ORGANIZATION_MAP`: Mapping between organization admins/users and LDAP groups. This controls which users are placed into which organizations relative to their LDAP group memberships. Configuration details are available in the documentation. (nested object)\n* `AUTH_LDAP_5_TEAM_MAP`: Mapping between team members (users) and LDAP groups. Configuration details are available in the documentation. (nested object)\n\n\n\n\n\n# Update a Setting:\n\nMake a PUT or PATCH request to this resource to update this\nsetting.  The following fields may be modified:\n\n\n* `AUTH_LDAP_SERVER_URI`: URI to connect to LDAP server, such as \u0026quot;ldap://ldap.example.com:389\u0026quot; (non-SSL) or \u0026quot;ldaps://ldap.example.com:636\u0026quot; (SSL). Multiple LDAP servers may be specified by separating with spaces or commas. LDAP authentication is disabled if this parameter is empty. (string, default=`\"\"`)\n* `AUTH_LDAP_BIND_DN`: DN (Distinguished Name) of user to bind for all search queries. This is the system user account we will use to login to query LDAP for other user information. Refer to the documentation for example syntax. (string, default=`\"\"`)\n* `AUTH_LDAP_BIND_PASSWORD`: Password used to bind LDAP user account. (string, default=`\"\"`)\n* `AUTH_LDAP_START_TLS`: Whether to enable TLS when the LDAP connection is not using SSL. (boolean, default=`False`)\n* `AUTH_LDAP_CONNECTION_OPTIONS`: Additional options to set for the LDAP connection.  LDAP referrals are disabled by default (to prevent certain LDAP queries from hanging with AD). Option names should be strings (e.g. \u0026quot;OPT_REFERRALS\u0026quot;). Refer to https://www.python-ldap.org/doc/html/ldap.html#options for possible options and values that can be set. (nested object, default=`{\u0026#x27;OPT_REFERRALS\u0026#x27;: 0, \u0026#x27;OPT_NETWORK_TIMEOUT\u0026#x27;: 30}`)\n* `AUTH_LDAP_USER_SEARCH`: LDAP search query to find users.  Any user that matches the given pattern will be able to login to the service.  The user should also be mapped into an organization (as defined in the AUTH_LDAP_ORGANIZATION_MAP setting).  If multiple search queries need to be supported use of \u0026quot;LDAPUnion\u0026quot; is possible. See the documentation for details. (list, default=`[]`)\n* `AUTH_LDAP_USER_DN_TEMPLATE`: Alternative to user search, if user DNs are all of the same format. This approach is more efficient for user lookups than searching if it is usable in your organizational environment. If this setting has a value it will be used instead of AUTH_LDAP_USER_SEARCH. (string, default=`\"\"`)\n* `AUTH_LDAP_USER_ATTR_MAP`: Mapping of LDAP user schema to API user attributes. The default setting is valid for ActiveDirectory but users with other LDAP configurations may need to change the values. Refer to the documentation for additional details. (nested object, default=`{}`)\n* `AUTH_LDAP_GROUP_SEARCH`: Users are mapped to organizations based on their membership in LDAP groups. This setting defines the LDAP search query to find groups. Unlike the user search, group search does not support LDAPSearchUnion. (list, default=`[]`)\n* `AUTH_LDAP_GROUP_TYPE`: The group type may need to be changed based on the type of the LDAP server.  Values are listed at: https://django-auth-ldap.readthedocs.io/en/stable/groups.html#types-of-groups (choice)\n    - `PosixGroupType`\n    - `GroupOfNamesType`\n    - `GroupOfUniqueNamesType`\n    - `ActiveDirectoryGroupType`\n    - `OrganizationalRoleGroupType`\n    - `MemberDNGroupType` (default)\n    - `NestedGroupOfNamesType`\n    - `NestedGroupOfUniqueNamesType`\n    - `NestedActiveDirectoryGroupType`\n    - `NestedOrganizationalRoleGroupType`\n    - `NestedMemberDNGroupType`\n    - `PosixUIDGroupType`\n* `AUTH_LDAP_GROUP_TYPE_PARAMS`: Key value parameters to send the chosen group type init method. (nested object, default=`OrderedDict([(\u0026#x27;member_attr\u0026#x27;, \u0026#x27;member\u0026#x27;), (\u0026#x27;name_attr\u0026#x27;, \u0026#x27;cn\u0026#x27;)])`)\n* `AUTH_LDAP_REQUIRE_GROUP`: Group DN required to login. If specified, user must be a member of this group to login via LDAP. If not set, everyone in LDAP that matches the user search will be able to login to the service. Only one require group is supported. (string, default=`\"\"`)\n* `AUTH_LDAP_DENY_GROUP`: Group DN denied from login. If specified, user will not be allowed to login if a member of this group.  Only one deny group is supported. (string, default=`\"\"`)\n* `AUTH_LDAP_USER_FLAGS_BY_GROUP`: Retrieve users from a given group. At this time, superuser and system auditors are the only groups supported. Refer to the documentation for more detail. (nested object, default=`{}`)\n* `AUTH_LDAP_ORGANIZATION_MAP`: Mapping between organization admins/users and LDAP groups. This controls which users are placed into which organizations relative to their LDAP group memberships. Configuration details are available in the documentation. (nested object, default=`{}`)\n* `AUTH_LDAP_TEAM_MAP`: Mapping between team members (users) and LDAP groups. Configuration details are available in the documentation. (nested object, default=`{}`)\n* `AUTH_LDAP_1_SERVER_URI`: URI to connect to LDAP server, such as \u0026quot;ldap://ldap.example.com:389\u0026quot; (non-SSL) or \u0026quot;ldaps://ldap.example.com:636\u0026quot; (SSL). Multiple LDAP servers may be specified by separating with spaces or commas. LDAP authentication is disabled if this parameter is empty. (string, default=`\"\"`)\n* `AUTH_LDAP_1_BIND_DN`: DN (Distinguished Name) of user to bind for all search queries. This is the system user account we will use to login to query LDAP for other user information. Refer to the documentation for example syntax. (string, default=`\"\"`)\n* `AUTH_LDAP_1_BIND_PASSWORD`: Password used to bind LDAP user account. (string, default=`\"\"`)\n* `AUTH_LDAP_1_START_TLS`: Whether to enable TLS when the LDAP connection is not using SSL. (boolean, default=`False`)\n* `AUTH_LDAP_1_CONNECTION_OPTIONS`: Additional options to set for the LDAP connection.  LDAP referrals are disabled by default (to prevent certain LDAP queries from hanging with AD). Option names should be strings (e.g. \u0026quot;OPT_REFERRALS\u0026quot;). Refer to https://www.python-ldap.org/doc/html/ldap.html#options for possible options and values that can be set. (nested object, default=`{\u0026#x27;OPT_REFERRALS\u0026#x27;: 0, \u0026#x27;OPT_NETWORK_TIMEOUT\u0026#x27;: 30}`)\n* `AUTH_LDAP_1_USER_SEARCH`: LDAP search query to find users.  Any user that matches the given pattern will be able to login to the service.  The user should also be mapped into an organization (as defined in the AUTH_LDAP_ORGANIZATION_MAP setting).  If multiple search queries need to be supported use of \u0026quot;LDAPUnion\u0026quot; is possible. See the documentation for details. (list, default=`[]`)\n* `AUTH_LDAP_1_USER_DN_TEMPLATE`: Alternative to user search, if user DNs are all of the same format. This approach is more efficient for user lookups than searching if it is usable in your organizational environment. If this setting has a value it will be used instead of AUTH_LDAP_USER_SEARCH. (string, default=`\"\"`)\n* `AUTH_LDAP_1_USER_ATTR_MAP`: Mapping of LDAP user schema to API user attributes. The default setting is valid for ActiveDirectory but users with other LDAP configurations may need to change the values. Refer to the documentation for additional details. (nested object, default=`{}`)\n* `AUTH_LDAP_1_GROUP_SEARCH`: Users are mapped to organizations based on their membership in LDAP groups. This setting defines the LDAP search query to find groups. Unlike the user search, group search does not support LDAPSearchUnion. (list, default=`[]`)\n* `AUTH_LDAP_1_GROUP_TYPE`: The group type may need to be changed based on the type of the LDAP server.  Values are listed at: https://django-auth-ldap.readthedocs.io/en/stable/groups.html#types-of-groups (choice)\n    - `PosixGroupType`\n    - `GroupOfNamesType`\n    - `GroupOfUniqueNamesType`\n    - `ActiveDirectoryGroupType`\n    - `OrganizationalRoleGroupType`\n    - `MemberDNGroupType` (default)\n    - `NestedGroupOfNamesType`\n    - `NestedGroupOfUniqueNamesType`\n    - `NestedActiveDirectoryGroupType`\n    - `NestedOrganizationalRoleGroupType`\n    - `NestedMemberDNGroupType`\n    - `PosixUIDGroupType`\n* `AUTH_LDAP_1_GROUP_TYPE_PARAMS`: Key value parameters to send the chosen group type init method. (nested object, default=`OrderedDict([(\u0026#x27;member_attr\u0026#x27;, \u0026#x27;member\u0026#x27;), (\u0026#x27;name_attr\u0026#x27;, \u0026#x27;cn\u0026#x27;)])`)\n* `AUTH_LDAP_1_REQUIRE_GROUP`: Group DN required to login. If specified, user must be a member of this group to login via LDAP. If not set, everyone in LDAP that matches the user search will be able to login to the service. Only one require group is supported. (string, default=`\"\"`)\n* `AUTH_LDAP_1_DENY_GROUP`: Group DN denied from login. If specified, user will not be allowed to login if a member of this group.  Only one deny group is supported. (string, default=`\"\"`)\n* `AUTH_LDAP_1_USER_FLAGS_BY_GROUP`: Retrieve users from a given group. At this time, superuser and system auditors are the only groups supported. Refer to the documentation for more detail. (nested object, default=`{}`)\n* `AUTH_LDAP_1_ORGANIZATION_MAP`: Mapping between organization admins/users and LDAP groups. This controls which users are placed into which organizations relative to their LDAP group memberships. Configuration details are available in the documentation. (nested object, default=`{}`)\n* `AUTH_LDAP_1_TEAM_MAP`: Mapping between team members (users) and LDAP groups. Configuration details are available in the documentation. (nested object, default=`{}`)\n* `AUTH_LDAP_2_SERVER_URI`: URI to connect to LDAP server, such as \u0026quot;ldap://ldap.example.com:389\u0026quot; (non-SSL) or \u0026quot;ldaps://ldap.example.com:636\u0026quot; (SSL). Multiple LDAP servers may be specified by separating with spaces or commas. LDAP authentication is disabled if this parameter is empty. (string, default=`\"\"`)\n* `AUTH_LDAP_2_BIND_DN`: DN (Distinguished Name) of user to bind for all search queries. This is the system user account we will use to login to query LDAP for other user information. Refer to the documentation for example syntax. (string, default=`\"\"`)\n* `AUTH_LDAP_2_BIND_PASSWORD`: Password used to bind LDAP user account. (string, default=`\"\"`)\n* `AUTH_LDAP_2_START_TLS`: Whether to enable TLS when the LDAP connection is not using SSL. (boolean, default=`False`)\n* `AUTH_LDAP_2_CONNECTION_OPTIONS`: Additional options to set for the LDAP connection.  LDAP referrals are disabled by default (to prevent certain LDAP queries from hanging with AD). Option names should be strings (e.g. \u0026quot;OPT_REFERRALS\u0026quot;). Refer to https://www.python-ldap.org/doc/html/ldap.html#options for possible options and values that can be set. (nested object, default=`{\u0026#x27;OPT_REFERRALS\u0026#x27;: 0, \u0026#x27;OPT_NETWORK_TIMEOUT\u0026#x27;: 30}`)\n* `AUTH_LDAP_2_USER_SEARCH`: LDAP search query to find users.  Any user that matches the given pattern will be able to login to the service.  The user should also be mapped into an organization (as defined in the AUTH_LDAP_ORGANIZATION_MAP setting).  If multiple search queries need to be supported use of \u0026quot;LDAPUnion\u0026quot; is possible. See the documentation for details. (list, default=`[]`)\n* `AUTH_LDAP_2_USER_DN_TEMPLATE`: Alternative to user search, if user DNs are all of the same format. This approach is more efficient for user lookups than searching if it is usable in your organizational environment. If this setting has a value it will be used instead of AUTH_LDAP_USER_SEARCH. (string, default=`\"\"`)\n* `AUTH_LDAP_2_USER_ATTR_MAP`: Mapping of LDAP user schema to API user attributes. The default setting is valid for ActiveDirectory but users with other LDAP configurations may need to change the values. Refer to the documentation for additional details. (nested object, default=`{}`)\n* `AUTH_LDAP_2_GROUP_SEARCH`: Users are mapped to organizations based on their membership in LDAP groups. This setting defines the LDAP search query to find groups. Unlike the user search, group search does not support LDAPSearchUnion. (list, default=`[]`)\n* `AUTH_LDAP_2_GROUP_TYPE`: The group type may need to be changed based on the type of the LDAP server.  Values are listed at: https://django-auth-ldap.readthedocs.io/en/stable/groups.html#types-of-groups (choice)\n    - `PosixGroupType`\n    - `GroupOfNamesType`\n    - `GroupOfUniqueNamesType`\n    - `ActiveDirectoryGroupType`\n    - `OrganizationalRoleGroupType`\n    - `MemberDNGroupType` (default)\n    - `NestedGroupOfNamesType`\n    - `NestedGroupOfUniqueNamesType`\n    - `NestedActiveDirectoryGroupType`\n    - `NestedOrganizationalRoleGroupType`\n    - `NestedMemberDNGroupType`\n    - `PosixUIDGroupType`\n* `AUTH_LDAP_2_GROUP_TYPE_PARAMS`: Key value parameters to send the chosen group type init method. (nested object, default=`OrderedDict([(\u0026#x27;member_attr\u0026#x27;, \u0026#x27;member\u0026#x27;), (\u0026#x27;name_attr\u0026#x27;, \u0026#x27;cn\u0026#x27;)])`)\n* `AUTH_LDAP_2_REQUIRE_GROUP`: Group DN required to login. If specified, user must be a member of this group to login via LDAP. If not set, everyone in LDAP that matches the user search will be able to login to the service. Only one require group is supported. (string, default=`\"\"`)\n* `AUTH_LDAP_2_DENY_GROUP`: Group DN denied from login. If specified, user will not be allowed to login if a member of this group.  Only one deny group is supported. (string, default=`\"\"`)\n* `AUTH_LDAP_2_USER_FLAGS_BY_GROUP`: Retrieve users from a given group. At this time, superuser and system auditors are the only groups supported. Refer to the documentation for more detail. (nested object, default=`{}`)\n* `AUTH_LDAP_2_ORGANIZATION_MAP`: Mapping between organization admins/users and LDAP groups. This controls which users are placed into which organizations relative to their LDAP group memberships. Configuration details are available in the documentation. (nested object, default=`{}`)\n* `AUTH_LDAP_2_TEAM_MAP`: Mapping between team members (users) and LDAP groups. Configuration details are available in the documentation. (nested object, default=`{}`)\n* `AUTH_LDAP_3_SERVER_URI`: URI to connect to LDAP server, such as \u0026quot;ldap://ldap.example.com:389\u0026quot; (non-SSL) or \u0026quot;ldaps://ldap.example.com:636\u0026quot; (SSL). Multiple LDAP servers may be specified by separating with spaces or commas. LDAP authentication is disabled if this parameter is empty. (string, default=`\"\"`)\n* `AUTH_LDAP_3_BIND_DN`: DN (Distinguished Name) of user to bind for all search queries. This is the system user account we will use to login to query LDAP for other user information. Refer to the documentation for example syntax. (string, default=`\"\"`)\n* `AUTH_LDAP_3_BIND_PASSWORD`: Password used to bind LDAP user account. (string, default=`\"\"`)\n* `AUTH_LDAP_3_START_TLS`: Whether to enable TLS when the LDAP connection is not using SSL. (boolean, default=`False`)\n* `AUTH_LDAP_3_CONNECTION_OPTIONS`: Additional options to set for the LDAP connection.  LDAP referrals are disabled by default (to prevent certain LDAP queries from hanging with AD). Option names should be strings (e.g. \u0026quot;OPT_REFERRALS\u0026quot;). Refer to https://www.python-ldap.org/doc/html/ldap.html#options for possible options and values that can be set. (nested object, default=`{\u0026#x27;OPT_REFERRALS\u0026#x27;: 0, \u0026#x27;OPT_NETWORK_TIMEOUT\u0026#x27;: 30}`)\n* `AUTH_LDAP_3_USER_SEARCH`: LDAP search query to find users.  Any user that matches the given pattern will be able to login to the service.  The user should also be mapped into an organization (as defined in the AUTH_LDAP_ORGANIZATION_MAP setting).  If multiple search queries need to be supported use of \u0026quot;LDAPUnion\u0026quot; is possible. See the documentation for details. (list, default=`[]`)\n* `AUTH_LDAP_3_USER_DN_TEMPLATE`: Alternative to user search, if user DNs are all of the same format. This approach is more efficient for user lookups than searching if it is usable in your organizational environment. If this setting has a value it will be used instead of AUTH_LDAP_USER_SEARCH. (string, default=`\"\"`)\n* `AUTH_LDAP_3_USER_ATTR_MAP`: Mapping of LDAP user schema to API user attributes. The default setting is valid for ActiveDirectory but users with other LDAP configurations may need to change the values. Refer to the documentation for additional details. (nested object, default=`{}`)\n* `AUTH_LDAP_3_GROUP_SEARCH`: Users are mapped to organizations based on their membership in LDAP groups. This setting defines the LDAP search query to find groups. Unlike the user search, group search does not support LDAPSearchUnion. (list, default=`[]`)\n* `AUTH_LDAP_3_GROUP_TYPE`: The group type may need to be changed based on the type of the LDAP server.  Values are listed at: https://django-auth-ldap.readthedocs.io/en/stable/groups.html#types-of-groups (choice)\n    - `PosixGroupType`\n    - `GroupOfNamesType`\n    - `GroupOfUniqueNamesType`\n    - `ActiveDirectoryGroupType`\n    - `OrganizationalRoleGroupType`\n    - `MemberDNGroupType` (default)\n    - `NestedGroupOfNamesType`\n    - `NestedGroupOfUniqueNamesType`\n    - `NestedActiveDirectoryGroupType`\n    - `NestedOrganizationalRoleGroupType`\n    - `NestedMemberDNGroupType`\n    - `PosixUIDGroupType`\n* `AUTH_LDAP_3_GROUP_TYPE_PARAMS`: Key value parameters to send the chosen group type init method. (nested object, default=`OrderedDict([(\u0026#x27;member_attr\u0026#x27;, \u0026#x27;member\u0026#x27;), (\u0026#x27;name_attr\u0026#x27;, \u0026#x27;cn\u0026#x27;)])`)\n* `AUTH_LDAP_3_REQUIRE_GROUP`: Group DN required to login. If specified, user must be a member of this group to login via LDAP. If not set, everyone in LDAP that matches the user search will be able to login to the service. Only one require group is supported. (string, default=`\"\"`)\n* `AUTH_LDAP_3_DENY_GROUP`: Group DN denied from login. If specified, user will not be allowed to login if a member of this group.  Only one deny group is supported. (string, default=`\"\"`)\n* `AUTH_LDAP_3_USER_FLAGS_BY_GROUP`: Retrieve users from a given group. At this time, superuser and system auditors are the only groups supported. Refer to the documentation for more detail. (nested object, default=`{}`)\n* `AUTH_LDAP_3_ORGANIZATION_MAP`: Mapping between organization admins/users and LDAP groups. This controls which users are placed into which organizations relative to their LDAP group memberships. Configuration details are available in the documentation. (nested object, default=`{}`)\n* `AUTH_LDAP_3_TEAM_MAP`: Mapping between team members (users) and LDAP groups. Configuration details are available in the documentation. (nested object, default=`{}`)\n* `AUTH_LDAP_4_SERVER_URI`: URI to connect to LDAP server, such as \u0026quot;ldap://ldap.example.com:389\u0026quot; (non-SSL) or \u0026quot;ldaps://ldap.example.com:636\u0026quot; (SSL). Multiple LDAP servers may be specified by separating with spaces or commas. LDAP authentication is disabled if this parameter is empty. (string, default=`\"\"`)\n* `AUTH_LDAP_4_BIND_DN`: DN (Distinguished Name) of user to bind for all search queries. This is the system user account we will use to login to query LDAP for other user information. Refer to the documentation for example syntax. (string, default=`\"\"`)\n* `AUTH_LDAP_4_BIND_PASSWORD`: Password used to bind LDAP user account. (string, default=`\"\"`)\n* `AUTH_LDAP_4_START_TLS`: Whether to enable TLS when the LDAP connection is not using SSL. (boolean, default=`False`)\n* `AUTH_LDAP_4_CONNECTION_OPTIONS`: Additional options to set for the LDAP connection.  LDAP referrals are disabled by default (to prevent certain LDAP queries from hanging with AD). Option names should be strings (e.g. \u0026quot;OPT_REFERRALS\u0026quot;). Refer to https://www.python-ldap.org/doc/html/ldap.html#options for possible options and values that can be set. (nested object, default=`{\u0026#x27;OPT_REFERRALS\u0026#x27;: 0, \u0026#x27;OPT_NETWORK_TIMEOUT\u0026#x27;: 30}`)\n* `AUTH_LDAP_4_USER_SEARCH`: LDAP search query to find users.  Any user that matches the given pattern will be able to login to the service.  The user should also be mapped into an organization (as defined in the AUTH_LDAP_ORGANIZATION_MAP setting).  If multiple search queries need to be supported use of \u0026quot;LDAPUnion\u0026quot; is possible. See the documentation for details. (list, default=`[]`)\n* `AUTH_LDAP_4_USER_DN_TEMPLATE`: Alternative to user search, if user DNs are all of the same format. This approach is more efficient for user lookups than searching if it is usable in your organizational environment. If this setting has a value it will be used instead of AUTH_LDAP_USER_SEARCH. (string, default=`\"\"`)\n* `AUTH_LDAP_4_USER_ATTR_MAP`: Mapping of LDAP user schema to API user attributes. The default setting is valid for ActiveDirectory but users with other LDAP configurations may need to change the values. Refer to the documentation for additional details. (nested object, default=`{}`)\n* `AUTH_LDAP_4_GROUP_SEARCH`: Users are mapped to organizations based on their membership in LDAP groups. This setting defines the LDAP search query to find groups. Unlike the user search, group search does not support LDAPSearchUnion. (list, default=`[]`)\n* `AUTH_LDAP_4_GROUP_TYPE`: The group type may need to be changed based on the type of the LDAP server.  Values are listed at: https://django-auth-ldap.readthedocs.io/en/stable/groups.html#types-of-groups (choice)\n    - `PosixGroupType`\n    - `GroupOfNamesType`\n    - `GroupOfUniqueNamesType`\n    - `ActiveDirectoryGroupType`\n    - `OrganizationalRoleGroupType`\n    - `MemberDNGroupType` (default)\n    - `NestedGroupOfNamesType`\n    - `NestedGroupOfUniqueNamesType`\n    - `NestedActiveDirectoryGroupType`\n    - `NestedOrganizationalRoleGroupType`\n    - `NestedMemberDNGroupType`\n    - `PosixUIDGroupType`\n* `AUTH_LDAP_4_GROUP_TYPE_PARAMS`: Key value parameters to send the chosen group type init method. (nested object, default=`OrderedDict([(\u0026#x27;member_attr\u0026#x27;, \u0026#x27;member\u0026#x27;), (\u0026#x27;name_attr\u0026#x27;, \u0026#x27;cn\u0026#x27;)])`)\n* `AUTH_LDAP_4_REQUIRE_GROUP`: Group DN required to login. If specified, user must be a member of this group to login via LDAP. If not set, everyone in LDAP that matches the user search will be able to login to the service. Only one require group is supported. (string, default=`\"\"`)\n* `AUTH_LDAP_4_DENY_GROUP`: Group DN denied from login. If specified, user will not be allowed to login if a member of this group.  Only one deny group is supported. (string, default=`\"\"`)\n* `AUTH_LDAP_4_USER_FLAGS_BY_GROUP`: Retrieve users from a given group. At this time, superuser and system auditors are the only groups supported. Refer to the documentation for more detail. (nested object, default=`{}`)\n* `AUTH_LDAP_4_ORGANIZATION_MAP`: Mapping between organization admins/users and LDAP groups. This controls which users are placed into which organizations relative to their LDAP group memberships. Configuration details are available in the documentation. (nested object, default=`{}`)\n* `AUTH_LDAP_4_TEAM_MAP`: Mapping between team members (users) and LDAP groups. Configuration details are available in the documentation. (nested object, default=`{}`)\n* `AUTH_LDAP_5_SERVER_URI`: URI to connect to LDAP server, such as \u0026quot;ldap://ldap.example.com:389\u0026quot; (non-SSL) or \u0026quot;ldaps://ldap.example.com:636\u0026quot; (SSL). Multiple LDAP servers may be specified by separating with spaces or commas. LDAP authentication is disabled if this parameter is empty. (string, default=`\"\"`)\n* `AUTH_LDAP_5_BIND_DN`: DN (Distinguished Name) of user to bind for all search queries. This is the system user account we will use to login to query LDAP for other user information. Refer to the documentation for example syntax. (string, default=`\"\"`)\n* `AUTH_LDAP_5_BIND_PASSWORD`: Password used to bind LDAP user account. (string, default=`\"\"`)\n* `AUTH_LDAP_5_START_TLS`: Whether to enable TLS when the LDAP connection is not using SSL. (boolean, default=`False`)\n* `AUTH_LDAP_5_CONNECTION_OPTIONS`: Additional options to set for the LDAP connection.  LDAP referrals are disabled by default (to prevent certain LDAP queries from hanging with AD). Option names should be strings (e.g. \u0026quot;OPT_REFERRALS\u0026quot;). Refer to https://www.python-ldap.org/doc/html/ldap.html#options for possible options and values that can be set. (nested object, default=`{\u0026#x27;OPT_REFERRALS\u0026#x27;: 0, \u0026#x27;OPT_NETWORK_TIMEOUT\u0026#x27;: 30}`)\n* `AUTH_LDAP_5_USER_SEARCH`: LDAP search query to find users.  Any user that matches the given pattern will be able to login to the service.  The user should also be mapped into an organization (as defined in the AUTH_LDAP_ORGANIZATION_MAP setting).  If multiple search queries need to be supported use of \u0026quot;LDAPUnion\u0026quot; is possible. See the documentation for details. (list, default=`[]`)\n* `AUTH_LDAP_5_USER_DN_TEMPLATE`: Alternative to user search, if user DNs are all of the same format. This approach is more efficient for user lookups than searching if it is usable in your organizational environment. If this setting has a value it will be used instead of AUTH_LDAP_USER_SEARCH. (string, default=`\"\"`)\n* `AUTH_LDAP_5_USER_ATTR_MAP`: Mapping of LDAP user schema to API user attributes. The default setting is valid for ActiveDirectory but users with other LDAP configurations may need to change the values. Refer to the documentation for additional details. (nested object, default=`{}`)\n* `AUTH_LDAP_5_GROUP_SEARCH`: Users are mapped to organizations based on their membership in LDAP groups. This setting defines the LDAP search query to find groups. Unlike the user search, group search does not support LDAPSearchUnion. (list, default=`[]`)\n* `AUTH_LDAP_5_GROUP_TYPE`: The group type may need to be changed based on the type of the LDAP server.  Values are listed at: https://django-auth-ldap.readthedocs.io/en/stable/groups.html#types-of-groups (choice)\n    - `PosixGroupType`\n    - `GroupOfNamesType`\n    - `GroupOfUniqueNamesType`\n    - `ActiveDirectoryGroupType`\n    - `OrganizationalRoleGroupType`\n    - `MemberDNGroupType` (default)\n    - `NestedGroupOfNamesType`\n    - `NestedGroupOfUniqueNamesType`\n    - `NestedActiveDirectoryGroupType`\n    - `NestedOrganizationalRoleGroupType`\n    - `NestedMemberDNGroupType`\n    - `PosixUIDGroupType`\n* `AUTH_LDAP_5_GROUP_TYPE_PARAMS`: Key value parameters to send the chosen group type init method. (nested object, default=`OrderedDict([(\u0026#x27;member_attr\u0026#x27;, \u0026#x27;member\u0026#x27;), (\u0026#x27;name_attr\u0026#x27;, \u0026#x27;cn\u0026#x27;)])`)\n* `AUTH_LDAP_5_REQUIRE_GROUP`: Group DN required to login. If specified, user must be a member of this group to login via LDAP. If not set, everyone in LDAP that matches the user search will be able to login to the service. Only one require group is supported. (string, default=`\"\"`)\n* `AUTH_LDAP_5_DENY_GROUP`: Group DN denied from login. If specified, user will not be allowed to login if a member of this group.  Only one deny group is supported. (string, default=`\"\"`)\n* `AUTH_LDAP_5_USER_FLAGS_BY_GROUP`: Retrieve users from a given group. At this time, superuser and system auditors are the only groups supported. Refer to the documentation for more detail. (nested object, default=`{}`)\n* `AUTH_LDAP_5_ORGANIZATION_MAP`: Mapping between organization admins/users and LDAP groups. This controls which users are placed into which organizations relative to their LDAP group memberships. Configuration details are available in the documentation. (nested object, default=`{}`)\n* `AUTH_LDAP_5_TEAM_MAP`: Mapping between team members (users) and LDAP groups. Configuration details are available in the documentation. (nested object, default=`{}`)\n\n\n\n\n\n\nFor a PUT request, include **all** fields in the request.\n\n\n\nFor a PATCH request, include only the fields that are being modified.\n\n\n\n# Delete a Setting:\n\nMake a DELETE request to this resource to delete this setting.",
  "Endpoint": "/api/v2/settings/ldap/",
  "Name": "SettingsAuthLDAP",
  "PackageName": "awx",
  "PropertyGetData": {
    "AUTH_LDAP_1_BIND_DN": {
      "category": "LDAP",
      "category_slug": "ldap",
      "computed": true,
      "defined_in_file": false,
      "help_text": "DN (Distinguished Name) of user to bind for all search queries. This is the system user account we will use to login to query LDAP for other user information. Refer to the documentation for example syntax.",
      "label": "LDAP Bind DN",
      "name": "AUTH_LDAP_1_BIND_DN",
      "required": false,
      "sensitive": false,
      "type": "string"
    },
    "AUTH_LDAP_1_BIND_PASSWORD": {
      "category": "LDAP",
      "category_slug": "ldap",
      "computed": true,
      "defined_in_file": false,
      "help_text": "Password used to bind LDAP user account.",
      "label": "LDAP Bind Password",
      "name": "AUTH_LDAP_1_BIND_PASSWORD",
      "required": false,
      "sensitive": true,
      "type": "string"
    },
    "AUTH_LDAP_1_CONNECTION_OPTIONS": {
      "category": "LDAP",
      "category_slug": "ldap",
      "child": {
        "type": "field"
      },
      "computed": true,
      "defined_in_file": false,
      "element_type": "string",
      "help_text": "Additional options to set for the LDAP connection.  LDAP referrals are disabled by default (to prevent certain LDAP queries from hanging with AD). Option names should be strings (e.g. \"OPT_REFERRALS\"). Refer to https://www.python-ldap.org/doc/html/ldap.html#options for possible options and values that can be set.",
      "label": "LDAP Connection Options",
      "name": "AUTH_LDAP_1_CONNECTION_OPTIONS",
      "required": false,
      "sensitive": false,
      "type": "json"
    },
    "AUTH_LDAP_1_DENY_GROUP": {
      "category": "LDAP",
      "category_slug": "ldap",
      "computed": true,
      "defined_in_file": false,
      "help_text": "Group DN denied from login. If specified, user will not be allowed to login if a member of this group.  Only one deny group is supported.",
      "label": "LDAP Deny Group",
      "name": "AUTH_LDAP_1_DENY_GROUP",
      "required": false,
      "sensitive": false,
      "type": "string"
    },
    "AUTH_LDAP_1_GROUP_SEARCH": {
      "category": "LDAP",
      "category_slug": "ldap",
      "child": {
        "type": "field"
      },
      "computed": true,
      "defined_in_file": false,
      "element_type": "string",
      "help_text": "Users are mapped to organizations based on their membership in LDAP groups. This setting defines the LDAP search query to find groups. Unlike the user search, group search does not support LDAPSearchUnion.",
      "label": "LDAP Group Search",
      "name": "AUTH_LDAP_1_GROUP_SEARCH",
      "required": false,
      "sensitive": false,
      "type": "list"
    },
    "AUTH_LDAP_1_GROUP_TYPE": {
      "category": "LDAP",
      "category_slug": "ldap",
      "choices": [
        [
          "PosixGroupType",
          "PosixGroupType"
        ],
        [
          "GroupOfNamesType",
          "GroupOfNamesType"
        ],
        [
          "GroupOfUniqueNamesType",
          "GroupOfUniqueNamesType"
        ],
        [
          "ActiveDirectoryGroupType",
          "ActiveDirectoryGroupType"
        ],
        [
          "OrganizationalRoleGroupType",
          "OrganizationalRoleGroupType"
        ],
        [
          "MemberDNGroupType",
          "MemberDNGroupType"
        ],
        [
          "NestedGroupOfNamesType",
          "NestedGroupOfNamesType"
        ],
        [
          "NestedGroupOfUniqueNamesType",
          "NestedGroupOfUniqueNamesType"
        ],
        [
          "NestedActiveDirectoryGroupType",
          "NestedActiveDirectoryGroupType"
        ],
        [
          "NestedOrganizationalRoleGroupType",
          "NestedOrganizationalRoleGroupType"
        ],
        [
          "NestedMemberDNGroupType",
          "NestedMemberDNGroupType"
        ],
        [
          "PosixUIDGroupType",
          "PosixUIDGroupType"
        ]
      ],
      "computed": true,
      "defined_in_file": false,
      "help_text": "The group type may need to be changed based on the type of the LDAP server.  Values are listed at: https://django-auth-ldap.readthedocs.io/en/stable/groups.html#types-of-groups",
      "label": "LDAP Group Type",
      "name": "AUTH_LDAP_1_GROUP_TYPE",
      "required": false,
      "sensitive": false,
      "type": "choice"
    },
    "AUTH_LDAP_1_GROUP_TYPE_PARAMS": {
      "category": "LDAP",
      "category_slug": "ldap",
      "child": {
        "type": "field"
      },
      "computed": true,
      "defined_in_file": false,
      "element_type": "string",
      "help_text": "Key value parameters to send the chosen group type init method.",
      "label": "LDAP Group Type Parameters",
      "name": "AUTH_LDAP_1_GROUP_TYPE_PARAMS",
      "required": false,
      "sensitive": false,
      "type": "json"
    },
    "AUTH_LDAP_1_ORGANIZATION_MAP": {
      "category": "LDAP",
      "category_slug": "ldap",
      "child": {
        "child": {
          "read_only": false,
          "required": true,
          "type": "field"
        },
        "type": "nested object"
      },
      "computed": true,
      "defined_in_file": false,
      "element_type": "nested object",
      "help_text": "Mapping between organization admins/users and LDAP groups. This controls which users are placed into which organizations relative to their LDAP group memberships. Configuration details are available in the documentation.",
      "label": "LDAP Organization Map",
      "name": "AUTH_LDAP_1_ORGANIZATION_MAP",
      "required": false,
      "sensitive": false,
      "type": "json"
    },
    "AUTH_LDAP_1_REQUIRE_GROUP": {
      "category": "LDAP",
      "category_slug": "ldap",
      "computed": true,
      "defined_in_file": false,
      "help_text": "Group DN required to login. If specified, user must be a member of this group to login via LDAP. If not set, everyone in LDAP that matches the user search will be able to login to the service. Only one require group is supported.",
      "label": "LDAP Require Group",
      "name": "AUTH_LDAP_1_REQUIRE_GROUP",
      "required": false,
      "sensitive": false,
      "type": "string"
    },
    "AUTH_LDAP_1_SERVER_URI": {
      "category": "LDAP",
      "category_slug": "ldap",
      "computed": true,
      "defined_in_file": false,
      "help_text": "URI to connect to LDAP server, such as \"ldap://ldap.example.com:389\" (non-SSL) or \"ldaps://ldap.example.com:636\" (SSL). Multiple LDAP servers may be specified by separating with spaces or commas. LDAP authentication is disabled if this parameter is empty.",
      "label": "LDAP Server URI",
      "name": "AUTH_LDAP_1_SERVER_URI",
      "required": false,
      "sensitive": false,
      "type": "string"
    },
    "AUTH_LDAP_1_START_TLS": {
      "category": "LDAP",
      "category_slug": "ldap",
      "computed": true,
      "defined_in_file": false,
      "help_text": "Whether to enable TLS when the LDAP connection is not using SSL.",
      "label": "LDAP Start TLS",
      "name": "AUTH_LDAP_1_START_TLS",
      "required": false,
      "sensitive": false,
      "type": "boolean"
    },
    "AUTH_LDAP_1_TEAM_MAP": {
      "category": "LDAP",
      "category_slug": "ldap",
      "child": {
        "child": {
          "read_only": false,
          "required": true,
          "type": "field"
        },
        "type": "nested object"
      },
      "computed": true,
      "defined_in_file": false,
      "element_type": "nested object",
      "help_text": "Mapping between team members (users) and LDAP groups. Configuration details are available in the documentation.",
      "label": "LDAP Team Map",
      "name": "AUTH_LDAP_1_TEAM_MAP",
      "required": false,
      "sensitive": false,
      "type": "json"
    },
    "AUTH_LDAP_1_USER_ATTR_MAP": {
      "category": "LDAP",
      "category_slug": "ldap",
      "child": {
        "type": "string"
      },
      "computed": true,
      "defined_in_file": false,
      "element_type": "string",
      "help_text": "Mapping of LDAP user schema to API user attributes. The default setting is valid for ActiveDirectory but users with other LDAP configurations may need to change the values. Refer to the documentation for additional details.",
      "label": "LDAP User Attribute Map",
      "name": "AUTH_LDAP_1_USER_ATTR_MAP",
      "required": false,
      "sensitive": false,
      "type": "json"
    },
    "AUTH_LDAP_1_USER_DN_TEMPLATE": {
      "category": "LDAP",
      "category_slug": "ldap",
      "computed": true,
      "defined_in_file": false,
      "help_text": "Alternative to user search, if user DNs are all of the same format. This approach is more efficient for user lookups than searching if it is usable in your organizational environment. If this setting has a value it will be used instead of AUTH_LDAP_USER_SEARCH.",
      "label": "LDAP User DN Template",
      "name": "AUTH_LDAP_1_USER_DN_TEMPLATE",
      "required": false,
      "sensitive": false,
      "type": "string"
    },
    "AUTH_LDAP_1_USER_FLAGS_BY_GROUP": {
      "category": "LDAP",
      "category_slug": "ldap",
      "child": {
        "child": {
          "read_only": false,
          "required": true,
          "type": "string"
        },
        "type": "list"
      },
      "computed": true,
      "defined_in_file": false,
      "element_type": "list",
      "help_text": "Retrieve users from a given group. At this time, superuser and system auditors are the only groups supported. Refer to the documentation for more detail.",
      "label": "LDAP User Flags By Group",
      "name": "AUTH_LDAP_1_USER_FLAGS_BY_GROUP",
      "required": false,
      "sensitive": false,
      "type": "json"
    },
    "AUTH_LDAP_1_USER_SEARCH": {
      "category": "LDAP",
      "category_slug": "ldap",
      "child": {
        "type": "field"
      },
      "computed": true,
      "defined_in_file": false,
      "element_type": "string",
      "help_text": "LDAP search query to find users.  Any user that matches the given pattern will be able to login to the service.  The user should also be mapped into an organization (as defined in the AUTH_LDAP_ORGANIZATION_MAP setting).  If multiple search queries need to be supported use of \"LDAPUnion\" is possible. See the documentation for details.",
      "label": "LDAP User Search",
      "name": "AUTH_LDAP_1_USER_SEARCH",
      "required": false,
      "sensitive": false,
      "type": "list"
    },
    "AUTH_LDAP_2_BIND_DN": {
      "category": "LDAP",
      "category_slug": "ldap",
      "computed": true,
      "defined_in_file": false,
      "help_text": "DN (Distinguished Name) of user to bind for all search queries. This is the system user account we will use to login to query LDAP for other user information. Refer to the documentation for example syntax.",
      "label": "LDAP Bind DN",
      "name": "AUTH_LDAP_2_BIND_DN",
      "required": false,
      "sensitive": false,
      "type": "string"
    },
    "AUTH_LDAP_2_BIND_PASSWORD": {
      "category": "LDAP",
      "category_slug": "ldap",
      "computed": true,
      "defined_in_file": false,
      "help_text": "Password used to bind LDAP user account.",
      "label": "LDAP Bind Password",
      "name": "AUTH_LDAP_2_BIND_PASSWORD",
      "required": false,
      "sensitive": true,
      "type": "string"
    },
    "AUTH_LDAP_2_CONNECTION_OPTIONS": {
      "category": "LDAP",
      "category_slug": "ldap",
      "child": {
        "type": "field"
      },
      "computed": true,
      "defined_in_file": false,
      "element_type": "string",
      "help_text": "Additional options to set for the LDAP connection.  LDAP referrals are disabled by default (to prevent certain LDAP queries from hanging with AD). Option names should be strings (e.g. \"OPT_REFERRALS\"). Refer to https://www.python-ldap.org/doc/html/ldap.html#options for possible options and values that can be set.",
      "label": "LDAP Connection Options",
      "name": "AUTH_LDAP_2_CONNECTION_OPTIONS",
      "required": false,
      "sensitive": false,
      "type": "json"
    },
    "AUTH_LDAP_2_DENY_GROUP": {
      "category": "LDAP",
      "category_slug": "ldap",
      "computed": true,
      "defined_in_file": false,
      "help_text": "Group DN denied from login. If specified, user will not be allowed to login if a member of this group.  Only one deny group is supported.",
      "label": "LDAP Deny Group",
      "name": "AUTH_LDAP_2_DENY_GROUP",
      "required": false,
      "sensitive": false,
      "type": "string"
    },
    "AUTH_LDAP_2_GROUP_SEARCH": {
      "category": "LDAP",
      "category_slug": "ldap",
      "child": {
        "type": "field"
      },
      "computed": true,
      "defined_in_file": false,
      "element_type": "string",
      "help_text": "Users are mapped to organizations based on their membership in LDAP groups. This setting defines the LDAP search query to find groups. Unlike the user search, group search does not support LDAPSearchUnion.",
      "label": "LDAP Group Search",
      "name": "AUTH_LDAP_2_GROUP_SEARCH",
      "required": false,
      "sensitive": false,
      "type": "list"
    },
    "AUTH_LDAP_2_GROUP_TYPE": {
      "category": "LDAP",
      "category_slug": "ldap",
      "choices": [
        [
          "PosixGroupType",
          "PosixGroupType"
        ],
        [
          "GroupOfNamesType",
          "GroupOfNamesType"
        ],
        [
          "GroupOfUniqueNamesType",
          "GroupOfUniqueNamesType"
        ],
        [
          "ActiveDirectoryGroupType",
          "ActiveDirectoryGroupType"
        ],
        [
          "OrganizationalRoleGroupType",
          "OrganizationalRoleGroupType"
        ],
        [
          "MemberDNGroupType",
          "MemberDNGroupType"
        ],
        [
          "NestedGroupOfNamesType",
          "NestedGroupOfNamesType"
        ],
        [
          "NestedGroupOfUniqueNamesType",
          "NestedGroupOfUniqueNamesType"
        ],
        [
          "NestedActiveDirectoryGroupType",
          "NestedActiveDirectoryGroupType"
        ],
        [
          "NestedOrganizationalRoleGroupType",
          "NestedOrganizationalRoleGroupType"
        ],
        [
          "NestedMemberDNGroupType",
          "NestedMemberDNGroupType"
        ],
        [
          "PosixUIDGroupType",
          "PosixUIDGroupType"
        ]
      ],
      "computed": true,
      "defined_in_file": false,
      "help_text": "The group type may need to be changed based on the type of the LDAP server.  Values are listed at: https://django-auth-ldap.readthedocs.io/en/stable/groups.html#types-of-groups",
      "label": "LDAP Group Type",
      "name": "AUTH_LDAP_2_GROUP_TYPE",
      "required": false,
      "sensitive": false,
      "type": "choice"
    },
    "AUTH_LDAP_2_GROUP_TYPE_PARAMS": {
      "category": "LDAP",
      "category_slug": "ldap",
      "child": {
        "type": "field"
      },
      "computed": true,
      "defined_in_file": false,
      "element_type": "string",
      "help_text": "Key value parameters to send the chosen group type init method.",
      "label": "LDAP Group Type Parameters",
      "name": "AUTH_LDAP_2_GROUP_TYPE_PARAMS",
      "required": false,
      "sensitive": false,
      "type": "json"
    },
    "AUTH_LDAP_2_ORGANIZATION_MAP": {
      "category": "LDAP",
      "category_slug": "ldap",
      "child": {
        "child": {
          "read_only": false,
          "required": true,
          "type": "field"
        },
        "type": "nested object"
      },
      "computed": true,
      "defined_in_file": false,
      "element_type": "nested object",
      "help_text": "Mapping between organization admins/users and LDAP groups. This controls which users are placed into which organizations relative to their LDAP group memberships. Configuration details are available in the documentation.",
      "label": "LDAP Organization Map",
      "name": "AUTH_LDAP_2_ORGANIZATION_MAP",
      "required": false,
      "sensitive": false,
      "type": "json"
    },
    "AUTH_LDAP_2_REQUIRE_GROUP": {
      "category": "LDAP",
      "category_slug": "ldap",
      "computed": true,
      "defined_in_file": false,
      "help_text": "Group DN required to login. If specified, user must be a member of this group to login via LDAP. If not set, everyone in LDAP that matches the user search will be able to login to the service. Only one require group is supported.",
      "label": "LDAP Require Group",
      "name": "AUTH_LDAP_2_REQUIRE_GROUP",
      "required": false,
      "sensitive": false,
      "type": "string"
    },
    "AUTH_LDAP_2_SERVER_URI": {
      "category": "LDAP",
      "category_slug": "ldap",
      "computed": true,
      "defined_in_file": false,
      "help_text": "URI to connect to LDAP server, such as \"ldap://ldap.example.com:389\" (non-SSL) or \"ldaps://ldap.example.com:636\" (SSL). Multiple LDAP servers may be specified by separating with spaces or commas. LDAP authentication is disabled if this parameter is empty.",
      "label": "LDAP Server URI",
      "name": "AUTH_LDAP_2_SERVER_URI",
      "required": false,
      "sensitive": false,
      "type": "string"
    },
    "AUTH_LDAP_2_START_TLS": {
      "category": "LDAP",
      "category_slug": "ldap",
      "computed": true,
      "defined_in_file": false,
      "help_text": "Whether to enable TLS when the LDAP connection is not using SSL.",
      "label": "LDAP Start TLS",
      "name": "AUTH_LDAP_2_START_TLS",
      "required": false,
      "sensitive": false,
      "type": "boolean"
    },
    "AUTH_LDAP_2_TEAM_MAP": {
      "category": "LDAP",
      "category_slug": "ldap",
      "child": {
        "child": {
          "read_only": false,
          "required": true,
          "type": "field"
        },
        "type": "nested object"
      },
      "computed": true,
      "defined_in_file": false,
      "element_type": "nested object",
      "help_text": "Mapping between team members (users) and LDAP groups. Configuration details are available in the documentation.",
      "label": "LDAP Team Map",
      "name": "AUTH_LDAP_2_TEAM_MAP",
      "required": false,
      "sensitive": false,
      "type": "json"
    },
    "AUTH_LDAP_2_USER_ATTR_MAP": {
      "category": "LDAP",
      "category_slug": "ldap",
      "child": {
        "type": "string"
      },
      "computed": true,
      "defined_in_file": false,
      "element_type": "string",
      "help_text": "Mapping of LDAP user schema to API user attributes. The default setting is valid for ActiveDirectory but users with other LDAP configurations may need to change the values. Refer to the documentation for additional details.",
      "label": "LDAP User Attribute Map",
      "name": "AUTH_LDAP_2_USER_ATTR_MAP",
      "required": false,
      "sensitive": false,
      "type": "json"
    },
    "AUTH_LDAP_2_USER_DN_TEMPLATE": {
      "category": "LDAP",
      "category_slug": "ldap",
      "computed": true,
      "defined_in_file": false,
      "help_text": "Alternative to user search, if user DNs are all of the same format. This approach is more efficient for user lookups than searching if it is usable in your organizational environment. If this setting has a value it will be used instead of AUTH_LDAP_USER_SEARCH.",
      "label": "LDAP User DN Template",
      "name": "AUTH_LDAP_2_USER_DN_TEMPLATE",
      "required": false,
      "sensitive": false,
      "type": "string"
    },
    "AUTH_LDAP_2_USER_FLAGS_BY_GROUP": {
      "category": "LDAP",
      "category_slug": "ldap",
      "child": {
        "child": {
          "read_only": false,
          "required": true,
          "type": "string"
        },
        "type": "list"
      },
      "computed": true,
      "defined_in_file": false,
      "element_type": "list",
      "help_text": "Retrieve users from a given group. At this time, superuser and system auditors are the only groups supported. Refer to the documentation for more detail.",
      "label": "LDAP User Flags By Group",
      "name": "AUTH_LDAP_2_USER_FLAGS_BY_GROUP",
      "required": false,
      "sensitive": false,
      "type": "json"
    },
    "AUTH_LDAP_2_USER_SEARCH": {
      "category": "LDAP",
      "category_slug": "ldap",
      "child": {
        "type": "field"
      },
      "computed": true,
      "defined_in_file": false,
      "element_type": "string",
      "help_text": "LDAP search query to find users.  Any user that matches the given pattern will be able to login to the service.  The user should also be mapped into an organization (as defined in the AUTH_LDAP_ORGANIZATION_MAP setting).  If multiple search queries need to be supported use of \"LDAPUnion\" is possible. See the documentation for details.",
      "label": "LDAP User Search",
      "name": "AUTH_LDAP_2_USER_SEARCH",
      "required": false,
      "sensitive": false,
      "type": "list"
    },
    "AUTH_LDAP_3_BIND_DN": {
      "category": "LDAP",
      "category_slug": "ldap",
      "computed": true,
      "defined_in_file": false,
      "help_text": "DN (Distinguished Name) of user to bind for all search queries. This is the system user account we will use to login to query LDAP for other user information. Refer to the documentation for example syntax.",
      "label": "LDAP Bind DN",
      "name": "AUTH_LDAP_3_BIND_DN",
      "required": false,
      "sensitive": false,
      "type": "string"
    },
    "AUTH_LDAP_3_BIND_PASSWORD": {
      "category": "LDAP",
      "category_slug": "ldap",
      "computed": true,
      "defined_in_file": false,
      "help_text": "Password used to bind LDAP user account.",
      "label": "LDAP Bind Password",
      "name": "AUTH_LDAP_3_BIND_PASSWORD",
      "required": false,
      "sensitive": true,
      "type": "string"
    },
    "AUTH_LDAP_3_CONNECTION_OPTIONS": {
      "category": "LDAP",
      "category_slug": "ldap",
      "child": {
        "type": "field"
      },
      "computed": true,
      "defined_in_file": false,
      "element_type": "string",
      "help_text": "Additional options to set for the LDAP connection.  LDAP referrals are disabled by default (to prevent certain LDAP queries from hanging with AD). Option names should be strings (e.g. \"OPT_REFERRALS\"). Refer to https://www.python-ldap.org/doc/html/ldap.html#options for possible options and values that can be set.",
      "label": "LDAP Connection Options",
      "name": "AUTH_LDAP_3_CONNECTION_OPTIONS",
      "required": false,
      "sensitive": false,
      "type": "json"
    },
    "AUTH_LDAP_3_DENY_GROUP": {
      "category": "LDAP",
      "category_slug": "ldap",
      "computed": true,
      "defined_in_file": false,
      "help_text": "Group DN denied from login. If specified, user will not be allowed to login if a member of this group.  Only one deny group is supported.",
      "label": "LDAP Deny Group",
      "name": "AUTH_LDAP_3_DENY_GROUP",
      "required": false,
      "sensitive": false,
      "type": "string"
    },
    "AUTH_LDAP_3_GROUP_SEARCH": {
      "category": "LDAP",
      "category_slug": "ldap",
      "child": {
        "type": "field"
      },
      "computed": true,
      "defined_in_file": false,
      "element_type": "string",
      "help_text": "Users are mapped to organizations based on their membership in LDAP groups. This setting defines the LDAP search query to find groups. Unlike the user search, group search does not support LDAPSearchUnion.",
      "label": "LDAP Group Search",
      "name": "AUTH_LDAP_3_GROUP_SEARCH",
      "required": false,
      "sensitive": false,
      "type": "list"
    },
    "AUTH_LDAP_3_GROUP_TYPE": {
      "category": "LDAP",
      "category_slug": "ldap",
      "choices": [
        [
          "PosixGroupType",
          "PosixGroupType"
        ],
        [
          "GroupOfNamesType",
          "GroupOfNamesType"
        ],
        [
          "GroupOfUniqueNamesType",
          "GroupOfUniqueNamesType"
        ],
        [
          "ActiveDirectoryGroupType",
          "ActiveDirectoryGroupType"
        ],
        [
          "OrganizationalRoleGroupType",
          "OrganizationalRoleGroupType"
        ],
        [
          "MemberDNGroupType",
          "MemberDNGroupType"
        ],
        [
          "NestedGroupOfNamesType",
          "NestedGroupOfNamesType"
        ],
        [
          "NestedGroupOfUniqueNamesType",
          "NestedGroupOfUniqueNamesType"
        ],
        [
          "NestedActiveDirectoryGroupType",
          "NestedActiveDirectoryGroupType"
        ],
        [
          "NestedOrganizationalRoleGroupType",
          "NestedOrganizationalRoleGroupType"
        ],
        [
          "NestedMemberDNGroupType",
          "NestedMemberDNGroupType"
        ],
        [
          "PosixUIDGroupType",
          "PosixUIDGroupType"
        ]
      ],
      "computed": true,
      "defined_in_file": false,
      "help_text": "The group type may need to be changed based on the type of the LDAP server.  Values are listed at: https://django-auth-ldap.readthedocs.io/en/stable/groups.html#types-of-groups",
      "label": "LDAP Group Type",
      "name": "AUTH_LDAP_3_GROUP_TYPE",
      "required": false,
      "sensitive": false,
      "type": "choice"
    },
    "AUTH_LDAP_3_GROUP_TYPE_PARAMS": {
      "category": "LDAP",
      "category_slug": "ldap",
      "child": {
        "type": "field"
      },
      "computed": true,
      "defined_in_file": false,
      "element_type": "string",
      "help_text": "Key value parameters to send the chosen group type init method.",
      "label": "LDAP Group Type Parameters",
      "name": "AUTH_LDAP_3_GROUP_TYPE_PARAMS",
      "required": false,
      "sensitive": false,
      "type": "json"
    },
    "AUTH_LDAP_3_ORGANIZATION_MAP": {
      "category": "LDAP",
      "category_slug": "ldap",
      "child": {
        "child": {
          "read_only": false,
          "required": true,
          "type": "field"
        },
        "type": "nested object"
      },
      "computed": true,
      "defined_in_file": false,
      "element_type": "nested object",
      "help_text": "Mapping between organization admins/users and LDAP groups. This controls which users are placed into which organizations relative to their LDAP group memberships. Configuration details are available in the documentation.",
      "label": "LDAP Organization Map",
      "name": "AUTH_LDAP_3_ORGANIZATION_MAP",
      "required": false,
      "sensitive": false,
      "type": "json"
    },
    "AUTH_LDAP_3_REQUIRE_GROUP": {
      "category": "LDAP",
      "category_slug": "ldap",
      "computed": true,
      "defined_in_file": false,
      "help_text": "Group DN required to login. If specified, user must be a member of this group to login via LDAP. If not set, everyone in LDAP that matches the user search will be able to login to the service. Only one require group is supported.",
      "label": "LDAP Require Group",
      "name": "AUTH_LDAP_3_REQUIRE_GROUP",
      "required": false,
      "sensitive": false,
      "type": "string"
    },
    "AUTH_LDAP_3_SERVER_URI": {
      "category": "LDAP",
      "category_slug": "ldap",
      "computed": true,
      "defined_in_file": false,
      "help_text": "URI to connect to LDAP server, such as \"ldap://ldap.example.com:389\" (non-SSL) or \"ldaps://ldap.example.com:636\" (SSL). Multiple LDAP servers may be specified by separating with spaces or commas. LDAP authentication is disabled if this parameter is empty.",
      "label": "LDAP Server URI",
      "name": "AUTH_LDAP_3_SERVER_URI",
      "required": false,
      "sensitive": false,
      "type": "string"
    },
    "AUTH_LDAP_3_START_TLS": {
      "category": "LDAP",
      "category_slug": "ldap",
      "computed": true,
      "defined_in_file": false,
      "help_text": "Whether to enable TLS when the LDAP connection is not using SSL.",
      "label": "LDAP Start TLS",
      "name": "AUTH_LDAP_3_START_TLS",
      "required": false,
      "sensitive": false,
      "type": "boolean"
    },
    "AUTH_LDAP_3_TEAM_MAP": {
      "category": "LDAP",
      "category_slug": "ldap",
      "child": {
        "child": {
          "read_only": false,
          "required": true,
          "type": "field"
        },
        "type": "nested object"
      },
      "computed": true,
      "defined_in_file": false,
      "element_type": "nested object",
      "help_text": "Mapping between team members (users) and LDAP groups. Configuration details are available in the documentation.",
      "label": "LDAP Team Map",
      "name": "AUTH_LDAP_3_TEAM_MAP",
      "required": false,
      "sensitive": false,
      "type": "json"
    },
    "AUTH_LDAP_3_USER_ATTR_MAP": {
      "category": "LDAP",
      "category_slug": "ldap",
      "child": {
        "type": "string"
      },
      "computed": true,
      "defined_in_file": false,
      "element_type": "string",
      "help_text": "Mapping of LDAP user schema to API user attributes. The default setting is valid for ActiveDirectory but users with other LDAP configurations may need to change the values. Refer to the documentation for additional details.",
      "label": "LDAP User Attribute Map",
      "name": "AUTH_LDAP_3_USER_ATTR_MAP",
      "required": false,
      "sensitive": false,
      "type": "json"
    },
    "AUTH_LDAP_3_USER_DN_TEMPLATE": {
      "category": "LDAP",
      "category_slug": "ldap",
      "computed": true,
      "defined_in_file": false,
      "help_text": "Alternative to user search, if user DNs are all of the same format. This approach is more efficient for user lookups than searching if it is usable in your organizational environment. If this setting has a value it will be used instead of AUTH_LDAP_USER_SEARCH.",
      "label": "LDAP User DN Template",
      "name": "AUTH_LDAP_3_USER_DN_TEMPLATE",
      "required": false,
      "sensitive": false,
      "type": "string"
    },
    "AUTH_LDAP_3_USER_FLAGS_BY_GROUP": {
      "category": "LDAP",
      "category_slug": "ldap",
      "child": {
        "child": {
          "read_only": false,
          "required": true,
          "type": "string"
        },
        "type": "list"
      },
      "computed": true,
      "defined_in_file": false,
      "element_type": "list",
      "help_text": "Retrieve users from a given group. At this time, superuser and system auditors are the only groups supported. Refer to the documentation for more detail.",
      "label": "LDAP User Flags By Group",
      "name": "AUTH_LDAP_3_USER_FLAGS_BY_GROUP",
      "required": false,
      "sensitive": false,
      "type": "json"
    },
    "AUTH_LDAP_3_USER_SEARCH": {
      "category": "LDAP",
      "category_slug": "ldap",
      "child": {
        "type": "field"
      },
      "computed": true,
      "defined_in_file": false,
      "element_type": "string",
      "help_text": "LDAP search query to find users.  Any user that matches the given pattern will be able to login to the service.  The user should also be mapped into an organization (as defined in the AUTH_LDAP_ORGANIZATION_MAP setting).  If multiple search queries need to be supported use of \"LDAPUnion\" is possible. See the documentation for details.",
      "label": "LDAP User Search",
      "name": "AUTH_LDAP_3_USER_SEARCH",
      "required": false,
      "sensitive": false,
      "type": "list"
    },
    "AUTH_LDAP_4_BIND_DN": {
      "category": "LDAP",
      "category_slug": "ldap",
      "computed": true,
      "defined_in_file": false,
      "help_text": "DN (Distinguished Name) of user to bind for all search queries. This is the system user account we will use to login to query LDAP for other user information. Refer to the documentation for example syntax.",
      "label": "LDAP Bind DN",
      "name": "AUTH_LDAP_4_BIND_DN",
      "required": false,
      "sensitive": false,
      "type": "string"
    },
    "AUTH_LDAP_4_BIND_PASSWORD": {
      "category": "LDAP",
      "category_slug": "ldap",
      "computed": true,
      "defined_in_file": false,
      "help_text": "Password used to bind LDAP user account.",
      "label": "LDAP Bind Password",
      "name": "AUTH_LDAP_4_BIND_PASSWORD",
      "required": false,
      "sensitive": true,
      "type": "string"
    },
    "AUTH_LDAP_4_CONNECTION_OPTIONS": {
      "category": "LDAP",
      "category_slug": "ldap",
      "child": {
        "type": "field"
      },
      "computed": true,
      "defined_in_file": false,
      "element_type": "string",
      "help_text": "Additional options to set for the LDAP connection.  LDAP referrals are disabled by default (to prevent certain LDAP queries from hanging with AD). Option names should be strings (e.g. \"OPT_REFERRALS\"). Refer to https://www.python-ldap.org/doc/html/ldap.html#options for possible options and values that can be set.",
      "label": "LDAP Connection Options",
      "name": "AUTH_LDAP_4_CONNECTION_OPTIONS",
      "required": false,
      "sensitive": false,
      "type": "json"
    },
    "AUTH_LDAP_4_DENY_GROUP": {
      "category": "LDAP",
      "category_slug": "ldap",
      "computed": true,
      "defined_in_file": false,
      "help_text": "Group DN denied from login. If specified, user will not be allowed to login if a member of this group.  Only one deny group is supported.",
      "label": "LDAP Deny Group",
      "name": "AUTH_LDAP_4_DENY_GROUP",
      "required": false,
      "sensitive": false,
      "type": "string"
    },
    "AUTH_LDAP_4_GROUP_SEARCH": {
      "category": "LDAP",
      "category_slug": "ldap",
      "child": {
        "type": "field"
      },
      "computed": true,
      "defined_in_file": false,
      "element_type": "string",
      "help_text": "Users are mapped to organizations based on their membership in LDAP groups. This setting defines the LDAP search query to find groups. Unlike the user search, group search does not support LDAPSearchUnion.",
      "label": "LDAP Group Search",
      "name": "AUTH_LDAP_4_GROUP_SEARCH",
      "required": false,
      "sensitive": false,
      "type": "list"
    },
    "AUTH_LDAP_4_GROUP_TYPE": {
      "category": "LDAP",
      "category_slug": "ldap",
      "choices": [
        [
          "PosixGroupType",
          "PosixGroupType"
        ],
        [
          "GroupOfNamesType",
          "GroupOfNamesType"
        ],
        [
          "GroupOfUniqueNamesType",
          "GroupOfUniqueNamesType"
        ],
        [
          "ActiveDirectoryGroupType",
          "ActiveDirectoryGroupType"
        ],
        [
          "OrganizationalRoleGroupType",
          "OrganizationalRoleGroupType"
        ],
        [
          "MemberDNGroupType",
          "MemberDNGroupType"
        ],
        [
          "NestedGroupOfNamesType",
          "NestedGroupOfNamesType"
        ],
        [
          "NestedGroupOfUniqueNamesType",
          "NestedGroupOfUniqueNamesType"
        ],
        [
          "NestedActiveDirectoryGroupType",
          "NestedActiveDirectoryGroupType"
        ],
        [
          "NestedOrganizationalRoleGroupType",
          "NestedOrganizationalRoleGroupType"
        ],
        [
          "NestedMemberDNGroupType",
          "NestedMemberDNGroupType"
        ],
        [
          "PosixUIDGroupType",
          "PosixUIDGroupType"
        ]
      ],
      "computed": true,
      "defined_in_file": false,
      "help_text": "The group type may need to be changed based on the type of the LDAP server.  Values are listed at: https://django-auth-ldap.readthedocs.io/en/stable/groups.html#types-of-groups",
      "label": "LDAP Group Type",
      "name": "AUTH_LDAP_4_GROUP_TYPE",
      "required": false,
      "sensitive": false,
      "type": "choice"
    },
    "AUTH_LDAP_4_GROUP_TYPE_PARAMS": {
      "category": "LDAP",
      "category_slug": "ldap",
      "child": {
        "type": "field"
      },
      "computed": true,
      "defined_in_file": false,
      "element_type": "string",
      "help_text": "Key value parameters to send the chosen group type init method.",
      "label": "LDAP Group Type Parameters",
      "name": "AUTH_LDAP_4_GROUP_TYPE_PARAMS",
      "required": false,
      "sensitive": false,
      "type": "json"
    },
    "AUTH_LDAP_4_ORGANIZATION_MAP": {
      "category": "LDAP",
      "category_slug": "ldap",
      "child": {
        "child": {
          "read_only": false,
          "required": true,
          "type": "field"
        },
        "type": "nested object"
      },
      "computed": true,
      "defined_in_file": false,
      "element_type": "nested object",
      "help_text": "Mapping between organization admins/users and LDAP groups. This controls which users are placed into which organizations relative to their LDAP group memberships. Configuration details are available in the documentation.",
      "label": "LDAP Organization Map",
      "name": "AUTH_LDAP_4_ORGANIZATION_MAP",
      "required": false,
      "sensitive": false,
      "type": "json"
    },
    "AUTH_LDAP_4_REQUIRE_GROUP": {
      "category": "LDAP",
      "category_slug": "ldap",
      "computed": true,
      "defined_in_file": false,
      "help_text": "Group DN required to login. If specified, user must be a member of this group to login via LDAP. If not set, everyone in LDAP that matches the user search will be able to login to the service. Only one require group is supported.",
      "label": "LDAP Require Group",
      "name": "AUTH_LDAP_4_REQUIRE_GROUP",
      "required": false,
      "sensitive": false,
      "type": "string"
    },
    "AUTH_LDAP_4_SERVER_URI": {
      "category": "LDAP",
      "category_slug": "ldap",
      "computed": true,
      "defined_in_file": false,
      "help_text": "URI to connect to LDAP server, such as \"ldap://ldap.example.com:389\" (non-SSL) or \"ldaps://ldap.example.com:636\" (SSL). Multiple LDAP servers may be specified by separating with spaces or commas. LDAP authentication is disabled if this parameter is empty.",
      "label": "LDAP Server URI",
      "name": "AUTH_LDAP_4_SERVER_URI",
      "required": false,
      "sensitive": false,
      "type": "string"
    },
    "AUTH_LDAP_4_START_TLS": {
      "category": "LDAP",
      "category_slug": "ldap",
      "computed": true,
      "defined_in_file": false,
      "help_text": "Whether to enable TLS when the LDAP connection is not using SSL.",
      "label": "LDAP Start TLS",
      "name": "AUTH_LDAP_4_START_TLS",
      "required": false,
      "sensitive": false,
      "type": "boolean"
    },
    "AUTH_LDAP_4_TEAM_MAP": {
      "category": "LDAP",
      "category_slug": "ldap",
      "child": {
        "child": {
          "read_only": false,
          "required": true,
          "type": "field"
        },
        "type": "nested object"
      },
      "computed": true,
      "defined_in_file": false,
      "element_type": "nested object",
      "help_text": "Mapping between team members (users) and LDAP groups. Configuration details are available in the documentation.",
      "label": "LDAP Team Map",
      "name": "AUTH_LDAP_4_TEAM_MAP",
      "required": false,
      "sensitive": false,
      "type": "json"
    },
    "AUTH_LDAP_4_USER_ATTR_MAP": {
      "category": "LDAP",
      "category_slug": "ldap",
      "child": {
        "type": "string"
      },
      "computed": true,
      "defined_in_file": false,
      "element_type": "string",
      "help_text": "Mapping of LDAP user schema to API user attributes. The default setting is valid for ActiveDirectory but users with other LDAP configurations may need to change the values. Refer to the documentation for additional details.",
      "label": "LDAP User Attribute Map",
      "name": "AUTH_LDAP_4_USER_ATTR_MAP",
      "required": false,
      "sensitive": false,
      "type": "json"
    },
    "AUTH_LDAP_4_USER_DN_TEMPLATE": {
      "category": "LDAP",
      "category_slug": "ldap",
      "computed": true,
      "defined_in_file": false,
      "help_text": "Alternative to user search, if user DNs are all of the same format. This approach is more efficient for user lookups than searching if it is usable in your organizational environment. If this setting has a value it will be used instead of AUTH_LDAP_USER_SEARCH.",
      "label": "LDAP User DN Template",
      "name": "AUTH_LDAP_4_USER_DN_TEMPLATE",
      "required": false,
      "sensitive": false,
      "type": "string"
    },
    "AUTH_LDAP_4_USER_FLAGS_BY_GROUP": {
      "category": "LDAP",
      "category_slug": "ldap",
      "child": {
        "child": {
          "read_only": false,
          "required": true,
          "type": "string"
        },
        "type": "list"
      },
      "computed": true,
      "defined_in_file": false,
      "element_type": "list",
      "help_text": "Retrieve users from a given group. At this time, superuser and system auditors are the only groups supported. Refer to the documentation for more detail.",
      "label": "LDAP User Flags By Group",
      "name": "AUTH_LDAP_4_USER_FLAGS_BY_GROUP",
      "required": false,
      "sensitive": false,
      "type": "json"
    },
    "AUTH_LDAP_4_USER_SEARCH": {
      "category": "LDAP",
      "category_slug": "ldap",
      "child": {
        "type": "field"
      },
      "computed": true,
      "defined_in_file": false,
      "element_type": "string",
      "help_text": "LDAP search query to find users.  Any user that matches the given pattern will be able to login to the service.  The user should also be mapped into an organization (as defined in the AUTH_LDAP_ORGANIZATION_MAP setting).  If multiple search queries need to be supported use of \"LDAPUnion\" is possible. See the documentation for details.",
      "label": "LDAP User Search",
      "name": "AUTH_LDAP_4_USER_SEARCH",
      "required": false,
      "sensitive": false,
      "type": "list"
    },
    "AUTH_LDAP_5_BIND_DN": {
      "category": "LDAP",
      "category_slug": "ldap",
      "computed": true,
      "defined_in_file": false,
      "help_text": "DN (Distinguished Name) of user to bind for all search queries. This is the system user account we will use to login to query LDAP for other user information. Refer to the documentation for example syntax.",
      "label": "LDAP Bind DN",
      "name": "AUTH_LDAP_5_BIND_DN",
      "required": false,
      "sensitive": false,
      "type": "string"
    },
    "AUTH_LDAP_5_BIND_PASSWORD": {
      "category": "LDAP",
      "category_slug": "ldap",
      "computed": true,
      "defined_in_file": false,
      "help_text": "Password used to bind LDAP user account.",
      "label": "LDAP Bind Password",
      "name": "AUTH_LDAP_5_BIND_PASSWORD",
      "required": false,
      "sensitive": true,
      "type": "string"
    },
    "AUTH_LDAP_5_CONNECTION_OPTIONS": {
      "category": "LDAP",
      "category_slug": "ldap",
      "child": {
        "type": "field"
      },
      "computed": true,
      "defined_in_file": false,
      "element_type": "string",
      "help_text": "Additional options to set for the LDAP connection.  LDAP referrals are disabled by default (to prevent certain LDAP queries from hanging with AD). Option names should be strings (e.g. \"OPT_REFERRALS\"). Refer to https://www.python-ldap.org/doc/html/ldap.html#options for possible options and values that can be set.",
      "label": "LDAP Connection Options",
      "name": "AUTH_LDAP_5_CONNECTION_OPTIONS",
      "required": false,
      "sensitive": false,
      "type": "json"
    },
    "AUTH_LDAP_5_DENY_GROUP": {
      "category": "LDAP",
      "category_slug": "ldap",
      "computed": true,
      "defined_in_file": false,
      "help_text": "Group DN denied from login. If specified, user will not be allowed to login if a member of this group.  Only one deny group is supported.",
      "label": "LDAP Deny Group",
      "name": "AUTH_LDAP_5_DENY_GROUP",
      "required": false,
      "sensitive": false,
      "type": "string"
    },
    "AUTH_LDAP_5_GROUP_SEARCH": {
      "category": "LDAP",
      "category_slug": "ldap",
      "child": {
        "type": "field"
      },
      "computed": true,
      "defined_in_file": false,
      "element_type": "string",
      "help_text": "Users are mapped to organizations based on their membership in LDAP groups. This setting defines the LDAP search query to find groups. Unlike the user search, group search does not support LDAPSearchUnion.",
      "label": "LDAP Group Search",
      "name": "AUTH_LDAP_5_GROUP_SEARCH",
      "required": false,
      "sensitive": false,
      "type": "list"
    },
    "AUTH_LDAP_5_GROUP_TYPE": {
      "category": "LDAP",
      "category_slug": "ldap",
      "choices": [
        [
          "PosixGroupType",
          "PosixGroupType"
        ],
        [
          "GroupOfNamesType",
          "GroupOfNamesType"
        ],
        [
          "GroupOfUniqueNamesType",
          "GroupOfUniqueNamesType"
        ],
        [
          "ActiveDirectoryGroupType",
          "ActiveDirectoryGroupType"
        ],
        [
          "OrganizationalRoleGroupType",
          "OrganizationalRoleGroupType"
        ],
        [
          "MemberDNGroupType",
          "MemberDNGroupType"
        ],
        [
          "NestedGroupOfNamesType",
          "NestedGroupOfNamesType"
        ],
        [
          "NestedGroupOfUniqueNamesType",
          "NestedGroupOfUniqueNamesType"
        ],
        [
          "NestedActiveDirectoryGroupType",
          "NestedActiveDirectoryGroupType"
        ],
        [
          "NestedOrganizationalRoleGroupType",
          "NestedOrganizationalRoleGroupType"
        ],
        [
          "NestedMemberDNGroupType",
          "NestedMemberDNGroupType"
        ],
        [
          "PosixUIDGroupType",
          "PosixUIDGroupType"
        ]
      ],
      "computed": true,
      "defined_in_file": false,
      "help_text": "The group type may need to be changed based on the type of the LDAP server.  Values are listed at: https://django-auth-ldap.readthedocs.io/en/stable/groups.html#types-of-groups",
      "label": "LDAP Group Type",
      "name": "AUTH_LDAP_5_GROUP_TYPE",
      "required": false,
      "sensitive": false,
      "type": "choice"
    },
    "AUTH_LDAP_5_GROUP_TYPE_PARAMS": {
      "category": "LDAP",
      "category_slug": "ldap",
      "child": {
        "type": "field"
      },
      "computed": true,
      "defined_in_file": false,
      "element_type": "string",
      "help_text": "Key value parameters to send the chosen group type init method.",
      "label": "LDAP Group Type Parameters",
      "name": "AUTH_LDAP_5_GROUP_TYPE_PARAMS",
      "required": false,
      "sensitive": false,
      "type": "json"
    },
    "AUTH_LDAP_5_ORGANIZATION_MAP": {
      "category": "LDAP",
      "category_slug": "ldap",
      "child": {
        "child": {
          "read_only": false,
          "required": true,
          "type": "field"
        },
        "type": "nested object"
      },
      "computed": true,
      "defined_in_file": false,
      "element_type": "nested object",
      "help_text": "Mapping between organization admins/users and LDAP groups. This controls which users are placed into which organizations relative to their LDAP group memberships. Configuration details are available in the documentation.",
      "label": "LDAP Organization Map",
      "name": "AUTH_LDAP_5_ORGANIZATION_MAP",
      "required": false,
      "sensitive": false,
      "type": "json"
    },
    "AUTH_LDAP_5_REQUIRE_GROUP": {
      "category": "LDAP",
      "category_slug": "ldap",
      "computed": true,
      "defined_in_file": false,
      "help_text": "Group DN required to login. If specified, user must be a member of this group to login via LDAP. If not set, everyone in LDAP that matches the user search will be able to login to the service. Only one require group is supported.",
      "label": "LDAP Require Group",
      "name": "AUTH_LDAP_5_REQUIRE_GROUP",
      "required": false,
      "sensitive": false,
      "type": "string"
    },
    "AUTH_LDAP_5_SERVER_URI": {
      "category": "LDAP",
      "category_slug": "ldap",
      "computed": true,
      "defined_in_file": false,
      "help_text": "URI to connect to LDAP server, such as \"ldap://ldap.example.com:389\" (non-SSL) or \"ldaps://ldap.example.com:636\" (SSL). Multiple LDAP servers may be specified by separating with spaces or commas. LDAP authentication is disabled if this parameter is empty.",
      "label": "LDAP Server URI",
      "name": "AUTH_LDAP_5_SERVER_URI",
      "required": false,
      "sensitive": false,
      "type": "string"
    },
    "AUTH_LDAP_5_START_TLS": {
      "category": "LDAP",
      "category_slug": "ldap",
      "computed": true,
      "defined_in_file": false,
      "help_text": "Whether to enable TLS when the LDAP connection is not using SSL.",
      "label": "LDAP Start TLS",
      "name": "AUTH_LDAP_5_START_TLS",
      "required": false,
      "sensitive": false,
      "type": "boolean"
    },
    "AUTH_LDAP_5_TEAM_MAP": {
      "category": "LDAP",
      "category_slug": "ldap",
      "child": {
        "child": {
          "read_only": false,
          "required": true,
          "type": "field"
        },
        "type": "nested object"
      },
      "computed": true,
      "defined_in_file": false,
      "element_type": "nested object",
      "help_text": "Mapping between team members (users) and LDAP groups. Configuration details are available in the documentation.",
      "label": "LDAP Team Map",
      "name": "AUTH_LDAP_5_TEAM_MAP",
      "required": false,
      "sensitive": false,
      "type": "json"
    },
    "AUTH_LDAP_5_USER_ATTR_MAP": {
      "category": "LDAP",
      "category_slug": "ldap",
      "child": {
        "type": "string"
      },
      "computed": true,
      "defined_in_file": false,
      "element_type": "string",
      "help_text": "Mapping of LDAP user schema to API user attributes. The default setting is valid for ActiveDirectory but users with other LDAP configurations may need to change the values. Refer to the documentation for additional details.",
      "label": "LDAP User Attribute Map",
      "name": "AUTH_LDAP_5_USER_ATTR_MAP",
      "required": false,
      "sensitive": false,
      "type": "json"
    },
    "AUTH_LDAP_5_USER_DN_TEMPLATE": {
      "category": "LDAP",
      "category_slug": "ldap",
      "computed": true,
      "defined_in_file": false,
      "help_text": "Alternative to user search, if user DNs are all of the same format. This approach is more efficient for user lookups than searching if it is usable in your organizational environment. If this setting has a value it will be used instead of AUTH_LDAP_USER_SEARCH.",
      "label": "LDAP User DN Template",
      "name": "AUTH_LDAP_5_USER_DN_TEMPLATE",
      "required": false,
      "sensitive": false,
      "type": "string"
    },
    "AUTH_LDAP_5_USER_FLAGS_BY_GROUP": {
      "category": "LDAP",
      "category_slug": "ldap",
      "child": {
        "child": {
          "read_only": false,
          "required": true,
          "type": "string"
        },
        "type": "list"
      },
      "computed": true,
      "defined_in_file": false,
      "element_type": "list",
      "help_text": "Retrieve users from a given group. At this time, superuser and system auditors are the only groups supported. Refer to the documentation for more detail.",
      "label": "LDAP User Flags By Group",
      "name": "AUTH_LDAP_5_USER_FLAGS_BY_GROUP",
      "required": false,
      "sensitive": false,
      "type": "json"
    },
    "AUTH_LDAP_5_USER_SEARCH": {
      "category": "LDAP",
      "category_slug": "ldap",
      "child": {
        "type": "field"
      },
      "computed": true,
      "defined_in_file": false,
      "element_type": "string",
      "help_text": "LDAP search query to find users.  Any user that matches the given pattern will be able to login to the service.  The user should also be mapped into an organization (as defined in the AUTH_LDAP_ORGANIZATION_MAP setting).  If multiple search queries need to be supported use of \"LDAPUnion\" is possible. See the documentation for details.",
      "label": "LDAP User Search",
      "name": "AUTH_LDAP_5_USER_SEARCH",
      "required": false,
      "sensitive": false,
      "type": "list"
    },
    "AUTH_LDAP_BIND_DN": {
      "category": "LDAP",
      "category_slug": "ldap",
      "computed": true,
      "defined_in_file": false,
      "help_text": "DN (Distinguished Name) of user to bind for all search queries. This is the system user account we will use to login to query LDAP for other user information. Refer to the documentation for example syntax.",
      "label": "LDAP Bind DN",
      "name": "AUTH_LDAP_BIND_DN",
      "required": false,
      "sensitive": false,
      "type": "string"
    },
    "AUTH_LDAP_BIND_PASSWORD": {
      "category": "LDAP",
      "category_slug": "ldap",
      "computed": true,
      "defined_in_file": false,
      "help_text": "Password used to bind LDAP user account.",
      "label": "LDAP Bind Password",
      "name": "AUTH_LDAP_BIND_PASSWORD",
      "required": false,
      "sensitive": true,
      "type": "string"
    },
    "AUTH_LDAP_CONNECTION_OPTIONS": {
      "category": "LDAP",
      "category_slug": "ldap",
      "child": {
        "type": "field"
      },
      "computed": true,
      "defined_in_file": false,
      "element_type": "string",
      "help_text": "Additional options to set for the LDAP connection.  LDAP referrals are disabled by default (to prevent certain LDAP queries from hanging with AD). Option names should be strings (e.g. \"OPT_REFERRALS\"). Refer to https://www.python-ldap.org/doc/html/ldap.html#options for possible options and values that can be set.",
      "label": "LDAP Connection Options",
      "name": "AUTH_LDAP_CONNECTION_OPTIONS",
      "required": false,
      "sensitive": false,
      "type": "json"
    },
    "AUTH_LDAP_DENY_GROUP": {
      "category": "LDAP",
      "category_slug": "ldap",
      "computed": true,
      "defined_in_file": false,
      "help_text": "Group DN denied from login. If specified, user will not be allowed to login if a member of this group.  Only one deny group is supported.",
      "label": "LDAP Deny Group",
      "name": "AUTH_LDAP_DENY_GROUP",
      "required": false,
      "sensitive": false,
      "type": "string"
    },
    "AUTH_LDAP_GROUP_SEARCH": {
      "category": "LDAP",
      "category_slug": "ldap",
      "child": {
        "type": "field"
      },
      "computed": true,
      "defined_in_file": false,
      "element_type": "string",
      "help_text": "Users are mapped to organizations based on their membership in LDAP groups. This setting defines the LDAP search query to find groups. Unlike the user search, group search does not support LDAPSearchUnion.",
      "label": "LDAP Group Search",
      "name": "AUTH_LDAP_GROUP_SEARCH",
      "required": false,
      "sensitive": false,
      "type": "list"
    },
    "AUTH_LDAP_GROUP_TYPE": {
      "category": "LDAP",
      "category_slug": "ldap",
      "choices": [
        [
          "PosixGroupType",
          "PosixGroupType"
        ],
        [
          "GroupOfNamesType",
          "GroupOfNamesType"
        ],
        [
          "GroupOfUniqueNamesType",
          "GroupOfUniqueNamesType"
        ],
        [
          "ActiveDirectoryGroupType",
          "ActiveDirectoryGroupType"
        ],
        [
          "OrganizationalRoleGroupType",
          "OrganizationalRoleGroupType"
        ],
        [
          "MemberDNGroupType",
          "MemberDNGroupType"
        ],
        [
          "NestedGroupOfNamesType",
          "NestedGroupOfNamesType"
        ],
        [
          "NestedGroupOfUniqueNamesType",
          "NestedGroupOfUniqueNamesType"
        ],
        [
          "NestedActiveDirectoryGroupType",
          "NestedActiveDirectoryGroupType"
        ],
        [
          "NestedOrganizationalRoleGroupType",
          "NestedOrganizationalRoleGroupType"
        ],
        [
          "NestedMemberDNGroupType",
          "NestedMemberDNGroupType"
        ],
        [
          "PosixUIDGroupType",
          "PosixUIDGroupType"
        ]
      ],
      "computed": true,
      "defined_in_file": false,
      "help_text": "The group type may need to be changed based on the type of the LDAP server.  Values are listed at: https://django-auth-ldap.readthedocs.io/en/stable/groups.html#types-of-groups",
      "label": "LDAP Group Type",
      "name": "AUTH_LDAP_GROUP_TYPE",
      "required": false,
      "sensitive": false,
      "type": "choice"
    },
    "AUTH_LDAP_GROUP_TYPE_PARAMS": {
      "category": "LDAP",
      "category_slug": "ldap",
      "child": {
        "type": "field"
      },
      "computed": true,
      "defined_in_file": false,
      "element_type": "string",
      "help_text": "Key value parameters to send the chosen group type init method.",
      "label": "LDAP Group Type Parameters",
      "name": "AUTH_LDAP_GROUP_TYPE_PARAMS",
      "required": false,
      "sensitive": false,
      "type": "json"
    },
    "AUTH_LDAP_ORGANIZATION_MAP": {
      "category": "LDAP",
      "category_slug": "ldap",
      "child": {
        "child": {
          "read_only": false,
          "required": true,
          "type": "field"
        },
        "type": "nested object"
      },
      "computed": true,
      "defined_in_file": false,
      "element_type": "nested object",
      "help_text": "Mapping between organization admins/users and LDAP groups. This controls which users are placed into which organizations relative to their LDAP group memberships. Configuration details are available in the documentation.",
      "label": "LDAP Organization Map",
      "name": "AUTH_LDAP_ORGANIZATION_MAP",
      "required": false,
      "sensitive": false,
      "type": "json"
    },
    "AUTH_LDAP_REQUIRE_GROUP": {
      "category": "LDAP",
      "category_slug": "ldap",
      "computed": true,
      "defined_in_file": false,
      "help_text": "Group DN required to login. If specified, user must be a member of this group to login via LDAP. If not set, everyone in LDAP that matches the user search will be able to login to the service. Only one require group is supported.",
      "label": "LDAP Require Group",
      "name": "AUTH_LDAP_REQUIRE_GROUP",
      "required": false,
      "sensitive": false,
      "type": "string"
    },
    "AUTH_LDAP_SERVER_URI": {
      "category": "LDAP",
      "category_slug": "ldap",
      "computed": true,
      "defined_in_file": false,
      "help_text": "URI to connect to LDAP server, such as \"ldap://ldap.example.com:389\" (non-SSL) or \"ldaps://ldap.example.com:636\" (SSL). Multiple LDAP servers may be specified by separating with spaces or commas. LDAP authentication is disabled if this parameter is empty.",
      "label": "LDAP Server URI",
      "name": "AUTH_LDAP_SERVER_URI",
      "required": false,
      "sensitive": false,
      "type": "string"
    },
    "AUTH_LDAP_START_TLS": {
      "category": "LDAP",
      "category_slug": "ldap",
      "computed": true,
      "defined_in_file": false,
      "help_text": "Whether to enable TLS when the LDAP connection is not using SSL.",
      "label": "LDAP Start TLS",
      "name": "AUTH_LDAP_START_TLS",
      "required": false,
      "sensitive": false,
      "type": "boolean"
    },
    "AUTH_LDAP_TEAM_MAP": {
      "category": "LDAP",
      "category_slug": "ldap",
      "child": {
        "child": {
          "read_only": false,
          "required": true,
          "type": "field"
        },
        "type": "nested object"
      },
      "computed": true,
      "defined_in_file": false,
      "element_type": "nested object",
      "help_text": "Mapping between team members (users) and LDAP groups. Configuration details are available in the documentation.",
      "label": "LDAP Team Map",
      "name": "AUTH_LDAP_TEAM_MAP",
      "required": false,
      "sensitive": false,
      "type": "json"
    },
    "AUTH_LDAP_USER_ATTR_MAP": {
      "category": "LDAP",
      "category_slug": "ldap",
      "child": {
        "type": "string"
      },
      "computed": true,
      "defined_in_file": false,
      "element_type": "string",
      "help_text": "Mapping of LDAP user schema to API user attributes. The default setting is valid for ActiveDirectory but users with other LDAP configurations may need to change the values. Refer to the documentation for additional details.",
      "label": "LDAP User Attribute Map",
      "name": "AUTH_LDAP_USER_ATTR_MAP",
      "required": false,
      "sensitive": false,
      "type": "json"
    },
    "AUTH_LDAP_USER_DN_TEMPLATE": {
      "category": "LDAP",
      "category_slug": "ldap",
      "computed": true,
      "defined_in_file": false,
      "help_text": "Alternative to user search, if user DNs are all of the same format. This approach is more efficient for user lookups than searching if it is usable in your organizational environment. If this setting has a value it will be used instead of AUTH_LDAP_USER_SEARCH.",
      "label": "LDAP User DN Template",
      "name": "AUTH_LDAP_USER_DN_TEMPLATE",
      "required": false,
      "sensitive": false,
      "type": "string"
    },
    "AUTH_LDAP_USER_FLAGS_BY_GROUP": {
      "category": "LDAP",
      "category_slug": "ldap",
      "child": {
        "child": {
          "read_only": false,
          "required": true,
          "type": "string"
        },
        "type": "list"
      },
      "computed": true,
      "defined_in_file": false,
      "element_type": "list",
      "help_text": "Retrieve users from a given group. At this time, superuser and system auditors are the only groups supported. Refer to the documentation for more detail.",
      "label": "LDAP User Flags By Group",
      "name": "AUTH_LDAP_USER_FLAGS_BY_GROUP",
      "required": false,
      "sensitive": false,
      "type": "json"
    },
    "AUTH_LDAP_USER_SEARCH": {
      "category": "LDAP",
      "category_slug": "ldap",
      "child": {
        "type": "field"
      },
      "computed": true,
      "defined_in_file": false,
      "element_type": "string",
      "help_text": "LDAP search query to find users.  Any user that matches the given pattern will be able to login to the service.  The user should also be mapped into an organization (as defined in the AUTH_LDAP_ORGANIZATION_MAP setting).  If multiple search queries need to be supported use of \"LDAPUnion\" is possible. See the documentation for details.",
      "label": "LDAP User Search",
      "name": "AUTH_LDAP_USER_SEARCH",
      "required": false,
      "sensitive": false,
      "type": "list"
    }
  },
  "PropertyGetKeys": [
    "AUTH_LDAP_1_BIND_DN",
    "AUTH_LDAP_1_BIND_PASSWORD",
    "AUTH_LDAP_1_CONNECTION_OPTIONS",
    "AUTH_LDAP_1_DENY_GROUP",
    "AUTH_LDAP_1_GROUP_SEARCH",
    "AUTH_LDAP_1_GROUP_TYPE",
    "AUTH_LDAP_1_GROUP_TYPE_PARAMS",
    "AUTH_LDAP_1_ORGANIZATION_MAP",
    "AUTH_LDAP_1_REQUIRE_GROUP",
    "AUTH_LDAP_1_SERVER_URI",
    "AUTH_LDAP_1_START_TLS",
    "AUTH_LDAP_1_TEAM_MAP",
    "AUTH_LDAP_1_USER_ATTR_MAP",
    "AUTH_LDAP_1_USER_DN_TEMPLATE",
    "AUTH_LDAP_1_USER_FLAGS_BY_GROUP",
    "AUTH_LDAP_1_USER_SEARCH",
    "AUTH_LDAP_2_BIND_DN",
    "AUTH_LDAP_2_BIND_PASSWORD",
    "AUTH_LDAP_2_CONNECTION_OPTIONS",
    "AUTH_LDAP_2_DENY_GROUP",
    "AUTH_LDAP_2_GROUP_SEARCH",
    "AUTH_LDAP_2_GROUP_TYPE",
    "AUTH_LDAP_2_GROUP_TYPE_PARAMS",
    "AUTH_LDAP_2_ORGANIZATION_MAP",
    "AUTH_LDAP_2_REQUIRE_GROUP",
    "AUTH_LDAP_2_SERVER_URI",
    "AUTH_LDAP_2_START_TLS",
    "AUTH_LDAP_2_TEAM_MAP",
    "AUTH_LDAP_2_USER_ATTR_MAP",
    "AUTH_LDAP_2_USER_DN_TEMPLATE",
    "AUTH_LDAP_2_USER_FLAGS_BY_GROUP",
    "AUTH_LDAP_2_USER_SEARCH",
    "AUTH_LDAP_3_BIND_DN",
    "AUTH_LDAP_3_BIND_PASSWORD",
    "AUTH_LDAP_3_CONNECTION_OPTIONS",
    "AUTH_LDAP_3_DENY_GROUP",
    "AUTH_LDAP_3_GROUP_SEARCH",
    "AUTH_LDAP_3_GROUP_TYPE",
    "AUTH_LDAP_3_GROUP_TYPE_PARAMS",
    "AUTH_LDAP_3_ORGANIZATION_MAP",
    "AUTH_LDAP_3_REQUIRE_GROUP",
    "AUTH_LDAP_3_SERVER_URI",
    "AUTH_LDAP_3_START_TLS",
    "AUTH_LDAP_3_TEAM_MAP",
    "AUTH_LDAP_3_USER_ATTR_MAP",
    "AUTH_LDAP_3_USER_DN_TEMPLATE",
    "AUTH_LDAP_3_USER_FLAGS_BY_GROUP",
    "AUTH_LDAP_3_USER_SEARCH",
    "AUTH_LDAP_4_BIND_DN",
    "AUTH_LDAP_4_BIND_PASSWORD",
    "AUTH_LDAP_4_CONNECTION_OPTIONS",
    "AUTH_LDAP_4_DENY_GROUP",
    "AUTH_LDAP_4_GROUP_SEARCH",
    "AUTH_LDAP_4_GROUP_TYPE",
    "AUTH_LDAP_4_GROUP_TYPE_PARAMS",
    "AUTH_LDAP_4_ORGANIZATION_MAP",
    "AUTH_LDAP_4_REQUIRE_GROUP",
    "AUTH_LDAP_4_SERVER_URI",
    "AUTH_LDAP_4_START_TLS",
    "AUTH_LDAP_4_TEAM_MAP",
    "AUTH_LDAP_4_USER_ATTR_MAP",
    "AUTH_LDAP_4_USER_DN_TEMPLATE",
    "AUTH_LDAP_4_USER_FLAGS_BY_GROUP",
    "AUTH_LDAP_4_USER_SEARCH",
    "AUTH_LDAP_5_BIND_DN",
    "AUTH_LDAP_5_BIND_PASSWORD",
    "AUTH_LDAP_5_CONNECTION_OPTIONS",
    "AUTH_LDAP_5_DENY_GROUP",
    "AUTH_LDAP_5_GROUP_SEARCH",
    "AUTH_LDAP_5_GROUP_TYPE",
    "AUTH_LDAP_5_GROUP_TYPE_PARAMS",
    "AUTH_LDAP_5_ORGANIZATION_MAP",
    "AUTH_LDAP_5_REQUIRE_GROUP",
    "AUTH_LDAP_5_SERVER_URI",
    "AUTH_LDAP_5_START_TLS",
    "AUTH_LDAP_5_TEAM_MAP",
    "AUTH_LDAP_5_USER_ATTR_MAP",
    "AUTH_LDAP_5_USER_DN_TEMPLATE",
    "AUTH_LDAP_5_USER_FLAGS_BY_GROUP",
    "AUTH_LDAP_5_USER_SEARCH",
    "AUTH_LDAP_BIND_DN",
    "AUTH_LDAP_BIND_PASSWORD",
    "AUTH_LDAP_CONNECTION_OPTIONS",
    "AUTH_LDAP_DENY_GROUP",
    "AUTH_LDAP_GROUP_SEARCH",
    "AUTH_LDAP_GROUP_TYPE",
    "AUTH_LDAP_GROUP_TYPE_PARAMS",
    "AUTH_LDAP_ORGANIZATION_MAP",
    "AUTH_LDAP_REQUIRE_GROUP",
    "AUTH_LDAP_SERVER_URI",
    "AUTH_LDAP_START_TLS",
    "AUTH_LDAP_TEAM_MAP",
    "AUTH_LDAP_USER_ATTR_MAP",
    "AUTH_LDAP_USER_DN_TEMPLATE",
    "AUTH_LDAP_USER_FLAGS_BY_GROUP",
    "AUTH_LDAP_USER_SEARCH"
  ],
  "PropertyPostData": {
    "AUTH_LDAP_1_BIND_DN": {
      "category": "LDAP",
      "category_slug": "ldap",
      "computed": true,
      "default": "",
      "default_value": "stringdefault.StaticString(``)",
      "help_text": "DN (Distinguished Name) of user to bind for all search queries. This is the system user account we will use to login to query LDAP for other user information. Refer to the documentation for example syntax.",
      "label": "LDAP Bind DN",
      "name": "AUTH_LDAP_1_BIND_DN",
      "required": false,
      "sensitive": false,
      "type": "string"
    },
    "AUTH_LDAP_1_BIND_PASSWORD": {
      "category": "LDAP",
      "category_slug": "ldap",
      "computed": true,
      "default": "",
      "default_value": "stringdefault.StaticString(``)",
      "help_text": "Password used to bind LDAP user account.",
      "label": "LDAP Bind Password",
      "name": "AUTH_LDAP_1_BIND_PASSWORD",
      "required": false,
      "sensitive": true,
      "type": "string"
    },
    "AUTH_LDAP_1_CONNECTION_OPTIONS": {
      "category": "LDAP",
      "category_slug": "ldap",
      "child": {
        "read_only": false,
        "required": true,
        "type": "field"
      },
      "computed": true,
      "default": {
        "OPT_NETWORK_TIMEOUT": 30,
        "OPT_REFERRALS": 0
      },
      "default_value": "stringdefault.StaticString(`{\"OPT_NETWORK_TIMEOUT\":30,\"OPT_REFERRALS\":0}`)",
      "element_type": "string",
      "help_text": "Additional options to set for the LDAP connection.  LDAP referrals are disabled by default (to prevent certain LDAP queries from hanging with AD). Option names should be strings (e.g. \"OPT_REFERRALS\"). Refer to https://www.python-ldap.org/doc/html/ldap.html#options for possible options and values that can be set.",
      "label": "LDAP Connection Options",
      "name": "AUTH_LDAP_1_CONNECTION_OPTIONS",
      "placeholder": {
        "OPT_NETWORK_TIMEOUT": 30,
        "OPT_REFERRALS": 0
      },
      "required": false,
      "sensitive": false,
      "type": "json"
    },
    "AUTH_LDAP_1_DENY_GROUP": {
      "category": "LDAP",
      "category_slug": "ldap",
      "computed": true,
      "default": null,
      "help_text": "Group DN denied from login. If specified, user will not be allowed to login if a member of this group.  Only one deny group is supported.",
      "label": "LDAP Deny Group",
      "name": "AUTH_LDAP_1_DENY_GROUP",
      "placeholder": "CN=Disabled Users,OU=Users,DC=example,DC=com",
      "required": false,
      "sensitive": false,
      "type": "string"
    },
    "AUTH_LDAP_1_GROUP_SEARCH": {
      "category": "LDAP",
      "category_slug": "ldap",
      "child": {
        "read_only": false,
        "required": true,
        "type": "field"
      },
      "computed": true,
      "default": [],
      "element_type": "string",
      "help_text": "Users are mapped to organizations based on their membership in LDAP groups. This setting defines the LDAP search query to find groups. Unlike the user search, group search does not support LDAPSearchUnion.",
      "label": "LDAP Group Search",
      "name": "AUTH_LDAP_1_GROUP_SEARCH",
      "placeholder": [
        "DC=example,DC=com",
        "SCOPE_SUBTREE",
        "(objectClass=group)"
      ],
      "required": false,
      "sensitive": false,
      "type": "list"
    },
    "AUTH_LDAP_1_GROUP_TYPE": {
      "category": "LDAP",
      "category_slug": "ldap",
      "choices": [
        [
          "PosixGroupType",
          "PosixGroupType"
        ],
        [
          "GroupOfNamesType",
          "GroupOfNamesType"
        ],
        [
          "GroupOfUniqueNamesType",
          "GroupOfUniqueNamesType"
        ],
        [
          "ActiveDirectoryGroupType",
          "ActiveDirectoryGroupType"
        ],
        [
          "OrganizationalRoleGroupType",
          "OrganizationalRoleGroupType"
        ],
        [
          "MemberDNGroupType",
          "MemberDNGroupType"
        ],
        [
          "NestedGroupOfNamesType",
          "NestedGroupOfNamesType"
        ],
        [
          "NestedGroupOfUniqueNamesType",
          "NestedGroupOfUniqueNamesType"
        ],
        [
          "NestedActiveDirectoryGroupType",
          "NestedActiveDirectoryGroupType"
        ],
        [
          "NestedOrganizationalRoleGroupType",
          "NestedOrganizationalRoleGroupType"
        ],
        [
          "NestedMemberDNGroupType",
          "NestedMemberDNGroupType"
        ],
        [
          "PosixUIDGroupType",
          "PosixUIDGroupType"
        ]
      ],
      "computed": true,
      "default": "MemberDNGroupType",
      "default_value": "stringdefault.StaticString(`MemberDNGroupType`)",
      "help_text": "The group type may need to be changed based on the type of the LDAP server.  Values are listed at: https://django-auth-ldap.readthedocs.io/en/stable/groups.html#types-of-groups",
      "label": "LDAP Group Type",
      "name": "AUTH_LDAP_1_GROUP_TYPE",
      "required": false,
      "sensitive": false,
      "type": "choice"
    },
    "AUTH_LDAP_1_GROUP_TYPE_PARAMS": {
      "category": "LDAP",
      "category_slug": "ldap",
      "child": {
        "read_only": false,
        "required": true,
        "type": "field"
      },
      "computed": true,
      "default": {
        "member_attr": "member",
        "name_attr": "cn"
      },
      "default_value": "stringdefault.StaticString(`{\"member_attr\":\"member\",\"name_attr\":\"cn\"}`)",
      "element_type": "string",
      "help_text": "Key value parameters to send the chosen group type init method.",
      "label": "LDAP Group Type Parameters",
      "name": "AUTH_LDAP_1_GROUP_TYPE_PARAMS",
      "placeholder": {
        "ldap_group_user_attr": "legacyuid",
        "member_attr": "member",
        "name_attr": "cn"
      },
      "required": false,
      "sensitive": false,
      "type": "json"
    },
    "AUTH_LDAP_1_ORGANIZATION_MAP": {
      "category": "LDAP",
      "category_slug": "ldap",
      "child": {
        "child": {
          "read_only": false,
          "required": true,
          "type": "field"
        },
        "read_only": false,
        "required": true,
        "type": "nested object"
      },
      "computed": true,
      "default": {},
      "default_value": "stringdefault.StaticString(`{}`)",
      "element_type": "nested object",
      "help_text": "Mapping between organization admins/users and LDAP groups. This controls which users are placed into which organizations relative to their LDAP group memberships. Configuration details are available in the documentation.",
      "label": "LDAP Organization Map",
      "name": "AUTH_LDAP_1_ORGANIZATION_MAP",
      "placeholder": {
        "Test Org": {
          "admins": "CN=Domain Admins,CN=Users,DC=example,DC=com",
          "auditors": "CN=Domain Auditors,CN=Users,DC=example,DC=com",
          "remove_admins": true,
          "remove_users": true,
          "users": [
            "CN=Domain Users,CN=Users,DC=example,DC=com"
          ]
        },
        "Test Org 2": {
          "admins": "CN=Administrators,CN=Builtin,DC=example,DC=com",
          "remove_admins": true,
          "remove_users": true,
          "users": true
        }
      },
      "required": false,
      "sensitive": false,
      "type": "json"
    },
    "AUTH_LDAP_1_REQUIRE_GROUP": {
      "category": "LDAP",
      "category_slug": "ldap",
      "computed": true,
      "default": null,
      "help_text": "Group DN required to login. If specified, user must be a member of this group to login via LDAP. If not set, everyone in LDAP that matches the user search will be able to login to the service. Only one require group is supported.",
      "label": "LDAP Require Group",
      "name": "AUTH_LDAP_1_REQUIRE_GROUP",
      "placeholder": "CN=Service Users,OU=Users,DC=example,DC=com",
      "required": false,
      "sensitive": false,
      "type": "string"
    },
    "AUTH_LDAP_1_SERVER_URI": {
      "category": "LDAP",
      "category_slug": "ldap",
      "computed": true,
      "default": "",
      "default_value": "stringdefault.StaticString(``)",
      "help_text": "URI to connect to LDAP server, such as \"ldap://ldap.example.com:389\" (non-SSL) or \"ldaps://ldap.example.com:636\" (SSL). Multiple LDAP servers may be specified by separating with spaces or commas. LDAP authentication is disabled if this parameter is empty.",
      "label": "LDAP Server URI",
      "name": "AUTH_LDAP_1_SERVER_URI",
      "placeholder": "ldaps://ldap.example.com:636",
      "required": false,
      "sensitive": false,
      "type": "string"
    },
    "AUTH_LDAP_1_START_TLS": {
      "category": "LDAP",
      "category_slug": "ldap",
      "computed": true,
      "default": false,
      "help_text": "Whether to enable TLS when the LDAP connection is not using SSL.",
      "label": "LDAP Start TLS",
      "name": "AUTH_LDAP_1_START_TLS",
      "required": false,
      "sensitive": false,
      "type": "boolean"
    },
    "AUTH_LDAP_1_TEAM_MAP": {
      "category": "LDAP",
      "category_slug": "ldap",
      "child": {
        "child": {
          "read_only": false,
          "required": true,
          "type": "field"
        },
        "read_only": false,
        "required": true,
        "type": "nested object"
      },
      "computed": true,
      "default": {},
      "default_value": "stringdefault.StaticString(`{}`)",
      "element_type": "nested object",
      "help_text": "Mapping between team members (users) and LDAP groups. Configuration details are available in the documentation.",
      "label": "LDAP Team Map",
      "name": "AUTH_LDAP_1_TEAM_MAP",
      "placeholder": {
        "My Team": {
          "organization": "Test Org",
          "remove": true,
          "users": [
            "CN=Domain Users,CN=Users,DC=example,DC=com"
          ]
        },
        "Other Team": {
          "organization": "Test Org 2",
          "remove": false,
          "users": "CN=Other Users,CN=Users,DC=example,DC=com"
        }
      },
      "required": false,
      "sensitive": false,
      "type": "json"
    },
    "AUTH_LDAP_1_USER_ATTR_MAP": {
      "category": "LDAP",
      "category_slug": "ldap",
      "child": {
        "read_only": false,
        "required": true,
        "type": "string"
      },
      "computed": true,
      "default": {},
      "default_value": "stringdefault.StaticString(`{}`)",
      "element_type": "string",
      "help_text": "Mapping of LDAP user schema to API user attributes. The default setting is valid for ActiveDirectory but users with other LDAP configurations may need to change the values. Refer to the documentation for additional details.",
      "label": "LDAP User Attribute Map",
      "name": "AUTH_LDAP_1_USER_ATTR_MAP",
      "placeholder": {
        "email": "mail",
        "first_name": "givenName",
        "last_name": "sn"
      },
      "required": false,
      "sensitive": false,
      "type": "json"
    },
    "AUTH_LDAP_1_USER_DN_TEMPLATE": {
      "category": "LDAP",
      "category_slug": "ldap",
      "computed": true,
      "default": null,
      "help_text": "Alternative to user search, if user DNs are all of the same format. This approach is more efficient for user lookups than searching if it is usable in your organizational environment. If this setting has a value it will be used instead of AUTH_LDAP_USER_SEARCH.",
      "label": "LDAP User DN Template",
      "name": "AUTH_LDAP_1_USER_DN_TEMPLATE",
      "placeholder": "uid=%(user)s,OU=Users,DC=example,DC=com",
      "required": false,
      "sensitive": false,
      "type": "string"
    },
    "AUTH_LDAP_1_USER_FLAGS_BY_GROUP": {
      "category": "LDAP",
      "category_slug": "ldap",
      "child": {
        "child": {
          "read_only": false,
          "required": true,
          "type": "string"
        },
        "read_only": false,
        "required": true,
        "type": "list"
      },
      "computed": true,
      "default": {},
      "default_value": "stringdefault.StaticString(`{}`)",
      "element_type": "list",
      "help_text": "Retrieve users from a given group. At this time, superuser and system auditors are the only groups supported. Refer to the documentation for more detail.",
      "label": "LDAP User Flags By Group",
      "name": "AUTH_LDAP_1_USER_FLAGS_BY_GROUP",
      "placeholder": {
        "is_superuser": "CN=Domain Admins,CN=Users,DC=example,DC=com",
        "is_system_auditor": "CN=Domain Auditors,CN=Users,DC=example,DC=com"
      },
      "required": false,
      "sensitive": false,
      "type": "json"
    },
    "AUTH_LDAP_1_USER_SEARCH": {
      "category": "LDAP",
      "category_slug": "ldap",
      "child": {
        "read_only": false,
        "required": true,
        "type": "field"
      },
      "computed": true,
      "default": [],
      "element_type": "string",
      "help_text": "LDAP search query to find users.  Any user that matches the given pattern will be able to login to the service.  The user should also be mapped into an organization (as defined in the AUTH_LDAP_ORGANIZATION_MAP setting).  If multiple search queries need to be supported use of \"LDAPUnion\" is possible. See the documentation for details.",
      "label": "LDAP User Search",
      "name": "AUTH_LDAP_1_USER_SEARCH",
      "placeholder": [
        "OU=Users,DC=example,DC=com",
        "SCOPE_SUBTREE",
        "(sAMAccountName=%(user)s)"
      ],
      "required": false,
      "sensitive": false,
      "type": "list"
    },
    "AUTH_LDAP_2_BIND_DN": {
      "category": "LDAP",
      "category_slug": "ldap",
      "computed": true,
      "default": "",
      "default_value": "stringdefault.StaticString(``)",
      "help_text": "DN (Distinguished Name) of user to bind for all search queries. This is the system user account we will use to login to query LDAP for other user information. Refer to the documentation for example syntax.",
      "label": "LDAP Bind DN",
      "name": "AUTH_LDAP_2_BIND_DN",
      "required": false,
      "sensitive": false,
      "type": "string"
    },
    "AUTH_LDAP_2_BIND_PASSWORD": {
      "category": "LDAP",
      "category_slug": "ldap",
      "computed": true,
      "default": "",
      "default_value": "stringdefault.StaticString(``)",
      "help_text": "Password used to bind LDAP user account.",
      "label": "LDAP Bind Password",
      "name": "AUTH_LDAP_2_BIND_PASSWORD",
      "required": false,
      "sensitive": true,
      "type": "string"
    },
    "AUTH_LDAP_2_CONNECTION_OPTIONS": {
      "category": "LDAP",
      "category_slug": "ldap",
      "child": {
        "read_only": false,
        "required": true,
        "type": "field"
      },
      "computed": true,
      "default": {
        "OPT_NETWORK_TIMEOUT": 30,
        "OPT_REFERRALS": 0
      },
      "default_value": "stringdefault.StaticString(`{\"OPT_NETWORK_TIMEOUT\":30,\"OPT_REFERRALS\":0}`)",
      "element_type": "string",
      "help_text": "Additional options to set for the LDAP connection.  LDAP referrals are disabled by default (to prevent certain LDAP queries from hanging with AD). Option names should be strings (e.g. \"OPT_REFERRALS\"). Refer to https://www.python-ldap.org/doc/html/ldap.html#options for possible options and values that can be set.",
      "label": "LDAP Connection Options",
      "name": "AUTH_LDAP_2_CONNECTION_OPTIONS",
      "placeholder": {
        "OPT_NETWORK_TIMEOUT": 30,
        "OPT_REFERRALS": 0
      },
      "required": false,
      "sensitive": false,
      "type": "json"
    },
    "AUTH_LDAP_2_DENY_GROUP": {
      "category": "LDAP",
      "category_slug": "ldap",
      "computed": true,
      "default": null,
      "help_text": "Group DN denied from login. If specified, user will not be allowed to login if a member of this group.  Only one deny group is supported.",
      "label": "LDAP Deny Group",
      "name": "AUTH_LDAP_2_DENY_GROUP",
      "placeholder": "CN=Disabled Users,OU=Users,DC=example,DC=com",
      "required": false,
      "sensitive": false,
      "type": "string"
    },
    "AUTH_LDAP_2_GROUP_SEARCH": {
      "category": "LDAP",
      "category_slug": "ldap",
      "child": {
        "read_only": false,
        "required": true,
        "type": "field"
      },
      "computed": true,
      "default": [],
      "element_type": "string",
      "help_text": "Users are mapped to organizations based on their membership in LDAP groups. This setting defines the LDAP search query to find groups. Unlike the user search, group search does not support LDAPSearchUnion.",
      "label": "LDAP Group Search",
      "name": "AUTH_LDAP_2_GROUP_SEARCH",
      "placeholder": [
        "DC=example,DC=com",
        "SCOPE_SUBTREE",
        "(objectClass=group)"
      ],
      "required": false,
      "sensitive": false,
      "type": "list"
    },
    "AUTH_LDAP_2_GROUP_TYPE": {
      "category": "LDAP",
      "category_slug": "ldap",
      "choices": [
        [
          "PosixGroupType",
          "PosixGroupType"
        ],
        [
          "GroupOfNamesType",
          "GroupOfNamesType"
        ],
        [
          "GroupOfUniqueNamesType",
          "GroupOfUniqueNamesType"
        ],
        [
          "ActiveDirectoryGroupType",
          "ActiveDirectoryGroupType"
        ],
        [
          "OrganizationalRoleGroupType",
          "OrganizationalRoleGroupType"
        ],
        [
          "MemberDNGroupType",
          "MemberDNGroupType"
        ],
        [
          "NestedGroupOfNamesType",
          "NestedGroupOfNamesType"
        ],
        [
          "NestedGroupOfUniqueNamesType",
          "NestedGroupOfUniqueNamesType"
        ],
        [
          "NestedActiveDirectoryGroupType",
          "NestedActiveDirectoryGroupType"
        ],
        [
          "NestedOrganizationalRoleGroupType",
          "NestedOrganizationalRoleGroupType"
        ],
        [
          "NestedMemberDNGroupType",
          "NestedMemberDNGroupType"
        ],
        [
          "PosixUIDGroupType",
          "PosixUIDGroupType"
        ]
      ],
      "computed": true,
      "default": "MemberDNGroupType",
      "default_value": "stringdefault.StaticString(`MemberDNGroupType`)",
      "help_text": "The group type may need to be changed based on the type of the LDAP server.  Values are listed at: https://django-auth-ldap.readthedocs.io/en/stable/groups.html#types-of-groups",
      "label": "LDAP Group Type",
      "name": "AUTH_LDAP_2_GROUP_TYPE",
      "required": false,
      "sensitive": false,
      "type": "choice"
    },
    "AUTH_LDAP_2_GROUP_TYPE_PARAMS": {
      "category": "LDAP",
      "category_slug": "ldap",
      "child": {
        "read_only": false,
        "required": true,
        "type": "field"
      },
      "computed": true,
      "default": {
        "member_attr": "member",
        "name_attr": "cn"
      },
      "default_value": "stringdefault.StaticString(`{\"member_attr\":\"member\",\"name_attr\":\"cn\"}`)",
      "element_type": "string",
      "help_text": "Key value parameters to send the chosen group type init method.",
      "label": "LDAP Group Type Parameters",
      "name": "AUTH_LDAP_2_GROUP_TYPE_PARAMS",
      "placeholder": {
        "ldap_group_user_attr": "legacyuid",
        "member_attr": "member",
        "name_attr": "cn"
      },
      "required": false,
      "sensitive": false,
      "type": "json"
    },
    "AUTH_LDAP_2_ORGANIZATION_MAP": {
      "category": "LDAP",
      "category_slug": "ldap",
      "child": {
        "child": {
          "read_only": false,
          "required": true,
          "type": "field"
        },
        "read_only": false,
        "required": true,
        "type": "nested object"
      },
      "computed": true,
      "default": {},
      "default_value": "stringdefault.StaticString(`{}`)",
      "element_type": "nested object",
      "help_text": "Mapping between organization admins/users and LDAP groups. This controls which users are placed into which organizations relative to their LDAP group memberships. Configuration details are available in the documentation.",
      "label": "LDAP Organization Map",
      "name": "AUTH_LDAP_2_ORGANIZATION_MAP",
      "placeholder": {
        "Test Org": {
          "admins": "CN=Domain Admins,CN=Users,DC=example,DC=com",
          "auditors": "CN=Domain Auditors,CN=Users,DC=example,DC=com",
          "remove_admins": true,
          "remove_users": true,
          "users": [
            "CN=Domain Users,CN=Users,DC=example,DC=com"
          ]
        },
        "Test Org 2": {
          "admins": "CN=Administrators,CN=Builtin,DC=example,DC=com",
          "remove_admins": true,
          "remove_users": true,
          "users": true
        }
      },
      "required": false,
      "sensitive": false,
      "type": "json"
    },
    "AUTH_LDAP_2_REQUIRE_GROUP": {
      "category": "LDAP",
      "category_slug": "ldap",
      "computed": true,
      "default": null,
      "help_text": "Group DN required to login. If specified, user must be a member of this group to login via LDAP. If not set, everyone in LDAP that matches the user search will be able to login to the service. Only one require group is supported.",
      "label": "LDAP Require Group",
      "name": "AUTH_LDAP_2_REQUIRE_GROUP",
      "placeholder": "CN=Service Users,OU=Users,DC=example,DC=com",
      "required": false,
      "sensitive": false,
      "type": "string"
    },
    "AUTH_LDAP_2_SERVER_URI": {
      "category": "LDAP",
      "category_slug": "ldap",
      "computed": true,
      "default": "",
      "default_value": "stringdefault.StaticString(``)",
      "help_text": "URI to connect to LDAP server, such as \"ldap://ldap.example.com:389\" (non-SSL) or \"ldaps://ldap.example.com:636\" (SSL). Multiple LDAP servers may be specified by separating with spaces or commas. LDAP authentication is disabled if this parameter is empty.",
      "label": "LDAP Server URI",
      "name": "AUTH_LDAP_2_SERVER_URI",
      "placeholder": "ldaps://ldap.example.com:636",
      "required": false,
      "sensitive": false,
      "type": "string"
    },
    "AUTH_LDAP_2_START_TLS": {
      "category": "LDAP",
      "category_slug": "ldap",
      "computed": true,
      "default": false,
      "help_text": "Whether to enable TLS when the LDAP connection is not using SSL.",
      "label": "LDAP Start TLS",
      "name": "AUTH_LDAP_2_START_TLS",
      "required": false,
      "sensitive": false,
      "type": "boolean"
    },
    "AUTH_LDAP_2_TEAM_MAP": {
      "category": "LDAP",
      "category_slug": "ldap",
      "child": {
        "child": {
          "read_only": false,
          "required": true,
          "type": "field"
        },
        "read_only": false,
        "required": true,
        "type": "nested object"
      },
      "computed": true,
      "default": {},
      "default_value": "stringdefault.StaticString(`{}`)",
      "element_type": "nested object",
      "help_text": "Mapping between team members (users) and LDAP groups. Configuration details are available in the documentation.",
      "label": "LDAP Team Map",
      "name": "AUTH_LDAP_2_TEAM_MAP",
      "placeholder": {
        "My Team": {
          "organization": "Test Org",
          "remove": true,
          "users": [
            "CN=Domain Users,CN=Users,DC=example,DC=com"
          ]
        },
        "Other Team": {
          "organization": "Test Org 2",
          "remove": false,
          "users": "CN=Other Users,CN=Users,DC=example,DC=com"
        }
      },
      "required": false,
      "sensitive": false,
      "type": "json"
    },
    "AUTH_LDAP_2_USER_ATTR_MAP": {
      "category": "LDAP",
      "category_slug": "ldap",
      "child": {
        "read_only": false,
        "required": true,
        "type": "string"
      },
      "computed": true,
      "default": {},
      "default_value": "stringdefault.StaticString(`{}`)",
      "element_type": "string",
      "help_text": "Mapping of LDAP user schema to API user attributes. The default setting is valid for ActiveDirectory but users with other LDAP configurations may need to change the values. Refer to the documentation for additional details.",
      "label": "LDAP User Attribute Map",
      "name": "AUTH_LDAP_2_USER_ATTR_MAP",
      "placeholder": {
        "email": "mail",
        "first_name": "givenName",
        "last_name": "sn"
      },
      "required": false,
      "sensitive": false,
      "type": "json"
    },
    "AUTH_LDAP_2_USER_DN_TEMPLATE": {
      "category": "LDAP",
      "category_slug": "ldap",
      "computed": true,
      "default": null,
      "help_text": "Alternative to user search, if user DNs are all of the same format. This approach is more efficient for user lookups than searching if it is usable in your organizational environment. If this setting has a value it will be used instead of AUTH_LDAP_USER_SEARCH.",
      "label": "LDAP User DN Template",
      "name": "AUTH_LDAP_2_USER_DN_TEMPLATE",
      "placeholder": "uid=%(user)s,OU=Users,DC=example,DC=com",
      "required": false,
      "sensitive": false,
      "type": "string"
    },
    "AUTH_LDAP_2_USER_FLAGS_BY_GROUP": {
      "category": "LDAP",
      "category_slug": "ldap",
      "child": {
        "child": {
          "read_only": false,
          "required": true,
          "type": "string"
        },
        "read_only": false,
        "required": true,
        "type": "list"
      },
      "computed": true,
      "default": {},
      "default_value": "stringdefault.StaticString(`{}`)",
      "element_type": "list",
      "help_text": "Retrieve users from a given group. At this time, superuser and system auditors are the only groups supported. Refer to the documentation for more detail.",
      "label": "LDAP User Flags By Group",
      "name": "AUTH_LDAP_2_USER_FLAGS_BY_GROUP",
      "placeholder": {
        "is_superuser": "CN=Domain Admins,CN=Users,DC=example,DC=com",
        "is_system_auditor": "CN=Domain Auditors,CN=Users,DC=example,DC=com"
      },
      "required": false,
      "sensitive": false,
      "type": "json"
    },
    "AUTH_LDAP_2_USER_SEARCH": {
      "category": "LDAP",
      "category_slug": "ldap",
      "child": {
        "read_only": false,
        "required": true,
        "type": "field"
      },
      "computed": true,
      "default": [],
      "element_type": "string",
      "help_text": "LDAP search query to find users.  Any user that matches the given pattern will be able to login to the service.  The user should also be mapped into an organization (as defined in the AUTH_LDAP_ORGANIZATION_MAP setting).  If multiple search queries need to be supported use of \"LDAPUnion\" is possible. See the documentation for details.",
      "label": "LDAP User Search",
      "name": "AUTH_LDAP_2_USER_SEARCH",
      "placeholder": [
        "OU=Users,DC=example,DC=com",
        "SCOPE_SUBTREE",
        "(sAMAccountName=%(user)s)"
      ],
      "required": false,
      "sensitive": false,
      "type": "list"
    },
    "AUTH_LDAP_3_BIND_DN": {
      "category": "LDAP",
      "category_slug": "ldap",
      "computed": true,
      "default": "",
      "default_value": "stringdefault.StaticString(``)",
      "help_text": "DN (Distinguished Name) of user to bind for all search queries. This is the system user account we will use to login to query LDAP for other user information. Refer to the documentation for example syntax.",
      "label": "LDAP Bind DN",
      "name": "AUTH_LDAP_3_BIND_DN",
      "required": false,
      "sensitive": false,
      "type": "string"
    },
    "AUTH_LDAP_3_BIND_PASSWORD": {
      "category": "LDAP",
      "category_slug": "ldap",
      "computed": true,
      "default": "",
      "default_value": "stringdefault.StaticString(``)",
      "help_text": "Password used to bind LDAP user account.",
      "label": "LDAP Bind Password",
      "name": "AUTH_LDAP_3_BIND_PASSWORD",
      "required": false,
      "sensitive": true,
      "type": "string"
    },
    "AUTH_LDAP_3_CONNECTION_OPTIONS": {
      "category": "LDAP",
      "category_slug": "ldap",
      "child": {
        "read_only": false,
        "required": true,
        "type": "field"
      },
      "computed": true,
      "default": {
        "OPT_NETWORK_TIMEOUT": 30,
        "OPT_REFERRALS": 0
      },
      "default_value": "stringdefault.StaticString(`{\"OPT_NETWORK_TIMEOUT\":30,\"OPT_REFERRALS\":0}`)",
      "element_type": "string",
      "help_text": "Additional options to set for the LDAP connection.  LDAP referrals are disabled by default (to prevent certain LDAP queries from hanging with AD). Option names should be strings (e.g. \"OPT_REFERRALS\"). Refer to https://www.python-ldap.org/doc/html/ldap.html#options for possible options and values that can be set.",
      "label": "LDAP Connection Options",
      "name": "AUTH_LDAP_3_CONNECTION_OPTIONS",
      "placeholder": {
        "OPT_NETWORK_TIMEOUT": 30,
        "OPT_REFERRALS": 0
      },
      "required": false,
      "sensitive": false,
      "type": "json"
    },
    "AUTH_LDAP_3_DENY_GROUP": {
      "category": "LDAP",
      "category_slug": "ldap",
      "computed": true,
      "default": null,
      "help_text": "Group DN denied from login. If specified, user will not be allowed to login if a member of this group.  Only one deny group is supported.",
      "label": "LDAP Deny Group",
      "name": "AUTH_LDAP_3_DENY_GROUP",
      "placeholder": "CN=Disabled Users,OU=Users,DC=example,DC=com",
      "required": false,
      "sensitive": false,
      "type": "string"
    },
    "AUTH_LDAP_3_GROUP_SEARCH": {
      "category": "LDAP",
      "category_slug": "ldap",
      "child": {
        "read_only": false,
        "required": true,
        "type": "field"
      },
      "computed": true,
      "default": [],
      "element_type": "string",
      "help_text": "Users are mapped to organizations based on their membership in LDAP groups. This setting defines the LDAP search query to find groups. Unlike the user search, group search does not support LDAPSearchUnion.",
      "label": "LDAP Group Search",
      "name": "AUTH_LDAP_3_GROUP_SEARCH",
      "placeholder": [
        "DC=example,DC=com",
        "SCOPE_SUBTREE",
        "(objectClass=group)"
      ],
      "required": false,
      "sensitive": false,
      "type": "list"
    },
    "AUTH_LDAP_3_GROUP_TYPE": {
      "category": "LDAP",
      "category_slug": "ldap",
      "choices": [
        [
          "PosixGroupType",
          "PosixGroupType"
        ],
        [
          "GroupOfNamesType",
          "GroupOfNamesType"
        ],
        [
          "GroupOfUniqueNamesType",
          "GroupOfUniqueNamesType"
        ],
        [
          "ActiveDirectoryGroupType",
          "ActiveDirectoryGroupType"
        ],
        [
          "OrganizationalRoleGroupType",
          "OrganizationalRoleGroupType"
        ],
        [
          "MemberDNGroupType",
          "MemberDNGroupType"
        ],
        [
          "NestedGroupOfNamesType",
          "NestedGroupOfNamesType"
        ],
        [
          "NestedGroupOfUniqueNamesType",
          "NestedGroupOfUniqueNamesType"
        ],
        [
          "NestedActiveDirectoryGroupType",
          "NestedActiveDirectoryGroupType"
        ],
        [
          "NestedOrganizationalRoleGroupType",
          "NestedOrganizationalRoleGroupType"
        ],
        [
          "NestedMemberDNGroupType",
          "NestedMemberDNGroupType"
        ],
        [
          "PosixUIDGroupType",
          "PosixUIDGroupType"
        ]
      ],
      "computed": true,
      "default": "MemberDNGroupType",
      "default_value": "stringdefault.StaticString(`MemberDNGroupType`)",
      "help_text": "The group type may need to be changed based on the type of the LDAP server.  Values are listed at: https://django-auth-ldap.readthedocs.io/en/stable/groups.html#types-of-groups",
      "label": "LDAP Group Type",
      "name": "AUTH_LDAP_3_GROUP_TYPE",
      "required": false,
      "sensitive": false,
      "type": "choice"
    },
    "AUTH_LDAP_3_GROUP_TYPE_PARAMS": {
      "category": "LDAP",
      "category_slug": "ldap",
      "child": {
        "read_only": false,
        "required": true,
        "type": "field"
      },
      "computed": true,
      "default": {
        "member_attr": "member",
        "name_attr": "cn"
      },
      "default_value": "stringdefault.StaticString(`{\"member_attr\":\"member\",\"name_attr\":\"cn\"}`)",
      "element_type": "string",
      "help_text": "Key value parameters to send the chosen group type init method.",
      "label": "LDAP Group Type Parameters",
      "name": "AUTH_LDAP_3_GROUP_TYPE_PARAMS",
      "placeholder": {
        "ldap_group_user_attr": "legacyuid",
        "member_attr": "member",
        "name_attr": "cn"
      },
      "required": false,
      "sensitive": false,
      "type": "json"
    },
    "AUTH_LDAP_3_ORGANIZATION_MAP": {
      "category": "LDAP",
      "category_slug": "ldap",
      "child": {
        "child": {
          "read_only": false,
          "required": true,
          "type": "field"
        },
        "read_only": false,
        "required": true,
        "type": "nested object"
      },
      "computed": true,
      "default": {},
      "default_value": "stringdefault.StaticString(`{}`)",
      "element_type": "nested object",
      "help_text": "Mapping between organization admins/users and LDAP groups. This controls which users are placed into which organizations relative to their LDAP group memberships. Configuration details are available in the documentation.",
      "label": "LDAP Organization Map",
      "name": "AUTH_LDAP_3_ORGANIZATION_MAP",
      "placeholder": {
        "Test Org": {
          "admins": "CN=Domain Admins,CN=Users,DC=example,DC=com",
          "auditors": "CN=Domain Auditors,CN=Users,DC=example,DC=com",
          "remove_admins": true,
          "remove_users": true,
          "users": [
            "CN=Domain Users,CN=Users,DC=example,DC=com"
          ]
        },
        "Test Org 2": {
          "admins": "CN=Administrators,CN=Builtin,DC=example,DC=com",
          "remove_admins": true,
          "remove_users": true,
          "users": true
        }
      },
      "required": false,
      "sensitive": false,
      "type": "json"
    },
    "AUTH_LDAP_3_REQUIRE_GROUP": {
      "category": "LDAP",
      "category_slug": "ldap",
      "computed": true,
      "default": null,
      "help_text": "Group DN required to login. If specified, user must be a member of this group to login via LDAP. If not set, everyone in LDAP that matches the user search will be able to login to the service. Only one require group is supported.",
      "label": "LDAP Require Group",
      "name": "AUTH_LDAP_3_REQUIRE_GROUP",
      "placeholder": "CN=Service Users,OU=Users,DC=example,DC=com",
      "required": false,
      "sensitive": false,
      "type": "string"
    },
    "AUTH_LDAP_3_SERVER_URI": {
      "category": "LDAP",
      "category_slug": "ldap",
      "computed": true,
      "default": "",
      "default_value": "stringdefault.StaticString(``)",
      "help_text": "URI to connect to LDAP server, such as \"ldap://ldap.example.com:389\" (non-SSL) or \"ldaps://ldap.example.com:636\" (SSL). Multiple LDAP servers may be specified by separating with spaces or commas. LDAP authentication is disabled if this parameter is empty.",
      "label": "LDAP Server URI",
      "name": "AUTH_LDAP_3_SERVER_URI",
      "placeholder": "ldaps://ldap.example.com:636",
      "required": false,
      "sensitive": false,
      "type": "string"
    },
    "AUTH_LDAP_3_START_TLS": {
      "category": "LDAP",
      "category_slug": "ldap",
      "computed": true,
      "default": false,
      "help_text": "Whether to enable TLS when the LDAP connection is not using SSL.",
      "label": "LDAP Start TLS",
      "name": "AUTH_LDAP_3_START_TLS",
      "required": false,
      "sensitive": false,
      "type": "boolean"
    },
    "AUTH_LDAP_3_TEAM_MAP": {
      "category": "LDAP",
      "category_slug": "ldap",
      "child": {
        "child": {
          "read_only": false,
          "required": true,
          "type": "field"
        },
        "read_only": false,
        "required": true,
        "type": "nested object"
      },
      "computed": true,
      "default": {},
      "default_value": "stringdefault.StaticString(`{}`)",
      "element_type": "nested object",
      "help_text": "Mapping between team members (users) and LDAP groups. Configuration details are available in the documentation.",
      "label": "LDAP Team Map",
      "name": "AUTH_LDAP_3_TEAM_MAP",
      "placeholder": {
        "My Team": {
          "organization": "Test Org",
          "remove": true,
          "users": [
            "CN=Domain Users,CN=Users,DC=example,DC=com"
          ]
        },
        "Other Team": {
          "organization": "Test Org 2",
          "remove": false,
          "users": "CN=Other Users,CN=Users,DC=example,DC=com"
        }
      },
      "required": false,
      "sensitive": false,
      "type": "json"
    },
    "AUTH_LDAP_3_USER_ATTR_MAP": {
      "category": "LDAP",
      "category_slug": "ldap",
      "child": {
        "read_only": false,
        "required": true,
        "type": "string"
      },
      "computed": true,
      "default": {},
      "default_value": "stringdefault.StaticString(`{}`)",
      "element_type": "string",
      "help_text": "Mapping of LDAP user schema to API user attributes. The default setting is valid for ActiveDirectory but users with other LDAP configurations may need to change the values. Refer to the documentation for additional details.",
      "label": "LDAP User Attribute Map",
      "name": "AUTH_LDAP_3_USER_ATTR_MAP",
      "placeholder": {
        "email": "mail",
        "first_name": "givenName",
        "last_name": "sn"
      },
      "required": false,
      "sensitive": false,
      "type": "json"
    },
    "AUTH_LDAP_3_USER_DN_TEMPLATE": {
      "category": "LDAP",
      "category_slug": "ldap",
      "computed": true,
      "default": null,
      "help_text": "Alternative to user search, if user DNs are all of the same format. This approach is more efficient for user lookups than searching if it is usable in your organizational environment. If this setting has a value it will be used instead of AUTH_LDAP_USER_SEARCH.",
      "label": "LDAP User DN Template",
      "name": "AUTH_LDAP_3_USER_DN_TEMPLATE",
      "placeholder": "uid=%(user)s,OU=Users,DC=example,DC=com",
      "required": false,
      "sensitive": false,
      "type": "string"
    },
    "AUTH_LDAP_3_USER_FLAGS_BY_GROUP": {
      "category": "LDAP",
      "category_slug": "ldap",
      "child": {
        "child": {
          "read_only": false,
          "required": true,
          "type": "string"
        },
        "read_only": false,
        "required": true,
        "type": "list"
      },
      "computed": true,
      "default": {},
      "default_value": "stringdefault.StaticString(`{}`)",
      "element_type": "list",
      "help_text": "Retrieve users from a given group. At this time, superuser and system auditors are the only groups supported. Refer to the documentation for more detail.",
      "label": "LDAP User Flags By Group",
      "name": "AUTH_LDAP_3_USER_FLAGS_BY_GROUP",
      "placeholder": {
        "is_superuser": "CN=Domain Admins,CN=Users,DC=example,DC=com",
        "is_system_auditor": "CN=Domain Auditors,CN=Users,DC=example,DC=com"
      },
      "required": false,
      "sensitive": false,
      "type": "json"
    },
    "AUTH_LDAP_3_USER_SEARCH": {
      "category": "LDAP",
      "category_slug": "ldap",
      "child": {
        "read_only": false,
        "required": true,
        "type": "field"
      },
      "computed": true,
      "default": [],
      "element_type": "string",
      "help_text": "LDAP search query to find users.  Any user that matches the given pattern will be able to login to the service.  The user should also be mapped into an organization (as defined in the AUTH_LDAP_ORGANIZATION_MAP setting).  If multiple search queries need to be supported use of \"LDAPUnion\" is possible. See the documentation for details.",
      "label": "LDAP User Search",
      "name": "AUTH_LDAP_3_USER_SEARCH",
      "placeholder": [
        "OU=Users,DC=example,DC=com",
        "SCOPE_SUBTREE",
        "(sAMAccountName=%(user)s)"
      ],
      "required": false,
      "sensitive": false,
      "type": "list"
    },
    "AUTH_LDAP_4_BIND_DN": {
      "category": "LDAP",
      "category_slug": "ldap",
      "computed": true,
      "default": "",
      "default_value": "stringdefault.StaticString(``)",
      "help_text": "DN (Distinguished Name) of user to bind for all search queries. This is the system user account we will use to login to query LDAP for other user information. Refer to the documentation for example syntax.",
      "label": "LDAP Bind DN",
      "name": "AUTH_LDAP_4_BIND_DN",
      "required": false,
      "sensitive": false,
      "type": "string"
    },
    "AUTH_LDAP_4_BIND_PASSWORD": {
      "category": "LDAP",
      "category_slug": "ldap",
      "computed": true,
      "default": "",
      "default_value": "stringdefault.StaticString(``)",
      "help_text": "Password used to bind LDAP user account.",
      "label": "LDAP Bind Password",
      "name": "AUTH_LDAP_4_BIND_PASSWORD",
      "required": false,
      "sensitive": true,
      "type": "string"
    },
    "AUTH_LDAP_4_CONNECTION_OPTIONS": {
      "category": "LDAP",
      "category_slug": "ldap",
      "child": {
        "read_only": false,
        "required": true,
        "type": "field"
      },
      "computed": true,
      "default": {
        "OPT_NETWORK_TIMEOUT": 30,
        "OPT_REFERRALS": 0
      },
      "default_value": "stringdefault.StaticString(`{\"OPT_NETWORK_TIMEOUT\":30,\"OPT_REFERRALS\":0}`)",
      "element_type": "string",
      "help_text": "Additional options to set for the LDAP connection.  LDAP referrals are disabled by default (to prevent certain LDAP queries from hanging with AD). Option names should be strings (e.g. \"OPT_REFERRALS\"). Refer to https://www.python-ldap.org/doc/html/ldap.html#options for possible options and values that can be set.",
      "label": "LDAP Connection Options",
      "name": "AUTH_LDAP_4_CONNECTION_OPTIONS",
      "placeholder": {
        "OPT_NETWORK_TIMEOUT": 30,
        "OPT_REFERRALS": 0
      },
      "required": false,
      "sensitive": false,
      "type": "json"
    },
    "AUTH_LDAP_4_DENY_GROUP": {
      "category": "LDAP",
      "category_slug": "ldap",
      "computed": true,
      "default": null,
      "help_text": "Group DN denied from login. If specified, user will not be allowed to login if a member of this group.  Only one deny group is supported.",
      "label": "LDAP Deny Group",
      "name": "AUTH_LDAP_4_DENY_GROUP",
      "placeholder": "CN=Disabled Users,OU=Users,DC=example,DC=com",
      "required": false,
      "sensitive": false,
      "type": "string"
    },
    "AUTH_LDAP_4_GROUP_SEARCH": {
      "category": "LDAP",
      "category_slug": "ldap",
      "child": {
        "read_only": false,
        "required": true,
        "type": "field"
      },
      "computed": true,
      "default": [],
      "element_type": "string",
      "help_text": "Users are mapped to organizations based on their membership in LDAP groups. This setting defines the LDAP search query to find groups. Unlike the user search, group search does not support LDAPSearchUnion.",
      "label": "LDAP Group Search",
      "name": "AUTH_LDAP_4_GROUP_SEARCH",
      "placeholder": [
        "DC=example,DC=com",
        "SCOPE_SUBTREE",
        "(objectClass=group)"
      ],
      "required": false,
      "sensitive": false,
      "type": "list"
    },
    "AUTH_LDAP_4_GROUP_TYPE": {
      "category": "LDAP",
      "category_slug": "ldap",
      "choices": [
        [
          "PosixGroupType",
          "PosixGroupType"
        ],
        [
          "GroupOfNamesType",
          "GroupOfNamesType"
        ],
        [
          "GroupOfUniqueNamesType",
          "GroupOfUniqueNamesType"
        ],
        [
          "ActiveDirectoryGroupType",
          "ActiveDirectoryGroupType"
        ],
        [
          "OrganizationalRoleGroupType",
          "OrganizationalRoleGroupType"
        ],
        [
          "MemberDNGroupType",
          "MemberDNGroupType"
        ],
        [
          "NestedGroupOfNamesType",
          "NestedGroupOfNamesType"
        ],
        [
          "NestedGroupOfUniqueNamesType",
          "NestedGroupOfUniqueNamesType"
        ],
        [
          "NestedActiveDirectoryGroupType",
          "NestedActiveDirectoryGroupType"
        ],
        [
          "NestedOrganizationalRoleGroupType",
          "NestedOrganizationalRoleGroupType"
        ],
        [
          "NestedMemberDNGroupType",
          "NestedMemberDNGroupType"
        ],
        [
          "PosixUIDGroupType",
          "PosixUIDGroupType"
        ]
      ],
      "computed": true,
      "default": "MemberDNGroupType",
      "default_value": "stringdefault.StaticString(`MemberDNGroupType`)",
      "help_text": "The group type may need to be changed based on the type of the LDAP server.  Values are listed at: https://django-auth-ldap.readthedocs.io/en/stable/groups.html#types-of-groups",
      "label": "LDAP Group Type",
      "name": "AUTH_LDAP_4_GROUP_TYPE",
      "required": false,
      "sensitive": false,
      "type": "choice"
    },
    "AUTH_LDAP_4_GROUP_TYPE_PARAMS": {
      "category": "LDAP",
      "category_slug": "ldap",
      "child": {
        "read_only": false,
        "required": true,
        "type": "field"
      },
      "computed": true,
      "default": {
        "member_attr": "member",
        "name_attr": "cn"
      },
      "default_value": "stringdefault.StaticString(`{\"member_attr\":\"member\",\"name_attr\":\"cn\"}`)",
      "element_type": "string",
      "help_text": "Key value parameters to send the chosen group type init method.",
      "label": "LDAP Group Type Parameters",
      "name": "AUTH_LDAP_4_GROUP_TYPE_PARAMS",
      "placeholder": {
        "ldap_group_user_attr": "legacyuid",
        "member_attr": "member",
        "name_attr": "cn"
      },
      "required": false,
      "sensitive": false,
      "type": "json"
    },
    "AUTH_LDAP_4_ORGANIZATION_MAP": {
      "category": "LDAP",
      "category_slug": "ldap",
      "child": {
        "child": {
          "read_only": false,
          "required": true,
          "type": "field"
        },
        "read_only": false,
        "required": true,
        "type": "nested object"
      },
      "computed": true,
      "default": {},
      "default_value": "stringdefault.StaticString(`{}`)",
      "element_type": "nested object",
      "help_text": "Mapping between organization admins/users and LDAP groups. This controls which users are placed into which organizations relative to their LDAP group memberships. Configuration details are available in the documentation.",
      "label": "LDAP Organization Map",
      "name": "AUTH_LDAP_4_ORGANIZATION_MAP",
      "placeholder": {
        "Test Org": {
          "admins": "CN=Domain Admins,CN=Users,DC=example,DC=com",
          "auditors": "CN=Domain Auditors,CN=Users,DC=example,DC=com",
          "remove_admins": true,
          "remove_users": true,
          "users": [
            "CN=Domain Users,CN=Users,DC=example,DC=com"
          ]
        },
        "Test Org 2": {
          "admins": "CN=Administrators,CN=Builtin,DC=example,DC=com",
          "remove_admins": true,
          "remove_users": true,
          "users": true
        }
      },
      "required": false,
      "sensitive": false,
      "type": "json"
    },
    "AUTH_LDAP_4_REQUIRE_GROUP": {
      "category": "LDAP",
      "category_slug": "ldap",
      "computed": true,
      "default": null,
      "help_text": "Group DN required to login. If specified, user must be a member of this group to login via LDAP. If not set, everyone in LDAP that matches the user search will be able to login to the service. Only one require group is supported.",
      "label": "LDAP Require Group",
      "name": "AUTH_LDAP_4_REQUIRE_GROUP",
      "placeholder": "CN=Service Users,OU=Users,DC=example,DC=com",
      "required": false,
      "sensitive": false,
      "type": "string"
    },
    "AUTH_LDAP_4_SERVER_URI": {
      "category": "LDAP",
      "category_slug": "ldap",
      "computed": true,
      "default": "",
      "default_value": "stringdefault.StaticString(``)",
      "help_text": "URI to connect to LDAP server, such as \"ldap://ldap.example.com:389\" (non-SSL) or \"ldaps://ldap.example.com:636\" (SSL). Multiple LDAP servers may be specified by separating with spaces or commas. LDAP authentication is disabled if this parameter is empty.",
      "label": "LDAP Server URI",
      "name": "AUTH_LDAP_4_SERVER_URI",
      "placeholder": "ldaps://ldap.example.com:636",
      "required": false,
      "sensitive": false,
      "type": "string"
    },
    "AUTH_LDAP_4_START_TLS": {
      "category": "LDAP",
      "category_slug": "ldap",
      "computed": true,
      "default": false,
      "help_text": "Whether to enable TLS when the LDAP connection is not using SSL.",
      "label": "LDAP Start TLS",
      "name": "AUTH_LDAP_4_START_TLS",
      "required": false,
      "sensitive": false,
      "type": "boolean"
    },
    "AUTH_LDAP_4_TEAM_MAP": {
      "category": "LDAP",
      "category_slug": "ldap",
      "child": {
        "child": {
          "read_only": false,
          "required": true,
          "type": "field"
        },
        "read_only": false,
        "required": true,
        "type": "nested object"
      },
      "computed": true,
      "default": {},
      "default_value": "stringdefault.StaticString(`{}`)",
      "element_type": "nested object",
      "help_text": "Mapping between team members (users) and LDAP groups. Configuration details are available in the documentation.",
      "label": "LDAP Team Map",
      "name": "AUTH_LDAP_4_TEAM_MAP",
      "placeholder": {
        "My Team": {
          "organization": "Test Org",
          "remove": true,
          "users": [
            "CN=Domain Users,CN=Users,DC=example,DC=com"
          ]
        },
        "Other Team": {
          "organization": "Test Org 2",
          "remove": false,
          "users": "CN=Other Users,CN=Users,DC=example,DC=com"
        }
      },
      "required": false,
      "sensitive": false,
      "type": "json"
    },
    "AUTH_LDAP_4_USER_ATTR_MAP": {
      "category": "LDAP",
      "category_slug": "ldap",
      "child": {
        "read_only": false,
        "required": true,
        "type": "string"
      },
      "computed": true,
      "default": {},
      "default_value": "stringdefault.StaticString(`{}`)",
      "element_type": "string",
      "help_text": "Mapping of LDAP user schema to API user attributes. The default setting is valid for ActiveDirectory but users with other LDAP configurations may need to change the values. Refer to the documentation for additional details.",
      "label": "LDAP User Attribute Map",
      "name": "AUTH_LDAP_4_USER_ATTR_MAP",
      "placeholder": {
        "email": "mail",
        "first_name": "givenName",
        "last_name": "sn"
      },
      "required": false,
      "sensitive": false,
      "type": "json"
    },
    "AUTH_LDAP_4_USER_DN_TEMPLATE": {
      "category": "LDAP",
      "category_slug": "ldap",
      "computed": true,
      "default": null,
      "help_text": "Alternative to user search, if user DNs are all of the same format. This approach is more efficient for user lookups than searching if it is usable in your organizational environment. If this setting has a value it will be used instead of AUTH_LDAP_USER_SEARCH.",
      "label": "LDAP User DN Template",
      "name": "AUTH_LDAP_4_USER_DN_TEMPLATE",
      "placeholder": "uid=%(user)s,OU=Users,DC=example,DC=com",
      "required": false,
      "sensitive": false,
      "type": "string"
    },
    "AUTH_LDAP_4_USER_FLAGS_BY_GROUP": {
      "category": "LDAP",
      "category_slug": "ldap",
      "child": {
        "child": {
          "read_only": false,
          "required": true,
          "type": "string"
        },
        "read_only": false,
        "required": true,
        "type": "list"
      },
      "computed": true,
      "default": {},
      "default_value": "stringdefault.StaticString(`{}`)",
      "element_type": "list",
      "help_text": "Retrieve users from a given group. At this time, superuser and system auditors are the only groups supported. Refer to the documentation for more detail.",
      "label": "LDAP User Flags By Group",
      "name": "AUTH_LDAP_4_USER_FLAGS_BY_GROUP",
      "placeholder": {
        "is_superuser": "CN=Domain Admins,CN=Users,DC=example,DC=com",
        "is_system_auditor": "CN=Domain Auditors,CN=Users,DC=example,DC=com"
      },
      "required": false,
      "sensitive": false,
      "type": "json"
    },
    "AUTH_LDAP_4_USER_SEARCH": {
      "category": "LDAP",
      "category_slug": "ldap",
      "child": {
        "read_only": false,
        "required": true,
        "type": "field"
      },
      "computed": true,
      "default": [],
      "element_type": "string",
      "help_text": "LDAP search query to find users.  Any user that matches the given pattern will be able to login to the service.  The user should also be mapped into an organization (as defined in the AUTH_LDAP_ORGANIZATION_MAP setting).  If multiple search queries need to be supported use of \"LDAPUnion\" is possible. See the documentation for details.",
      "label": "LDAP User Search",
      "name": "AUTH_LDAP_4_USER_SEARCH",
      "placeholder": [
        "OU=Users,DC=example,DC=com",
        "SCOPE_SUBTREE",
        "(sAMAccountName=%(user)s)"
      ],
      "required": false,
      "sensitive": false,
      "type": "list"
    },
    "AUTH_LDAP_5_BIND_DN": {
      "category": "LDAP",
      "category_slug": "ldap",
      "computed": true,
      "default": "",
      "default_value": "stringdefault.StaticString(``)",
      "help_text": "DN (Distinguished Name) of user to bind for all search queries. This is the system user account we will use to login to query LDAP for other user information. Refer to the documentation for example syntax.",
      "label": "LDAP Bind DN",
      "name": "AUTH_LDAP_5_BIND_DN",
      "required": false,
      "sensitive": false,
      "type": "string"
    },
    "AUTH_LDAP_5_BIND_PASSWORD": {
      "category": "LDAP",
      "category_slug": "ldap",
      "computed": true,
      "default": "",
      "default_value": "stringdefault.StaticString(``)",
      "help_text": "Password used to bind LDAP user account.",
      "label": "LDAP Bind Password",
      "name": "AUTH_LDAP_5_BIND_PASSWORD",
      "required": false,
      "sensitive": true,
      "type": "string"
    },
    "AUTH_LDAP_5_CONNECTION_OPTIONS": {
      "category": "LDAP",
      "category_slug": "ldap",
      "child": {
        "read_only": false,
        "required": true,
        "type": "field"
      },
      "computed": true,
      "default": {
        "OPT_NETWORK_TIMEOUT": 30,
        "OPT_REFERRALS": 0
      },
      "default_value": "stringdefault.StaticString(`{\"OPT_NETWORK_TIMEOUT\":30,\"OPT_REFERRALS\":0}`)",
      "element_type": "string",
      "help_text": "Additional options to set for the LDAP connection.  LDAP referrals are disabled by default (to prevent certain LDAP queries from hanging with AD). Option names should be strings (e.g. \"OPT_REFERRALS\"). Refer to https://www.python-ldap.org/doc/html/ldap.html#options for possible options and values that can be set.",
      "label": "LDAP Connection Options",
      "name": "AUTH_LDAP_5_CONNECTION_OPTIONS",
      "placeholder": {
        "OPT_NETWORK_TIMEOUT": 30,
        "OPT_REFERRALS": 0
      },
      "required": false,
      "sensitive": false,
      "type": "json"
    },
    "AUTH_LDAP_5_DENY_GROUP": {
      "category": "LDAP",
      "category_slug": "ldap",
      "computed": true,
      "default": null,
      "help_text": "Group DN denied from login. If specified, user will not be allowed to login if a member of this group.  Only one deny group is supported.",
      "label": "LDAP Deny Group",
      "name": "AUTH_LDAP_5_DENY_GROUP",
      "placeholder": "CN=Disabled Users,OU=Users,DC=example,DC=com",
      "required": false,
      "sensitive": false,
      "type": "string"
    },
    "AUTH_LDAP_5_GROUP_SEARCH": {
      "category": "LDAP",
      "category_slug": "ldap",
      "child": {
        "read_only": false,
        "required": true,
        "type": "field"
      },
      "computed": true,
      "default": [],
      "element_type": "string",
      "help_text": "Users are mapped to organizations based on their membership in LDAP groups. This setting defines the LDAP search query to find groups. Unlike the user search, group search does not support LDAPSearchUnion.",
      "label": "LDAP Group Search",
      "name": "AUTH_LDAP_5_GROUP_SEARCH",
      "placeholder": [
        "DC=example,DC=com",
        "SCOPE_SUBTREE",
        "(objectClass=group)"
      ],
      "required": false,
      "sensitive": false,
      "type": "list"
    },
    "AUTH_LDAP_5_GROUP_TYPE": {
      "category": "LDAP",
      "category_slug": "ldap",
      "choices": [
        [
          "PosixGroupType",
          "PosixGroupType"
        ],
        [
          "GroupOfNamesType",
          "GroupOfNamesType"
        ],
        [
          "GroupOfUniqueNamesType",
          "GroupOfUniqueNamesType"
        ],
        [
          "ActiveDirectoryGroupType",
          "ActiveDirectoryGroupType"
        ],
        [
          "OrganizationalRoleGroupType",
          "OrganizationalRoleGroupType"
        ],
        [
          "MemberDNGroupType",
          "MemberDNGroupType"
        ],
        [
          "NestedGroupOfNamesType",
          "NestedGroupOfNamesType"
        ],
        [
          "NestedGroupOfUniqueNamesType",
          "NestedGroupOfUniqueNamesType"
        ],
        [
          "NestedActiveDirectoryGroupType",
          "NestedActiveDirectoryGroupType"
        ],
        [
          "NestedOrganizationalRoleGroupType",
          "NestedOrganizationalRoleGroupType"
        ],
        [
          "NestedMemberDNGroupType",
          "NestedMemberDNGroupType"
        ],
        [
          "PosixUIDGroupType",
          "PosixUIDGroupType"
        ]
      ],
      "computed": true,
      "default": "MemberDNGroupType",
      "default_value": "stringdefault.StaticString(`MemberDNGroupType`)",
      "help_text": "The group type may need to be changed based on the type of the LDAP server.  Values are listed at: https://django-auth-ldap.readthedocs.io/en/stable/groups.html#types-of-groups",
      "label": "LDAP Group Type",
      "name": "AUTH_LDAP_5_GROUP_TYPE",
      "required": false,
      "sensitive": false,
      "type": "choice"
    },
    "AUTH_LDAP_5_GROUP_TYPE_PARAMS": {
      "category": "LDAP",
      "category_slug": "ldap",
      "child": {
        "read_only": false,
        "required": true,
        "type": "field"
      },
      "computed": true,
      "default": {
        "member_attr": "member",
        "name_attr": "cn"
      },
      "default_value": "stringdefault.StaticString(`{\"member_attr\":\"member\",\"name_attr\":\"cn\"}`)",
      "element_type": "string",
      "help_text": "Key value parameters to send the chosen group type init method.",
      "label": "LDAP Group Type Parameters",
      "name": "AUTH_LDAP_5_GROUP_TYPE_PARAMS",
      "placeholder": {
        "ldap_group_user_attr": "legacyuid",
        "member_attr": "member",
        "name_attr": "cn"
      },
      "required": false,
      "sensitive": false,
      "type": "json"
    },
    "AUTH_LDAP_5_ORGANIZATION_MAP": {
      "category": "LDAP",
      "category_slug": "ldap",
      "child": {
        "child": {
          "read_only": false,
          "required": true,
          "type": "field"
        },
        "read_only": false,
        "required": true,
        "type": "nested object"
      },
      "computed": true,
      "default": {},
      "default_value": "stringdefault.StaticString(`{}`)",
      "element_type": "nested object",
      "help_text": "Mapping between organization admins/users and LDAP groups. This controls which users are placed into which organizations relative to their LDAP group memberships. Configuration details are available in the documentation.",
      "label": "LDAP Organization Map",
      "name": "AUTH_LDAP_5_ORGANIZATION_MAP",
      "placeholder": {
        "Test Org": {
          "admins": "CN=Domain Admins,CN=Users,DC=example,DC=com",
          "auditors": "CN=Domain Auditors,CN=Users,DC=example,DC=com",
          "remove_admins": true,
          "remove_users": true,
          "users": [
            "CN=Domain Users,CN=Users,DC=example,DC=com"
          ]
        },
        "Test Org 2": {
          "admins": "CN=Administrators,CN=Builtin,DC=example,DC=com",
          "remove_admins": true,
          "remove_users": true,
          "users": true
        }
      },
      "required": false,
      "sensitive": false,
      "type": "json"
    },
    "AUTH_LDAP_5_REQUIRE_GROUP": {
      "category": "LDAP",
      "category_slug": "ldap",
      "computed": true,
      "default": null,
      "help_text": "Group DN required to login. If specified, user must be a member of this group to login via LDAP. If not set, everyone in LDAP that matches the user search will be able to login to the service. Only one require group is supported.",
      "label": "LDAP Require Group",
      "name": "AUTH_LDAP_5_REQUIRE_GROUP",
      "placeholder": "CN=Service Users,OU=Users,DC=example,DC=com",
      "required": false,
      "sensitive": false,
      "type": "string"
    },
    "AUTH_LDAP_5_SERVER_URI": {
      "category": "LDAP",
      "category_slug": "ldap",
      "computed": true,
      "default": "",
      "default_value": "stringdefault.StaticString(``)",
      "help_text": "URI to connect to LDAP server, such as \"ldap://ldap.example.com:389\" (non-SSL) or \"ldaps://ldap.example.com:636\" (SSL). Multiple LDAP servers may be specified by separating with spaces or commas. LDAP authentication is disabled if this parameter is empty.",
      "label": "LDAP Server URI",
      "name": "AUTH_LDAP_5_SERVER_URI",
      "placeholder": "ldaps://ldap.example.com:636",
      "required": false,
      "sensitive": false,
      "type": "string"
    },
    "AUTH_LDAP_5_START_TLS": {
      "category": "LDAP",
      "category_slug": "ldap",
      "computed": true,
      "default": false,
      "help_text": "Whether to enable TLS when the LDAP connection is not using SSL.",
      "label": "LDAP Start TLS",
      "name": "AUTH_LDAP_5_START_TLS",
      "required": false,
      "sensitive": false,
      "type": "boolean"
    },
    "AUTH_LDAP_5_TEAM_MAP": {
      "category": "LDAP",
      "category_slug": "ldap",
      "child": {
        "child": {
          "read_only": false,
          "required": true,
          "type": "field"
        },
        "read_only": false,
        "required": true,
        "type": "nested object"
      },
      "computed": true,
      "default": {},
      "default_value": "stringdefault.StaticString(`{}`)",
      "element_type": "nested object",
      "help_text": "Mapping between team members (users) and LDAP groups. Configuration details are available in the documentation.",
      "label": "LDAP Team Map",
      "name": "AUTH_LDAP_5_TEAM_MAP",
      "placeholder": {
        "My Team": {
          "organization": "Test Org",
          "remove": true,
          "users": [
            "CN=Domain Users,CN=Users,DC=example,DC=com"
          ]
        },
        "Other Team": {
          "organization": "Test Org 2",
          "remove": false,
          "users": "CN=Other Users,CN=Users,DC=example,DC=com"
        }
      },
      "required": false,
      "sensitive": false,
      "type": "json"
    },
    "AUTH_LDAP_5_USER_ATTR_MAP": {
      "category": "LDAP",
      "category_slug": "ldap",
      "child": {
        "read_only": false,
        "required": true,
        "type": "string"
      },
      "computed": true,
      "default": {},
      "default_value": "stringdefault.StaticString(`{}`)",
      "element_type": "string",
      "help_text": "Mapping of LDAP user schema to API user attributes. The default setting is valid for ActiveDirectory but users with other LDAP configurations may need to change the values. Refer to the documentation for additional details.",
      "label": "LDAP User Attribute Map",
      "name": "AUTH_LDAP_5_USER_ATTR_MAP",
      "placeholder": {
        "email": "mail",
        "first_name": "givenName",
        "last_name": "sn"
      },
      "required": false,
      "sensitive": false,
      "type": "json"
    },
    "AUTH_LDAP_5_USER_DN_TEMPLATE": {
      "category": "LDAP",
      "category_slug": "ldap",
      "computed": true,
      "default": null,
      "help_text": "Alternative to user search, if user DNs are all of the same format. This approach is more efficient for user lookups than searching if it is usable in your organizational environment. If this setting has a value it will be used instead of AUTH_LDAP_USER_SEARCH.",
      "label": "LDAP User DN Template",
      "name": "AUTH_LDAP_5_USER_DN_TEMPLATE",
      "placeholder": "uid=%(user)s,OU=Users,DC=example,DC=com",
      "required": false,
      "sensitive": false,
      "type": "string"
    },
    "AUTH_LDAP_5_USER_FLAGS_BY_GROUP": {
      "category": "LDAP",
      "category_slug": "ldap",
      "child": {
        "child": {
          "read_only": false,
          "required": true,
          "type": "string"
        },
        "read_only": false,
        "required": true,
        "type": "list"
      },
      "computed": true,
      "default": {},
      "default_value": "stringdefault.StaticString(`{}`)",
      "element_type": "list",
      "help_text": "Retrieve users from a given group. At this time, superuser and system auditors are the only groups supported. Refer to the documentation for more detail.",
      "label": "LDAP User Flags By Group",
      "name": "AUTH_LDAP_5_USER_FLAGS_BY_GROUP",
      "placeholder": {
        "is_superuser": "CN=Domain Admins,CN=Users,DC=example,DC=com",
        "is_system_auditor": "CN=Domain Auditors,CN=Users,DC=example,DC=com"
      },
      "required": false,
      "sensitive": false,
      "type": "json"
    },
    "AUTH_LDAP_5_USER_SEARCH": {
      "category": "LDAP",
      "category_slug": "ldap",
      "child": {
        "read_only": false,
        "required": true,
        "type": "field"
      },
      "computed": true,
      "default": [],
      "element_type": "string",
      "help_text": "LDAP search query to find users.  Any user that matches the given pattern will be able to login to the service.  The user should also be mapped into an organization (as defined in the AUTH_LDAP_ORGANIZATION_MAP setting).  If multiple search queries need to be supported use of \"LDAPUnion\" is possible. See the documentation for details.",
      "label": "LDAP User Search",
      "name": "AUTH_LDAP_5_USER_SEARCH",
      "placeholder": [
        "OU=Users,DC=example,DC=com",
        "SCOPE_SUBTREE",
        "(sAMAccountName=%(user)s)"
      ],
      "required": false,
      "sensitive": false,
      "type": "list"
    },
    "AUTH_LDAP_BIND_DN": {
      "category": "LDAP",
      "category_slug": "ldap",
      "computed": true,
      "default": "",
      "default_value": "stringdefault.StaticString(``)",
      "help_text": "DN (Distinguished Name) of user to bind for all search queries. This is the system user account we will use to login to query LDAP for other user information. Refer to the documentation for example syntax.",
      "label": "LDAP Bind DN",
      "name": "AUTH_LDAP_BIND_DN",
      "required": false,
      "sensitive": false,
      "type": "string"
    },
    "AUTH_LDAP_BIND_PASSWORD": {
      "category": "LDAP",
      "category_slug": "ldap",
      "computed": true,
      "default": "",
      "default_value": "stringdefault.StaticString(``)",
      "help_text": "Password used to bind LDAP user account.",
      "label": "LDAP Bind Password",
      "name": "AUTH_LDAP_BIND_PASSWORD",
      "required": false,
      "sensitive": true,
      "type": "string"
    },
    "AUTH_LDAP_CONNECTION_OPTIONS": {
      "category": "LDAP",
      "category_slug": "ldap",
      "child": {
        "read_only": false,
        "required": true,
        "type": "field"
      },
      "computed": true,
      "default": {
        "OPT_NETWORK_TIMEOUT": 30,
        "OPT_REFERRALS": 0
      },
      "default_value": "stringdefault.StaticString(`{\"OPT_NETWORK_TIMEOUT\":30,\"OPT_REFERRALS\":0}`)",
      "element_type": "string",
      "help_text": "Additional options to set for the LDAP connection.  LDAP referrals are disabled by default (to prevent certain LDAP queries from hanging with AD). Option names should be strings (e.g. \"OPT_REFERRALS\"). Refer to https://www.python-ldap.org/doc/html/ldap.html#options for possible options and values that can be set.",
      "label": "LDAP Connection Options",
      "name": "AUTH_LDAP_CONNECTION_OPTIONS",
      "placeholder": {
        "OPT_NETWORK_TIMEOUT": 30,
        "OPT_REFERRALS": 0
      },
      "required": false,
      "sensitive": false,
      "type": "json"
    },
    "AUTH_LDAP_DENY_GROUP": {
      "category": "LDAP",
      "category_slug": "ldap",
      "computed": true,
      "default": null,
      "help_text": "Group DN denied from login. If specified, user will not be allowed to login if a member of this group.  Only one deny group is supported.",
      "label": "LDAP Deny Group",
      "name": "AUTH_LDAP_DENY_GROUP",
      "placeholder": "CN=Disabled Users,OU=Users,DC=example,DC=com",
      "required": false,
      "sensitive": false,
      "type": "string"
    },
    "AUTH_LDAP_GROUP_SEARCH": {
      "category": "LDAP",
      "category_slug": "ldap",
      "child": {
        "read_only": false,
        "required": true,
        "type": "field"
      },
      "computed": true,
      "default": [],
      "element_type": "string",
      "help_text": "Users are mapped to organizations based on their membership in LDAP groups. This setting defines the LDAP search query to find groups. Unlike the user search, group search does not support LDAPSearchUnion.",
      "label": "LDAP Group Search",
      "name": "AUTH_LDAP_GROUP_SEARCH",
      "placeholder": [
        "DC=example,DC=com",
        "SCOPE_SUBTREE",
        "(objectClass=group)"
      ],
      "required": false,
      "sensitive": false,
      "type": "list"
    },
    "AUTH_LDAP_GROUP_TYPE": {
      "category": "LDAP",
      "category_slug": "ldap",
      "choices": [
        [
          "PosixGroupType",
          "PosixGroupType"
        ],
        [
          "GroupOfNamesType",
          "GroupOfNamesType"
        ],
        [
          "GroupOfUniqueNamesType",
          "GroupOfUniqueNamesType"
        ],
        [
          "ActiveDirectoryGroupType",
          "ActiveDirectoryGroupType"
        ],
        [
          "OrganizationalRoleGroupType",
          "OrganizationalRoleGroupType"
        ],
        [
          "MemberDNGroupType",
          "MemberDNGroupType"
        ],
        [
          "NestedGroupOfNamesType",
          "NestedGroupOfNamesType"
        ],
        [
          "NestedGroupOfUniqueNamesType",
          "NestedGroupOfUniqueNamesType"
        ],
        [
          "NestedActiveDirectoryGroupType",
          "NestedActiveDirectoryGroupType"
        ],
        [
          "NestedOrganizationalRoleGroupType",
          "NestedOrganizationalRoleGroupType"
        ],
        [
          "NestedMemberDNGroupType",
          "NestedMemberDNGroupType"
        ],
        [
          "PosixUIDGroupType",
          "PosixUIDGroupType"
        ]
      ],
      "computed": true,
      "default": "MemberDNGroupType",
      "default_value": "stringdefault.StaticString(`MemberDNGroupType`)",
      "help_text": "The group type may need to be changed based on the type of the LDAP server.  Values are listed at: https://django-auth-ldap.readthedocs.io/en/stable/groups.html#types-of-groups",
      "label": "LDAP Group Type",
      "name": "AUTH_LDAP_GROUP_TYPE",
      "required": false,
      "sensitive": false,
      "type": "choice"
    },
    "AUTH_LDAP_GROUP_TYPE_PARAMS": {
      "category": "LDAP",
      "category_slug": "ldap",
      "child": {
        "read_only": false,
        "required": true,
        "type": "field"
      },
      "computed": true,
      "default": {
        "member_attr": "member",
        "name_attr": "cn"
      },
      "default_value": "stringdefault.StaticString(`{\"member_attr\":\"member\",\"name_attr\":\"cn\"}`)",
      "element_type": "string",
      "help_text": "Key value parameters to send the chosen group type init method.",
      "label": "LDAP Group Type Parameters",
      "name": "AUTH_LDAP_GROUP_TYPE_PARAMS",
      "placeholder": {
        "ldap_group_user_attr": "legacyuid",
        "member_attr": "member",
        "name_attr": "cn"
      },
      "required": false,
      "sensitive": false,
      "type": "json"
    },
    "AUTH_LDAP_ORGANIZATION_MAP": {
      "category": "LDAP",
      "category_slug": "ldap",
      "child": {
        "child": {
          "read_only": false,
          "required": true,
          "type": "field"
        },
        "read_only": false,
        "required": true,
        "type": "nested object"
      },
      "computed": true,
      "default": {},
      "default_value": "stringdefault.StaticString(`{}`)",
      "element_type": "nested object",
      "help_text": "Mapping between organization admins/users and LDAP groups. This controls which users are placed into which organizations relative to their LDAP group memberships. Configuration details are available in the documentation.",
      "label": "LDAP Organization Map",
      "name": "AUTH_LDAP_ORGANIZATION_MAP",
      "placeholder": {
        "Test Org": {
          "admins": "CN=Domain Admins,CN=Users,DC=example,DC=com",
          "auditors": "CN=Domain Auditors,CN=Users,DC=example,DC=com",
          "remove_admins": true,
          "remove_users": true,
          "users": [
            "CN=Domain Users,CN=Users,DC=example,DC=com"
          ]
        },
        "Test Org 2": {
          "admins": "CN=Administrators,CN=Builtin,DC=example,DC=com",
          "remove_admins": true,
          "remove_users": true,
          "users": true
        }
      },
      "required": false,
      "sensitive": false,
      "type": "json"
    },
    "AUTH_LDAP_REQUIRE_GROUP": {
      "category": "LDAP",
      "category_slug": "ldap",
      "computed": true,
      "default": null,
      "help_text": "Group DN required to login. If specified, user must be a member of this group to login via LDAP. If not set, everyone in LDAP that matches the user search will be able to login to the service. Only one require group is supported.",
      "label": "LDAP Require Group",
      "name": "AUTH_LDAP_REQUIRE_GROUP",
      "placeholder": "CN=Service Users,OU=Users,DC=example,DC=com",
      "required": false,
      "sensitive": false,
      "type": "string"
    },
    "AUTH_LDAP_SERVER_URI": {
      "category": "LDAP",
      "category_slug": "ldap",
      "computed": true,
      "default": "",
      "default_value": "stringdefault.StaticString(``)",
      "help_text": "URI to connect to LDAP server, such as \"ldap://ldap.example.com:389\" (non-SSL) or \"ldaps://ldap.example.com:636\" (SSL). Multiple LDAP servers may be specified by separating with spaces or commas. LDAP authentication is disabled if this parameter is empty.",
      "label": "LDAP Server URI",
      "name": "AUTH_LDAP_SERVER_URI",
      "placeholder": "ldaps://ldap.example.com:636",
      "required": false,
      "sensitive": false,
      "type": "string"
    },
    "AUTH_LDAP_START_TLS": {
      "category": "LDAP",
      "category_slug": "ldap",
      "computed": true,
      "default": false,
      "help_text": "Whether to enable TLS when the LDAP connection is not using SSL.",
      "label": "LDAP Start TLS",
      "name": "AUTH_LDAP_START_TLS",
      "required": false,
      "sensitive": false,
      "type": "boolean"
    },
    "AUTH_LDAP_TEAM_MAP": {
      "category": "LDAP",
      "category_slug": "ldap",
      "child": {
        "child": {
          "read_only": false,
          "required": true,
          "type": "field"
        },
        "read_only": false,
        "required": true,
        "type": "nested object"
      },
      "computed": true,
      "default": {},
      "default_value": "stringdefault.StaticString(`{}`)",
      "element_type": "nested object",
      "help_text": "Mapping between team members (users) and LDAP groups. Configuration details are available in the documentation.",
      "label": "LDAP Team Map",
      "name": "AUTH_LDAP_TEAM_MAP",
      "placeholder": {
        "My Team": {
          "organization": "Test Org",
          "remove": true,
          "users": [
            "CN=Domain Users,CN=Users,DC=example,DC=com"
          ]
        },
        "Other Team": {
          "organization": "Test Org 2",
          "remove": false,
          "users": "CN=Other Users,CN=Users,DC=example,DC=com"
        }
      },
      "required": false,
      "sensitive": false,
      "type": "json"
    },
    "AUTH_LDAP_USER_ATTR_MAP": {
      "category": "LDAP",
      "category_slug": "ldap",
      "child": {
        "read_only": false,
        "required": true,
        "type": "string"
      },
      "computed": true,
      "default": {},
      "default_value": "stringdefault.StaticString(`{}`)",
      "element_type": "string",
      "help_text": "Mapping of LDAP user schema to API user attributes. The default setting is valid for ActiveDirectory but users with other LDAP configurations may need to change the values. Refer to the documentation for additional details.",
      "label": "LDAP User Attribute Map",
      "name": "AUTH_LDAP_USER_ATTR_MAP",
      "placeholder": {
        "email": "mail",
        "first_name": "givenName",
        "last_name": "sn"
      },
      "required": false,
      "sensitive": false,
      "type": "json"
    },
    "AUTH_LDAP_USER_DN_TEMPLATE": {
      "category": "LDAP",
      "category_slug": "ldap",
      "computed": true,
      "default": null,
      "help_text": "Alternative to user search, if user DNs are all of the same format. This approach is more efficient for user lookups than searching if it is usable in your organizational environment. If this setting has a value it will be used instead of AUTH_LDAP_USER_SEARCH.",
      "label": "LDAP User DN Template",
      "name": "AUTH_LDAP_USER_DN_TEMPLATE",
      "placeholder": "uid=%(user)s,OU=Users,DC=example,DC=com",
      "required": false,
      "sensitive": false,
      "type": "string"
    },
    "AUTH_LDAP_USER_FLAGS_BY_GROUP": {
      "category": "LDAP",
      "category_slug": "ldap",
      "child": {
        "child": {
          "read_only": false,
          "required": true,
          "type": "string"
        },
        "read_only": false,
        "required": true,
        "type": "list"
      },
      "computed": true,
      "default": {},
      "default_value": "stringdefault.StaticString(`{}`)",
      "element_type": "list",
      "help_text": "Retrieve users from a given group. At this time, superuser and system auditors are the only groups supported. Refer to the documentation for more detail.",
      "label": "LDAP User Flags By Group",
      "name": "AUTH_LDAP_USER_FLAGS_BY_GROUP",
      "placeholder": {
        "is_superuser": "CN=Domain Admins,CN=Users,DC=example,DC=com",
        "is_system_auditor": "CN=Domain Auditors,CN=Users,DC=example,DC=com"
      },
      "required": false,
      "sensitive": false,
      "type": "json"
    },
    "AUTH_LDAP_USER_SEARCH": {
      "category": "LDAP",
      "category_slug": "ldap",
      "child": {
        "read_only": false,
        "required": true,
        "type": "field"
      },
      "computed": true,
      "default": [],
      "element_type": "string",
      "help_text": "LDAP search query to find users.  Any user that matches the given pattern will be able to login to the service.  The user should also be mapped into an organization (as defined in the AUTH_LDAP_ORGANIZATION_MAP setting).  If multiple search queries need to be supported use of \"LDAPUnion\" is possible. See the documentation for details.",
      "label": "LDAP User Search",
      "name": "AUTH_LDAP_USER_SEARCH",
      "placeholder": [
        "OU=Users,DC=example,DC=com",
        "SCOPE_SUBTREE",
        "(sAMAccountName=%(user)s)"
      ],
      "required": false,
      "sensitive": false,
      "type": "list"
    }
  },
  "PropertyPostKeys": [
    "AUTH_LDAP_1_BIND_DN",
    "AUTH_LDAP_1_BIND_PASSWORD",
    "AUTH_LDAP_1_CONNECTION_OPTIONS",
    "AUTH_LDAP_1_DENY_GROUP",
    "AUTH_LDAP_1_GROUP_SEARCH",
    "AUTH_LDAP_1_GROUP_TYPE",
    "AUTH_LDAP_1_GROUP_TYPE_PARAMS",
    "AUTH_LDAP_1_ORGANIZATION_MAP",
    "AUTH_LDAP_1_REQUIRE_GROUP",
    "AUTH_LDAP_1_SERVER_URI",
    "AUTH_LDAP_1_START_TLS",
    "AUTH_LDAP_1_TEAM_MAP",
    "AUTH_LDAP_1_USER_ATTR_MAP",
    "AUTH_LDAP_1_USER_DN_TEMPLATE",
    "AUTH_LDAP_1_USER_FLAGS_BY_GROUP",
    "AUTH_LDAP_1_USER_SEARCH",
    "AUTH_LDAP_2_BIND_DN",
    "AUTH_LDAP_2_BIND_PASSWORD",
    "AUTH_LDAP_2_CONNECTION_OPTIONS",
    "AUTH_LDAP_2_DENY_GROUP",
    "AUTH_LDAP_2_GROUP_SEARCH",
    "AUTH_LDAP_2_GROUP_TYPE",
    "AUTH_LDAP_2_GROUP_TYPE_PARAMS",
    "AUTH_LDAP_2_ORGANIZATION_MAP",
    "AUTH_LDAP_2_REQUIRE_GROUP",
    "AUTH_LDAP_2_SERVER_URI",
    "AUTH_LDAP_2_START_TLS",
    "AUTH_LDAP_2_TEAM_MAP",
    "AUTH_LDAP_2_USER_ATTR_MAP",
    "AUTH_LDAP_2_USER_DN_TEMPLATE",
    "AUTH_LDAP_2_USER_FLAGS_BY_GROUP",
    "AUTH_LDAP_2_USER_SEARCH",
    "AUTH_LDAP_3_BIND_DN",
    "AUTH_LDAP_3_BIND_PASSWORD",
    "AUTH_LDAP_3_CONNECTION_OPTIONS",
    "AUTH_LDAP_3_DENY_GROUP",
    "AUTH_LDAP_3_GROUP_SEARCH",
    "AUTH_LDAP_3_GROUP_TYPE",
    "AUTH_LDAP_3_GROUP_TYPE_PARAMS",
    "AUTH_LDAP_3_ORGANIZATION_MAP",
    "AUTH_LDAP_3_REQUIRE_GROUP",
    "AUTH_LDAP_3_SERVER_URI",
    "AUTH_LDAP_3_START_TLS",
    "AUTH_LDAP_3_TEAM_MAP",
    "AUTH_LDAP_3_USER_ATTR_MAP",
    "AUTH_LDAP_3_USER_DN_TEMPLATE",
    "AUTH_LDAP_3_USER_FLAGS_BY_GROUP",
    "AUTH_LDAP_3_USER_SEARCH",
    "AUTH_LDAP_4_BIND_DN",
    "AUTH_LDAP_4_BIND_PASSWORD",
    "AUTH_LDAP_4_CONNECTION_OPTIONS",
    "AUTH_LDAP_4_DENY_GROUP",
    "AUTH_LDAP_4_GROUP_SEARCH",
    "AUTH_LDAP_4_GROUP_TYPE",
    "AUTH_LDAP_4_GROUP_TYPE_PARAMS",
    "AUTH_LDAP_4_ORGANIZATION_MAP",
    "AUTH_LDAP_4_REQUIRE_GROUP",
    "AUTH_LDAP_4_SERVER_URI",
    "AUTH_LDAP_4_START_TLS",
    "AUTH_LDAP_4_TEAM_MAP",
    "AUTH_LDAP_4_USER_ATTR_MAP",
    "AUTH_LDAP_4_USER_DN_TEMPLATE",
    "AUTH_LDAP_4_USER_FLAGS_BY_GROUP",
    "AUTH_LDAP_4_USER_SEARCH",
    "AUTH_LDAP_5_BIND_DN",
    "AUTH_LDAP_5_BIND_PASSWORD",
    "AUTH_LDAP_5_CONNECTION_OPTIONS",
    "AUTH_LDAP_5_DENY_GROUP",
    "AUTH_LDAP_5_GROUP_SEARCH",
    "AUTH_LDAP_5_GROUP_TYPE",
    "AUTH_LDAP_5_GROUP_TYPE_PARAMS",
    "AUTH_LDAP_5_ORGANIZATION_MAP",
    "AUTH_LDAP_5_REQUIRE_GROUP",
    "AUTH_LDAP_5_SERVER_URI",
    "AUTH_LDAP_5_START_TLS",
    "AUTH_LDAP_5_TEAM_MAP",
    "AUTH_LDAP_5_USER_ATTR_MAP",
    "AUTH_LDAP_5_USER_DN_TEMPLATE",
    "AUTH_LDAP_5_USER_FLAGS_BY_GROUP",
    "AUTH_LDAP_5_USER_SEARCH",
    "AUTH_LDAP_BIND_DN",
    "AUTH_LDAP_BIND_PASSWORD",
    "AUTH_LDAP_CONNECTION_OPTIONS",
    "AUTH_LDAP_DENY_GROUP",
    "AUTH_LDAP_GROUP_SEARCH",
    "AUTH_LDAP_GROUP_TYPE",
    "AUTH_LDAP_GROUP_TYPE_PARAMS",
    "AUTH_LDAP_ORGANIZATION_MAP",
    "AUTH_LDAP_REQUIRE_GROUP",
    "AUTH_LDAP_SERVER_URI",
    "AUTH_LDAP_START_TLS",
    "AUTH_LDAP_TEAM_MAP",
    "AUTH_LDAP_USER_ATTR_MAP",
    "AUTH_LDAP_USER_DN_TEMPLATE",
    "AUTH_LDAP_USER_FLAGS_BY_GROUP",
    "AUTH_LDAP_USER_SEARCH"
  ],
  "PropertyWriteOnlyData": {},
  "PropertyWriteOnlyKeys": null
}