{
  "ApiVersion": "24.2.0",
  "Config": {
    "endpoint": "/api/v2/settings/system/",
    "name": "SettingsMiscSystem",
    "type_name": "settings_misc_system",
    "id_key": "id",
    "property_overrides": {
      "DEFAULT_EXECUTION_ENVIRONMENT": {
        "type": "id",
        "description": "",
        "sensitive": false,
        "required": false,
        "trim": false,
        "post_wrap": false,
        "default_value": "",
        "element_type": ""
      },
      "LICENSE": {
        "type": "string",
        "description": "",
        "sensitive": false,
        "required": false,
        "trim": false,
        "post_wrap": false,
        "default_value": "",
        "element_type": ""
      }
    },
    "enabled": true,
    "has_object_roles": false,
    "has_survey_spec": false,
    "associate_disassociate_groups": null,
    "field_constraints": null,
    "skip_write_only": false,
    "undeletable": true,
    "pre_state_set_hook_function": "",
    "no_id": true,
    "no_terraform_data_source": false,
    "no_terraform_resource": false,
    "api_property_resource_key": "PUT",
    "api_property_data_key": "GET",
    "property_name_leave_as_is": true,
    "api_data_override": null,
    "remove_fields_data_source": null,
    "remove_fields_resource": [
      "CLEANUP_HOST_METRICS_LAST_TS",
      "HOST_METRIC_SUMMARY_TASK_LAST_TS",
      "AUTOMATION_ANALYTICS_LAST_GATHER",
      "CUSTOM_VENV_PATHS"
    ],
    "credential_types": null
  },
  "Description": "# Retrieve a Setting:\n\nMake GET request to this resource to retrieve a single setting\nrecord containing the following fields:\n\n* `ACTIVITY_STREAM_ENABLED`: Enable capturing activity for the activity stream. (boolean)\n* `ACTIVITY_STREAM_ENABLED_FOR_INVENTORY_SYNC`: Enable capturing activity for the activity stream when running inventory sync. (boolean)\n* `ORG_ADMINS_CAN_SEE_ALL_USERS`: Controls whether any Organization Admin can view all users and teams, even those not associated with their Organization. (boolean)\n* `MANAGE_ORGANIZATION_AUTH`: Controls whether any Organization Admin has the privileges to create and manage users and teams. You may want to disable this ability if you are using an LDAP or SAML integration. (boolean)\n* `TOWER_URL_BASE`: This setting is used by services like notifications to render a valid url to the service. (string)\n* `REMOTE_HOST_HEADERS`: HTTP headers and meta keys to search to determine remote host name or IP. Add additional items to this list, such as \u0026quot;HTTP_X_FORWARDED_FOR\u0026quot;, if behind a reverse proxy. See the \u0026quot;Proxy Support\u0026quot; section of the AAP Installation guide for more details. (list)\n* `PROXY_IP_ALLOWED_LIST`: If the service is behind a reverse proxy/load balancer, use this setting to configure the proxy IP addresses from which the service should trust custom REMOTE_HOST_HEADERS header values. If this setting is an empty list (the default), the headers specified by REMOTE_HOST_HEADERS will be trusted unconditionally\u0026#x27;) (list)\n* `CSRF_TRUSTED_ORIGINS`: If the service is behind a reverse proxy/load balancer, use this setting to configure the schema://addresses from which the service should trust Origin header values.  (list)\n* `LICENSE`: The license controls which features and functionality are enabled. Use /api/v2/config/ to update or change the license. (nested object)\n* `REDHAT_USERNAME`: This username is used to send data to Automation Analytics (string)\n* `REDHAT_PASSWORD`: This password is used to send data to Automation Analytics (string)\n* `SUBSCRIPTIONS_USERNAME`: This username is used to retrieve subscription and content information (string)\n* `SUBSCRIPTIONS_PASSWORD`: This password is used to retrieve subscription and content information (string)\n* `AUTOMATION_ANALYTICS_URL`: This setting is used to to configure the upload URL for data collection for Automation Analytics. (string)\n* `INSTALL_UUID`:  (string)\n* `DEFAULT_CONTROL_PLANE_QUEUE_NAME`:  (string)\n* `DEFAULT_EXECUTION_QUEUE_NAME`:  (string)\n* `DEFAULT_EXECUTION_ENVIRONMENT`: The Execution Environment to be used when one has not been configured for a job template. (field)\n* `CUSTOM_VENV_PATHS`: Paths where Tower will look for custom virtual environments (in addition to /var/lib/awx/venv/). Enter one path per line. (list)\n* `INSIGHTS_TRACKING_STATE`: Enables the service to gather data on automation and send it to Automation Analytics. (boolean)\n* `AUTOMATION_ANALYTICS_LAST_GATHER`:  (datetime)\n* `AUTOMATION_ANALYTICS_LAST_ENTRIES`:  (string)\n* `AUTOMATION_ANALYTICS_GATHER_INTERVAL`: Interval (in seconds) between data gathering. (integer)\n* `IS_K8S`: Indicates whether the instance is part of a kubernetes-based deployment. (boolean)\n* `UI_NEXT`: Enable preview of new user interface. (boolean)\n* `SUBSCRIPTION_USAGE_MODEL`:  (choice)\n    - `\"\"`: Default model for AWX - no subscription. Deletion of host_metrics will not be considered for purposes of managed host counting\n    - `unique_managed_hosts`: Usage based on unique managed nodes in a large historical time frame and delete functionality for no longer used managed nodes\n* `CLEANUP_HOST_METRICS_LAST_TS`:  (datetime)\n* `HOST_METRIC_SUMMARY_TASK_LAST_TS`:  (datetime)\n\n\n\n\n\n# Update a Setting:\n\nMake a PUT or PATCH request to this resource to update this\nsetting.  The following fields may be modified:\n\n\n* `ACTIVITY_STREAM_ENABLED`: Enable capturing activity for the activity stream. (boolean, required)\n* `ACTIVITY_STREAM_ENABLED_FOR_INVENTORY_SYNC`: Enable capturing activity for the activity stream when running inventory sync. (boolean, required)\n* `ORG_ADMINS_CAN_SEE_ALL_USERS`: Controls whether any Organization Admin can view all users and teams, even those not associated with their Organization. (boolean, required)\n* `MANAGE_ORGANIZATION_AUTH`: Controls whether any Organization Admin has the privileges to create and manage users and teams. You may want to disable this ability if you are using an LDAP or SAML integration. (boolean, required)\n* `TOWER_URL_BASE`: This setting is used by services like notifications to render a valid url to the service. (string, required)\n* `REMOTE_HOST_HEADERS`: HTTP headers and meta keys to search to determine remote host name or IP. Add additional items to this list, such as \u0026quot;HTTP_X_FORWARDED_FOR\u0026quot;, if behind a reverse proxy. See the \u0026quot;Proxy Support\u0026quot; section of the AAP Installation guide for more details. (list, required)\n* `PROXY_IP_ALLOWED_LIST`: If the service is behind a reverse proxy/load balancer, use this setting to configure the proxy IP addresses from which the service should trust custom REMOTE_HOST_HEADERS header values. If this setting is an empty list (the default), the headers specified by REMOTE_HOST_HEADERS will be trusted unconditionally\u0026#x27;) (list, default=`[]`)\n* `CSRF_TRUSTED_ORIGINS`: If the service is behind a reverse proxy/load balancer, use this setting to configure the schema://addresses from which the service should trust Origin header values.  (list, default=`[]`)\n\n* `REDHAT_USERNAME`: This username is used to send data to Automation Analytics (string, default=`\"\"`)\n* `REDHAT_PASSWORD`: This password is used to send data to Automation Analytics (string, default=`\"\"`)\n* `SUBSCRIPTIONS_USERNAME`: This username is used to retrieve subscription and content information (string, default=`\"\"`)\n* `SUBSCRIPTIONS_PASSWORD`: This password is used to retrieve subscription and content information (string, default=`\"\"`)\n* `AUTOMATION_ANALYTICS_URL`: This setting is used to to configure the upload URL for data collection for Automation Analytics. (string, default=`\"https://example.com\"`)\n\n\n\n* `DEFAULT_EXECUTION_ENVIRONMENT`: The Execution Environment to be used when one has not been configured for a job template. (field, default=`None`)\n* `CUSTOM_VENV_PATHS`: Paths where Tower will look for custom virtual environments (in addition to /var/lib/awx/venv/). Enter one path per line. (list, default=`[]`)\n* `INSIGHTS_TRACKING_STATE`: Enables the service to gather data on automation and send it to Automation Analytics. (boolean, default=`False`)\n* `AUTOMATION_ANALYTICS_LAST_GATHER`:  (datetime, default=`None`)\n* `AUTOMATION_ANALYTICS_LAST_ENTRIES`:  (string, default=`\"\"`)\n* `AUTOMATION_ANALYTICS_GATHER_INTERVAL`: Interval (in seconds) between data gathering. (integer, default=`14400`)\n\n* `UI_NEXT`: Enable preview of new user interface. (boolean, default=`True`)\n* `SUBSCRIPTION_USAGE_MODEL`:  (choice)\n    - `\"\"`: Default model for AWX - no subscription. Deletion of host_metrics will not be considered for purposes of managed host counting (default)\n    - `unique_managed_hosts`: Usage based on unique managed nodes in a large historical time frame and delete functionality for no longer used managed nodes\n* `CLEANUP_HOST_METRICS_LAST_TS`:  (datetime, required)\n* `HOST_METRIC_SUMMARY_TASK_LAST_TS`:  (datetime, required)\n\n\n\n\n\n\nFor a PUT request, include **all** fields in the request.\n\n\n\nFor a PATCH request, include only the fields that are being modified.\n\n\n\n# Delete a Setting:\n\nMake a DELETE request to this resource to delete this setting.",
  "Endpoint": "/api/v2/settings/system/",
  "Name": "SettingsMiscSystem",
  "PackageName": "awx",
  "PropertyGetData": {
    "ACTIVITY_STREAM_ENABLED": {
      "category": "System",
      "category_slug": "system",
      "computed": true,
      "defined_in_file": false,
      "help_text": "Enable capturing activity for the activity stream.",
      "hidden": false,
      "label": "Enable Activity Stream",
      "name": "ACTIVITY_STREAM_ENABLED",
      "required": false,
      "sensitive": false,
      "type": "boolean"
    },
    "ACTIVITY_STREAM_ENABLED_FOR_INVENTORY_SYNC": {
      "category": "System",
      "category_slug": "system",
      "computed": true,
      "defined_in_file": false,
      "help_text": "Enable capturing activity for the activity stream when running inventory sync.",
      "hidden": false,
      "label": "Enable Activity Stream for Inventory Sync",
      "name": "ACTIVITY_STREAM_ENABLED_FOR_INVENTORY_SYNC",
      "required": false,
      "sensitive": false,
      "type": "boolean"
    },
    "AUTOMATION_ANALYTICS_GATHER_INTERVAL": {
      "category": "System",
      "category_slug": "system",
      "computed": true,
      "defined_in_file": false,
      "help_text": "Interval (in seconds) between data gathering.",
      "hidden": false,
      "label": "Automation Analytics Gather Interval",
      "min_value": 1800,
      "name": "AUTOMATION_ANALYTICS_GATHER_INTERVAL",
      "required": false,
      "sensitive": false,
      "type": "integer",
      "unit": "seconds"
    },
    "AUTOMATION_ANALYTICS_LAST_ENTRIES": {
      "category": "System",
      "category_slug": "system",
      "computed": true,
      "defined_in_file": false,
      "hidden": false,
      "label": "Last gathered entries from the data collection service of Automation Analytics",
      "name": "AUTOMATION_ANALYTICS_LAST_ENTRIES",
      "required": false,
      "sensitive": false,
      "type": "string"
    },
    "AUTOMATION_ANALYTICS_LAST_GATHER": {
      "category": "System",
      "category_slug": "system",
      "computed": true,
      "defined_in_file": false,
      "hidden": false,
      "label": "Last gather date for Automation Analytics.",
      "name": "AUTOMATION_ANALYTICS_LAST_GATHER",
      "required": false,
      "sensitive": false,
      "type": "datetime"
    },
    "AUTOMATION_ANALYTICS_URL": {
      "category": "System",
      "category_slug": "system",
      "computed": true,
      "defined_in_file": false,
      "help_text": "This setting is used to to configure the upload URL for data collection for Automation Analytics.",
      "hidden": false,
      "label": "Automation Analytics upload URL",
      "name": "AUTOMATION_ANALYTICS_URL",
      "required": false,
      "sensitive": false,
      "type": "string"
    },
    "CLEANUP_HOST_METRICS_LAST_TS": {
      "category": "System",
      "category_slug": "system",
      "computed": true,
      "defined_in_file": false,
      "hidden": false,
      "label": "Last cleanup date for HostMetrics",
      "name": "CLEANUP_HOST_METRICS_LAST_TS",
      "required": false,
      "sensitive": false,
      "type": "datetime"
    },
    "CSRF_TRUSTED_ORIGINS": {
      "category": "System",
      "category_slug": "system",
      "child": {
        "hidden": false,
        "type": "string"
      },
      "computed": true,
      "defined_in_file": false,
      "element_type": "string",
      "help_text": "If the service is behind a reverse proxy/load balancer, use this setting to configure the schema://addresses from which the service should trust Origin header values. ",
      "hidden": false,
      "label": "CSRF Trusted Origins List",
      "name": "CSRF_TRUSTED_ORIGINS",
      "required": false,
      "sensitive": false,
      "type": "list"
    },
    "CUSTOM_VENV_PATHS": {
      "category": "System",
      "category_slug": "system",
      "child": {
        "hidden": false,
        "type": "string"
      },
      "computed": true,
      "defined_in_file": false,
      "element_type": "string",
      "help_text": "Paths where Tower will look for custom virtual environments (in addition to /var/lib/awx/venv/). Enter one path per line.",
      "hidden": false,
      "label": "Custom virtual environment paths",
      "name": "CUSTOM_VENV_PATHS",
      "required": false,
      "sensitive": false,
      "type": "list"
    },
    "DEFAULT_CONTROL_PLANE_QUEUE_NAME": {
      "category": "System",
      "category_slug": "system",
      "computed": true,
      "defined_in_file": false,
      "hidden": false,
      "label": "The instance group where control plane tasks run",
      "name": "DEFAULT_CONTROL_PLANE_QUEUE_NAME",
      "required": false,
      "sensitive": false,
      "type": "string"
    },
    "DEFAULT_EXECUTION_ENVIRONMENT": {
      "category": "System",
      "category_slug": "system",
      "computed": true,
      "defined_in_file": false,
      "help_text": "The Execution Environment to be used when one has not been configured for a job template.",
      "hidden": false,
      "label": "Global default execution environment",
      "name": "DEFAULT_EXECUTION_ENVIRONMENT",
      "post_wrap": false,
      "required": false,
      "sensitive": false,
      "trim": false,
      "type": "id"
    },
    "DEFAULT_EXECUTION_QUEUE_NAME": {
      "category": "System",
      "category_slug": "system",
      "computed": true,
      "defined_in_file": false,
      "hidden": false,
      "label": "The instance group where user jobs run (currently only on non-VM installs)",
      "name": "DEFAULT_EXECUTION_QUEUE_NAME",
      "required": false,
      "sensitive": false,
      "type": "string"
    },
    "HOST_METRIC_SUMMARY_TASK_LAST_TS": {
      "category": "System",
      "category_slug": "system",
      "computed": true,
      "defined_in_file": false,
      "hidden": false,
      "label": "Last computing date of HostMetricSummaryMonthly",
      "name": "HOST_METRIC_SUMMARY_TASK_LAST_TS",
      "required": false,
      "sensitive": false,
      "type": "datetime"
    },
    "INSIGHTS_TRACKING_STATE": {
      "category": "System",
      "category_slug": "system",
      "computed": true,
      "defined_in_file": false,
      "help_text": "Enables the service to gather data on automation and send it to Automation Analytics.",
      "hidden": false,
      "label": "Gather data for Automation Analytics",
      "name": "INSIGHTS_TRACKING_STATE",
      "required": false,
      "sensitive": false,
      "type": "boolean"
    },
    "INSTALL_UUID": {
      "category": "System",
      "category_slug": "system",
      "computed": true,
      "defined_in_file": false,
      "hidden": false,
      "label": "Unique identifier for an installation",
      "name": "INSTALL_UUID",
      "required": false,
      "sensitive": false,
      "type": "string"
    },
    "IS_K8S": {
      "category": "System",
      "category_slug": "system",
      "computed": true,
      "defined_in_file": false,
      "help_text": "Indicates whether the instance is part of a kubernetes-based deployment.",
      "hidden": false,
      "label": "Is k8s",
      "name": "IS_K8S",
      "required": false,
      "sensitive": false,
      "type": "boolean"
    },
    "LICENSE": {
      "category": "System",
      "category_slug": "system",
      "child": {
        "hidden": false,
        "type": "field"
      },
      "computed": true,
      "defined_in_file": false,
      "element_type": "string",
      "help_text": "The license controls which features and functionality are enabled. Use /api/v2/config/ to update or change the license.",
      "hidden": false,
      "label": "License",
      "name": "LICENSE",
      "post_wrap": false,
      "required": false,
      "sensitive": false,
      "trim": false,
      "type": "string"
    },
    "MANAGE_ORGANIZATION_AUTH": {
      "category": "System",
      "category_slug": "system",
      "computed": true,
      "defined_in_file": false,
      "help_text": "Controls whether any Organization Admin has the privileges to create and manage users and teams. You may want to disable this ability if you are using an LDAP or SAML integration.",
      "hidden": false,
      "label": "Organization Admins Can Manage Users and Teams",
      "name": "MANAGE_ORGANIZATION_AUTH",
      "required": false,
      "sensitive": false,
      "type": "boolean"
    },
    "ORG_ADMINS_CAN_SEE_ALL_USERS": {
      "category": "System",
      "category_slug": "system",
      "computed": true,
      "defined_in_file": false,
      "help_text": "Controls whether any Organization Admin can view all users and teams, even those not associated with their Organization.",
      "hidden": false,
      "label": "All Users Visible to Organization Admins",
      "name": "ORG_ADMINS_CAN_SEE_ALL_USERS",
      "required": false,
      "sensitive": false,
      "type": "boolean"
    },
    "PROXY_IP_ALLOWED_LIST": {
      "category": "System",
      "category_slug": "system",
      "child": {
        "hidden": false,
        "type": "string"
      },
      "computed": true,
      "defined_in_file": false,
      "element_type": "string",
      "help_text": "If the service is behind a reverse proxy/load balancer, use this setting to configure the proxy IP addresses from which the service should trust custom REMOTE_HOST_HEADERS header values. If this setting is an empty list (the default), the headers specified by REMOTE_HOST_HEADERS will be trusted unconditionally')",
      "hidden": false,
      "label": "Proxy IP Allowed List",
      "name": "PROXY_IP_ALLOWED_LIST",
      "required": false,
      "sensitive": false,
      "type": "list"
    },
    "REDHAT_PASSWORD": {
      "category": "System",
      "category_slug": "system",
      "computed": true,
      "defined_in_file": false,
      "help_text": "This password is used to send data to Automation Analytics",
      "hidden": false,
      "label": "Red Hat customer password",
      "name": "REDHAT_PASSWORD",
      "required": false,
      "sensitive": false,
      "type": "string"
    },
    "REDHAT_USERNAME": {
      "category": "System",
      "category_slug": "system",
      "computed": true,
      "defined_in_file": false,
      "help_text": "This username is used to send data to Automation Analytics",
      "hidden": false,
      "label": "Red Hat customer username",
      "name": "REDHAT_USERNAME",
      "required": false,
      "sensitive": false,
      "type": "string"
    },
    "REMOTE_HOST_HEADERS": {
      "category": "System",
      "category_slug": "system",
      "child": {
        "hidden": false,
        "type": "string"
      },
      "computed": true,
      "defined_in_file": false,
      "element_type": "string",
      "help_text": "HTTP headers and meta keys to search to determine remote host name or IP. Add additional items to this list, such as \"HTTP_X_FORWARDED_FOR\", if behind a reverse proxy. See the \"Proxy Support\" section of the AAP Installation guide for more details.",
      "hidden": false,
      "label": "Remote Host Headers",
      "name": "REMOTE_HOST_HEADERS",
      "required": false,
      "sensitive": false,
      "type": "list"
    },
    "SUBSCRIPTIONS_PASSWORD": {
      "category": "System",
      "category_slug": "system",
      "computed": true,
      "defined_in_file": false,
      "help_text": "This password is used to retrieve subscription and content information",
      "hidden": false,
      "label": "Red Hat or Satellite password",
      "name": "SUBSCRIPTIONS_PASSWORD",
      "required": false,
      "sensitive": false,
      "type": "string"
    },
    "SUBSCRIPTIONS_USERNAME": {
      "category": "System",
      "category_slug": "system",
      "computed": true,
      "defined_in_file": false,
      "help_text": "This username is used to retrieve subscription and content information",
      "hidden": false,
      "label": "Red Hat or Satellite username",
      "name": "SUBSCRIPTIONS_USERNAME",
      "required": false,
      "sensitive": false,
      "type": "string"
    },
    "SUBSCRIPTION_USAGE_MODEL": {
      "category": "System",
      "category_slug": "system",
      "choices": [
        [
          "",
          "Default model for AWX - no subscription. Deletion of host_metrics will not be considered for purposes of managed host counting"
        ],
        [
          "unique_managed_hosts",
          "Usage based on unique managed nodes in a large historical time frame and delete functionality for no longer used managed nodes"
        ]
      ],
      "computed": true,
      "defined_in_file": false,
      "hidden": false,
      "label": "Defines subscription usage model and shows Host Metrics",
      "name": "SUBSCRIPTION_USAGE_MODEL",
      "required": false,
      "sensitive": false,
      "type": "choice"
    },
    "TOWER_URL_BASE": {
      "category": "System",
      "category_slug": "system",
      "computed": true,
      "defined_in_file": false,
      "help_text": "This setting is used by services like notifications to render a valid url to the service.",
      "hidden": false,
      "label": "Base URL of the service",
      "name": "TOWER_URL_BASE",
      "required": false,
      "sensitive": false,
      "type": "string"
    },
    "UI_NEXT": {
      "category": "System",
      "category_slug": "system",
      "computed": true,
      "defined_in_file": false,
      "help_text": "Enable preview of new user interface.",
      "hidden": true,
      "label": "Enable Preview of New User Interface",
      "name": "UI_NEXT",
      "required": false,
      "sensitive": false,
      "type": "boolean"
    }
  },
  "PropertyGetKeys": [
    "ACTIVITY_STREAM_ENABLED",
    "ACTIVITY_STREAM_ENABLED_FOR_INVENTORY_SYNC",
    "AUTOMATION_ANALYTICS_GATHER_INTERVAL",
    "AUTOMATION_ANALYTICS_LAST_ENTRIES",
    "AUTOMATION_ANALYTICS_LAST_GATHER",
    "AUTOMATION_ANALYTICS_URL",
    "CLEANUP_HOST_METRICS_LAST_TS",
    "CSRF_TRUSTED_ORIGINS",
    "CUSTOM_VENV_PATHS",
    "DEFAULT_CONTROL_PLANE_QUEUE_NAME",
    "DEFAULT_EXECUTION_ENVIRONMENT",
    "DEFAULT_EXECUTION_QUEUE_NAME",
    "HOST_METRIC_SUMMARY_TASK_LAST_TS",
    "INSIGHTS_TRACKING_STATE",
    "INSTALL_UUID",
    "IS_K8S",
    "LICENSE",
    "MANAGE_ORGANIZATION_AUTH",
    "ORG_ADMINS_CAN_SEE_ALL_USERS",
    "PROXY_IP_ALLOWED_LIST",
    "REDHAT_PASSWORD",
    "REDHAT_USERNAME",
    "REMOTE_HOST_HEADERS",
    "SUBSCRIPTIONS_PASSWORD",
    "SUBSCRIPTIONS_USERNAME",
    "SUBSCRIPTION_USAGE_MODEL",
    "TOWER_URL_BASE",
    "UI_NEXT"
  ],
  "PropertyPostData": {
    "ACTIVITY_STREAM_ENABLED": {
      "category": "System",
      "category_slug": "system",
      "computed": true,
      "default": true,
      "help_text": "Enable capturing activity for the activity stream.",
      "hidden": false,
      "label": "Enable Activity Stream",
      "name": "ACTIVITY_STREAM_ENABLED",
      "required": false,
      "sensitive": false,
      "type": "boolean"
    },
    "ACTIVITY_STREAM_ENABLED_FOR_INVENTORY_SYNC": {
      "category": "System",
      "category_slug": "system",
      "computed": true,
      "default": false,
      "help_text": "Enable capturing activity for the activity stream when running inventory sync.",
      "hidden": false,
      "label": "Enable Activity Stream for Inventory Sync",
      "name": "ACTIVITY_STREAM_ENABLED_FOR_INVENTORY_SYNC",
      "required": false,
      "sensitive": false,
      "type": "boolean"
    },
    "AUTOMATION_ANALYTICS_GATHER_INTERVAL": {
      "category": "System",
      "category_slug": "system",
      "computed": true,
      "default": 14400,
      "default_value": "int64default.StaticInt64(14400)",
      "help_text": "Interval (in seconds) between data gathering.",
      "hidden": false,
      "label": "Automation Analytics Gather Interval",
      "min_value": 1800,
      "name": "AUTOMATION_ANALYTICS_GATHER_INTERVAL",
      "required": false,
      "sensitive": false,
      "type": "integer",
      "unit": "seconds"
    },
    "AUTOMATION_ANALYTICS_LAST_ENTRIES": {
      "category": "System",
      "category_slug": "system",
      "computed": true,
      "default": "",
      "default_value": "stringdefault.StaticString(``)",
      "hidden": false,
      "label": "Last gathered entries from the data collection service of Automation Analytics",
      "name": "AUTOMATION_ANALYTICS_LAST_ENTRIES",
      "required": false,
      "sensitive": false,
      "type": "string"
    },
    "AUTOMATION_ANALYTICS_URL": {
      "category": "System",
      "category_slug": "system",
      "computed": true,
      "default": "https://example.com",
      "default_value": "stringdefault.StaticString(`https://example.com`)",
      "help_text": "This setting is used to to configure the upload URL for data collection for Automation Analytics.",
      "hidden": false,
      "label": "Automation Analytics upload URL",
      "name": "AUTOMATION_ANALYTICS_URL",
      "required": false,
      "sensitive": false,
      "type": "string"
    },
    "CSRF_TRUSTED_ORIGINS": {
      "category": "System",
      "category_slug": "system",
      "child": {
        "hidden": false,
        "read_only": false,
        "required": true,
        "type": "string"
      },
      "computed": true,
      "default": [],
      "element_type": "string",
      "help_text": "If the service is behind a reverse proxy/load balancer, use this setting to configure the schema://addresses from which the service should trust Origin header values. ",
      "hidden": false,
      "label": "CSRF Trusted Origins List",
      "name": "CSRF_TRUSTED_ORIGINS",
      "required": false,
      "sensitive": false,
      "type": "list"
    },
    "DEFAULT_EXECUTION_ENVIRONMENT": {
      "category": "System",
      "category_slug": "system",
      "computed": true,
      "default": null,
      "help_text": "The Execution Environment to be used when one has not been configured for a job template.",
      "hidden": false,
      "label": "Global default execution environment",
      "name": "DEFAULT_EXECUTION_ENVIRONMENT",
      "post_wrap": false,
      "required": false,
      "sensitive": false,
      "trim": false,
      "type": "id"
    },
    "INSIGHTS_TRACKING_STATE": {
      "category": "System",
      "category_slug": "system",
      "computed": true,
      "default": false,
      "help_text": "Enables the service to gather data on automation and send it to Automation Analytics.",
      "hidden": false,
      "label": "Gather data for Automation Analytics",
      "name": "INSIGHTS_TRACKING_STATE",
      "required": false,
      "sensitive": false,
      "type": "boolean"
    },
    "MANAGE_ORGANIZATION_AUTH": {
      "category": "System",
      "category_slug": "system",
      "computed": true,
      "default": true,
      "help_text": "Controls whether any Organization Admin has the privileges to create and manage users and teams. You may want to disable this ability if you are using an LDAP or SAML integration.",
      "hidden": false,
      "label": "Organization Admins Can Manage Users and Teams",
      "name": "MANAGE_ORGANIZATION_AUTH",
      "required": false,
      "sensitive": false,
      "type": "boolean"
    },
    "ORG_ADMINS_CAN_SEE_ALL_USERS": {
      "category": "System",
      "category_slug": "system",
      "computed": true,
      "default": true,
      "help_text": "Controls whether any Organization Admin can view all users and teams, even those not associated with their Organization.",
      "hidden": false,
      "label": "All Users Visible to Organization Admins",
      "name": "ORG_ADMINS_CAN_SEE_ALL_USERS",
      "required": false,
      "sensitive": false,
      "type": "boolean"
    },
    "PROXY_IP_ALLOWED_LIST": {
      "category": "System",
      "category_slug": "system",
      "child": {
        "hidden": false,
        "read_only": false,
        "required": true,
        "type": "string"
      },
      "computed": true,
      "default": [],
      "element_type": "string",
      "help_text": "If the service is behind a reverse proxy/load balancer, use this setting to configure the proxy IP addresses from which the service should trust custom REMOTE_HOST_HEADERS header values. If this setting is an empty list (the default), the headers specified by REMOTE_HOST_HEADERS will be trusted unconditionally')",
      "hidden": false,
      "label": "Proxy IP Allowed List",
      "name": "PROXY_IP_ALLOWED_LIST",
      "required": false,
      "sensitive": false,
      "type": "list"
    },
    "REDHAT_PASSWORD": {
      "category": "System",
      "category_slug": "system",
      "computed": true,
      "default": "",
      "default_value": "stringdefault.StaticString(``)",
      "help_text": "This password is used to send data to Automation Analytics",
      "hidden": false,
      "label": "Red Hat customer password",
      "name": "REDHAT_PASSWORD",
      "required": false,
      "sensitive": false,
      "type": "string"
    },
    "REDHAT_USERNAME": {
      "category": "System",
      "category_slug": "system",
      "computed": true,
      "default": "",
      "default_value": "stringdefault.StaticString(``)",
      "help_text": "This username is used to send data to Automation Analytics",
      "hidden": false,
      "label": "Red Hat customer username",
      "name": "REDHAT_USERNAME",
      "required": false,
      "sensitive": false,
      "type": "string"
    },
    "REMOTE_HOST_HEADERS": {
      "category": "System",
      "category_slug": "system",
      "child": {
        "hidden": false,
        "read_only": false,
        "required": true,
        "type": "string"
      },
      "computed": true,
      "default": [
        "REMOTE_ADDR",
        "REMOTE_HOST"
      ],
      "element_type": "string",
      "help_text": "HTTP headers and meta keys to search to determine remote host name or IP. Add additional items to this list, such as \"HTTP_X_FORWARDED_FOR\", if behind a reverse proxy. See the \"Proxy Support\" section of the AAP Installation guide for more details.",
      "hidden": false,
      "label": "Remote Host Headers",
      "name": "REMOTE_HOST_HEADERS",
      "required": false,
      "sensitive": false,
      "type": "list"
    },
    "SUBSCRIPTIONS_PASSWORD": {
      "category": "System",
      "category_slug": "system",
      "computed": true,
      "default": "",
      "default_value": "stringdefault.StaticString(``)",
      "help_text": "This password is used to retrieve subscription and content information",
      "hidden": false,
      "label": "Red Hat or Satellite password",
      "name": "SUBSCRIPTIONS_PASSWORD",
      "required": false,
      "sensitive": false,
      "type": "string"
    },
    "SUBSCRIPTIONS_USERNAME": {
      "category": "System",
      "category_slug": "system",
      "computed": true,
      "default": "",
      "default_value": "stringdefault.StaticString(``)",
      "help_text": "This username is used to retrieve subscription and content information",
      "hidden": false,
      "label": "Red Hat or Satellite username",
      "name": "SUBSCRIPTIONS_USERNAME",
      "required": false,
      "sensitive": false,
      "type": "string"
    },
    "SUBSCRIPTION_USAGE_MODEL": {
      "category": "System",
      "category_slug": "system",
      "choices": [
        [
          "",
          "Default model for AWX - no subscription. Deletion of host_metrics will not be considered for purposes of managed host counting"
        ],
        [
          "unique_managed_hosts",
          "Usage based on unique managed nodes in a large historical time frame and delete functionality for no longer used managed nodes"
        ]
      ],
      "computed": true,
      "default": "",
      "default_value": "stringdefault.StaticString(``)",
      "hidden": false,
      "label": "Defines subscription usage model and shows Host Metrics",
      "name": "SUBSCRIPTION_USAGE_MODEL",
      "required": false,
      "sensitive": false,
      "type": "choice"
    },
    "TOWER_URL_BASE": {
      "category": "System",
      "category_slug": "system",
      "computed": true,
      "default": "https://localhost:8043",
      "default_value": "stringdefault.StaticString(`https://localhost:8043`)",
      "help_text": "This setting is used by services like notifications to render a valid url to the service.",
      "hidden": false,
      "label": "Base URL of the service",
      "name": "TOWER_URL_BASE",
      "required": false,
      "sensitive": false,
      "type": "string"
    },
    "UI_NEXT": {
      "category": "System",
      "category_slug": "system",
      "computed": true,
      "default": true,
      "help_text": "Enable preview of new user interface.",
      "hidden": true,
      "label": "Enable Preview of New User Interface",
      "name": "UI_NEXT",
      "required": false,
      "sensitive": false,
      "type": "boolean"
    }
  },
  "PropertyPostKeys": [
    "ACTIVITY_STREAM_ENABLED",
    "ACTIVITY_STREAM_ENABLED_FOR_INVENTORY_SYNC",
    "AUTOMATION_ANALYTICS_GATHER_INTERVAL",
    "AUTOMATION_ANALYTICS_LAST_ENTRIES",
    "AUTOMATION_ANALYTICS_URL",
    "CSRF_TRUSTED_ORIGINS",
    "DEFAULT_EXECUTION_ENVIRONMENT",
    "INSIGHTS_TRACKING_STATE",
    "MANAGE_ORGANIZATION_AUTH",
    "ORG_ADMINS_CAN_SEE_ALL_USERS",
    "PROXY_IP_ALLOWED_LIST",
    "REDHAT_PASSWORD",
    "REDHAT_USERNAME",
    "REMOTE_HOST_HEADERS",
    "SUBSCRIPTIONS_PASSWORD",
    "SUBSCRIPTIONS_USERNAME",
    "SUBSCRIPTION_USAGE_MODEL",
    "TOWER_URL_BASE",
    "UI_NEXT"
  ],
  "PropertyWriteOnlyData": {},
  "PropertyWriteOnlyKeys": null
}