{
  "ApiVersion": "24.2.0",
  "Config": {
    "endpoint": "/api/v2/settings/jobs/",
    "name": "SettingsJobs",
    "type_name": "settings_jobs",
    "id_key": "id",
    "property_overrides": {
      "AWX_TASK_ENV": {
        "type": "json",
        "description": "",
        "sensitive": false,
        "required": false,
        "trim": false,
        "post_wrap": false,
        "default_value": "",
        "element_type": ""
      },
      "GALAXY_TASK_ENV": {
        "type": "json",
        "description": "",
        "sensitive": false,
        "required": false,
        "trim": false,
        "post_wrap": false,
        "default_value": "",
        "element_type": ""
      }
    },
    "enabled": true,
    "has_object_roles": false,
    "has_survey_spec": false,
    "associate_disassociate_groups": null,
    "field_constraints": null,
    "skip_write_only": false,
    "undeletable": true,
    "pre_state_set_hook_function": "",
    "no_id": true,
    "no_terraform_data_source": false,
    "no_terraform_resource": false,
    "api_property_resource_key": "PUT",
    "api_property_data_key": "GET",
    "property_name_leave_as_is": true,
    "api_data_override": null,
    "remove_fields_data_source": null,
    "remove_fields_resource": null,
    "credential_types": null
  },
  "Description": "# Retrieve a Setting:\n\nMake GET request to this resource to retrieve a single setting\nrecord containing the following fields:\n\n* `AD_HOC_COMMANDS`: List of modules allowed to be used by ad-hoc jobs. (list)\n* `ALLOW_JINJA_IN_EXTRA_VARS`: Ansible allows variable substitution via the Jinja2 templating language for --extra-vars. This poses a potential security risk where users with the ability to specify extra vars at job launch time can use Jinja2 templates to run arbitrary Python.  It is recommended that this value be set to \u0026quot;template\u0026quot; or \u0026quot;never\u0026quot;. (choice)\n    - `always`: Always\n    - `never`: Never\n    - `template`: Only On Job Template Definitions\n* `AWX_ISOLATION_BASE_PATH`: The directory in which the service will create new temporary directories for job execution and isolation (such as credential files). (string)\n* `AWX_ISOLATION_SHOW_PATHS`: List of paths that would otherwise be hidden to expose to isolated jobs. Enter one path per line. Volumes will be mounted from the execution node to the container. The supported format is HOST-DIR[:CONTAINER-DIR[:OPTIONS]].  (list)\n* `AWX_TASK_ENV`: Additional environment variables set for playbook runs, inventory updates, project updates, and notification sending. (nested object)\n* `AWX_RUNNER_KEEPALIVE_SECONDS`: Only applies to jobs running in a Container Group. If not 0, send a message every so-many seconds to keep connection open. (integer)\n* `GALAXY_TASK_ENV`: Additional environment variables set for invocations of ansible-galaxy within project updates. Useful if you must use a proxy server for ansible-galaxy but not git. (nested object)\n* `PROJECT_UPDATE_VVV`: Adds the CLI -vvv flag to ansible-playbook runs of project_update.yml used for project updates. (boolean)\n* `AWX_ROLES_ENABLED`: Allows roles to be dynamically downloaded from a requirements.yml file for SCM projects. (boolean)\n* `AWX_COLLECTIONS_ENABLED`: Allows collections to be dynamically downloaded from a requirements.yml file for SCM projects. (boolean)\n* `AWX_SHOW_PLAYBOOK_LINKS`: Follow symbolic links when scanning for playbooks. Be aware that setting this to True can lead to infinite recursion if a link points to a parent directory of itself. (boolean)\n* `AWX_MOUNT_ISOLATED_PATHS_ON_K8S`: Expose paths via hostPath for the Pods created by a Container Group. HostPath volumes present many security risks, and it is a best practice to avoid the use of HostPaths when possible.  (boolean)\n* `GALAXY_IGNORE_CERTS`: If set to true, certificate validation will not be done when installing content from any Galaxy server. (boolean)\n* `STDOUT_MAX_BYTES_DISPLAY`: Maximum Size of Standard Output in bytes to display before requiring the output be downloaded. (integer)\n* `EVENT_STDOUT_MAX_BYTES_DISPLAY`: Maximum Size of Standard Output in bytes to display for a single job or ad hoc command event. `stdout` will end with `â€¦` when truncated. (integer)\n* `MAX_WEBSOCKET_EVENT_RATE`: Maximum number of messages to update the UI live job output with per second. Value of 0 means no limit. (integer)\n* `SCHEDULE_MAX_JOBS`: Maximum number of the same job template that can be waiting to run when launching from a schedule before no more are created. (integer)\n* `AWX_ANSIBLE_CALLBACK_PLUGINS`: List of paths to search for extra callback plugins to be used when running jobs. Enter one path per line. (list)\n* `DEFAULT_JOB_TIMEOUT`: Maximum time in seconds to allow jobs to run. Use value of 0 to indicate that no timeout should be imposed. A timeout set on an individual job template will override this. (integer)\n* `DEFAULT_JOB_IDLE_TIMEOUT`: If no output is detected from ansible in this number of seconds the execution will be terminated. Use value of 0 to indicate that no idle timeout should be imposed. (integer)\n* `DEFAULT_INVENTORY_UPDATE_TIMEOUT`: Maximum time in seconds to allow inventory updates to run. Use value of 0 to indicate that no timeout should be imposed. A timeout set on an individual inventory source will override this. (integer)\n* `DEFAULT_PROJECT_UPDATE_TIMEOUT`: Maximum time in seconds to allow project updates to run. Use value of 0 to indicate that no timeout should be imposed. A timeout set on an individual project will override this. (integer)\n* `ANSIBLE_FACT_CACHE_TIMEOUT`: Maximum time, in seconds, that stored Ansible facts are considered valid since the last time they were modified. Only valid, non-stale, facts will be accessible by a playbook. Note, this does not influence the deletion of ansible_facts from the database. Use a value of 0 to indicate that no timeout should be imposed. (integer)\n* `MAX_FORKS`: Saving a Job Template with more than this number of forks will result in an error. When set to 0, no limit is applied. (integer)\n* `DEFAULT_CONTAINER_RUN_OPTIONS`: List of options to pass to podman run example: [\u0026#x27;--network\u0026#x27;, \u0026#x27;slirp4netns:enable_ipv6=true\u0026#x27;, \u0026#x27;--log-level\u0026#x27;, \u0026#x27;debug\u0026#x27;] (list)\n\n\n\n\n\n# Update a Setting:\n\nMake a PUT or PATCH request to this resource to update this\nsetting.  The following fields may be modified:\n\n\n* `AD_HOC_COMMANDS`: List of modules allowed to be used by ad-hoc jobs. (list, default=`[\u0026#x27;command\u0026#x27;, \u0026#x27;shell\u0026#x27;, \u0026#x27;yum\u0026#x27;, \u0026#x27;apt\u0026#x27;, \u0026#x27;apt_key\u0026#x27;, \u0026#x27;apt_repository\u0026#x27;, \u0026#x27;apt_rpm\u0026#x27;, \u0026#x27;service\u0026#x27;, \u0026#x27;group\u0026#x27;, \u0026#x27;user\u0026#x27;, \u0026#x27;mount\u0026#x27;, \u0026#x27;ping\u0026#x27;, \u0026#x27;selinux\u0026#x27;, \u0026#x27;setup\u0026#x27;, \u0026#x27;win_ping\u0026#x27;, \u0026#x27;win_service\u0026#x27;, \u0026#x27;win_updates\u0026#x27;, \u0026#x27;win_group\u0026#x27;, \u0026#x27;win_user\u0026#x27;]`)\n* `ALLOW_JINJA_IN_EXTRA_VARS`: Ansible allows variable substitution via the Jinja2 templating language for --extra-vars. This poses a potential security risk where users with the ability to specify extra vars at job launch time can use Jinja2 templates to run arbitrary Python.  It is recommended that this value be set to \u0026quot;template\u0026quot; or \u0026quot;never\u0026quot;. (choice, required)\n    - `always`: Always\n    - `never`: Never\n    - `template`: Only On Job Template Definitions (default)\n* `AWX_ISOLATION_BASE_PATH`: The directory in which the service will create new temporary directories for job execution and isolation (such as credential files). (string, required)\n* `AWX_ISOLATION_SHOW_PATHS`: List of paths that would otherwise be hidden to expose to isolated jobs. Enter one path per line. Volumes will be mounted from the execution node to the container. The supported format is HOST-DIR[:CONTAINER-DIR[:OPTIONS]].  (list, default=`[]`)\n* `AWX_TASK_ENV`: Additional environment variables set for playbook runs, inventory updates, project updates, and notification sending. (nested object, default=`{}`)\n* `AWX_RUNNER_KEEPALIVE_SECONDS`: Only applies to jobs running in a Container Group. If not 0, send a message every so-many seconds to keep connection open. (integer, required)\n* `GALAXY_TASK_ENV`: Additional environment variables set for invocations of ansible-galaxy within project updates. Useful if you must use a proxy server for ansible-galaxy but not git. (nested object, required)\n* `PROJECT_UPDATE_VVV`: Adds the CLI -vvv flag to ansible-playbook runs of project_update.yml used for project updates. (boolean, required)\n* `AWX_ROLES_ENABLED`: Allows roles to be dynamically downloaded from a requirements.yml file for SCM projects. (boolean, default=`True`)\n* `AWX_COLLECTIONS_ENABLED`: Allows collections to be dynamically downloaded from a requirements.yml file for SCM projects. (boolean, default=`True`)\n* `AWX_SHOW_PLAYBOOK_LINKS`: Follow symbolic links when scanning for playbooks. Be aware that setting this to True can lead to infinite recursion if a link points to a parent directory of itself. (boolean, default=`False`)\n* `AWX_MOUNT_ISOLATED_PATHS_ON_K8S`: Expose paths via hostPath for the Pods created by a Container Group. HostPath volumes present many security risks, and it is a best practice to avoid the use of HostPaths when possible.  (boolean, default=`False`)\n* `GALAXY_IGNORE_CERTS`: If set to true, certificate validation will not be done when installing content from any Galaxy server. (boolean, default=`False`)\n* `STDOUT_MAX_BYTES_DISPLAY`: Maximum Size of Standard Output in bytes to display before requiring the output be downloaded. (integer, required)\n* `EVENT_STDOUT_MAX_BYTES_DISPLAY`: Maximum Size of Standard Output in bytes to display for a single job or ad hoc command event. `stdout` will end with `â€¦` when truncated. (integer, required)\n* `MAX_WEBSOCKET_EVENT_RATE`: Maximum number of messages to update the UI live job output with per second. Value of 0 means no limit. (integer, default=`30`)\n* `SCHEDULE_MAX_JOBS`: Maximum number of the same job template that can be waiting to run when launching from a schedule before no more are created. (integer, required)\n* `AWX_ANSIBLE_CALLBACK_PLUGINS`: List of paths to search for extra callback plugins to be used when running jobs. Enter one path per line. (list, default=`[]`)\n* `DEFAULT_JOB_TIMEOUT`: Maximum time in seconds to allow jobs to run. Use value of 0 to indicate that no timeout should be imposed. A timeout set on an individual job template will override this. (integer, default=`0`)\n* `DEFAULT_JOB_IDLE_TIMEOUT`: If no output is detected from ansible in this number of seconds the execution will be terminated. Use value of 0 to indicate that no idle timeout should be imposed. (integer, default=`0`)\n* `DEFAULT_INVENTORY_UPDATE_TIMEOUT`: Maximum time in seconds to allow inventory updates to run. Use value of 0 to indicate that no timeout should be imposed. A timeout set on an individual inventory source will override this. (integer, default=`0`)\n* `DEFAULT_PROJECT_UPDATE_TIMEOUT`: Maximum time in seconds to allow project updates to run. Use value of 0 to indicate that no timeout should be imposed. A timeout set on an individual project will override this. (integer, default=`0`)\n* `ANSIBLE_FACT_CACHE_TIMEOUT`: Maximum time, in seconds, that stored Ansible facts are considered valid since the last time they were modified. Only valid, non-stale, facts will be accessible by a playbook. Note, this does not influence the deletion of ansible_facts from the database. Use a value of 0 to indicate that no timeout should be imposed. (integer, default=`0`)\n* `MAX_FORKS`: Saving a Job Template with more than this number of forks will result in an error. When set to 0, no limit is applied. (integer, default=`200`)\n* `DEFAULT_CONTAINER_RUN_OPTIONS`: List of options to pass to podman run example: [\u0026#x27;--network\u0026#x27;, \u0026#x27;slirp4netns:enable_ipv6=true\u0026#x27;, \u0026#x27;--log-level\u0026#x27;, \u0026#x27;debug\u0026#x27;] (list, default=`[\u0026#x27;--network\u0026#x27;, \u0026#x27;slirp4netns:enable_ipv6=true\u0026#x27;]`)\n\n\n\n\n\n\nFor a PUT request, include **all** fields in the request.\n\n\n\nFor a PATCH request, include only the fields that are being modified.\n\n\n\n# Delete a Setting:\n\nMake a DELETE request to this resource to delete this setting.",
  "Endpoint": "/api/v2/settings/jobs/",
  "Name": "SettingsJobs",
  "PackageName": "awx",
  "PropertyGetData": {
    "AD_HOC_COMMANDS": {
      "category": "Jobs",
      "category_slug": "jobs",
      "child": {
        "hidden": false,
        "type": "string"
      },
      "computed": true,
      "defined_in_file": false,
      "element_type": "string",
      "help_text": "List of modules allowed to be used by ad-hoc jobs.",
      "hidden": false,
      "label": "Ansible Modules Allowed for Ad Hoc Jobs",
      "name": "AD_HOC_COMMANDS",
      "required": false,
      "sensitive": false,
      "type": "list"
    },
    "ALLOW_JINJA_IN_EXTRA_VARS": {
      "category": "Jobs",
      "category_slug": "jobs",
      "choices": [
        [
          "always",
          "Always"
        ],
        [
          "never",
          "Never"
        ],
        [
          "template",
          "Only On Job Template Definitions"
        ]
      ],
      "computed": true,
      "defined_in_file": false,
      "help_text": "Ansible allows variable substitution via the Jinja2 templating language for --extra-vars. This poses a potential security risk where users with the ability to specify extra vars at job launch time can use Jinja2 templates to run arbitrary Python.  It is recommended that this value be set to \"template\" or \"never\".",
      "hidden": false,
      "label": "When can extra variables contain Jinja templates?",
      "name": "ALLOW_JINJA_IN_EXTRA_VARS",
      "required": false,
      "sensitive": false,
      "type": "choice"
    },
    "ANSIBLE_FACT_CACHE_TIMEOUT": {
      "category": "Jobs",
      "category_slug": "jobs",
      "computed": true,
      "defined_in_file": false,
      "help_text": "Maximum time, in seconds, that stored Ansible facts are considered valid since the last time they were modified. Only valid, non-stale, facts will be accessible by a playbook. Note, this does not influence the deletion of ansible_facts from the database. Use a value of 0 to indicate that no timeout should be imposed.",
      "hidden": false,
      "label": "Per-Host Ansible Fact Cache Timeout",
      "min_value": 0,
      "name": "ANSIBLE_FACT_CACHE_TIMEOUT",
      "required": false,
      "sensitive": false,
      "type": "integer",
      "unit": "seconds"
    },
    "AWX_ANSIBLE_CALLBACK_PLUGINS": {
      "category": "Jobs",
      "category_slug": "jobs",
      "child": {
        "hidden": false,
        "type": "string"
      },
      "computed": true,
      "defined_in_file": false,
      "element_type": "string",
      "help_text": "List of paths to search for extra callback plugins to be used when running jobs. Enter one path per line.",
      "hidden": false,
      "label": "Ansible Callback Plugins",
      "name": "AWX_ANSIBLE_CALLBACK_PLUGINS",
      "required": false,
      "sensitive": false,
      "type": "list"
    },
    "AWX_COLLECTIONS_ENABLED": {
      "category": "Jobs",
      "category_slug": "jobs",
      "computed": true,
      "defined_in_file": false,
      "help_text": "Allows collections to be dynamically downloaded from a requirements.yml file for SCM projects.",
      "hidden": false,
      "label": "Enable Collection(s) Download",
      "name": "AWX_COLLECTIONS_ENABLED",
      "required": false,
      "sensitive": false,
      "type": "boolean"
    },
    "AWX_ISOLATION_BASE_PATH": {
      "category": "Jobs",
      "category_slug": "jobs",
      "computed": true,
      "defined_in_file": false,
      "help_text": "The directory in which the service will create new temporary directories for job execution and isolation (such as credential files).",
      "hidden": false,
      "label": "Job execution path",
      "name": "AWX_ISOLATION_BASE_PATH",
      "required": false,
      "sensitive": false,
      "type": "string"
    },
    "AWX_ISOLATION_SHOW_PATHS": {
      "category": "Jobs",
      "category_slug": "jobs",
      "child": {
        "hidden": false,
        "type": "string"
      },
      "computed": true,
      "defined_in_file": false,
      "element_type": "string",
      "help_text": "List of paths that would otherwise be hidden to expose to isolated jobs. Enter one path per line. Volumes will be mounted from the execution node to the container. The supported format is HOST-DIR[:CONTAINER-DIR[:OPTIONS]]. ",
      "hidden": false,
      "label": "Paths to expose to isolated jobs",
      "name": "AWX_ISOLATION_SHOW_PATHS",
      "required": false,
      "sensitive": false,
      "type": "list"
    },
    "AWX_MOUNT_ISOLATED_PATHS_ON_K8S": {
      "category": "Jobs",
      "category_slug": "jobs",
      "computed": true,
      "defined_in_file": false,
      "help_text": "Expose paths via hostPath for the Pods created by a Container Group. HostPath volumes present many security risks, and it is a best practice to avoid the use of HostPaths when possible. ",
      "hidden": false,
      "label": "Expose host paths for Container Groups",
      "name": "AWX_MOUNT_ISOLATED_PATHS_ON_K8S",
      "required": false,
      "sensitive": false,
      "type": "boolean"
    },
    "AWX_ROLES_ENABLED": {
      "category": "Jobs",
      "category_slug": "jobs",
      "computed": true,
      "defined_in_file": false,
      "help_text": "Allows roles to be dynamically downloaded from a requirements.yml file for SCM projects.",
      "hidden": false,
      "label": "Enable Role Download",
      "name": "AWX_ROLES_ENABLED",
      "required": false,
      "sensitive": false,
      "type": "boolean"
    },
    "AWX_RUNNER_KEEPALIVE_SECONDS": {
      "category": "Jobs",
      "category_slug": "jobs",
      "computed": true,
      "defined_in_file": false,
      "help_text": "Only applies to jobs running in a Container Group. If not 0, send a message every so-many seconds to keep connection open.",
      "hidden": false,
      "label": "K8S Ansible Runner Keep-Alive Message Interval",
      "name": "AWX_RUNNER_KEEPALIVE_SECONDS",
      "required": false,
      "sensitive": false,
      "type": "integer"
    },
    "AWX_SHOW_PLAYBOOK_LINKS": {
      "category": "Jobs",
      "category_slug": "jobs",
      "computed": true,
      "defined_in_file": false,
      "help_text": "Follow symbolic links when scanning for playbooks. Be aware that setting this to True can lead to infinite recursion if a link points to a parent directory of itself.",
      "hidden": false,
      "label": "Follow symlinks",
      "name": "AWX_SHOW_PLAYBOOK_LINKS",
      "required": false,
      "sensitive": false,
      "type": "boolean"
    },
    "AWX_TASK_ENV": {
      "category": "Jobs",
      "category_slug": "jobs",
      "child": {
        "hidden": false,
        "type": "string"
      },
      "computed": true,
      "defined_in_file": false,
      "element_type": "string",
      "help_text": "Additional environment variables set for playbook runs, inventory updates, project updates, and notification sending.",
      "hidden": false,
      "label": "Extra Environment Variables",
      "name": "AWX_TASK_ENV",
      "post_wrap": false,
      "required": false,
      "sensitive": false,
      "trim": false,
      "type": "json"
    },
    "DEFAULT_CONTAINER_RUN_OPTIONS": {
      "category": "Jobs",
      "category_slug": "jobs",
      "child": {
        "hidden": false,
        "type": "string"
      },
      "computed": true,
      "defined_in_file": false,
      "element_type": "string",
      "help_text": "List of options to pass to podman run example: ['--network', 'slirp4netns:enable_ipv6=true', '--log-level', 'debug']",
      "hidden": false,
      "label": "Container Run Options",
      "name": "DEFAULT_CONTAINER_RUN_OPTIONS",
      "required": false,
      "sensitive": false,
      "type": "list"
    },
    "DEFAULT_INVENTORY_UPDATE_TIMEOUT": {
      "category": "Jobs",
      "category_slug": "jobs",
      "computed": true,
      "defined_in_file": false,
      "help_text": "Maximum time in seconds to allow inventory updates to run. Use value of 0 to indicate that no timeout should be imposed. A timeout set on an individual inventory source will override this.",
      "hidden": false,
      "label": "Default Inventory Update Timeout",
      "min_value": 0,
      "name": "DEFAULT_INVENTORY_UPDATE_TIMEOUT",
      "required": false,
      "sensitive": false,
      "type": "integer",
      "unit": "seconds"
    },
    "DEFAULT_JOB_IDLE_TIMEOUT": {
      "category": "Jobs",
      "category_slug": "jobs",
      "computed": true,
      "defined_in_file": false,
      "help_text": "If no output is detected from ansible in this number of seconds the execution will be terminated. Use value of 0 to indicate that no idle timeout should be imposed.",
      "hidden": false,
      "label": "Default Job Idle Timeout",
      "min_value": 0,
      "name": "DEFAULT_JOB_IDLE_TIMEOUT",
      "required": false,
      "sensitive": false,
      "type": "integer",
      "unit": "seconds"
    },
    "DEFAULT_JOB_TIMEOUT": {
      "category": "Jobs",
      "category_slug": "jobs",
      "computed": true,
      "defined_in_file": false,
      "help_text": "Maximum time in seconds to allow jobs to run. Use value of 0 to indicate that no timeout should be imposed. A timeout set on an individual job template will override this.",
      "hidden": false,
      "label": "Default Job Timeout",
      "min_value": 0,
      "name": "DEFAULT_JOB_TIMEOUT",
      "required": false,
      "sensitive": false,
      "type": "integer",
      "unit": "seconds"
    },
    "DEFAULT_PROJECT_UPDATE_TIMEOUT": {
      "category": "Jobs",
      "category_slug": "jobs",
      "computed": true,
      "defined_in_file": false,
      "help_text": "Maximum time in seconds to allow project updates to run. Use value of 0 to indicate that no timeout should be imposed. A timeout set on an individual project will override this.",
      "hidden": false,
      "label": "Default Project Update Timeout",
      "min_value": 0,
      "name": "DEFAULT_PROJECT_UPDATE_TIMEOUT",
      "required": false,
      "sensitive": false,
      "type": "integer",
      "unit": "seconds"
    },
    "EVENT_STDOUT_MAX_BYTES_DISPLAY": {
      "category": "Jobs",
      "category_slug": "jobs",
      "computed": true,
      "defined_in_file": false,
      "help_text": "Maximum Size of Standard Output in bytes to display for a single job or ad hoc command event. `stdout` will end with `â€¦` when truncated.",
      "hidden": false,
      "label": "Job Event Standard Output Maximum Display Size",
      "min_value": 0,
      "name": "EVENT_STDOUT_MAX_BYTES_DISPLAY",
      "required": false,
      "sensitive": false,
      "type": "integer"
    },
    "GALAXY_IGNORE_CERTS": {
      "category": "Jobs",
      "category_slug": "jobs",
      "computed": true,
      "defined_in_file": false,
      "help_text": "If set to true, certificate validation will not be done when installing content from any Galaxy server.",
      "hidden": false,
      "label": "Ignore Ansible Galaxy SSL Certificate Verification",
      "name": "GALAXY_IGNORE_CERTS",
      "required": false,
      "sensitive": false,
      "type": "boolean"
    },
    "GALAXY_TASK_ENV": {
      "category": "Jobs",
      "category_slug": "jobs",
      "child": {
        "hidden": false,
        "type": "string"
      },
      "computed": true,
      "defined_in_file": false,
      "element_type": "string",
      "help_text": "Additional environment variables set for invocations of ansible-galaxy within project updates. Useful if you must use a proxy server for ansible-galaxy but not git.",
      "hidden": false,
      "label": "Environment Variables for Galaxy Commands",
      "name": "GALAXY_TASK_ENV",
      "post_wrap": false,
      "required": false,
      "sensitive": false,
      "trim": false,
      "type": "json"
    },
    "MAX_FORKS": {
      "category": "Jobs",
      "category_slug": "jobs",
      "computed": true,
      "defined_in_file": false,
      "help_text": "Saving a Job Template with more than this number of forks will result in an error. When set to 0, no limit is applied.",
      "hidden": false,
      "label": "Maximum number of forks per job",
      "name": "MAX_FORKS",
      "required": false,
      "sensitive": false,
      "type": "integer"
    },
    "MAX_WEBSOCKET_EVENT_RATE": {
      "category": "Jobs",
      "category_slug": "jobs",
      "computed": true,
      "defined_in_file": false,
      "help_text": "Maximum number of messages to update the UI live job output with per second. Value of 0 means no limit.",
      "hidden": false,
      "label": "Job Event Maximum Websocket Messages Per Second",
      "min_value": 0,
      "name": "MAX_WEBSOCKET_EVENT_RATE",
      "required": false,
      "sensitive": false,
      "type": "integer"
    },
    "PROJECT_UPDATE_VVV": {
      "category": "Jobs",
      "category_slug": "jobs",
      "computed": true,
      "defined_in_file": false,
      "help_text": "Adds the CLI -vvv flag to ansible-playbook runs of project_update.yml used for project updates.",
      "hidden": false,
      "label": "Run Project Updates With Higher Verbosity",
      "name": "PROJECT_UPDATE_VVV",
      "required": false,
      "sensitive": false,
      "type": "boolean"
    },
    "SCHEDULE_MAX_JOBS": {
      "category": "Jobs",
      "category_slug": "jobs",
      "computed": true,
      "defined_in_file": false,
      "help_text": "Maximum number of the same job template that can be waiting to run when launching from a schedule before no more are created.",
      "hidden": false,
      "label": "Maximum Scheduled Jobs",
      "min_value": 1,
      "name": "SCHEDULE_MAX_JOBS",
      "required": false,
      "sensitive": false,
      "type": "integer"
    },
    "STDOUT_MAX_BYTES_DISPLAY": {
      "category": "Jobs",
      "category_slug": "jobs",
      "computed": true,
      "defined_in_file": false,
      "help_text": "Maximum Size of Standard Output in bytes to display before requiring the output be downloaded.",
      "hidden": false,
      "label": "Standard Output Maximum Display Size",
      "min_value": 0,
      "name": "STDOUT_MAX_BYTES_DISPLAY",
      "required": false,
      "sensitive": false,
      "type": "integer"
    }
  },
  "PropertyGetKeys": [
    "AD_HOC_COMMANDS",
    "ALLOW_JINJA_IN_EXTRA_VARS",
    "ANSIBLE_FACT_CACHE_TIMEOUT",
    "AWX_ANSIBLE_CALLBACK_PLUGINS",
    "AWX_COLLECTIONS_ENABLED",
    "AWX_ISOLATION_BASE_PATH",
    "AWX_ISOLATION_SHOW_PATHS",
    "AWX_MOUNT_ISOLATED_PATHS_ON_K8S",
    "AWX_ROLES_ENABLED",
    "AWX_RUNNER_KEEPALIVE_SECONDS",
    "AWX_SHOW_PLAYBOOK_LINKS",
    "AWX_TASK_ENV",
    "DEFAULT_CONTAINER_RUN_OPTIONS",
    "DEFAULT_INVENTORY_UPDATE_TIMEOUT",
    "DEFAULT_JOB_IDLE_TIMEOUT",
    "DEFAULT_JOB_TIMEOUT",
    "DEFAULT_PROJECT_UPDATE_TIMEOUT",
    "EVENT_STDOUT_MAX_BYTES_DISPLAY",
    "GALAXY_IGNORE_CERTS",
    "GALAXY_TASK_ENV",
    "MAX_FORKS",
    "MAX_WEBSOCKET_EVENT_RATE",
    "PROJECT_UPDATE_VVV",
    "SCHEDULE_MAX_JOBS",
    "STDOUT_MAX_BYTES_DISPLAY"
  ],
  "PropertyPostData": {
    "AD_HOC_COMMANDS": {
      "category": "Jobs",
      "category_slug": "jobs",
      "child": {
        "hidden": false,
        "read_only": false,
        "required": true,
        "type": "string"
      },
      "computed": true,
      "default": [
        "command",
        "shell",
        "yum",
        "apt",
        "apt_key",
        "apt_repository",
        "apt_rpm",
        "service",
        "group",
        "user",
        "mount",
        "ping",
        "selinux",
        "setup",
        "win_ping",
        "win_service",
        "win_updates",
        "win_group",
        "win_user"
      ],
      "element_type": "string",
      "help_text": "List of modules allowed to be used by ad-hoc jobs.",
      "hidden": false,
      "label": "Ansible Modules Allowed for Ad Hoc Jobs",
      "name": "AD_HOC_COMMANDS",
      "required": false,
      "sensitive": false,
      "type": "list"
    },
    "ALLOW_JINJA_IN_EXTRA_VARS": {
      "category": "Jobs",
      "category_slug": "jobs",
      "choices": [
        [
          "always",
          "Always"
        ],
        [
          "never",
          "Never"
        ],
        [
          "template",
          "Only On Job Template Definitions"
        ]
      ],
      "computed": true,
      "default": "template",
      "default_value": "stringdefault.StaticString(`template`)",
      "help_text": "Ansible allows variable substitution via the Jinja2 templating language for --extra-vars. This poses a potential security risk where users with the ability to specify extra vars at job launch time can use Jinja2 templates to run arbitrary Python.  It is recommended that this value be set to \"template\" or \"never\".",
      "hidden": false,
      "label": "When can extra variables contain Jinja templates?",
      "name": "ALLOW_JINJA_IN_EXTRA_VARS",
      "required": false,
      "sensitive": false,
      "type": "choice"
    },
    "ANSIBLE_FACT_CACHE_TIMEOUT": {
      "category": "Jobs",
      "category_slug": "jobs",
      "computed": true,
      "default": 0,
      "default_value": "int64default.StaticInt64(0)",
      "help_text": "Maximum time, in seconds, that stored Ansible facts are considered valid since the last time they were modified. Only valid, non-stale, facts will be accessible by a playbook. Note, this does not influence the deletion of ansible_facts from the database. Use a value of 0 to indicate that no timeout should be imposed.",
      "hidden": false,
      "label": "Per-Host Ansible Fact Cache Timeout",
      "min_value": 0,
      "name": "ANSIBLE_FACT_CACHE_TIMEOUT",
      "required": false,
      "sensitive": false,
      "type": "integer",
      "unit": "seconds"
    },
    "AWX_ANSIBLE_CALLBACK_PLUGINS": {
      "category": "Jobs",
      "category_slug": "jobs",
      "child": {
        "hidden": false,
        "read_only": false,
        "required": true,
        "type": "string"
      },
      "computed": true,
      "default": [],
      "element_type": "string",
      "help_text": "List of paths to search for extra callback plugins to be used when running jobs. Enter one path per line.",
      "hidden": false,
      "label": "Ansible Callback Plugins",
      "name": "AWX_ANSIBLE_CALLBACK_PLUGINS",
      "required": false,
      "sensitive": false,
      "type": "list"
    },
    "AWX_COLLECTIONS_ENABLED": {
      "category": "Jobs",
      "category_slug": "jobs",
      "computed": true,
      "default": true,
      "help_text": "Allows collections to be dynamically downloaded from a requirements.yml file for SCM projects.",
      "hidden": false,
      "label": "Enable Collection(s) Download",
      "name": "AWX_COLLECTIONS_ENABLED",
      "required": false,
      "sensitive": false,
      "type": "boolean"
    },
    "AWX_ISOLATION_BASE_PATH": {
      "category": "Jobs",
      "category_slug": "jobs",
      "computed": true,
      "default": "/tmp",
      "default_value": "stringdefault.StaticString(`/tmp`)",
      "help_text": "The directory in which the service will create new temporary directories for job execution and isolation (such as credential files).",
      "hidden": false,
      "label": "Job execution path",
      "name": "AWX_ISOLATION_BASE_PATH",
      "required": false,
      "sensitive": false,
      "type": "string"
    },
    "AWX_ISOLATION_SHOW_PATHS": {
      "category": "Jobs",
      "category_slug": "jobs",
      "child": {
        "hidden": false,
        "read_only": false,
        "required": true,
        "type": "string"
      },
      "computed": true,
      "default": [],
      "element_type": "string",
      "help_text": "List of paths that would otherwise be hidden to expose to isolated jobs. Enter one path per line. Volumes will be mounted from the execution node to the container. The supported format is HOST-DIR[:CONTAINER-DIR[:OPTIONS]]. ",
      "hidden": false,
      "label": "Paths to expose to isolated jobs",
      "name": "AWX_ISOLATION_SHOW_PATHS",
      "required": false,
      "sensitive": false,
      "type": "list"
    },
    "AWX_MOUNT_ISOLATED_PATHS_ON_K8S": {
      "category": "Jobs",
      "category_slug": "jobs",
      "computed": true,
      "default": false,
      "help_text": "Expose paths via hostPath for the Pods created by a Container Group. HostPath volumes present many security risks, and it is a best practice to avoid the use of HostPaths when possible. ",
      "hidden": false,
      "label": "Expose host paths for Container Groups",
      "name": "AWX_MOUNT_ISOLATED_PATHS_ON_K8S",
      "required": false,
      "sensitive": false,
      "type": "boolean"
    },
    "AWX_ROLES_ENABLED": {
      "category": "Jobs",
      "category_slug": "jobs",
      "computed": true,
      "default": true,
      "help_text": "Allows roles to be dynamically downloaded from a requirements.yml file for SCM projects.",
      "hidden": false,
      "label": "Enable Role Download",
      "name": "AWX_ROLES_ENABLED",
      "required": false,
      "sensitive": false,
      "type": "boolean"
    },
    "AWX_RUNNER_KEEPALIVE_SECONDS": {
      "category": "Jobs",
      "category_slug": "jobs",
      "computed": true,
      "default": 0,
      "default_value": "int64default.StaticInt64(0)",
      "help_text": "Only applies to jobs running in a Container Group. If not 0, send a message every so-many seconds to keep connection open.",
      "hidden": false,
      "label": "K8S Ansible Runner Keep-Alive Message Interval",
      "name": "AWX_RUNNER_KEEPALIVE_SECONDS",
      "placeholder": 240,
      "required": false,
      "sensitive": false,
      "type": "integer"
    },
    "AWX_SHOW_PLAYBOOK_LINKS": {
      "category": "Jobs",
      "category_slug": "jobs",
      "computed": true,
      "default": false,
      "help_text": "Follow symbolic links when scanning for playbooks. Be aware that setting this to True can lead to infinite recursion if a link points to a parent directory of itself.",
      "hidden": false,
      "label": "Follow symlinks",
      "name": "AWX_SHOW_PLAYBOOK_LINKS",
      "required": false,
      "sensitive": false,
      "type": "boolean"
    },
    "AWX_TASK_ENV": {
      "category": "Jobs",
      "category_slug": "jobs",
      "child": {
        "hidden": false,
        "read_only": false,
        "required": true,
        "type": "string"
      },
      "computed": true,
      "default": {},
      "default_value": "stringdefault.StaticString(`{}`)",
      "element_type": "string",
      "help_text": "Additional environment variables set for playbook runs, inventory updates, project updates, and notification sending.",
      "hidden": false,
      "label": "Extra Environment Variables",
      "name": "AWX_TASK_ENV",
      "placeholder": {
        "HTTP_PROXY": "myproxy.local:8080"
      },
      "post_wrap": false,
      "required": false,
      "sensitive": false,
      "trim": false,
      "type": "json"
    },
    "DEFAULT_CONTAINER_RUN_OPTIONS": {
      "category": "Jobs",
      "category_slug": "jobs",
      "child": {
        "hidden": false,
        "read_only": false,
        "required": true,
        "type": "string"
      },
      "computed": true,
      "default": [
        "--network",
        "slirp4netns:enable_ipv6=true"
      ],
      "element_type": "string",
      "help_text": "List of options to pass to podman run example: ['--network', 'slirp4netns:enable_ipv6=true', '--log-level', 'debug']",
      "hidden": false,
      "label": "Container Run Options",
      "name": "DEFAULT_CONTAINER_RUN_OPTIONS",
      "required": false,
      "sensitive": false,
      "type": "list"
    },
    "DEFAULT_INVENTORY_UPDATE_TIMEOUT": {
      "category": "Jobs",
      "category_slug": "jobs",
      "computed": true,
      "default": 0,
      "default_value": "int64default.StaticInt64(0)",
      "help_text": "Maximum time in seconds to allow inventory updates to run. Use value of 0 to indicate that no timeout should be imposed. A timeout set on an individual inventory source will override this.",
      "hidden": false,
      "label": "Default Inventory Update Timeout",
      "min_value": 0,
      "name": "DEFAULT_INVENTORY_UPDATE_TIMEOUT",
      "required": false,
      "sensitive": false,
      "type": "integer",
      "unit": "seconds"
    },
    "DEFAULT_JOB_IDLE_TIMEOUT": {
      "category": "Jobs",
      "category_slug": "jobs",
      "computed": true,
      "default": 0,
      "default_value": "int64default.StaticInt64(0)",
      "help_text": "If no output is detected from ansible in this number of seconds the execution will be terminated. Use value of 0 to indicate that no idle timeout should be imposed.",
      "hidden": false,
      "label": "Default Job Idle Timeout",
      "min_value": 0,
      "name": "DEFAULT_JOB_IDLE_TIMEOUT",
      "required": false,
      "sensitive": false,
      "type": "integer",
      "unit": "seconds"
    },
    "DEFAULT_JOB_TIMEOUT": {
      "category": "Jobs",
      "category_slug": "jobs",
      "computed": true,
      "default": 0,
      "default_value": "int64default.StaticInt64(0)",
      "help_text": "Maximum time in seconds to allow jobs to run. Use value of 0 to indicate that no timeout should be imposed. A timeout set on an individual job template will override this.",
      "hidden": false,
      "label": "Default Job Timeout",
      "min_value": 0,
      "name": "DEFAULT_JOB_TIMEOUT",
      "required": false,
      "sensitive": false,
      "type": "integer",
      "unit": "seconds"
    },
    "DEFAULT_PROJECT_UPDATE_TIMEOUT": {
      "category": "Jobs",
      "category_slug": "jobs",
      "computed": true,
      "default": 0,
      "default_value": "int64default.StaticInt64(0)",
      "help_text": "Maximum time in seconds to allow project updates to run. Use value of 0 to indicate that no timeout should be imposed. A timeout set on an individual project will override this.",
      "hidden": false,
      "label": "Default Project Update Timeout",
      "min_value": 0,
      "name": "DEFAULT_PROJECT_UPDATE_TIMEOUT",
      "required": false,
      "sensitive": false,
      "type": "integer",
      "unit": "seconds"
    },
    "EVENT_STDOUT_MAX_BYTES_DISPLAY": {
      "category": "Jobs",
      "category_slug": "jobs",
      "computed": true,
      "default": 1024,
      "default_value": "int64default.StaticInt64(1024)",
      "help_text": "Maximum Size of Standard Output in bytes to display for a single job or ad hoc command event. `stdout` will end with `â€¦` when truncated.",
      "hidden": false,
      "label": "Job Event Standard Output Maximum Display Size",
      "min_value": 0,
      "name": "EVENT_STDOUT_MAX_BYTES_DISPLAY",
      "required": false,
      "sensitive": false,
      "type": "integer"
    },
    "GALAXY_IGNORE_CERTS": {
      "category": "Jobs",
      "category_slug": "jobs",
      "computed": true,
      "default": false,
      "help_text": "If set to true, certificate validation will not be done when installing content from any Galaxy server.",
      "hidden": false,
      "label": "Ignore Ansible Galaxy SSL Certificate Verification",
      "name": "GALAXY_IGNORE_CERTS",
      "required": false,
      "sensitive": false,
      "type": "boolean"
    },
    "GALAXY_TASK_ENV": {
      "category": "Jobs",
      "category_slug": "jobs",
      "child": {
        "hidden": false,
        "read_only": false,
        "required": true,
        "type": "string"
      },
      "computed": true,
      "default": {
        "ANSIBLE_FORCE_COLOR": "false",
        "GIT_SSH_COMMAND": "ssh -o StrictHostKeyChecking=no"
      },
      "default_value": "stringdefault.StaticString(`{\"ANSIBLE_FORCE_COLOR\":\"false\",\"GIT_SSH_COMMAND\":\"ssh -o StrictHostKeyChecking=no\"}`)",
      "element_type": "string",
      "help_text": "Additional environment variables set for invocations of ansible-galaxy within project updates. Useful if you must use a proxy server for ansible-galaxy but not git.",
      "hidden": false,
      "label": "Environment Variables for Galaxy Commands",
      "name": "GALAXY_TASK_ENV",
      "placeholder": {
        "HTTP_PROXY": "myproxy.local:8080"
      },
      "post_wrap": false,
      "required": false,
      "sensitive": false,
      "trim": false,
      "type": "json"
    },
    "MAX_FORKS": {
      "category": "Jobs",
      "category_slug": "jobs",
      "computed": true,
      "default": 200,
      "default_value": "int64default.StaticInt64(200)",
      "help_text": "Saving a Job Template with more than this number of forks will result in an error. When set to 0, no limit is applied.",
      "hidden": false,
      "label": "Maximum number of forks per job",
      "name": "MAX_FORKS",
      "required": false,
      "sensitive": false,
      "type": "integer"
    },
    "MAX_WEBSOCKET_EVENT_RATE": {
      "category": "Jobs",
      "category_slug": "jobs",
      "computed": true,
      "default": 30,
      "default_value": "int64default.StaticInt64(30)",
      "help_text": "Maximum number of messages to update the UI live job output with per second. Value of 0 means no limit.",
      "hidden": false,
      "label": "Job Event Maximum Websocket Messages Per Second",
      "min_value": 0,
      "name": "MAX_WEBSOCKET_EVENT_RATE",
      "required": false,
      "sensitive": false,
      "type": "integer"
    },
    "PROJECT_UPDATE_VVV": {
      "category": "Jobs",
      "category_slug": "jobs",
      "computed": true,
      "default": false,
      "help_text": "Adds the CLI -vvv flag to ansible-playbook runs of project_update.yml used for project updates.",
      "hidden": false,
      "label": "Run Project Updates With Higher Verbosity",
      "name": "PROJECT_UPDATE_VVV",
      "required": false,
      "sensitive": false,
      "type": "boolean"
    },
    "SCHEDULE_MAX_JOBS": {
      "category": "Jobs",
      "category_slug": "jobs",
      "computed": true,
      "default": 10,
      "default_value": "int64default.StaticInt64(10)",
      "help_text": "Maximum number of the same job template that can be waiting to run when launching from a schedule before no more are created.",
      "hidden": false,
      "label": "Maximum Scheduled Jobs",
      "min_value": 1,
      "name": "SCHEDULE_MAX_JOBS",
      "required": false,
      "sensitive": false,
      "type": "integer"
    },
    "STDOUT_MAX_BYTES_DISPLAY": {
      "category": "Jobs",
      "category_slug": "jobs",
      "computed": true,
      "default": 1048576,
      "default_value": "int64default.StaticInt64(1.048576e+06)",
      "help_text": "Maximum Size of Standard Output in bytes to display before requiring the output be downloaded.",
      "hidden": false,
      "label": "Standard Output Maximum Display Size",
      "min_value": 0,
      "name": "STDOUT_MAX_BYTES_DISPLAY",
      "required": false,
      "sensitive": false,
      "type": "integer"
    }
  },
  "PropertyPostKeys": [
    "AD_HOC_COMMANDS",
    "ALLOW_JINJA_IN_EXTRA_VARS",
    "ANSIBLE_FACT_CACHE_TIMEOUT",
    "AWX_ANSIBLE_CALLBACK_PLUGINS",
    "AWX_COLLECTIONS_ENABLED",
    "AWX_ISOLATION_BASE_PATH",
    "AWX_ISOLATION_SHOW_PATHS",
    "AWX_MOUNT_ISOLATED_PATHS_ON_K8S",
    "AWX_ROLES_ENABLED",
    "AWX_RUNNER_KEEPALIVE_SECONDS",
    "AWX_SHOW_PLAYBOOK_LINKS",
    "AWX_TASK_ENV",
    "DEFAULT_CONTAINER_RUN_OPTIONS",
    "DEFAULT_INVENTORY_UPDATE_TIMEOUT",
    "DEFAULT_JOB_IDLE_TIMEOUT",
    "DEFAULT_JOB_TIMEOUT",
    "DEFAULT_PROJECT_UPDATE_TIMEOUT",
    "EVENT_STDOUT_MAX_BYTES_DISPLAY",
    "GALAXY_IGNORE_CERTS",
    "GALAXY_TASK_ENV",
    "MAX_FORKS",
    "MAX_WEBSOCKET_EVENT_RATE",
    "PROJECT_UPDATE_VVV",
    "SCHEDULE_MAX_JOBS",
    "STDOUT_MAX_BYTES_DISPLAY"
  ],
  "PropertyWriteOnlyData": {},
  "PropertyWriteOnlyKeys": null
}