{
  "ApiVersion": "24.1.0",
  "Config": {
    "endpoint": "/api/v2/inventory_sources/",
    "name": "InventorySource",
    "type_name": "inventory_source",
    "id_key": "id",
    "property_overrides": {
      "source_vars": {
        "type": "json",
        "description": "",
        "trim": false,
        "post_wrap": true,
        "default_value": "",
        "element_type": ""
      }
    },
    "search_fields": [
      {
        "url_suffix": "%d/",
        "name": "by_id",
        "fields": [
          {
            "name": "id",
            "url_escape_value": false
          }
        ]
      },
      {
        "url_suffix": "?name__exact=%s",
        "name": "by_name",
        "fields": [
          {
            "name": "name",
            "url_escape_value": true
          }
        ],
        "multiple_results": true
      }
    ],
    "enabled": true,
    "has_object_roles": false,
    "has_survey_spec": false,
    "associate_disassociate_groups": null,
    "field_constraints": null,
    "skip_write_only": false,
    "undeletable": false,
    "pre_state_set_hook_function": "hooks.RequireResourceStateOrOrig",
    "no_id": false,
    "no_terraform_data_source": false,
    "no_terraform_resource": false,
    "api_property_resource_key": "POST",
    "api_property_data_key": "GET",
    "property_name_leave_as_is": false,
    "api_data_override": null,
    "remove_fields_data_source": [
      "custom_virtualenv",
      "status"
    ],
    "remove_fields_resource": [
      "custom_virtualenv",
      "status"
    ],
    "credential_types": null
  },
  "Description": "# List Inventory Sources:\n\nMake a GET request to this resource to retrieve the list of\ninventory sources.\n\nThe resulting data structure contains:\n\n    {\n        \"count\": 99,\n        \"next\": null,\n        \"previous\": null,\n        \"results\": [\n            ...\n        ]\n    }\n\nThe `count` field indicates the total number of inventory sources\nfound for the given query.  The `next` and `previous` fields provides links to\nadditional results if there are more than will fit on a single page.  The\n`results` list contains zero or more inventory source records.  \n\n## Results\n\nEach inventory source data structure includes the following fields:\n\n* `id`: Database ID for this inventory source. (integer)\n* `type`: Data type for this inventory source. (choice)\n* `url`: URL for this inventory source. (string)\n* `related`: Data structure with URLs of related resources. (object)\n* `summary_fields`: Data structure with name/description for related resources.  The output for some objects may be limited for performance reasons. (object)\n* `created`: Timestamp when this inventory source was created. (datetime)\n* `modified`: Timestamp when this inventory source was last modified. (datetime)\n* `name`: Name of this inventory source. (string)\n* `description`: Optional description of this inventory source. (string)\n* `source`:  (choice)\n    - `file`: File, Directory or Script\n    - `constructed`: Template additional groups and hostvars at runtime\n    - `scm`: Sourced from a Project\n    - `ec2`: Amazon EC2\n    - `gce`: Google Compute Engine\n    - `azure_rm`: Microsoft Azure Resource Manager\n    - `vmware`: VMware vCenter\n    - `satellite6`: Red Hat Satellite 6\n    - `openstack`: OpenStack\n    - `rhv`: Red Hat Virtualization\n    - `controller`: Red Hat Ansible Automation Platform\n    - `insights`: Red Hat Insights\n    - `terraform`: Terraform State\n* `source_path`:  (string)\n* `source_vars`: Inventory source variables in YAML or JSON format. (string)\n* `scm_branch`: Inventory source SCM branch. Project default used if blank. Only allowed if project allow_override field is set to true. (string)\n* `credential`: Cloud credential to use for inventory updates. (integer)\n* `enabled_var`: Retrieve the enabled state from the given dict of host variables. The enabled variable may be specified as \u0026quot;foo.bar\u0026quot;, in which case the lookup will traverse into nested dicts, equivalent to: from_dict.get(\u0026quot;foo\u0026quot;, {}).get(\u0026quot;bar\u0026quot;, default) (string)\n* `enabled_value`: Only used when enabled_var is set. Value when the host is considered enabled. For example if enabled_var=\u0026quot;status.power_state\u0026quot;and enabled_value=\u0026quot;powered_on\u0026quot; with host variables:{   \u0026quot;status\u0026quot;: {     \u0026quot;power_state\u0026quot;: \u0026quot;powered_on\u0026quot;,     \u0026quot;created\u0026quot;: \u0026quot;2020-08-04T18:13:04+00:00\u0026quot;,     \u0026quot;healthy\u0026quot;: true    },    \u0026quot;name\u0026quot;: \u0026quot;foobar\u0026quot;,    \u0026quot;ip_address\u0026quot;: \u0026quot;192.168.2.1\u0026quot;}The host would be marked enabled. If power_state where any value other than powered_on then the host would be disabled when imported. If the key is not found then the host will be enabled (string)\n* `host_filter`: This field is deprecated and will be removed in a future release. Regex where only matching hosts will be imported. (string)\n* `overwrite`: Overwrite local groups and hosts from remote inventory source. (boolean)\n* `overwrite_vars`: Overwrite local variables from remote inventory source. (boolean)\n* `custom_virtualenv`: Local absolute file path containing a custom Python virtualenv to use (string)\n* `timeout`: The amount of time (in seconds) to run before the task is canceled. (integer)\n* `verbosity`:  (choice)\n    - `0`: 0 (WARNING)\n    - `1`: 1 (INFO)\n    - `2`: 2 (DEBUG)\n* `limit`: Enter host, group or pattern match (string)\n* `last_job_run`:  (datetime)\n* `last_job_failed`:  (boolean)\n* `next_job_run`:  (datetime)\n* `status`:  (choice)\n    - `new`: New\n    - `pending`: Pending\n    - `waiting`: Waiting\n    - `running`: Running\n    - `successful`: Successful\n    - `failed`: Failed\n    - `error`: Error\n    - `canceled`: Canceled\n    - `never updated`: Never Updated\n    - `none`: No External Source\n* `execution_environment`: The container image to be used for execution. (id)\n* `inventory`:  (id)\n* `update_on_launch`:  (boolean)\n* `update_cache_timeout`:  (integer)\n* `source_project`: Project containing inventory file used as source. (id)\n* `last_update_failed`:  (boolean)\n* `last_updated`:  (datetime)\n\n\n\n## Sorting\n\nTo specify that inventory sources are returned in a particular\norder, use the `order_by` query string parameter on the GET request.\n\n    ?order_by=name\n\nPrefix the field name with a dash `-` to sort in reverse:\n\n    ?order_by=-name\n\nMultiple sorting fields may be specified by separating the field names with a\ncomma `,`:\n\n    ?order_by=name,some_other_field\n\n## Pagination\n\nUse the `page_size` query string parameter to change the number of results\nreturned for each request.  Use the `page` query string parameter to retrieve\na particular page of results.\n\n    ?page_size=100\u0026page=2\n\nThe `previous` and `next` links returned with the results will set these query\nstring parameters automatically.\n\n## Searching\n\nUse the `search` query string parameter to perform a case-insensitive search\nwithin all designated text fields of a model.\n\n    ?search=findme\n\n(_Added in Ansible Tower 3.1.0_) Search across related fields:\n\n    ?related__search=findme\n\nNote: If you want to provide more than one search term, multiple\nsearch fields with the same key, like `?related__search=foo\u0026related__search=bar`,\nwill be ORed together. Terms separated by commas, like `?related__search=foo,bar`\nwill be ANDed together.\n\n## Filtering\n\nAny additional query string parameters may be used to filter the list of\nresults returned to those matching a given value.  Only fields and relations\nthat exist in the database may be used for filtering.  Any special characters\nin the specified value should be url-encoded. For example:\n\n    ?field=value%20xyz\n\nFields may also span relations, only for fields and relationships defined in\nthe database:\n\n    ?other__field=value\n\nTo exclude results matching certain criteria, prefix the field parameter with\n`not__`:\n\n    ?not__field=value\n\nBy default, all query string filters are AND'ed together, so\nonly the results matching *all* filters will be returned.  To combine results\nmatching *any* one of multiple criteria, prefix each query string parameter\nwith `or__`:\n\n    ?or__field=value\u0026or__field=othervalue\n    ?or__not__field=value\u0026or__field=othervalue\n\n(_Added in Ansible Tower 1.4.5_) The default AND filtering applies all filters\nsimultaneously to each related object being filtered across database\nrelationships.  The chain filter instead applies filters separately for each\nrelated object. To use, prefix the query string parameter with `chain__`:\n\n    ?chain__related__field=value\u0026chain__related__field2=othervalue\n    ?chain__not__related__field=value\u0026chain__related__field2=othervalue\n\nIf the first query above were written as\n`?related__field=value\u0026related__field2=othervalue`, it would return only the\nprimary objects where the *same* related object satisfied both conditions.  As\nwritten using the chain filter, it would return the intersection of primary\nobjects matching each condition.\n\nField lookups may also be used for more advanced queries, by appending the\nlookup to the field name:\n\n    ?field__lookup=value\n\nThe following field lookups are supported:\n\n* `exact`: Exact match (default lookup if not specified).\n* `iexact`: Case-insensitive version of `exact`.\n* `contains`: Field contains value.\n* `icontains`: Case-insensitive version of `contains`.\n* `startswith`: Field starts with value.\n* `istartswith`: Case-insensitive version of `startswith`.\n* `endswith`: Field ends with value.\n* `iendswith`: Case-insensitive version of `endswith`.\n* `regex`: Field matches the given regular expression.\n* `iregex`: Case-insensitive version of `regex`.\n* `gt`: Greater than comparison.\n* `gte`: Greater than or equal to comparison.\n* `lt`: Less than comparison.\n* `lte`: Less than or equal to comparison.\n* `isnull`: Check whether the given field or related object is null; expects a\n  boolean value.\n* `in`: Check whether the given field's value is present in the list provided;\n  expects a list of items.\n\nBoolean values may be specified as `True` or `1` for true, `False` or `0` for\nfalse (both case-insensitive).\n\nNull values may be specified as `None` or `Null` (both case-insensitive),\nthough it is preferred to use the `isnull` lookup to explicitly check for null\nvalues.\n\nLists (for the `in` lookup) may be specified as a comma-separated list of\nvalues.\n\n(_Added in Ansible Tower 3.1.0_) Filtering based on the requesting user's\nlevel of access by query string parameter.\n\n* `role_level`: Level of role to filter on, such as `admin_role`\n\n\n\n\n# Create an Inventory Source:\n\nMake a POST request to this resource with the following inventory source\nfields to create a new inventory source:\n\n\n\n\n\n\n\n\n\n* `name`: Name of this inventory source. (string, required)\n* `description`: Optional description of this inventory source. (string, default=`\"\"`)\n* `source`:  (choice)\n    - `file`: File, Directory or Script\n    - `constructed`: Template additional groups and hostvars at runtime\n    - `scm`: Sourced from a Project\n    - `ec2`: Amazon EC2\n    - `gce`: Google Compute Engine\n    - `azure_rm`: Microsoft Azure Resource Manager\n    - `vmware`: VMware vCenter\n    - `satellite6`: Red Hat Satellite 6\n    - `openstack`: OpenStack\n    - `rhv`: Red Hat Virtualization\n    - `controller`: Red Hat Ansible Automation Platform\n    - `insights`: Red Hat Insights\n    - `terraform`: Terraform State\n* `source_path`:  (string, default=`\"\"`)\n* `source_vars`: Inventory source variables in YAML or JSON format. (string, default=`\"\"`)\n* `scm_branch`: Inventory source SCM branch. Project default used if blank. Only allowed if project allow_override field is set to true. (string, default=`\"\"`)\n* `credential`: Cloud credential to use for inventory updates. (integer, default=`None`)\n* `enabled_var`: Retrieve the enabled state from the given dict of host variables. The enabled variable may be specified as \u0026quot;foo.bar\u0026quot;, in which case the lookup will traverse into nested dicts, equivalent to: from_dict.get(\u0026quot;foo\u0026quot;, {}).get(\u0026quot;bar\u0026quot;, default) (string, default=`\"\"`)\n* `enabled_value`: Only used when enabled_var is set. Value when the host is considered enabled. For example if enabled_var=\u0026quot;status.power_state\u0026quot;and enabled_value=\u0026quot;powered_on\u0026quot; with host variables:{   \u0026quot;status\u0026quot;: {     \u0026quot;power_state\u0026quot;: \u0026quot;powered_on\u0026quot;,     \u0026quot;created\u0026quot;: \u0026quot;2020-08-04T18:13:04+00:00\u0026quot;,     \u0026quot;healthy\u0026quot;: true    },    \u0026quot;name\u0026quot;: \u0026quot;foobar\u0026quot;,    \u0026quot;ip_address\u0026quot;: \u0026quot;192.168.2.1\u0026quot;}The host would be marked enabled. If power_state where any value other than powered_on then the host would be disabled when imported. If the key is not found then the host will be enabled (string, default=`\"\"`)\n* `host_filter`: This field is deprecated and will be removed in a future release. Regex where only matching hosts will be imported. (string, default=`\"\"`)\n* `overwrite`: Overwrite local groups and hosts from remote inventory source. (boolean, default=`False`)\n* `overwrite_vars`: Overwrite local variables from remote inventory source. (boolean, default=`False`)\n\n* `timeout`: The amount of time (in seconds) to run before the task is canceled. (integer, default=`0`)\n* `verbosity`:  (choice)\n    - `0`: 0 (WARNING)\n    - `1`: 1 (INFO) (default)\n    - `2`: 2 (DEBUG)\n* `limit`: Enter host, group or pattern match (string, default=`\"\"`)\n\n\n\n\n* `execution_environment`: The container image to be used for execution. (id, default=``)\n* `inventory`:  (id, required)\n* `update_on_launch`:  (boolean, default=`False`)\n* `update_cache_timeout`:  (integer, default=`0`)\n* `source_project`: Project containing inventory file used as source. (id, default=``)",
  "Endpoint": "/api/v2/inventory_sources/",
  "Name": "InventorySource",
  "PackageName": "awx",
  "PropertyGetData": {
    "credential": {
      "computed": true,
      "filterable": false,
      "help_text": "Cloud credential to use for inventory updates.",
      "hidden": false,
      "label": "Credential",
      "min_value": 1,
      "name": "credential",
      "required": false,
      "sensitive": false,
      "type": "integer"
    },
    "description": {
      "computed": true,
      "filterable": true,
      "help_text": "Optional description of this inventory source.",
      "hidden": false,
      "label": "Description",
      "name": "description",
      "required": false,
      "sensitive": false,
      "type": "string"
    },
    "enabled_value": {
      "computed": true,
      "filterable": true,
      "help_text": "Only used when enabled_var is set. Value when the host is considered enabled. For example if enabled_var=\"status.power_state\"and enabled_value=\"powered_on\" with host variables:{   \"status\": {     \"power_state\": \"powered_on\",     \"created\": \"2020-08-04T18:13:04+00:00\",     \"healthy\": true    },    \"name\": \"foobar\",    \"ip_address\": \"192.168.2.1\"}The host would be marked enabled. If power_state where any value other than powered_on then the host would be disabled when imported. If the key is not found then the host will be enabled",
      "hidden": false,
      "label": "Enabled value",
      "name": "enabled_value",
      "required": false,
      "sensitive": false,
      "type": "string"
    },
    "enabled_var": {
      "computed": true,
      "filterable": true,
      "help_text": "Retrieve the enabled state from the given dict of host variables. The enabled variable may be specified as \"foo.bar\", in which case the lookup will traverse into nested dicts, equivalent to: from_dict.get(\"foo\", {}).get(\"bar\", default)",
      "hidden": false,
      "label": "Enabled var",
      "name": "enabled_var",
      "required": false,
      "sensitive": false,
      "type": "string"
    },
    "execution_environment": {
      "computed": true,
      "filterable": true,
      "help_text": "The container image to be used for execution.",
      "hidden": false,
      "label": "Execution environment",
      "name": "execution_environment",
      "required": false,
      "sensitive": false,
      "type": "id"
    },
    "host_filter": {
      "computed": true,
      "filterable": true,
      "help_text": "This field is deprecated and will be removed in a future release. Regex where only matching hosts will be imported.",
      "hidden": false,
      "label": "Host filter",
      "name": "host_filter",
      "required": false,
      "sensitive": false,
      "type": "string"
    },
    "id": {
      "computed": true,
      "filterable": true,
      "help_text": "Database ID for this inventory source.",
      "hidden": false,
      "label": "ID",
      "name": "id",
      "required": false,
      "sensitive": false,
      "type": "integer"
    },
    "inventory": {
      "computed": true,
      "filterable": true,
      "hidden": false,
      "label": "Inventory",
      "name": "inventory",
      "required": false,
      "sensitive": false,
      "type": "id"
    },
    "limit": {
      "computed": true,
      "filterable": true,
      "help_text": "Enter host, group or pattern match",
      "hidden": false,
      "label": "Limit",
      "name": "limit",
      "required": false,
      "sensitive": false,
      "type": "string"
    },
    "name": {
      "computed": true,
      "filterable": true,
      "help_text": "Name of this inventory source.",
      "hidden": false,
      "label": "Name",
      "name": "name",
      "required": false,
      "sensitive": false,
      "type": "string"
    },
    "overwrite": {
      "computed": true,
      "filterable": true,
      "help_text": "Overwrite local groups and hosts from remote inventory source.",
      "hidden": false,
      "label": "Overwrite",
      "name": "overwrite",
      "required": false,
      "sensitive": false,
      "type": "boolean"
    },
    "overwrite_vars": {
      "computed": true,
      "filterable": true,
      "help_text": "Overwrite local variables from remote inventory source.",
      "hidden": false,
      "label": "Overwrite vars",
      "name": "overwrite_vars",
      "required": false,
      "sensitive": false,
      "type": "boolean"
    },
    "scm_branch": {
      "computed": true,
      "filterable": true,
      "help_text": "Inventory source SCM branch. Project default used if blank. Only allowed if project allow_override field is set to true.",
      "hidden": false,
      "label": "Scm branch",
      "name": "scm_branch",
      "required": false,
      "sensitive": false,
      "type": "string"
    },
    "source": {
      "choices": [
        [
          "file",
          "File, Directory or Script"
        ],
        [
          "constructed",
          "Template additional groups and hostvars at runtime"
        ],
        [
          "scm",
          "Sourced from a Project"
        ],
        [
          "ec2",
          "Amazon EC2"
        ],
        [
          "gce",
          "Google Compute Engine"
        ],
        [
          "azure_rm",
          "Microsoft Azure Resource Manager"
        ],
        [
          "vmware",
          "VMware vCenter"
        ],
        [
          "satellite6",
          "Red Hat Satellite 6"
        ],
        [
          "openstack",
          "OpenStack"
        ],
        [
          "rhv",
          "Red Hat Virtualization"
        ],
        [
          "controller",
          "Red Hat Ansible Automation Platform"
        ],
        [
          "insights",
          "Red Hat Insights"
        ],
        [
          "terraform",
          "Terraform State"
        ]
      ],
      "computed": true,
      "filterable": true,
      "hidden": false,
      "label": "Source",
      "name": "source",
      "required": false,
      "sensitive": false,
      "type": "choice"
    },
    "source_path": {
      "computed": true,
      "filterable": true,
      "hidden": false,
      "label": "Source path",
      "name": "source_path",
      "required": false,
      "sensitive": false,
      "type": "string"
    },
    "source_project": {
      "computed": true,
      "filterable": true,
      "help_text": "Project containing inventory file used as source.",
      "hidden": false,
      "label": "Source project",
      "name": "source_project",
      "required": false,
      "sensitive": false,
      "type": "id"
    },
    "source_vars": {
      "computed": true,
      "filterable": true,
      "help_text": "Inventory source variables in YAML or JSON format.",
      "hidden": false,
      "label": "Source vars",
      "name": "source_vars",
      "required": false,
      "sensitive": false,
      "type": "json"
    },
    "timeout": {
      "computed": true,
      "filterable": true,
      "help_text": "The amount of time (in seconds) to run before the task is canceled.",
      "hidden": false,
      "label": "Timeout",
      "max_value": 2147483647,
      "min_value": -2147483648,
      "name": "timeout",
      "required": false,
      "sensitive": false,
      "type": "integer"
    },
    "update_cache_timeout": {
      "computed": true,
      "filterable": true,
      "hidden": false,
      "label": "Update cache timeout",
      "max_value": 2147483647,
      "min_value": 0,
      "name": "update_cache_timeout",
      "required": false,
      "sensitive": false,
      "type": "integer"
    },
    "update_on_launch": {
      "computed": true,
      "filterable": true,
      "hidden": false,
      "label": "Update on launch",
      "name": "update_on_launch",
      "required": false,
      "sensitive": false,
      "type": "boolean"
    },
    "verbosity": {
      "choices": [
        [
          0,
          "0 (WARNING)"
        ],
        [
          1,
          "1 (INFO)"
        ],
        [
          2,
          "2 (DEBUG)"
        ]
      ],
      "computed": true,
      "filterable": true,
      "hidden": false,
      "label": "Verbosity",
      "name": "verbosity",
      "required": false,
      "sensitive": false,
      "type": "choice"
    }
  },
  "PropertyGetKeys": [
    "credential",
    "description",
    "enabled_value",
    "enabled_var",
    "execution_environment",
    "host_filter",
    "id",
    "inventory",
    "limit",
    "name",
    "overwrite",
    "overwrite_vars",
    "scm_branch",
    "source",
    "source_path",
    "source_project",
    "source_vars",
    "timeout",
    "update_cache_timeout",
    "update_on_launch",
    "verbosity"
  ],
  "PropertyPostData": {
    "credential": {
      "computed": true,
      "default": null,
      "filterable": false,
      "help_text": "Cloud credential to use for inventory updates.",
      "hidden": false,
      "label": "Credential",
      "min_value": 1,
      "name": "credential",
      "required": false,
      "sensitive": false,
      "type": "integer"
    },
    "description": {
      "computed": true,
      "default": "",
      "default_value": "stringdefault.StaticString(``)",
      "filterable": true,
      "help_text": "Optional description of this inventory source.",
      "hidden": false,
      "label": "Description",
      "name": "description",
      "required": false,
      "sensitive": false,
      "type": "string"
    },
    "enabled_value": {
      "computed": true,
      "default": "",
      "default_value": "stringdefault.StaticString(``)",
      "filterable": true,
      "help_text": "Only used when enabled_var is set. Value when the host is considered enabled. For example if enabled_var=\"status.power_state\"and enabled_value=\"powered_on\" with host variables:{   \"status\": {     \"power_state\": \"powered_on\",     \"created\": \"2020-08-04T18:13:04+00:00\",     \"healthy\": true    },    \"name\": \"foobar\",    \"ip_address\": \"192.168.2.1\"}The host would be marked enabled. If power_state where any value other than powered_on then the host would be disabled when imported. If the key is not found then the host will be enabled",
      "hidden": false,
      "label": "Enabled value",
      "name": "enabled_value",
      "required": false,
      "sensitive": false,
      "type": "string"
    },
    "enabled_var": {
      "computed": true,
      "default": "",
      "default_value": "stringdefault.StaticString(``)",
      "filterable": true,
      "help_text": "Retrieve the enabled state from the given dict of host variables. The enabled variable may be specified as \"foo.bar\", in which case the lookup will traverse into nested dicts, equivalent to: from_dict.get(\"foo\", {}).get(\"bar\", default)",
      "hidden": false,
      "label": "Enabled var",
      "name": "enabled_var",
      "required": false,
      "sensitive": false,
      "type": "string"
    },
    "execution_environment": {
      "computed": true,
      "filterable": true,
      "help_text": "The container image to be used for execution.",
      "hidden": false,
      "label": "Execution environment",
      "name": "execution_environment",
      "required": false,
      "sensitive": false,
      "type": "id"
    },
    "host_filter": {
      "computed": true,
      "default": "",
      "default_value": "stringdefault.StaticString(``)",
      "filterable": true,
      "help_text": "This field is deprecated and will be removed in a future release. Regex where only matching hosts will be imported.",
      "hidden": false,
      "label": "Host filter",
      "name": "host_filter",
      "required": false,
      "sensitive": false,
      "type": "string"
    },
    "inventory": {
      "computed": false,
      "filterable": true,
      "hidden": false,
      "label": "Inventory",
      "name": "inventory",
      "required": true,
      "sensitive": false,
      "type": "id"
    },
    "limit": {
      "computed": true,
      "default": "",
      "default_value": "stringdefault.StaticString(``)",
      "filterable": true,
      "help_text": "Enter host, group or pattern match",
      "hidden": false,
      "label": "Limit",
      "name": "limit",
      "required": false,
      "sensitive": false,
      "type": "string"
    },
    "name": {
      "computed": false,
      "filterable": true,
      "help_text": "Name of this inventory source.",
      "hidden": false,
      "label": "Name",
      "max_length": 512,
      "name": "name",
      "required": true,
      "sensitive": false,
      "type": "string"
    },
    "overwrite": {
      "computed": true,
      "default": false,
      "filterable": true,
      "help_text": "Overwrite local groups and hosts from remote inventory source.",
      "hidden": false,
      "label": "Overwrite",
      "name": "overwrite",
      "required": false,
      "sensitive": false,
      "type": "boolean"
    },
    "overwrite_vars": {
      "computed": true,
      "default": false,
      "filterable": true,
      "help_text": "Overwrite local variables from remote inventory source.",
      "hidden": false,
      "label": "Overwrite vars",
      "name": "overwrite_vars",
      "required": false,
      "sensitive": false,
      "type": "boolean"
    },
    "scm_branch": {
      "computed": true,
      "default": "",
      "default_value": "stringdefault.StaticString(``)",
      "filterable": true,
      "help_text": "Inventory source SCM branch. Project default used if blank. Only allowed if project allow_override field is set to true.",
      "hidden": false,
      "label": "Scm branch",
      "max_length": 1024,
      "name": "scm_branch",
      "required": false,
      "sensitive": false,
      "type": "string"
    },
    "source": {
      "choices": [
        [
          "file",
          "File, Directory or Script"
        ],
        [
          "constructed",
          "Template additional groups and hostvars at runtime"
        ],
        [
          "scm",
          "Sourced from a Project"
        ],
        [
          "ec2",
          "Amazon EC2"
        ],
        [
          "gce",
          "Google Compute Engine"
        ],
        [
          "azure_rm",
          "Microsoft Azure Resource Manager"
        ],
        [
          "vmware",
          "VMware vCenter"
        ],
        [
          "satellite6",
          "Red Hat Satellite 6"
        ],
        [
          "openstack",
          "OpenStack"
        ],
        [
          "rhv",
          "Red Hat Virtualization"
        ],
        [
          "controller",
          "Red Hat Ansible Automation Platform"
        ],
        [
          "insights",
          "Red Hat Insights"
        ],
        [
          "terraform",
          "Terraform State"
        ]
      ],
      "computed": true,
      "default": null,
      "filterable": true,
      "hidden": false,
      "label": "Source",
      "name": "source",
      "required": false,
      "sensitive": false,
      "type": "choice"
    },
    "source_path": {
      "computed": true,
      "default": "",
      "default_value": "stringdefault.StaticString(``)",
      "filterable": true,
      "hidden": false,
      "label": "Source path",
      "max_length": 1024,
      "name": "source_path",
      "required": false,
      "sensitive": false,
      "type": "string"
    },
    "source_project": {
      "computed": true,
      "filterable": true,
      "help_text": "Project containing inventory file used as source.",
      "hidden": false,
      "label": "Source project",
      "name": "source_project",
      "required": false,
      "sensitive": false,
      "type": "id"
    },
    "source_vars": {
      "computed": true,
      "default": "",
      "default_value": "stringdefault.StaticString(``)",
      "filterable": true,
      "help_text": "Inventory source variables in YAML or JSON format.",
      "hidden": false,
      "label": "Source vars",
      "name": "source_vars",
      "required": false,
      "sensitive": false,
      "type": "json"
    },
    "timeout": {
      "computed": true,
      "default": 0,
      "default_value": "int64default.StaticInt64(0)",
      "filterable": true,
      "help_text": "The amount of time (in seconds) to run before the task is canceled.",
      "hidden": false,
      "label": "Timeout",
      "max_value": 2147483647,
      "min_value": -2147483648,
      "name": "timeout",
      "required": false,
      "sensitive": false,
      "type": "integer"
    },
    "update_cache_timeout": {
      "computed": true,
      "default": 0,
      "default_value": "int64default.StaticInt64(0)",
      "filterable": true,
      "hidden": false,
      "label": "Update cache timeout",
      "max_value": 2147483647,
      "min_value": 0,
      "name": "update_cache_timeout",
      "required": false,
      "sensitive": false,
      "type": "integer"
    },
    "update_on_launch": {
      "computed": true,
      "default": false,
      "filterable": true,
      "hidden": false,
      "label": "Update on launch",
      "name": "update_on_launch",
      "required": false,
      "sensitive": false,
      "type": "boolean"
    },
    "verbosity": {
      "choices": [
        [
          0,
          "0 (WARNING)"
        ],
        [
          1,
          "1 (INFO)"
        ],
        [
          2,
          "2 (DEBUG)"
        ]
      ],
      "computed": true,
      "default": 1,
      "default_value": "stringdefault.StaticString(`1`)",
      "filterable": true,
      "hidden": false,
      "label": "Verbosity",
      "name": "verbosity",
      "required": false,
      "sensitive": false,
      "type": "choice"
    }
  },
  "PropertyPostKeys": [
    "credential",
    "description",
    "enabled_value",
    "enabled_var",
    "execution_environment",
    "host_filter",
    "inventory",
    "limit",
    "name",
    "overwrite",
    "overwrite_vars",
    "scm_branch",
    "source",
    "source_path",
    "source_project",
    "source_vars",
    "timeout",
    "update_cache_timeout",
    "update_on_launch",
    "verbosity"
  ],
  "PropertyWriteOnlyData": {},
  "PropertyWriteOnlyKeys": null
}