{
  "ApiVersion": "23.8.1",
  "Config": {
    "endpoint": "/api/v2/settings/oidc/",
    "name": "SettingsOpenIDConnect",
    "type_name": "settings_oidc",
    "id_key": "id",
    "enabled": true,
    "has_object_roles": false,
    "has_survey_spec": false,
    "associate_disassociate_groups": null,
    "field_constraints": null,
    "skip_write_only": false,
    "undeletable": true,
    "pre_state_set_hook_function": "",
    "no_id": true,
    "no_terraform_data_source": false,
    "no_terraform_resource": false,
    "api_property_resource_key": "PUT",
    "api_property_data_key": "GET",
    "property_name_leave_as_is": true,
    "api_data_override": null,
    "remove_fields_data_source": null,
    "remove_fields_resource": null,
    "credential_types": null
  },
  "Description": "# Retrieve a Setting:\n\nMake GET request to this resource to retrieve a single setting\nrecord containing the following fields:\n\n* `SOCIAL_AUTH_OIDC_KEY`: The OIDC key (Client ID) from your IDP. (string)\n* `SOCIAL_AUTH_OIDC_SECRET`: The OIDC secret (Client Secret) from your IDP. (string)\n* `SOCIAL_AUTH_OIDC_OIDC_ENDPOINT`: The URL for your OIDC provider including the path up to /.well-known/openid-configuration (string)\n* `SOCIAL_AUTH_OIDC_VERIFY_SSL`: Verify the OIDC provider ssl certificate. (boolean)\n\n\n\n\n\n# Update a Setting:\n\nMake a PUT or PATCH request to this resource to update this\nsetting.  The following fields may be modified:\n\n\n* `SOCIAL_AUTH_OIDC_KEY`: The OIDC key (Client ID) from your IDP. (string, default=`\"\"`)\n* `SOCIAL_AUTH_OIDC_SECRET`: The OIDC secret (Client Secret) from your IDP. (string, default=`\"\"`)\n* `SOCIAL_AUTH_OIDC_OIDC_ENDPOINT`: The URL for your OIDC provider including the path up to /.well-known/openid-configuration (string, default=`\"\"`)\n* `SOCIAL_AUTH_OIDC_VERIFY_SSL`: Verify the OIDC provider ssl certificate. (boolean, default=`True`)\n\n\n\n\n\n\nFor a PUT request, include **all** fields in the request.\n\n\n\nFor a PATCH request, include only the fields that are being modified.\n\n\n\n# Delete a Setting:\n\nMake a DELETE request to this resource to delete this setting.",
  "Endpoint": "/api/v2/settings/oidc/",
  "Name": "SettingsOpenIDConnect",
  "PackageName": "awx",
  "PropertyGetData": {
    "SOCIAL_AUTH_OIDC_KEY": {
      "category": "Generic OIDC",
      "category_slug": "oidc",
      "computed": true,
      "defined_in_file": false,
      "help_text": "The OIDC key (Client ID) from your IDP.",
      "label": "OIDC Key",
      "name": "SOCIAL_AUTH_OIDC_KEY",
      "required": false,
      "sensitive": false,
      "type": "string"
    },
    "SOCIAL_AUTH_OIDC_OIDC_ENDPOINT": {
      "category": "Generic OIDC",
      "category_slug": "oidc",
      "computed": true,
      "defined_in_file": false,
      "help_text": "The URL for your OIDC provider including the path up to /.well-known/openid-configuration",
      "label": "OIDC Provider URL",
      "name": "SOCIAL_AUTH_OIDC_OIDC_ENDPOINT",
      "required": false,
      "sensitive": false,
      "type": "string"
    },
    "SOCIAL_AUTH_OIDC_SECRET": {
      "category": "Generic OIDC",
      "category_slug": "oidc",
      "computed": true,
      "defined_in_file": false,
      "help_text": "The OIDC secret (Client Secret) from your IDP.",
      "label": "OIDC Secret",
      "name": "SOCIAL_AUTH_OIDC_SECRET",
      "required": false,
      "sensitive": false,
      "type": "string"
    },
    "SOCIAL_AUTH_OIDC_VERIFY_SSL": {
      "category": "Generic OIDC",
      "category_slug": "oidc",
      "computed": true,
      "defined_in_file": false,
      "help_text": "Verify the OIDC provider ssl certificate.",
      "label": "Verify OIDC Provider Certificate",
      "name": "SOCIAL_AUTH_OIDC_VERIFY_SSL",
      "required": false,
      "sensitive": false,
      "type": "boolean"
    }
  },
  "PropertyGetKeys": [
    "SOCIAL_AUTH_OIDC_KEY",
    "SOCIAL_AUTH_OIDC_OIDC_ENDPOINT",
    "SOCIAL_AUTH_OIDC_SECRET",
    "SOCIAL_AUTH_OIDC_VERIFY_SSL"
  ],
  "PropertyPostData": {
    "SOCIAL_AUTH_OIDC_KEY": {
      "category": "Generic OIDC",
      "category_slug": "oidc",
      "computed": true,
      "default": null,
      "help_text": "The OIDC key (Client ID) from your IDP.",
      "label": "OIDC Key",
      "name": "SOCIAL_AUTH_OIDC_KEY",
      "required": false,
      "sensitive": false,
      "type": "string"
    },
    "SOCIAL_AUTH_OIDC_OIDC_ENDPOINT": {
      "category": "Generic OIDC",
      "category_slug": "oidc",
      "computed": true,
      "default": "",
      "default_value": "stringdefault.StaticString(``)",
      "help_text": "The URL for your OIDC provider including the path up to /.well-known/openid-configuration",
      "label": "OIDC Provider URL",
      "name": "SOCIAL_AUTH_OIDC_OIDC_ENDPOINT",
      "required": false,
      "sensitive": false,
      "type": "string"
    },
    "SOCIAL_AUTH_OIDC_SECRET": {
      "category": "Generic OIDC",
      "category_slug": "oidc",
      "computed": true,
      "default": "",
      "default_value": "stringdefault.StaticString(``)",
      "help_text": "The OIDC secret (Client Secret) from your IDP.",
      "label": "OIDC Secret",
      "name": "SOCIAL_AUTH_OIDC_SECRET",
      "required": false,
      "sensitive": false,
      "type": "string"
    },
    "SOCIAL_AUTH_OIDC_VERIFY_SSL": {
      "category": "Generic OIDC",
      "category_slug": "oidc",
      "computed": true,
      "default": true,
      "help_text": "Verify the OIDC provider ssl certificate.",
      "label": "Verify OIDC Provider Certificate",
      "name": "SOCIAL_AUTH_OIDC_VERIFY_SSL",
      "required": false,
      "sensitive": false,
      "type": "boolean"
    }
  },
  "PropertyPostKeys": [
    "SOCIAL_AUTH_OIDC_KEY",
    "SOCIAL_AUTH_OIDC_OIDC_ENDPOINT",
    "SOCIAL_AUTH_OIDC_SECRET",
    "SOCIAL_AUTH_OIDC_VERIFY_SSL"
  ],
  "PropertyWriteOnlyData": {},
  "PropertyWriteOnlyKeys": null
}