{
  "ApiVersion": "24.6.1",
  "Config": {
    "endpoint": "/api/v2/inventories/",
    "name": "Inventory",
    "type_name": "inventory",
    "id_key": "id",
    "property_overrides": {
      "variables": {
        "type": "json-yaml",
        "description": "Inventory variables in JSON format",
        "sensitive": false,
        "required": false,
        "trim": false,
        "post_wrap": true,
        "default_value": "{}",
        "element_type": ""
      }
    },
    "search_fields": [
      {
        "url_suffix": "%d/",
        "name": "by_id",
        "fields": [
          {
            "name": "id"
          }
        ]
      },
      {
        "url_suffix": "?name__exact=%s",
        "name": "by_name",
        "fields": [
          {
            "name": "name",
            "url_escape_value": true
          }
        ],
        "multiple_results": true
      }
    ],
    "enabled": true,
    "has_object_roles": true,
    "has_survey_spec": false,
    "associate_disassociate_groups": null,
    "field_constraints": null,
    "skip_write_only": false,
    "undeletable": false,
    "pre_state_set_hook_function": "",
    "no_id": false,
    "no_terraform_data_source": false,
    "no_terraform_resource": false,
    "api_property_resource_key": "POST",
    "api_property_data_key": "GET",
    "property_name_leave_as_is": false,
    "api_data_override": null,
    "remove_fields_data_source": null,
    "remove_fields_resource": null,
    "credential_types": null
  },
  "Description": "# List Inventories:\n\nMake a GET request to this resource to retrieve the list of\ninventories.\n\nThe resulting data structure contains:\n\n    {\n        \"count\": 99,\n        \"next\": null,\n        \"previous\": null,\n        \"results\": [\n            ...\n        ]\n    }\n\nThe `count` field indicates the total number of inventories\nfound for the given query.  The `next` and `previous` fields provides links to\nadditional results if there are more than will fit on a single page.  The\n`results` list contains zero or more inventory records.  \n\n## Results\n\nEach inventory data structure includes the following fields:\n\n* `id`: Database ID for this inventory. (integer)\n* `type`: Data type for this inventory. (choice)\n* `url`: URL for this inventory. (string)\n* `related`: Data structure with URLs of related resources. (object)\n* `summary_fields`: Data structure with name/description for related resources.  The output for some objects may be limited for performance reasons. (object)\n* `created`: Timestamp when this inventory was created. (datetime)\n* `modified`: Timestamp when this inventory was last modified. (datetime)\n* `name`: Name of this inventory. (string)\n* `description`: Optional description of this inventory. (string)\n* `organization`: Organization containing this inventory. (id)\n* `kind`: Kind of inventory being represented. (choice)\n    - `\"\"`: Hosts have a direct link to this inventory.\n    - `smart`: Hosts for inventory generated using the host_filter property.\n    - `constructed`: Parse list of source inventories with the constructed inventory plugin.\n* `host_filter`: Filter that will be applied to the hosts of this inventory. (string)\n* `variables`: Inventory variables in JSON or YAML format. (json)\n* `has_active_failures`: This field is deprecated and will be removed in a future release. Flag indicating whether any hosts in this inventory have failed. (boolean)\n* `total_hosts`: This field is deprecated and will be removed in a future release. Total number of hosts in this inventory. (integer)\n* `hosts_with_active_failures`: This field is deprecated and will be removed in a future release. Number of hosts in this inventory with active failures. (integer)\n* `total_groups`: This field is deprecated and will be removed in a future release. Total number of groups in this inventory. (integer)\n* `has_inventory_sources`: This field is deprecated and will be removed in a future release. Flag indicating whether this inventory has any external inventory sources. (boolean)\n* `total_inventory_sources`: Total number of external inventory sources configured within this inventory. (integer)\n* `inventory_sources_with_failures`: Number of external inventory sources in this inventory with failures. (integer)\n* `pending_deletion`: Flag indicating the inventory is being deleted. (boolean)\n* `prevent_instance_group_fallback`: If enabled, the inventory will prevent adding any organization instance groups to the list of preferred instances groups to run associated job templates on.If this setting is enabled and you provided an empty list, the global instance groups will be applied. (boolean)\n\n\n\n## Sorting\n\nTo specify that inventories are returned in a particular\norder, use the `order_by` query string parameter on the GET request.\n\n    ?order_by=name\n\nPrefix the field name with a dash `-` to sort in reverse:\n\n    ?order_by=-name\n\nMultiple sorting fields may be specified by separating the field names with a\ncomma `,`:\n\n    ?order_by=name,some_other_field\n\n## Pagination\n\nUse the `page_size` query string parameter to change the number of results\nreturned for each request.  Use the `page` query string parameter to retrieve\na particular page of results.\n\n    ?page_size=100\u0026page=2\n\nThe `previous` and `next` links returned with the results will set these query\nstring parameters automatically.\n\n## Searching\n\nUse the `search` query string parameter to perform a case-insensitive search\nwithin all designated text fields of a model.\n\n    ?search=findme\n\n(_Added in Ansible Tower 3.1.0_) Search across related fields:\n\n    ?related__search=findme\n\nNote: If you want to provide more than one search term, multiple\nsearch fields with the same key, like `?related__search=foo\u0026related__search=bar`,\nwill be ORed together. Terms separated by commas, like `?related__search=foo,bar`\nwill be ANDed together.\n\n## Filtering\n\nAny additional query string parameters may be used to filter the list of\nresults returned to those matching a given value.  Only fields and relations\nthat exist in the database may be used for filtering.  Any special characters\nin the specified value should be url-encoded. For example:\n\n    ?field=value%20xyz\n\nFields may also span relations, only for fields and relationships defined in\nthe database:\n\n    ?other__field=value\n\nTo exclude results matching certain criteria, prefix the field parameter with\n`not__`:\n\n    ?not__field=value\n\nBy default, all query string filters are AND'ed together, so\nonly the results matching *all* filters will be returned.  To combine results\nmatching *any* one of multiple criteria, prefix each query string parameter\nwith `or__`:\n\n    ?or__field=value\u0026or__field=othervalue\n    ?or__not__field=value\u0026or__field=othervalue\n\n(_Added in Ansible Tower 1.4.5_) The default AND filtering applies all filters\nsimultaneously to each related object being filtered across database\nrelationships.  The chain filter instead applies filters separately for each\nrelated object. To use, prefix the query string parameter with `chain__`:\n\n    ?chain__related__field=value\u0026chain__related__field2=othervalue\n    ?chain__not__related__field=value\u0026chain__related__field2=othervalue\n\nIf the first query above were written as\n`?related__field=value\u0026related__field2=othervalue`, it would return only the\nprimary objects where the *same* related object satisfied both conditions.  As\nwritten using the chain filter, it would return the intersection of primary\nobjects matching each condition.\n\nField lookups may also be used for more advanced queries, by appending the\nlookup to the field name:\n\n    ?field__lookup=value\n\nThe following field lookups are supported:\n\n* `exact`: Exact match (default lookup if not specified).\n* `iexact`: Case-insensitive version of `exact`.\n* `contains`: Field contains value.\n* `icontains`: Case-insensitive version of `contains`.\n* `startswith`: Field starts with value.\n* `istartswith`: Case-insensitive version of `startswith`.\n* `endswith`: Field ends with value.\n* `iendswith`: Case-insensitive version of `endswith`.\n* `regex`: Field matches the given regular expression.\n* `iregex`: Case-insensitive version of `regex`.\n* `gt`: Greater than comparison.\n* `gte`: Greater than or equal to comparison.\n* `lt`: Less than comparison.\n* `lte`: Less than or equal to comparison.\n* `isnull`: Check whether the given field or related object is null; expects a\n  boolean value.\n* `in`: Check whether the given field's value is present in the list provided;\n  expects a list of items.\n\nBoolean values may be specified as `True` or `1` for true, `False` or `0` for\nfalse (both case-insensitive).\n\nNull values may be specified as `None` or `Null` (both case-insensitive),\nthough it is preferred to use the `isnull` lookup to explicitly check for null\nvalues.\n\nLists (for the `in` lookup) may be specified as a comma-separated list of\nvalues.\n\n(_Added in Ansible Tower 3.1.0_) Filtering based on the requesting user's\nlevel of access by query string parameter.\n\n* `role_level`: Level of role to filter on, such as `admin_role`\n\n\n\n\n# Create an Inventory:\n\nMake a POST request to this resource with the following inventory\nfields to create a new inventory:\n\n\n\n\n\n\n\n\n\n* `name`: Name of this inventory. (string, required)\n* `description`: Optional description of this inventory. (string, default=`\"\"`)\n* `organization`: Organization containing this inventory. (id, required)\n* `kind`: Kind of inventory being represented. (choice)\n    - `\"\"`: Hosts have a direct link to this inventory. (default)\n    - `smart`: Hosts for inventory generated using the host_filter property.\n    - `constructed`: Parse list of source inventories with the constructed inventory plugin.\n* `host_filter`: Filter that will be applied to the hosts of this inventory. (string, default=`\"\"`)\n* `variables`: Inventory variables in JSON or YAML format. (json, default=``)\n\n\n\n\n\n\n\n\n* `prevent_instance_group_fallback`: If enabled, the inventory will prevent adding any organization instance groups to the list of preferred instances groups to run associated job templates on.If this setting is enabled and you provided an empty list, the global instance groups will be applied. (boolean, default=`False`)",
  "Endpoint": "/api/v2/inventories/",
  "Name": "Inventory",
  "PackageName": "awx",
  "PropertyGetData": {
    "description": {
      "computed": true,
      "filterable": true,
      "help_text": "Optional description of this inventory.",
      "hidden": false,
      "label": "Description",
      "name": "description",
      "required": false,
      "sensitive": false,
      "type": "string"
    },
    "has_active_failures": {
      "computed": true,
      "filterable": true,
      "help_text": "This field is deprecated and will be removed in a future release. Flag indicating whether any hosts in this inventory have failed.",
      "hidden": false,
      "label": "Has active failures",
      "name": "has_active_failures",
      "required": false,
      "sensitive": false,
      "type": "boolean"
    },
    "has_inventory_sources": {
      "computed": true,
      "filterable": true,
      "help_text": "This field is deprecated and will be removed in a future release. Flag indicating whether this inventory has any external inventory sources.",
      "hidden": false,
      "label": "Has inventory sources",
      "name": "has_inventory_sources",
      "required": false,
      "sensitive": false,
      "type": "boolean"
    },
    "host_filter": {
      "computed": true,
      "filterable": true,
      "help_text": "Filter that will be applied to the hosts of this inventory.",
      "hidden": false,
      "label": "Host filter",
      "name": "host_filter",
      "required": false,
      "sensitive": false,
      "type": "string"
    },
    "hosts_with_active_failures": {
      "computed": true,
      "filterable": true,
      "help_text": "This field is deprecated and will be removed in a future release. Number of hosts in this inventory with active failures.",
      "hidden": false,
      "label": "Hosts with active failures",
      "min_value": 0,
      "name": "hosts_with_active_failures",
      "required": false,
      "sensitive": false,
      "type": "integer"
    },
    "id": {
      "computed": true,
      "filterable": true,
      "help_text": "Database ID for this inventory.",
      "hidden": false,
      "label": "ID",
      "name": "id",
      "required": false,
      "sensitive": false,
      "type": "integer"
    },
    "inventory_sources_with_failures": {
      "computed": true,
      "filterable": true,
      "help_text": "Number of external inventory sources in this inventory with failures.",
      "hidden": false,
      "label": "Inventory sources with failures",
      "min_value": 0,
      "name": "inventory_sources_with_failures",
      "required": false,
      "sensitive": false,
      "type": "integer"
    },
    "kind": {
      "choices": [
        [
          "",
          "Hosts have a direct link to this inventory."
        ],
        [
          "smart",
          "Hosts for inventory generated using the host_filter property."
        ],
        [
          "constructed",
          "Parse list of source inventories with the constructed inventory plugin."
        ]
      ],
      "computed": true,
      "filterable": true,
      "help_text": "Kind of inventory being represented.",
      "hidden": false,
      "label": "Kind",
      "name": "kind",
      "required": false,
      "sensitive": false,
      "type": "choice"
    },
    "name": {
      "computed": true,
      "filterable": true,
      "help_text": "Name of this inventory.",
      "hidden": false,
      "label": "Name",
      "name": "name",
      "required": false,
      "sensitive": false,
      "type": "string"
    },
    "organization": {
      "computed": true,
      "filterable": true,
      "help_text": "Organization containing this inventory.",
      "hidden": false,
      "label": "Organization",
      "name": "organization",
      "required": false,
      "sensitive": false,
      "type": "id"
    },
    "pending_deletion": {
      "computed": true,
      "filterable": true,
      "help_text": "Flag indicating the inventory is being deleted.",
      "hidden": false,
      "label": "Pending deletion",
      "name": "pending_deletion",
      "required": false,
      "sensitive": false,
      "type": "boolean"
    },
    "prevent_instance_group_fallback": {
      "computed": true,
      "filterable": true,
      "help_text": "If enabled, the inventory will prevent adding any organization instance groups to the list of preferred instances groups to run associated job templates on.If this setting is enabled and you provided an empty list, the global instance groups will be applied.",
      "hidden": false,
      "label": "Prevent instance group fallback",
      "name": "prevent_instance_group_fallback",
      "required": false,
      "sensitive": false,
      "type": "boolean"
    },
    "total_groups": {
      "computed": true,
      "filterable": true,
      "help_text": "This field is deprecated and will be removed in a future release. Total number of groups in this inventory.",
      "hidden": false,
      "label": "Total groups",
      "min_value": 0,
      "name": "total_groups",
      "required": false,
      "sensitive": false,
      "type": "integer"
    },
    "total_hosts": {
      "computed": true,
      "filterable": true,
      "help_text": "This field is deprecated and will be removed in a future release. Total number of hosts in this inventory.",
      "hidden": false,
      "label": "Total hosts",
      "min_value": 0,
      "name": "total_hosts",
      "required": false,
      "sensitive": false,
      "type": "integer"
    },
    "total_inventory_sources": {
      "computed": true,
      "filterable": true,
      "help_text": "Total number of external inventory sources configured within this inventory.",
      "hidden": false,
      "label": "Total inventory sources",
      "min_value": 0,
      "name": "total_inventory_sources",
      "required": false,
      "sensitive": false,
      "type": "integer"
    },
    "variables": {
      "computed": true,
      "default": "{}",
      "default_value": "stringdefault.StaticString(`{}`)",
      "filterable": true,
      "help_text": "Inventory variables in JSON format",
      "hidden": false,
      "label": "Variables",
      "name": "variables",
      "post_wrap": true,
      "required": false,
      "sensitive": false,
      "trim": false,
      "type": "json-yaml"
    }
  },
  "PropertyGetKeys": [
    "description",
    "has_active_failures",
    "has_inventory_sources",
    "host_filter",
    "hosts_with_active_failures",
    "id",
    "inventory_sources_with_failures",
    "kind",
    "name",
    "organization",
    "pending_deletion",
    "prevent_instance_group_fallback",
    "total_groups",
    "total_hosts",
    "total_inventory_sources",
    "variables"
  ],
  "PropertyPostData": {
    "description": {
      "computed": true,
      "default": "",
      "default_value": "stringdefault.StaticString(``)",
      "filterable": true,
      "help_text": "Optional description of this inventory.",
      "hidden": false,
      "label": "Description",
      "name": "description",
      "required": false,
      "sensitive": false,
      "type": "string"
    },
    "host_filter": {
      "computed": true,
      "default": null,
      "filterable": true,
      "help_text": "Filter that will be applied to the hosts of this inventory.",
      "hidden": false,
      "label": "Host filter",
      "name": "host_filter",
      "required": false,
      "sensitive": false,
      "type": "string"
    },
    "kind": {
      "choices": [
        [
          "",
          "Hosts have a direct link to this inventory."
        ],
        [
          "smart",
          "Hosts for inventory generated using the host_filter property."
        ],
        [
          "constructed",
          "Parse list of source inventories with the constructed inventory plugin."
        ]
      ],
      "computed": true,
      "default": "",
      "default_value": "stringdefault.StaticString(``)",
      "filterable": true,
      "help_text": "Kind of inventory being represented.",
      "hidden": false,
      "label": "Kind",
      "name": "kind",
      "required": false,
      "sensitive": false,
      "type": "choice"
    },
    "name": {
      "computed": false,
      "filterable": true,
      "help_text": "Name of this inventory.",
      "hidden": false,
      "label": "Name",
      "max_length": 512,
      "name": "name",
      "required": true,
      "sensitive": false,
      "type": "string"
    },
    "organization": {
      "computed": false,
      "filterable": true,
      "help_text": "Organization containing this inventory.",
      "hidden": false,
      "label": "Organization",
      "name": "organization",
      "required": true,
      "sensitive": false,
      "type": "id"
    },
    "prevent_instance_group_fallback": {
      "computed": true,
      "default": false,
      "filterable": true,
      "help_text": "If enabled, the inventory will prevent adding any organization instance groups to the list of preferred instances groups to run associated job templates on.If this setting is enabled and you provided an empty list, the global instance groups will be applied.",
      "hidden": false,
      "label": "Prevent instance group fallback",
      "name": "prevent_instance_group_fallback",
      "required": false,
      "sensitive": false,
      "type": "boolean"
    },
    "variables": {
      "computed": true,
      "default": "{}",
      "default_value": "stringdefault.StaticString(`{}`)",
      "filterable": true,
      "help_text": "Inventory variables in JSON format",
      "hidden": false,
      "label": "Variables",
      "name": "variables",
      "post_wrap": true,
      "required": false,
      "sensitive": false,
      "trim": false,
      "type": "json-yaml"
    }
  },
  "PropertyPostKeys": [
    "description",
    "host_filter",
    "kind",
    "name",
    "organization",
    "prevent_instance_group_fallback",
    "variables"
  ],
  "PropertyWriteOnlyData": {},
  "PropertyWriteOnlyKeys": null
}