{
  "ApiVersion": "24.6.1",
  "Config": {
    "endpoint": "/api/v2/settings/logging/",
    "name": "SettingsMiscLogging",
    "type_name": "settings_misc_logging",
    "id_key": "id",
    "enabled": true,
    "has_object_roles": false,
    "has_survey_spec": false,
    "associate_disassociate_groups": null,
    "field_constraints": null,
    "skip_write_only": false,
    "undeletable": true,
    "pre_state_set_hook_function": "",
    "no_id": true,
    "no_terraform_data_source": false,
    "no_terraform_resource": false,
    "api_property_resource_key": "PUT",
    "api_property_data_key": "GET",
    "property_name_leave_as_is": true,
    "api_data_override": null,
    "remove_fields_data_source": null,
    "remove_fields_resource": null,
    "credential_types": null
  },
  "Description": "# Retrieve a Setting:\n\nMake GET request to this resource to retrieve a single setting\nrecord containing the following fields:\n\n* `LOG_AGGREGATOR_HOST`: Hostname/IP where external logs will be sent to. (string)\n* `LOG_AGGREGATOR_PORT`: Port on Logging Aggregator to send logs to (if required and not provided in Logging Aggregator). (integer)\n* `LOG_AGGREGATOR_TYPE`: Format messages for the chosen log aggregator. (choice)\n    - `None`: ---------\n    - `logstash`\n    - `splunk`\n    - `loggly`\n    - `sumologic`\n    - `other`\n* `LOG_AGGREGATOR_USERNAME`: Username for external log aggregator (if required; HTTP/s only). (string)\n* `LOG_AGGREGATOR_PASSWORD`: Password or authentication token for external log aggregator (if required; HTTP/s only). (string)\n* `LOG_AGGREGATOR_LOGGERS`: List of loggers that will send HTTP logs to the collector, these can include any or all of: \nawx - service logs\nactivity_stream - activity stream records\njob_events - callback data from Ansible job events\nsystem_tracking - facts gathered from scan jobs\nbroadcast_websocket - errors pertaining to websockets broadcast metrics\n (list)\n* `LOG_AGGREGATOR_INDIVIDUAL_FACTS`: If set, system tracking facts will be sent for each package, service, or other item found in a scan, allowing for greater search query granularity. If unset, facts will be sent as a single dictionary, allowing for greater efficiency in fact processing. (boolean)\n* `LOG_AGGREGATOR_ENABLED`: Enable sending logs to external log aggregator. (boolean)\n* `LOG_AGGREGATOR_TOWER_UUID`: Useful to uniquely identify instances. (string)\n* `LOG_AGGREGATOR_PROTOCOL`: Protocol used to communicate with log aggregator.  HTTPS/HTTP assumes HTTPS unless http:// is explicitly used in the Logging Aggregator hostname. (choice)\n    - `https`: HTTPS/HTTP\n    - `tcp`: TCP\n    - `udp`: UDP\n* `LOG_AGGREGATOR_TCP_TIMEOUT`: Number of seconds for a TCP connection to external log aggregator to timeout. Applies to HTTPS and TCP log aggregator protocols. (integer)\n* `LOG_AGGREGATOR_VERIFY_CERT`: Flag to control enable/disable of certificate verification when LOG_AGGREGATOR_PROTOCOL is \u0026quot;https\u0026quot;. If enabled, the log handler will verify certificate sent by external log aggregator before establishing connection. (boolean)\n* `LOG_AGGREGATOR_LEVEL`: Level threshold used by log handler. Severities from lowest to highest are DEBUG, INFO, WARNING, ERROR, CRITICAL. Messages less severe than the threshold will be ignored by log handler. (messages under category awx.anlytics ignore this setting) (choice)\n    - `DEBUG`\n    - `INFO`\n    - `WARNING`\n    - `ERROR`\n    - `CRITICAL`\n* `LOG_AGGREGATOR_ACTION_QUEUE_SIZE`: Defines how large the rsyslog action queue can grow in number of messages stored. This can have an impact on memory utilization. When the queue reaches 75% of this number, the queue will start writing to disk (queue.highWatermark in rsyslog). When it reaches 90%, NOTICE, INFO, and DEBUG messages will start to be discarded (queue.discardMark with queue.discardSeverity=5). (integer)\n* `LOG_AGGREGATOR_ACTION_MAX_DISK_USAGE_GB`: Amount of data to store (in gigabytes) if an rsyslog action takes time to process an incoming message (defaults to 1). Equivalent to the rsyslogd queue.maxdiskspace setting on the action (e.g. omhttp). It stores files in the directory specified by LOG_AGGREGATOR_MAX_DISK_USAGE_PATH. (integer)\n* `LOG_AGGREGATOR_MAX_DISK_USAGE_PATH`: Location to persist logs that should be retried after an outage of the external log aggregator (defaults to /var/lib/awx). Equivalent to the rsyslogd queue.spoolDirectory setting. (string)\n* `LOG_AGGREGATOR_RSYSLOGD_DEBUG`: Enabled high verbosity debugging for rsyslogd.  Useful for debugging connection issues for external log aggregation. (boolean)\n* `API_400_ERROR_LOG_FORMAT`: The format of logged messages when an API 4XX error occurs, the following variables will be substituted: \nstatus_code - The HTTP status code of the error\nuser_name - The user name attempting to use the API\nurl_path - The URL path to the API endpoint called\nremote_addr - The remote address seen for the user\nerror - The error set by the api endpoint\nVariables need to be in the format {\u0026lt;variable name\u0026gt;}. (string)\n\n\n\n\n\n# Update a Setting:\n\nMake a PUT or PATCH request to this resource to update this\nsetting.  The following fields may be modified:\n\n\n* `LOG_AGGREGATOR_HOST`: Hostname/IP where external logs will be sent to. (string, default=`\"\"`)\n* `LOG_AGGREGATOR_PORT`: Port on Logging Aggregator to send logs to (if required and not provided in Logging Aggregator). (integer, default=`None`)\n* `LOG_AGGREGATOR_TYPE`: Format messages for the chosen log aggregator. (choice)\n    - `None`: --------- (default)\n    - `logstash`\n    - `splunk`\n    - `loggly`\n    - `sumologic`\n    - `other`\n* `LOG_AGGREGATOR_USERNAME`: Username for external log aggregator (if required; HTTP/s only). (string, default=`\"\"`)\n* `LOG_AGGREGATOR_PASSWORD`: Password or authentication token for external log aggregator (if required; HTTP/s only). (string, default=`\"\"`)\n* `LOG_AGGREGATOR_LOGGERS`: List of loggers that will send HTTP logs to the collector, these can include any or all of: \nawx - service logs\nactivity_stream - activity stream records\njob_events - callback data from Ansible job events\nsystem_tracking - facts gathered from scan jobs\nbroadcast_websocket - errors pertaining to websockets broadcast metrics\n (list, default=`[\u0026#x27;awx\u0026#x27;, \u0026#x27;activity_stream\u0026#x27;, \u0026#x27;job_events\u0026#x27;, \u0026#x27;system_tracking\u0026#x27;, \u0026#x27;broadcast_websocket\u0026#x27;]`)\n* `LOG_AGGREGATOR_INDIVIDUAL_FACTS`: If set, system tracking facts will be sent for each package, service, or other item found in a scan, allowing for greater search query granularity. If unset, facts will be sent as a single dictionary, allowing for greater efficiency in fact processing. (boolean, default=`False`)\n* `LOG_AGGREGATOR_ENABLED`: Enable sending logs to external log aggregator. (boolean, default=`False`)\n* `LOG_AGGREGATOR_TOWER_UUID`: Useful to uniquely identify instances. (string, default=`\"\"`)\n* `LOG_AGGREGATOR_PROTOCOL`: Protocol used to communicate with log aggregator.  HTTPS/HTTP assumes HTTPS unless http:// is explicitly used in the Logging Aggregator hostname. (choice)\n    - `https`: HTTPS/HTTP (default)\n    - `tcp`: TCP\n    - `udp`: UDP\n* `LOG_AGGREGATOR_TCP_TIMEOUT`: Number of seconds for a TCP connection to external log aggregator to timeout. Applies to HTTPS and TCP log aggregator protocols. (integer, default=`5`)\n* `LOG_AGGREGATOR_VERIFY_CERT`: Flag to control enable/disable of certificate verification when LOG_AGGREGATOR_PROTOCOL is \u0026quot;https\u0026quot;. If enabled, the log handler will verify certificate sent by external log aggregator before establishing connection. (boolean, default=`True`)\n* `LOG_AGGREGATOR_LEVEL`: Level threshold used by log handler. Severities from lowest to highest are DEBUG, INFO, WARNING, ERROR, CRITICAL. Messages less severe than the threshold will be ignored by log handler. (messages under category awx.anlytics ignore this setting) (choice)\n    - `DEBUG`\n    - `INFO` (default)\n    - `WARNING`\n    - `ERROR`\n    - `CRITICAL`\n* `LOG_AGGREGATOR_ACTION_QUEUE_SIZE`: Defines how large the rsyslog action queue can grow in number of messages stored. This can have an impact on memory utilization. When the queue reaches 75% of this number, the queue will start writing to disk (queue.highWatermark in rsyslog). When it reaches 90%, NOTICE, INFO, and DEBUG messages will start to be discarded (queue.discardMark with queue.discardSeverity=5). (integer, default=`131072`)\n* `LOG_AGGREGATOR_ACTION_MAX_DISK_USAGE_GB`: Amount of data to store (in gigabytes) if an rsyslog action takes time to process an incoming message (defaults to 1). Equivalent to the rsyslogd queue.maxdiskspace setting on the action (e.g. omhttp). It stores files in the directory specified by LOG_AGGREGATOR_MAX_DISK_USAGE_PATH. (integer, default=`1`)\n* `LOG_AGGREGATOR_MAX_DISK_USAGE_PATH`: Location to persist logs that should be retried after an outage of the external log aggregator (defaults to /var/lib/awx). Equivalent to the rsyslogd queue.spoolDirectory setting. (string, default=`\"/var/lib/awx\"`)\n* `LOG_AGGREGATOR_RSYSLOGD_DEBUG`: Enabled high verbosity debugging for rsyslogd.  Useful for debugging connection issues for external log aggregation. (boolean, default=`False`)\n* `API_400_ERROR_LOG_FORMAT`: The format of logged messages when an API 4XX error occurs, the following variables will be substituted: \nstatus_code - The HTTP status code of the error\nuser_name - The user name attempting to use the API\nurl_path - The URL path to the API endpoint called\nremote_addr - The remote address seen for the user\nerror - The error set by the api endpoint\nVariables need to be in the format {\u0026lt;variable name\u0026gt;}. (string, default=`\"status {status_code} received by user {user_name} attempting to access {url_path} from {remote_addr}\"`)\n\n\n\n\n\n\nFor a PUT request, include **all** fields in the request.\n\n\n\nFor a PATCH request, include only the fields that are being modified.\n\n\n\n# Delete a Setting:\n\nMake a DELETE request to this resource to delete this setting.",
  "Endpoint": "/api/v2/settings/logging/",
  "Name": "SettingsMiscLogging",
  "PackageName": "awx",
  "PropertyGetData": {
    "API_400_ERROR_LOG_FORMAT": {
      "category": "Logging",
      "category_slug": "logging",
      "computed": true,
      "defined_in_file": false,
      "help_text": "The format of logged messages when an API 4XX error occurs, the following variables will be substituted: \nstatus_code - The HTTP status code of the error\nuser_name - The user name attempting to use the API\nurl_path - The URL path to the API endpoint called\nremote_addr - The remote address seen for the user\nerror - The error set by the api endpoint\nVariables need to be in the format {\u003cvariable name\u003e}.",
      "hidden": false,
      "label": "Log Format For API 4XX Errors",
      "name": "API_400_ERROR_LOG_FORMAT",
      "required": false,
      "sensitive": false,
      "type": "string"
    },
    "LOG_AGGREGATOR_ACTION_MAX_DISK_USAGE_GB": {
      "category": "Logging",
      "category_slug": "logging",
      "computed": true,
      "defined_in_file": false,
      "help_text": "Amount of data to store (in gigabytes) if an rsyslog action takes time to process an incoming message (defaults to 1). Equivalent to the rsyslogd queue.maxdiskspace setting on the action (e.g. omhttp). It stores files in the directory specified by LOG_AGGREGATOR_MAX_DISK_USAGE_PATH.",
      "hidden": false,
      "label": "Maximum disk persistence for rsyslogd action queuing (in GB)",
      "min_value": 1,
      "name": "LOG_AGGREGATOR_ACTION_MAX_DISK_USAGE_GB",
      "required": false,
      "sensitive": false,
      "type": "integer"
    },
    "LOG_AGGREGATOR_ACTION_QUEUE_SIZE": {
      "category": "Logging",
      "category_slug": "logging",
      "computed": true,
      "defined_in_file": false,
      "help_text": "Defines how large the rsyslog action queue can grow in number of messages stored. This can have an impact on memory utilization. When the queue reaches 75% of this number, the queue will start writing to disk (queue.highWatermark in rsyslog). When it reaches 90%, NOTICE, INFO, and DEBUG messages will start to be discarded (queue.discardMark with queue.discardSeverity=5).",
      "hidden": false,
      "label": "Maximum number of messages that can be stored in the log action queue",
      "min_value": 1,
      "name": "LOG_AGGREGATOR_ACTION_QUEUE_SIZE",
      "required": false,
      "sensitive": false,
      "type": "integer"
    },
    "LOG_AGGREGATOR_ENABLED": {
      "category": "Logging",
      "category_slug": "logging",
      "computed": true,
      "defined_in_file": false,
      "help_text": "Enable sending logs to external log aggregator.",
      "hidden": false,
      "label": "Enable External Logging",
      "name": "LOG_AGGREGATOR_ENABLED",
      "required": false,
      "sensitive": false,
      "type": "boolean"
    },
    "LOG_AGGREGATOR_HOST": {
      "category": "Logging",
      "category_slug": "logging",
      "computed": true,
      "defined_in_file": false,
      "help_text": "Hostname/IP where external logs will be sent to.",
      "hidden": false,
      "label": "Logging Aggregator",
      "name": "LOG_AGGREGATOR_HOST",
      "required": false,
      "sensitive": false,
      "type": "string"
    },
    "LOG_AGGREGATOR_INDIVIDUAL_FACTS": {
      "category": "Logging",
      "category_slug": "logging",
      "computed": true,
      "defined_in_file": false,
      "help_text": "If set, system tracking facts will be sent for each package, service, or other item found in a scan, allowing for greater search query granularity. If unset, facts will be sent as a single dictionary, allowing for greater efficiency in fact processing.",
      "hidden": false,
      "label": "Log System Tracking Facts Individually",
      "name": "LOG_AGGREGATOR_INDIVIDUAL_FACTS",
      "required": false,
      "sensitive": false,
      "type": "boolean"
    },
    "LOG_AGGREGATOR_LEVEL": {
      "category": "Logging",
      "category_slug": "logging",
      "choices": [
        [
          "DEBUG",
          "DEBUG"
        ],
        [
          "INFO",
          "INFO"
        ],
        [
          "WARNING",
          "WARNING"
        ],
        [
          "ERROR",
          "ERROR"
        ],
        [
          "CRITICAL",
          "CRITICAL"
        ]
      ],
      "computed": true,
      "defined_in_file": false,
      "help_text": "Level threshold used by log handler. Severities from lowest to highest are DEBUG, INFO, WARNING, ERROR, CRITICAL. Messages less severe than the threshold will be ignored by log handler. (messages under category awx.anlytics ignore this setting)",
      "hidden": false,
      "label": "Logging Aggregator Level Threshold",
      "name": "LOG_AGGREGATOR_LEVEL",
      "required": false,
      "sensitive": false,
      "type": "choice"
    },
    "LOG_AGGREGATOR_LOGGERS": {
      "category": "Logging",
      "category_slug": "logging",
      "child": {
        "hidden": false,
        "type": "string"
      },
      "computed": true,
      "defined_in_file": false,
      "element_type": "string",
      "help_text": "List of loggers that will send HTTP logs to the collector, these can include any or all of: \nawx - service logs\nactivity_stream - activity stream records\njob_events - callback data from Ansible job events\nsystem_tracking - facts gathered from scan jobs\nbroadcast_websocket - errors pertaining to websockets broadcast metrics\n",
      "hidden": false,
      "label": "Loggers Sending Data to Log Aggregator Form",
      "name": "LOG_AGGREGATOR_LOGGERS",
      "required": false,
      "sensitive": false,
      "type": "list"
    },
    "LOG_AGGREGATOR_MAX_DISK_USAGE_PATH": {
      "category": "Logging",
      "category_slug": "logging",
      "computed": true,
      "defined_in_file": false,
      "help_text": "Location to persist logs that should be retried after an outage of the external log aggregator (defaults to /var/lib/awx). Equivalent to the rsyslogd queue.spoolDirectory setting.",
      "hidden": false,
      "label": "File system location for rsyslogd disk persistence",
      "name": "LOG_AGGREGATOR_MAX_DISK_USAGE_PATH",
      "required": false,
      "sensitive": false,
      "type": "string"
    },
    "LOG_AGGREGATOR_PASSWORD": {
      "category": "Logging",
      "category_slug": "logging",
      "computed": true,
      "defined_in_file": false,
      "help_text": "Password or authentication token for external log aggregator (if required; HTTP/s only).",
      "hidden": false,
      "label": "Logging Aggregator Password/Token",
      "name": "LOG_AGGREGATOR_PASSWORD",
      "required": false,
      "sensitive": false,
      "type": "string"
    },
    "LOG_AGGREGATOR_PORT": {
      "category": "Logging",
      "category_slug": "logging",
      "computed": true,
      "defined_in_file": false,
      "help_text": "Port on Logging Aggregator to send logs to (if required and not provided in Logging Aggregator).",
      "hidden": false,
      "label": "Logging Aggregator Port",
      "name": "LOG_AGGREGATOR_PORT",
      "required": false,
      "sensitive": false,
      "type": "integer"
    },
    "LOG_AGGREGATOR_PROTOCOL": {
      "category": "Logging",
      "category_slug": "logging",
      "choices": [
        [
          "https",
          "HTTPS/HTTP"
        ],
        [
          "tcp",
          "TCP"
        ],
        [
          "udp",
          "UDP"
        ]
      ],
      "computed": true,
      "defined_in_file": false,
      "help_text": "Protocol used to communicate with log aggregator.  HTTPS/HTTP assumes HTTPS unless http:// is explicitly used in the Logging Aggregator hostname.",
      "hidden": false,
      "label": "Logging Aggregator Protocol",
      "name": "LOG_AGGREGATOR_PROTOCOL",
      "required": false,
      "sensitive": false,
      "type": "choice"
    },
    "LOG_AGGREGATOR_RSYSLOGD_DEBUG": {
      "category": "Logging",
      "category_slug": "logging",
      "computed": true,
      "defined_in_file": false,
      "help_text": "Enabled high verbosity debugging for rsyslogd.  Useful for debugging connection issues for external log aggregation.",
      "hidden": false,
      "label": "Enable rsyslogd debugging",
      "name": "LOG_AGGREGATOR_RSYSLOGD_DEBUG",
      "required": false,
      "sensitive": false,
      "type": "boolean"
    },
    "LOG_AGGREGATOR_TCP_TIMEOUT": {
      "category": "Logging",
      "category_slug": "logging",
      "computed": true,
      "defined_in_file": false,
      "help_text": "Number of seconds for a TCP connection to external log aggregator to timeout. Applies to HTTPS and TCP log aggregator protocols.",
      "hidden": false,
      "label": "TCP Connection Timeout",
      "name": "LOG_AGGREGATOR_TCP_TIMEOUT",
      "required": false,
      "sensitive": false,
      "type": "integer",
      "unit": "seconds"
    },
    "LOG_AGGREGATOR_TOWER_UUID": {
      "category": "Logging",
      "category_slug": "logging",
      "computed": true,
      "defined_in_file": false,
      "help_text": "Useful to uniquely identify instances.",
      "hidden": false,
      "label": "Cluster-wide unique identifier.",
      "name": "LOG_AGGREGATOR_TOWER_UUID",
      "required": false,
      "sensitive": false,
      "type": "string"
    },
    "LOG_AGGREGATOR_TYPE": {
      "category": "Logging",
      "category_slug": "logging",
      "choices": [
        [
          null,
          "---------"
        ],
        [
          "logstash",
          "logstash"
        ],
        [
          "splunk",
          "splunk"
        ],
        [
          "loggly",
          "loggly"
        ],
        [
          "sumologic",
          "sumologic"
        ],
        [
          "other",
          "other"
        ]
      ],
      "computed": true,
      "defined_in_file": false,
      "help_text": "Format messages for the chosen log aggregator.",
      "hidden": false,
      "label": "Logging Aggregator Type",
      "name": "LOG_AGGREGATOR_TYPE",
      "required": false,
      "sensitive": false,
      "type": "choice"
    },
    "LOG_AGGREGATOR_USERNAME": {
      "category": "Logging",
      "category_slug": "logging",
      "computed": true,
      "defined_in_file": false,
      "help_text": "Username for external log aggregator (if required; HTTP/s only).",
      "hidden": false,
      "label": "Logging Aggregator Username",
      "name": "LOG_AGGREGATOR_USERNAME",
      "required": false,
      "sensitive": false,
      "type": "string"
    },
    "LOG_AGGREGATOR_VERIFY_CERT": {
      "category": "Logging",
      "category_slug": "logging",
      "computed": true,
      "defined_in_file": false,
      "help_text": "Flag to control enable/disable of certificate verification when LOG_AGGREGATOR_PROTOCOL is \"https\". If enabled, the log handler will verify certificate sent by external log aggregator before establishing connection.",
      "hidden": false,
      "label": "Enable/disable HTTPS certificate verification",
      "name": "LOG_AGGREGATOR_VERIFY_CERT",
      "required": false,
      "sensitive": false,
      "type": "boolean"
    }
  },
  "PropertyGetKeys": [
    "API_400_ERROR_LOG_FORMAT",
    "LOG_AGGREGATOR_ACTION_MAX_DISK_USAGE_GB",
    "LOG_AGGREGATOR_ACTION_QUEUE_SIZE",
    "LOG_AGGREGATOR_ENABLED",
    "LOG_AGGREGATOR_HOST",
    "LOG_AGGREGATOR_INDIVIDUAL_FACTS",
    "LOG_AGGREGATOR_LEVEL",
    "LOG_AGGREGATOR_LOGGERS",
    "LOG_AGGREGATOR_MAX_DISK_USAGE_PATH",
    "LOG_AGGREGATOR_PASSWORD",
    "LOG_AGGREGATOR_PORT",
    "LOG_AGGREGATOR_PROTOCOL",
    "LOG_AGGREGATOR_RSYSLOGD_DEBUG",
    "LOG_AGGREGATOR_TCP_TIMEOUT",
    "LOG_AGGREGATOR_TOWER_UUID",
    "LOG_AGGREGATOR_TYPE",
    "LOG_AGGREGATOR_USERNAME",
    "LOG_AGGREGATOR_VERIFY_CERT"
  ],
  "PropertyPostData": {
    "API_400_ERROR_LOG_FORMAT": {
      "category": "Logging",
      "category_slug": "logging",
      "computed": true,
      "default": "status {status_code} received by user {user_name} attempting to access {url_path} from {remote_addr}",
      "default_value": "stringdefault.StaticString(`status {status_code} received by user {user_name} attempting to access {url_path} from {remote_addr}`)",
      "help_text": "The format of logged messages when an API 4XX error occurs, the following variables will be substituted: \nstatus_code - The HTTP status code of the error\nuser_name - The user name attempting to use the API\nurl_path - The URL path to the API endpoint called\nremote_addr - The remote address seen for the user\nerror - The error set by the api endpoint\nVariables need to be in the format {\u003cvariable name\u003e}.",
      "hidden": false,
      "label": "Log Format For API 4XX Errors",
      "name": "API_400_ERROR_LOG_FORMAT",
      "required": false,
      "sensitive": false,
      "type": "string"
    },
    "LOG_AGGREGATOR_ACTION_MAX_DISK_USAGE_GB": {
      "category": "Logging",
      "category_slug": "logging",
      "computed": true,
      "default": 1,
      "default_value": "int64default.StaticInt64(1)",
      "help_text": "Amount of data to store (in gigabytes) if an rsyslog action takes time to process an incoming message (defaults to 1). Equivalent to the rsyslogd queue.maxdiskspace setting on the action (e.g. omhttp). It stores files in the directory specified by LOG_AGGREGATOR_MAX_DISK_USAGE_PATH.",
      "hidden": false,
      "label": "Maximum disk persistence for rsyslogd action queuing (in GB)",
      "min_value": 1,
      "name": "LOG_AGGREGATOR_ACTION_MAX_DISK_USAGE_GB",
      "required": false,
      "sensitive": false,
      "type": "integer"
    },
    "LOG_AGGREGATOR_ACTION_QUEUE_SIZE": {
      "category": "Logging",
      "category_slug": "logging",
      "computed": true,
      "default": 131072,
      "default_value": "int64default.StaticInt64(131072)",
      "help_text": "Defines how large the rsyslog action queue can grow in number of messages stored. This can have an impact on memory utilization. When the queue reaches 75% of this number, the queue will start writing to disk (queue.highWatermark in rsyslog). When it reaches 90%, NOTICE, INFO, and DEBUG messages will start to be discarded (queue.discardMark with queue.discardSeverity=5).",
      "hidden": false,
      "label": "Maximum number of messages that can be stored in the log action queue",
      "min_value": 1,
      "name": "LOG_AGGREGATOR_ACTION_QUEUE_SIZE",
      "required": false,
      "sensitive": false,
      "type": "integer"
    },
    "LOG_AGGREGATOR_ENABLED": {
      "category": "Logging",
      "category_slug": "logging",
      "computed": true,
      "default": false,
      "help_text": "Enable sending logs to external log aggregator.",
      "hidden": false,
      "label": "Enable External Logging",
      "name": "LOG_AGGREGATOR_ENABLED",
      "required": false,
      "sensitive": false,
      "type": "boolean"
    },
    "LOG_AGGREGATOR_HOST": {
      "category": "Logging",
      "category_slug": "logging",
      "computed": true,
      "default": null,
      "help_text": "Hostname/IP where external logs will be sent to.",
      "hidden": false,
      "label": "Logging Aggregator",
      "name": "LOG_AGGREGATOR_HOST",
      "required": false,
      "sensitive": false,
      "type": "string"
    },
    "LOG_AGGREGATOR_INDIVIDUAL_FACTS": {
      "category": "Logging",
      "category_slug": "logging",
      "computed": true,
      "default": false,
      "help_text": "If set, system tracking facts will be sent for each package, service, or other item found in a scan, allowing for greater search query granularity. If unset, facts will be sent as a single dictionary, allowing for greater efficiency in fact processing.",
      "hidden": false,
      "label": "Log System Tracking Facts Individually",
      "name": "LOG_AGGREGATOR_INDIVIDUAL_FACTS",
      "required": false,
      "sensitive": false,
      "type": "boolean"
    },
    "LOG_AGGREGATOR_LEVEL": {
      "category": "Logging",
      "category_slug": "logging",
      "choices": [
        [
          "DEBUG",
          "DEBUG"
        ],
        [
          "INFO",
          "INFO"
        ],
        [
          "WARNING",
          "WARNING"
        ],
        [
          "ERROR",
          "ERROR"
        ],
        [
          "CRITICAL",
          "CRITICAL"
        ]
      ],
      "computed": true,
      "default": "INFO",
      "default_value": "stringdefault.StaticString(`INFO`)",
      "help_text": "Level threshold used by log handler. Severities from lowest to highest are DEBUG, INFO, WARNING, ERROR, CRITICAL. Messages less severe than the threshold will be ignored by log handler. (messages under category awx.anlytics ignore this setting)",
      "hidden": false,
      "label": "Logging Aggregator Level Threshold",
      "name": "LOG_AGGREGATOR_LEVEL",
      "required": false,
      "sensitive": false,
      "type": "choice"
    },
    "LOG_AGGREGATOR_LOGGERS": {
      "category": "Logging",
      "category_slug": "logging",
      "child": {
        "hidden": false,
        "read_only": false,
        "required": true,
        "type": "string"
      },
      "computed": true,
      "default": [
        "awx",
        "activity_stream",
        "job_events",
        "system_tracking",
        "broadcast_websocket"
      ],
      "element_type": "string",
      "help_text": "List of loggers that will send HTTP logs to the collector, these can include any or all of: \nawx - service logs\nactivity_stream - activity stream records\njob_events - callback data from Ansible job events\nsystem_tracking - facts gathered from scan jobs\nbroadcast_websocket - errors pertaining to websockets broadcast metrics\n",
      "hidden": false,
      "label": "Loggers Sending Data to Log Aggregator Form",
      "name": "LOG_AGGREGATOR_LOGGERS",
      "required": false,
      "sensitive": false,
      "type": "list"
    },
    "LOG_AGGREGATOR_MAX_DISK_USAGE_PATH": {
      "category": "Logging",
      "category_slug": "logging",
      "computed": true,
      "default": "/var/lib/awx",
      "default_value": "stringdefault.StaticString(`/var/lib/awx`)",
      "help_text": "Location to persist logs that should be retried after an outage of the external log aggregator (defaults to /var/lib/awx). Equivalent to the rsyslogd queue.spoolDirectory setting.",
      "hidden": false,
      "label": "File system location for rsyslogd disk persistence",
      "name": "LOG_AGGREGATOR_MAX_DISK_USAGE_PATH",
      "required": false,
      "sensitive": false,
      "type": "string"
    },
    "LOG_AGGREGATOR_PASSWORD": {
      "category": "Logging",
      "category_slug": "logging",
      "computed": true,
      "default": "",
      "default_value": "stringdefault.StaticString(``)",
      "help_text": "Password or authentication token for external log aggregator (if required; HTTP/s only).",
      "hidden": false,
      "label": "Logging Aggregator Password/Token",
      "name": "LOG_AGGREGATOR_PASSWORD",
      "required": false,
      "sensitive": false,
      "type": "string"
    },
    "LOG_AGGREGATOR_PORT": {
      "category": "Logging",
      "category_slug": "logging",
      "computed": true,
      "default": null,
      "help_text": "Port on Logging Aggregator to send logs to (if required and not provided in Logging Aggregator).",
      "hidden": false,
      "label": "Logging Aggregator Port",
      "name": "LOG_AGGREGATOR_PORT",
      "required": false,
      "sensitive": false,
      "type": "integer"
    },
    "LOG_AGGREGATOR_PROTOCOL": {
      "category": "Logging",
      "category_slug": "logging",
      "choices": [
        [
          "https",
          "HTTPS/HTTP"
        ],
        [
          "tcp",
          "TCP"
        ],
        [
          "udp",
          "UDP"
        ]
      ],
      "computed": true,
      "default": "https",
      "default_value": "stringdefault.StaticString(`https`)",
      "help_text": "Protocol used to communicate with log aggregator.  HTTPS/HTTP assumes HTTPS unless http:// is explicitly used in the Logging Aggregator hostname.",
      "hidden": false,
      "label": "Logging Aggregator Protocol",
      "name": "LOG_AGGREGATOR_PROTOCOL",
      "required": false,
      "sensitive": false,
      "type": "choice"
    },
    "LOG_AGGREGATOR_RSYSLOGD_DEBUG": {
      "category": "Logging",
      "category_slug": "logging",
      "computed": true,
      "default": false,
      "help_text": "Enabled high verbosity debugging for rsyslogd.  Useful for debugging connection issues for external log aggregation.",
      "hidden": false,
      "label": "Enable rsyslogd debugging",
      "name": "LOG_AGGREGATOR_RSYSLOGD_DEBUG",
      "required": false,
      "sensitive": false,
      "type": "boolean"
    },
    "LOG_AGGREGATOR_TCP_TIMEOUT": {
      "category": "Logging",
      "category_slug": "logging",
      "computed": true,
      "default": 5,
      "default_value": "int64default.StaticInt64(5)",
      "help_text": "Number of seconds for a TCP connection to external log aggregator to timeout. Applies to HTTPS and TCP log aggregator protocols.",
      "hidden": false,
      "label": "TCP Connection Timeout",
      "name": "LOG_AGGREGATOR_TCP_TIMEOUT",
      "required": false,
      "sensitive": false,
      "type": "integer",
      "unit": "seconds"
    },
    "LOG_AGGREGATOR_TOWER_UUID": {
      "category": "Logging",
      "category_slug": "logging",
      "computed": true,
      "default": "",
      "default_value": "stringdefault.StaticString(``)",
      "help_text": "Useful to uniquely identify instances.",
      "hidden": false,
      "label": "Cluster-wide unique identifier.",
      "name": "LOG_AGGREGATOR_TOWER_UUID",
      "required": false,
      "sensitive": false,
      "type": "string"
    },
    "LOG_AGGREGATOR_TYPE": {
      "category": "Logging",
      "category_slug": "logging",
      "choices": [
        [
          null,
          "---------"
        ],
        [
          "logstash",
          "logstash"
        ],
        [
          "splunk",
          "splunk"
        ],
        [
          "loggly",
          "loggly"
        ],
        [
          "sumologic",
          "sumologic"
        ],
        [
          "other",
          "other"
        ]
      ],
      "computed": true,
      "default": null,
      "help_text": "Format messages for the chosen log aggregator.",
      "hidden": false,
      "label": "Logging Aggregator Type",
      "name": "LOG_AGGREGATOR_TYPE",
      "required": false,
      "sensitive": false,
      "type": "choice"
    },
    "LOG_AGGREGATOR_USERNAME": {
      "category": "Logging",
      "category_slug": "logging",
      "computed": true,
      "default": "",
      "default_value": "stringdefault.StaticString(``)",
      "help_text": "Username for external log aggregator (if required; HTTP/s only).",
      "hidden": false,
      "label": "Logging Aggregator Username",
      "name": "LOG_AGGREGATOR_USERNAME",
      "required": false,
      "sensitive": false,
      "type": "string"
    },
    "LOG_AGGREGATOR_VERIFY_CERT": {
      "category": "Logging",
      "category_slug": "logging",
      "computed": true,
      "default": true,
      "help_text": "Flag to control enable/disable of certificate verification when LOG_AGGREGATOR_PROTOCOL is \"https\". If enabled, the log handler will verify certificate sent by external log aggregator before establishing connection.",
      "hidden": false,
      "label": "Enable/disable HTTPS certificate verification",
      "name": "LOG_AGGREGATOR_VERIFY_CERT",
      "required": false,
      "sensitive": false,
      "type": "boolean"
    }
  },
  "PropertyPostKeys": [
    "API_400_ERROR_LOG_FORMAT",
    "LOG_AGGREGATOR_ACTION_MAX_DISK_USAGE_GB",
    "LOG_AGGREGATOR_ACTION_QUEUE_SIZE",
    "LOG_AGGREGATOR_ENABLED",
    "LOG_AGGREGATOR_HOST",
    "LOG_AGGREGATOR_INDIVIDUAL_FACTS",
    "LOG_AGGREGATOR_LEVEL",
    "LOG_AGGREGATOR_LOGGERS",
    "LOG_AGGREGATOR_MAX_DISK_USAGE_PATH",
    "LOG_AGGREGATOR_PASSWORD",
    "LOG_AGGREGATOR_PORT",
    "LOG_AGGREGATOR_PROTOCOL",
    "LOG_AGGREGATOR_RSYSLOGD_DEBUG",
    "LOG_AGGREGATOR_TCP_TIMEOUT",
    "LOG_AGGREGATOR_TOWER_UUID",
    "LOG_AGGREGATOR_TYPE",
    "LOG_AGGREGATOR_USERNAME",
    "LOG_AGGREGATOR_VERIFY_CERT"
  ],
  "PropertyWriteOnlyData": {},
  "PropertyWriteOnlyKeys": null
}