{
  "ApiVersion": "23.5.1",
  "Config": {
    "endpoint": "/api/v2/hosts/",
    "name": "Host",
    "type_name": "host",
    "id_key": "id",
    "property_overrides": {
      "variables": {
        "type": "",
        "description": "",
        "trim": false,
        "post_wrap": true,
        "default_value": "{}",
        "element_type": ""
      }
    },
    "search_fields": [
      {
        "url_suffix": "%d/",
        "name": "by_id",
        "fields": [
          {
            "name": "id",
            "url_escape_value": false
          }
        ]
      },
      {
        "url_suffix": "?name__exact=%s",
        "name": "by_name",
        "fields": [
          {
            "name": "name",
            "url_escape_value": true
          }
        ],
        "multiple_results": true
      }
    ],
    "enabled": true,
    "has_object_roles": true,
    "has_survey_spec": false,
    "associate_disassociate_groups": [
      {
        "name": "Host",
        "endpoint": "/api/v2/hosts/%d/groups/",
        "type": "Group",
        "associate_type": ""
      }
    ],
    "field_constraints": null,
    "skip_write_only": false,
    "undeletable": false,
    "pre_state_set_hook_function": "",
    "no_id": false,
    "no_terraform_data_source": false,
    "no_terraform_resource": false,
    "api_property_resource_key": "POST",
    "api_property_data_key": "GET",
    "property_name_leave_as_is": false,
    "api_data_override": null,
    "remove_fields_data_source": [
      "ansible_facts_modified",
      "has_active_failures",
      "has_inventory_sources"
    ],
    "remove_fields_resource": [
      "ansible_facts_modified",
      "last_job",
      "last_job_host_summary"
    ],
    "credential_types": null
  },
  "Description": "# List Hosts:\n\nMake a GET request to this resource to retrieve the list of\nhosts.\n\nThe resulting data structure contains:\n\n    {\n        \"count\": 99,\n        \"next\": null,\n        \"previous\": null,\n        \"results\": [\n            ...\n        ]\n    }\n\nThe `count` field indicates the total number of hosts\nfound for the given query.  The `next` and `previous` fields provides links to\nadditional results if there are more than will fit on a single page.  The\n`results` list contains zero or more host records.  \n\n## Results\n\nEach host data structure includes the following fields:\n\n* `id`: Database ID for this host. (integer)\n* `type`: Data type for this host. (choice)\n* `url`: URL for this host. (string)\n* `related`: Data structure with URLs of related resources. (object)\n* `summary_fields`: Data structure with name/description for related resources.  The output for some objects may be limited for performance reasons. (object)\n* `created`: Timestamp when this host was created. (datetime)\n* `modified`: Timestamp when this host was last modified. (datetime)\n* `name`: Name of this host. (string)\n* `description`: Optional description of this host. (string)\n* `inventory`:  (id)\n* `enabled`: Is this host online and available for running jobs? (boolean)\n* `instance_id`: The value used by the remote inventory source to uniquely identify the host (string)\n* `variables`: Host variables in JSON or YAML format. (json)\n* `has_active_failures`:  (field)\n* `has_inventory_sources`:  (field)\n* `last_job`:  (id)\n* `last_job_host_summary`:  (id)\n* `ansible_facts_modified`: The date and time ansible_facts was last modified. (datetime)\n\n\n\n## Sorting\n\nTo specify that hosts are returned in a particular\norder, use the `order_by` query string parameter on the GET request.\n\n    ?order_by=name\n\nPrefix the field name with a dash `-` to sort in reverse:\n\n    ?order_by=-name\n\nMultiple sorting fields may be specified by separating the field names with a\ncomma `,`:\n\n    ?order_by=name,some_other_field\n\n## Pagination\n\nUse the `page_size` query string parameter to change the number of results\nreturned for each request.  Use the `page` query string parameter to retrieve\na particular page of results.\n\n    ?page_size=100\u0026page=2\n\nThe `previous` and `next` links returned with the results will set these query\nstring parameters automatically.\n\n## Searching\n\nUse the `search` query string parameter to perform a case-insensitive search\nwithin all designated text fields of a model.\n\n    ?search=findme\n\n(_Added in Ansible Tower 3.1.0_) Search across related fields:\n\n    ?related__search=findme\n\nNote: If you want to provide more than one search term, multiple\nsearch fields with the same key, like `?related__search=foo\u0026related__search=bar`,\nwill be ORed together. Terms separated by commas, like `?related__search=foo,bar`\nwill be ANDed together.\n\n## Filtering\n\nAny additional query string parameters may be used to filter the list of\nresults returned to those matching a given value.  Only fields and relations\nthat exist in the database may be used for filtering.  Any special characters\nin the specified value should be url-encoded. For example:\n\n    ?field=value%20xyz\n\nFields may also span relations, only for fields and relationships defined in\nthe database:\n\n    ?other__field=value\n\nTo exclude results matching certain criteria, prefix the field parameter with\n`not__`:\n\n    ?not__field=value\n\nBy default, all query string filters are AND'ed together, so\nonly the results matching *all* filters will be returned.  To combine results\nmatching *any* one of multiple criteria, prefix each query string parameter\nwith `or__`:\n\n    ?or__field=value\u0026or__field=othervalue\n    ?or__not__field=value\u0026or__field=othervalue\n\n(_Added in Ansible Tower 1.4.5_) The default AND filtering applies all filters\nsimultaneously to each related object being filtered across database\nrelationships.  The chain filter instead applies filters separately for each\nrelated object. To use, prefix the query string parameter with `chain__`:\n\n    ?chain__related__field=value\u0026chain__related__field2=othervalue\n    ?chain__not__related__field=value\u0026chain__related__field2=othervalue\n\nIf the first query above were written as\n`?related__field=value\u0026related__field2=othervalue`, it would return only the\nprimary objects where the *same* related object satisfied both conditions.  As\nwritten using the chain filter, it would return the intersection of primary\nobjects matching each condition.\n\nField lookups may also be used for more advanced queries, by appending the\nlookup to the field name:\n\n    ?field__lookup=value\n\nThe following field lookups are supported:\n\n* `exact`: Exact match (default lookup if not specified).\n* `iexact`: Case-insensitive version of `exact`.\n* `contains`: Field contains value.\n* `icontains`: Case-insensitive version of `contains`.\n* `startswith`: Field starts with value.\n* `istartswith`: Case-insensitive version of `startswith`.\n* `endswith`: Field ends with value.\n* `iendswith`: Case-insensitive version of `endswith`.\n* `regex`: Field matches the given regular expression.\n* `iregex`: Case-insensitive version of `regex`.\n* `gt`: Greater than comparison.\n* `gte`: Greater than or equal to comparison.\n* `lt`: Less than comparison.\n* `lte`: Less than or equal to comparison.\n* `isnull`: Check whether the given field or related object is null; expects a\n  boolean value.\n* `in`: Check whether the given field's value is present in the list provided;\n  expects a list of items.\n\nBoolean values may be specified as `True` or `1` for true, `False` or `0` for\nfalse (both case-insensitive).\n\nNull values may be specified as `None` or `Null` (both case-insensitive),\nthough it is preferred to use the `isnull` lookup to explicitly check for null\nvalues.\n\nLists (for the `in` lookup) may be specified as a comma-separated list of\nvalues.\n\n(_Added in Ansible Tower 3.1.0_) Filtering based on the requesting user's\nlevel of access by query string parameter.\n\n* `role_level`: Level of role to filter on, such as `admin_role`\n\n\n\n\n`host_filter` is available on this endpoint. The filter supports: relational queries, `and` `or` boolean logic, as well as expression grouping via `()`.\n\n    ?host_filter=name=my_host\n    ?host_filter=name=\"my host\" or name=my_host\n    ?host_filter=groups__name=\"my group\"\n    ?host_filter=name=my_host and groups__name=\"my group\"\n    ?host_filter=name=my_host and groups__name=\"my group\"\n    ?host_filter=(name=my_host and groups__name=\"my group\") or (name=my_host2 and groups__name=my_group2)\n\n`host_filter` can also be used to query JSON data in the related `ansible_facts`. `__` may be used to traverse JSON dictionaries. `[]` may be used to traverse JSON arrays.\n\n    ?host_filter=ansible_facts__ansible_processor_vcpus=8\n    ?host_filter=ansible_facts__ansible_processor_vcpus=8 and name=\"my_host\" and ansible_facts__ansible_lo__ipv6[]__scope=host",
  "Endpoint": "/api/v2/hosts/",
  "Name": "Host",
  "PackageName": "awx",
  "PropertyGetData": {
    "description": {
      "computed": true,
      "filterable": true,
      "help_text": "Optional description of this host.",
      "label": "Description",
      "name": "description",
      "required": false,
      "sensitive": false,
      "type": "string"
    },
    "enabled": {
      "computed": true,
      "filterable": true,
      "help_text": "Is this host online and available for running jobs?",
      "label": "Enabled",
      "name": "enabled",
      "required": false,
      "sensitive": false,
      "type": "boolean"
    },
    "id": {
      "computed": true,
      "filterable": true,
      "help_text": "Database ID for this host.",
      "label": "ID",
      "name": "id",
      "required": false,
      "sensitive": false,
      "type": "integer"
    },
    "instance_id": {
      "computed": true,
      "filterable": true,
      "help_text": "The value used by the remote inventory source to uniquely identify the host",
      "label": "Instance id",
      "name": "instance_id",
      "required": false,
      "sensitive": false,
      "type": "string"
    },
    "inventory": {
      "computed": true,
      "filterable": true,
      "label": "Inventory",
      "name": "inventory",
      "required": false,
      "sensitive": false,
      "type": "id"
    },
    "last_job": {
      "computed": true,
      "filterable": true,
      "label": "Last job",
      "name": "last_job",
      "required": false,
      "sensitive": false,
      "type": "id"
    },
    "last_job_host_summary": {
      "computed": true,
      "filterable": true,
      "label": "Last job host summary",
      "name": "last_job_host_summary",
      "required": false,
      "sensitive": false,
      "type": "id"
    },
    "name": {
      "computed": true,
      "filterable": true,
      "help_text": "Name of this host.",
      "label": "Name",
      "name": "name",
      "required": false,
      "sensitive": false,
      "type": "string"
    },
    "variables": {
      "computed": true,
      "default": "{}",
      "default_value": "stringdefault.StaticString(`{}`)",
      "filterable": true,
      "help_text": "Host variables in JSON or YAML format.",
      "label": "Variables",
      "name": "variables",
      "required": false,
      "sensitive": false,
      "type": "json"
    }
  },
  "PropertyGetKeys": [
    "description",
    "enabled",
    "id",
    "instance_id",
    "inventory",
    "last_job",
    "last_job_host_summary",
    "name",
    "variables"
  ],
  "PropertyPostData": {
    "description": {
      "computed": true,
      "default": "",
      "default_value": "stringdefault.StaticString(``)",
      "filterable": true,
      "help_text": "Optional description of this host.",
      "label": "Description",
      "name": "description",
      "required": false,
      "sensitive": false,
      "type": "string"
    },
    "enabled": {
      "computed": true,
      "default": true,
      "filterable": true,
      "help_text": "Is this host online and available for running jobs?",
      "label": "Enabled",
      "name": "enabled",
      "required": false,
      "sensitive": false,
      "type": "boolean"
    },
    "instance_id": {
      "computed": true,
      "default": "",
      "default_value": "stringdefault.StaticString(``)",
      "filterable": true,
      "help_text": "The value used by the remote inventory source to uniquely identify the host",
      "label": "Instance id",
      "max_length": 1024,
      "name": "instance_id",
      "required": false,
      "sensitive": false,
      "type": "string"
    },
    "inventory": {
      "computed": false,
      "filterable": true,
      "label": "Inventory",
      "name": "inventory",
      "required": true,
      "sensitive": false,
      "type": "id"
    },
    "name": {
      "computed": false,
      "filterable": true,
      "help_text": "Name of this host.",
      "label": "Name",
      "max_length": 512,
      "name": "name",
      "required": true,
      "sensitive": false,
      "type": "string"
    },
    "variables": {
      "computed": true,
      "default": "{}",
      "default_value": "stringdefault.StaticString(`{}`)",
      "filterable": true,
      "help_text": "Host variables in JSON or YAML format.",
      "label": "Variables",
      "name": "variables",
      "required": false,
      "sensitive": false,
      "type": "json"
    }
  },
  "PropertyPostKeys": [
    "description",
    "enabled",
    "instance_id",
    "inventory",
    "name",
    "variables"
  ],
  "PropertyWriteOnlyData": {},
  "PropertyWriteOnlyKeys": null
}